{"sentence": "Box 0 contains the boat and the shoe and the television, Box 1 contains the camera and the car and the plane, Box 2 contains the cake, Box 3 contains the fan, Box 4 contains the cross and the file and the note, Box 5 contains the chemical, Box 6 contains nothing. Move the cake from Box 2 to Box 6. Put the dish and the stone into Box 5. Move the television from Box 0 to Box 6. Put the drink into Box 2. Move the chemical and the stone from Box 5 to Box 2.", "sample_id": 0, "numops": 1, "final_states": {"Box 0": ["the boat", "the shoe"], "Box 1": ["the camera", "the plane", "the car"], "Box 2": ["the chemical", "the stone", "the drink"], "Box 3": ["the fan"], "Box 4": ["the file", "the note", "the cross"], "Box 5": ["the dish"], "Box 6": ["the television", "the cake"]}}
{"sentence": "Box 0 contains the cash and the ticket, Box 1 contains nothing, Box 2 contains the beer and the brain and the guitar, Box 3 contains the medicine and the newspaper, Box 4 contains the crown, Box 5 contains the ice and the painting, Box 6 contains the bomb and the boot and the plane. Put the meat into Box 5. Move the ticket from Box 0 to Box 1. Remove the newspaper from Box 3. Remove the guitar from Box 2. Remove the brain from Box 2. Remove the beer from Box 2. Move the ticket from Box 1 to Box 3. Move the medicine from Box 3 to Box 2. Move the cash from Box 0 to Box 3.", "sample_id": 6, "numops": 2, "final_states": {"Box 0": ["nothing"], "Box 1": ["nothing", "the meat"], "Box 2": ["the painting", "the medicine", "the ice"], "Box 3": ["the cash", "the ticket"], "Box 4": ["the crown"], "Box 5": ["the painting", "the ice", "the meat", "the string"], "Box 6": ["the plane", "the bomb", "the boot"]}}
{"sentence": "Box 0 contains the creature, Box 1 contains the cash and the drug, Box 2 contains the letter and the magazine and the ring, Box 3 contains nothing, Box 4 contains nothing, Box 5 contains the coffee and the rock and the ticket, Box 6 contains nothing. Move the letter from Box 2 to Box 6. Put the crown into Box 6. Move the creature from Box 0 to Box 4. Put the milk and the sheet into Box 4. Remove the cash from Box 1. Remove the crown from Box 6. Remove the coffee and the ticket from Box 5. Move the sheet from Box 4 to Box 6. Put the train into Box 4. Remove the sheet from Box 6.", "sample_id": 11, "numops": 1, "final_states": {"Box 0": ["nothing"], "Box 1": ["the drug"], "Box 2": ["the magazine", "the ring"], "Box 3": ["nothing"], "Box 4": ["the creature", "the milk", "the train"], "Box 5": ["the rock"], "Box 6": ["the letter"]}}
{"sentence": "Box 0 contains the bomb and the boot, Box 1 contains nothing, Box 2 contains nothing, Box 3 contains the rose and the tissue, Box 4 contains the jacket, Box 5 contains the fish and the painting, Box 6 contains the cross. Put the machine into Box 3. Remove the painting from Box 5. Remove the fish from Box 5. Move the machine and the rose from Box 3 to Box 4. Move the cross from Box 6 to Box 1. Move the cross from Box 1 to Box 3. Move the cross from Box 3 to Box 6. Move the cross from Box 6 to Box 0. Put the bell and the bottle into Box 3.", "sample_id": 12, "numops": 1, "final_states": {"Box 0": ["the bomb", "the boot", "the cross"], "Box 1": ["nothing"], "Box 2": ["nothing"], "Box 3": ["the bell", "the bottle", "the tissue"], "Box 4": ["the rose", "the machine", "the jacket"], "Box 5": ["nothing"], "Box 6": ["nothing"]}}
{"sentence": "Box 0 contains the dress and the suit and the tape, Box 1 contains the apple and the note, Box 2 contains the cash and the coat and the jacket, Box 3 contains the file, Box 4 contains nothing, Box 5 contains nothing, Box 6 contains the engine. Remove the suit from Box 0. Remove the coat and the jacket from Box 2. Remove the tape from Box 0. Move the apple from Box 1 to Box 0. Put the brick into Box 5. Move the file from Box 3 to Box 0. Remove the cash from Box 2. Put the cream into Box 1. Move the cream and the note from Box 1 to Box 5.", "sample_id": 42, "numops": 4, "final_states": {"Box 0": ["the file", "the apple", "the dress"], "Box 1": ["nothing"], "Box 2": ["nothing"], "Box 3": ["nothing"], "Box 4": ["nothing"], "Box 5": ["the cream", "the note", "the brick"], "Box 6": ["the engine"]}}
{"sentence": "Box 0 contains the block, Box 1 contains the card and the paper, Box 2 contains nothing, Box 3 contains the meat, Box 4 contains the suit, Box 5 contains the fish and the wheel, Box 6 contains nothing. Put the pipe into Box 4. Put the ring into Box 2. Move the meat from Box 3 to Box 4. Move the suit from Box 4 to Box 2. Remove the block from Box 0. Remove the ring and the suit from Box 2. Remove the meat from Box 4.", "sample_id": 46, "numops": 1, "final_states": {"Box 0": ["nothing"], "Box 1": ["the card", "the paper"], "Box 2": ["nothing"], "Box 3": ["nothing"], "Box 4": ["the paper", "the pipe"], "Box 5": ["the fish", "the wheel"], "Box 6": ["nothing"]}}
{"sentence": "Box 0 contains the jacket and the key and the stone, Box 1 contains the fig and the file and the glass, Box 2 contains the disk and the shirt, Box 3 contains the cigarette and the tape and the tie, Box 4 contains the document and the guitar, Box 5 contains the train, Box 6 contains the hat and the newspaper and the pot. Remove the jacket and the key from Box 0. Remove the stone from Box 0. Move the train from Box 5 to Box 0. Remove the fig and the glass from Box 1. Move the file from Box 1 to Box 2. Move the tape and the tie from Box 3 to Box 0. Move the tape and the tie from Box 0 to Box 5. Move the pot from Box 6 to Box 4. Remove the train from Box 0. Put the note and the stone into Box 0.", "sample_id": 51, "numops": 7, "final_states": {"Box 0": ["the stone", "the note"], "Box 1": ["nothing"], "Box 2": ["the file", "the shirt", "the disk"], "Box 3": ["the apple", "the key", "the cigarette"], "Box 4": ["the pot", "the document", "the guitar"], "Box 5": ["the cream", "the tape", "the tie"], "Box 6": ["the newspaper", "the hat"]}}
{"sentence": "Box 0 contains the coffee and the fish and the gift, Box 1 contains the coat and the shoe, Box 2 contains the ball and the computer, Box 3 contains the leaf and the string, Box 4 contains the branch and the letter and the shell, Box 5 contains the document, Box 6 contains the bread and the clock and the wheel. Remove the leaf from Box 3. Remove the fish from Box 0. Remove the bread and the clock from Box 6. Move the ball from Box 2 to Box 0.", "sample_id": 53, "numops": 2, "final_states": {"Box 0": ["the coffee", "the gift", "the ball"], "Box 1": ["the coat", "the shoe"], "Box 2": ["the computer"], "Box 3": ["the string"], "Box 4": ["the shell", "the branch", "the letter"], "Box 5": ["the document"], "Box 6": ["the wheel"]}}
{"sentence": "Box 0 contains the key and the ring and the train, Box 1 contains the dish and the tape and the wire, Box 2 contains the bottle and the jacket, Box 3 contains the bag and the brick and the plant, Box 4 contains the car and the flower, Box 5 contains the boat, Box 6 contains the boot and the coat and the sheet. Move the key and the train from Box 0 to Box 5. Remove the bag and the brick from Box 3. Put the pipe into Box 0. Remove the jacket from Box 2. Remove the bottle from Box 2. Remove the car from Box 4. Remove the flower from Box 4. Move the coat and the sheet from Box 6 to Box 4. Put the picture into Box 2. Remove the sheet from Box 4. Remove the picture from Box 2.", "sample_id": 56, "numops": 2, "final_states": {"Box 0": ["the pipe", "the ring"], "Box 1": ["the dish", "the wire", "the tape"], "Box 2": ["nothing"], "Box 3": ["the plant"], "Box 4": ["the coat"], "Box 5": ["the key", "the boat", "the train"], "Box 6": ["the boot"]}}
{"sentence": "Box 0 contains the branch and the cream, Box 1 contains the wire, Box 2 contains the bowl and the flower and the plate, Box 3 contains the bomb and the knife, Box 4 contains the coat and the newspaper and the pot, Box 5 contains the boat and the camera and the cheese, Box 6 contains the boot and the chemical and the shirt. Remove the newspaper and the pot from Box 4. Move the boat from Box 5 to Box 4. Remove the camera and the cheese from Box 5. Remove the bowl and the flower and the plate from Box 2. Remove the bomb from Box 3. Remove the wire from Box 1. Move the knife from Box 3 to Box 4.", "sample_id": 59, "numops": 0, "final_states": {"Box 0": ["the cream", "nothing", "the branch"], "Box 1": ["nothing", "the boat", "the coat"], "Box 2": ["nothing"], "Box 3": ["nothing"], "Box 4": ["the knife", "the boat", "the coat"], "Box 5": ["the chemical", "nothing"], "Box 6": ["the cream", "the boot", "the shirt", "the chemical", "the branch"]}}
{"sentence": "Box 0 contains nothing, Box 1 contains nothing, Box 2 contains the boat, Box 3 contains the drug, Box 4 contains the chemical and the mirror and the shell, Box 5 contains the creature and the painting and the rock, Box 6 contains the block. Put the bread and the pipe into Box 0. Move the block from Box 6 to Box 2. Remove the creature and the painting from Box 5. Move the rock from Box 5 to Box 6. Put the cup into Box 0. Put the cigarette into Box 6. Move the cigarette and the rock from Box 6 to Box 3. Move the chemical and the mirror and the shell from Box 4 to Box 6. Move the chemical and the shell from Box 6 to Box 4.", "sample_id": 61, "numops": 2, "final_states": {"Box 0": ["the bread", "the pipe", "the cup"], "Box 1": ["the chemical", "nothing"], "Box 2": ["the boat", "the block"], "Box 3": ["the bread", "the drug", "the cigarette", "the rock"], "Box 4": ["the shell", "the chemical"], "Box 5": ["nothing", "the cigarette"], "Box 6": ["the mirror"]}}
{"sentence": "Box 0 contains the clock and the magazine, Box 1 contains the chemical and the letter and the string, Box 2 contains the computer and the picture and the tissue, Box 3 contains nothing, Box 4 contains the block and the glass and the tea, Box 5 contains the milk, Box 6 contains the boot and the wheel. Remove the boot from Box 6. Move the milk from Box 5 to Box 6. Remove the chemical and the string from Box 1. Move the letter from Box 1 to Box 5. Move the picture and the tissue from Box 2 to Box 1. Remove the magazine from Box 0. Remove the clock from Box 0. Put the cash and the creature into Box 2. Put the pipe into Box 0. Remove the creature from Box 2.", "sample_id": 64, "numops": 3, "final_states": {"Box 0": ["the pipe"], "Box 1": ["the picture", "the tissue"], "Box 2": ["the computer", "the cash"], "Box 3": ["nothing"], "Box 4": ["the glass", "the block", "the tea"], "Box 5": ["the letter"], "Box 6": ["the milk", "the wheel"]}}
{"sentence": "Box 0 contains nothing, Box 1 contains the bowl and the disk, Box 2 contains the bottle and the rock and the wire, Box 3 contains the apple and the ice and the shirt, Box 4 contains the branch and the card and the crown, Box 5 contains the tie, Box 6 contains the leaf and the ring. Remove the tie from Box 5. Remove the bottle and the rock and the wire from Box 2. Remove the leaf from Box 6. Put the machine into Box 5. Remove the machine from Box 5. Move the disk from Box 1 to Box 5. Put the flower and the magazine into Box 2. Remove the apple and the ice from Box 3. Move the bowl from Box 1 to Box 6. Move the shirt from Box 3 to Box 0. Move the disk from Box 5 to Box 1.", "sample_id": 65, "numops": 1, "final_states": {"Box 0": ["the shirt"], "Box 1": ["the disk"], "Box 2": ["the flower", "the magazine"], "Box 3": ["nothing"], "Box 4": ["the card", "the branch", "the crown"], "Box 5": ["nothing"], "Box 6": ["the bowl", "the ring"]}}
{"sentence": "Box 0 contains the document and the guitar and the tea, Box 1 contains nothing, Box 2 contains the apple and the phone, Box 3 contains the boat and the glass and the suit, Box 4 contains the fan, Box 5 contains the jacket, Box 6 contains the camera.", "sample_id": 66, "numops": 0, "final_states": {"Box 0": ["the document", "the guitar", "the tea"], "Box 1": ["nothing"], "Box 2": ["the apple", "the phone"], "Box 3": ["the glass", "the boat", "the suit"], "Box 4": ["the fan"], "Box 5": ["the jacket"], "Box 6": ["the camera"]}}
{"sentence": "Box 0 contains the pot and the suit and the ticket, Box 1 contains the cake and the string and the wire, Box 2 contains the bus and the document, Box 3 contains the bell and the cigarette and the mirror, Box 4 contains nothing, Box 5 contains the cup, Box 6 contains the leaf. Move the pot from Box 0 to Box 2. Move the cup from Box 5 to Box 4. Move the leaf from Box 6 to Box 0. Remove the cake and the wire from Box 1. Put the map into Box 4. Put the camera into Box 4. Move the string from Box 1 to Box 5. Put the newspaper into Box 5. Remove the suit from Box 0. Remove the bell and the mirror from Box 3. Remove the ticket from Box 0. Remove the leaf from Box 0.", "sample_id": 70, "numops": 5, "final_states": {"Box 0": ["nothing"], "Box 1": ["nothing"], "Box 2": ["the pot", "the document", "the bus"], "Box 3": ["the cigarette"], "Box 4": ["the camera", "the map", "the cup"], "Box 5": ["the newspaper", "the string"], "Box 6": ["nothing"]}}
{"sentence": "Box 0 contains the jacket, Box 1 contains the machine and the note, Box 2 contains nothing, Box 3 contains the dress and the television, Box 4 contains the apple and the bread, Box 5 contains nothing, Box 6 contains the book and the paper. Move the television from Box 3 to Box 5. Remove the dress from Box 3. Remove the television from Box 5. Move the book from Box 6 to Box 1. Remove the jacket from Box 0. Put the boot into Box 6. Move the boot from Box 6 to Box 2. Put the bottle into Box 0. Move the bottle from Box 0 to Box 6. Put the knife into Box 5. Remove the bottle from Box 6. Remove the paper from Box 6.", "sample_id": 81, "numops": 3, "final_states": {"Box 0": ["nothing"], "Box 1": ["the note", "the book", "the machine"], "Box 2": ["the boot"], "Box 3": ["nothing"], "Box 4": ["the apple", "the bread"], "Box 5": ["the knife"], "Box 6": ["nothing"]}}
{"sentence": "Box 0 contains the card and the cash, Box 1 contains the bone and the boot and the pot, Box 2 contains the bill and the seed, Box 3 contains the paper, Box 4 contains the fish, Box 5 contains the brain and the file, Box 6 contains the ball and the boat and the medicine. Remove the bone and the boot and the pot from Box 1. Put the bone into Box 1. Put the mirror into Box 1. Move the fish from Box 4 to Box 0. Remove the mirror from Box 1. Put the tie into Box 5. Remove the brain from Box 5. Remove the card from Box 0.", "sample_id": 85, "numops": 2, "final_states": {"Box 0": ["the fish", "the cash"], "Box 1": ["the bone"], "Box 2": ["the bill", "the seed"], "Box 3": ["the paper", "nothing"], "Box 4": ["nothing"], "Box 5": ["the file", "the tie"], "Box 6": ["the medicine", "the boat", "the ball"]}}
{"sentence": "Box 0 contains the card and the cheese and the seed, Box 1 contains the bottle and the plane, Box 2 contains the drink and the egg and the key, Box 3 contains the ball and the bread and the rose, Box 4 contains the apple, Box 5 contains the creature and the painting, Box 6 contains the bill and the computer and the jacket. Put the drug into Box 4. Remove the creature from Box 5. Remove the plane from Box 1. Remove the card and the cheese from Box 0. Remove the drink from Box 2. Move the drug from Box 4 to Box 5.", "sample_id": 91, "numops": 1, "final_states": {"Box 0": ["the seed"], "Box 1": ["the bottle"], "Box 2": ["the rose", "the key", "the egg"], "Box 3": ["the rose", "the bread", "the ball"], "Box 4": ["the apple"], "Box 5": ["the painting", "the drug"], "Box 6": ["the jacket", "the computer", "the bill"]}}
{"sentence": "Box 0 contains the brain and the rose, Box 1 contains nothing, Box 2 contains the egg, Box 3 contains the cash and the cigarette and the train, Box 4 contains the disk, Box 5 contains the computer and the drink, Box 6 contains the jacket. Put the pot into Box 1. Move the pot from Box 1 to Box 0. Remove the jacket from Box 6. Remove the brain and the pot and the rose from Box 0. Put the cake into Box 4.", "sample_id": 98, "numops": 2, "final_states": {"Box 0": ["nothing"], "Box 1": ["nothing", "the disk"], "Box 2": ["nothing", "the egg"], "Box 3": ["the train", "the cigarette", "the cash"], "Box 4": ["nothing", "the disk", "the cake"], "Box 5": ["the computer", "the boat", "the drink"], "Box 6": ["nothing"]}}
{"sentence": "Box 0 contains nothing, Box 1 contains nothing, Box 2 contains the camera and the tape, Box 3 contains the dish, Box 4 contains the cake and the map and the plate, Box 5 contains the cigarette and the painting and the shoe, Box 6 contains the brick and the magazine. Remove the cigarette from Box 5. Put the cream into Box 1. Move the cream from Box 1 to Box 6. Remove the map and the plate from Box 4.", "sample_id": 103, "numops": 0, "final_states": {"Box 0": ["nothing"], "Box 1": ["nothing"], "Box 2": ["the camera", "nothing", "the tape"], "Box 3": ["the dish"], "Box 4": ["the shell", "the magazine", "the cake"], "Box 5": ["the painting", "the shoe"], "Box 6": ["the cream", "the magazine", "the brick"]}}
{"sentence": "Box 0 contains the tea, Box 1 contains nothing, Box 2 contains the block and the brain, Box 3 contains the book and the ice and the ring, Box 4 contains the creature and the hat and the wheel, Box 5 contains the fig and the note and the train, Box 6 contains the ball. Move the block from Box 2 to Box 1. Put the magazine and the shirt into Box 0. Move the wheel from Box 4 to Box 2. Remove the train from Box 5. Put the dress into Box 1.", "sample_id": 109, "numops": 1, "final_states": {"Box 0": ["the magazine", "the shirt", "the tea"], "Box 1": ["the block", "the dress"], "Box 2": ["the brain", "the wheel"], "Box 3": ["the book", "the ice", "the ring"], "Box 4": ["the creature", "the hat"], "Box 5": ["the fig", "the note"], "Box 6": ["the ball"]}}
{"sentence": "Box 0 contains the apple and the shell, Box 1 contains the guitar and the magazine, Box 2 contains the cake, Box 3 contains nothing, Box 4 contains the cup and the engine and the rose, Box 5 contains the ball and the branch, Box 6 contains the card and the cash and the key. Move the card and the key from Box 6 to Box 2. Put the tape into Box 0. Remove the magazine from Box 1. Remove the apple and the shell from Box 0. Move the guitar from Box 1 to Box 5. Remove the cake and the card from Box 2. Move the key from Box 2 to Box 6.", "sample_id": 115, "numops": 2, "final_states": {"Box 0": ["the tape"], "Box 1": ["nothing"], "Box 2": ["nothing"], "Box 3": ["nothing"], "Box 4": ["the rose", "the engine", "the cup"], "Box 5": ["the guitar", "the branch", "the ball"], "Box 6": ["the key", "the cash"]}}
{"sentence": "Box 0 contains the computer and the sheet and the stone, Box 1 contains the cup and the fish, Box 2 contains the brick and the coffee and the knife, Box 3 contains the ice and the machine, Box 4 contains the fan and the magazine, Box 5 contains nothing, Box 6 contains the boat and the chemical. Move the fan from Box 4 to Box 6. Remove the ice from Box 3. Remove the cup from Box 1. Move the fish from Box 1 to Box 5. Move the machine from Box 3 to Box 1. Move the magazine from Box 4 to Box 5. Remove the machine from Box 1. Move the magazine from Box 5 to Box 3. Remove the computer and the sheet from Box 0. Remove the magazine from Box 3. Remove the stone from Box 0.", "sample_id": 117, "numops": 2, "final_states": {"Box 0": ["nothing"], "Box 1": ["nothing"], "Box 2": ["the coffee", "the knife", "the brick"], "Box 3": ["nothing"], "Box 4": ["nothing"], "Box 5": ["the fish"], "Box 6": ["the fan", "the chemical", "the boat"]}}
{"sentence": "Box 0 contains the branch and the phone and the shoe, Box 1 contains the egg and the game and the pot, Box 2 contains the pipe, Box 3 contains the machine and the train, Box 4 contains the hat, Box 5 contains the chemical, Box 6 contains the bottle and the coat and the document. Remove the document from Box 6. Move the bottle from Box 6 to Box 5. Remove the machine and the train from Box 3. Remove the pipe from Box 2. Put the television into Box 2. Remove the pot from Box 1. Put the book and the plant into Box 2. Move the coat from Box 6 to Box 1. Move the coat and the egg and the game from Box 1 to Box 3.", "sample_id": 120, "numops": 0, "final_states": {"Box 0": ["the phone", "the branch", "the shoe"], "Box 1": ["nothing"], "Box 2": ["the television", "the plant", "the book"], "Box 3": ["the game", "the egg", "the coat"], "Box 4": ["the hat"], "Box 5": ["the chemical", "the bottle"], "Box 6": ["nothing"]}}
{"sentence": "Box 0 contains nothing, Box 1 contains nothing, Box 2 contains the radio and the tissue, Box 3 contains the bell and the chemical, Box 4 contains the creature and the flower and the shoe, Box 5 contains the drug, Box 6 contains the computer and the dish and the tie. Move the creature and the flower and the shoe from Box 4 to Box 1. Remove the bell and the chemical from Box 3. Move the tissue from Box 2 to Box 5. Remove the radio from Box 2. Put the bottle into Box 2. Put the string into Box 4. Move the bottle from Box 2 to Box 4. Remove the creature and the flower and the shoe from Box 1. Move the bottle from Box 4 to Box 3. Put the bag and the bus and the cup into Box 2. Move the dish from Box 6 to Box 1.", "sample_id": 123, "numops": 0, "final_states": {"Box 0": ["nothing"], "Box 1": ["the dish"], "Box 2": ["the bag", "the bus", "the cup"], "Box 3": ["the bottle"], "Box 4": ["the string"], "Box 5": ["the drug", "the tissue"], "Box 6": ["the computer", "the tie"]}}
{"sentence": "Box 0 contains the apple and the sheet, Box 1 contains the tape, Box 2 contains the cheese and the plane, Box 3 contains the boot and the computer and the disk, Box 4 contains the glass and the machine and the picture, Box 5 contains the bell and the plant, Box 6 contains the ball and the hat and the meat. Move the machine from Box 4 to Box 0. Move the disk from Box 3 to Box 5. Move the computer from Box 3 to Box 1. Move the plane from Box 2 to Box 4. Remove the boot from Box 3. Remove the glass from Box 4. Move the cheese from Box 2 to Box 1. Remove the ball and the meat from Box 6.", "sample_id": 124, "numops": 1, "final_states": {"Box 0": ["the apple", "the sheet", "the machine"], "Box 1": ["the computer", "the cheese", "the tape"], "Box 2": ["nothing"], "Box 3": ["nothing"], "Box 4": ["the picture", "the plane"], "Box 5": ["the plant", "the bell", "the disk"], "Box 6": ["the hat"]}}
{"sentence": "Box 0 contains the apple, Box 1 contains the block and the document and the jacket, Box 2 contains the machine, Box 3 contains nothing, Box 4 contains the sheet and the tissue, Box 5 contains the egg and the ice, Box 6 contains the mirror and the plane and the string. Remove the ice from Box 5. Remove the apple from Box 0.", "sample_id": 126, "numops": 1, "final_states": {"Box 0": ["nothing"], "Box 1": ["the block", "the jacket", "the document"], "Box 2": ["the bag", "the machine"], "Box 3": ["the sheet", "nothing", "the tissue"], "Box 4": ["the sheet", "nothing", "the tissue"], "Box 5": ["nothing", "the egg"], "Box 6": ["the mirror", "the plane", "the string"]}}
{"sentence": "Box 0 contains the rose, Box 1 contains nothing, Box 2 contains the letter, Box 3 contains the game, Box 4 contains the bread and the radio and the tape, Box 5 contains the bell and the camera and the clock, Box 6 contains the apple and the computer and the tie. Move the letter from Box 2 to Box 1. Remove the rose from Box 0. Put the shoe into Box 0. Put the flower into Box 0.", "sample_id": 136, "numops": 3, "final_states": {"Box 0": ["the flower", "the egg", "the shoe"], "Box 1": ["nothing", "the letter"], "Box 2": ["the bread", "the shoe", "the flower", "nothing"], "Box 3": ["the game", "the chemical", "the cake"], "Box 4": ["the bread", "the tape", "nothing", "the radio"], "Box 5": ["the bell", "the camera", "the clock"], "Box 6": ["the apple", "the computer", "the tie"]}}
{"sentence": "Box 0 contains the cross and the egg and the gift, Box 1 contains nothing, Box 2 contains the crown and the fig, Box 3 contains the brain and the dish, Box 4 contains the computer and the fish and the meat, Box 5 contains the beer and the cheese and the seed, Box 6 contains the bell and the document and the wire. Remove the fish and the meat from Box 4. Move the document from Box 6 to Box 1. Move the document from Box 1 to Box 4. Remove the cross and the gift from Box 0. Remove the egg from Box 0. Put the gift into Box 4. Move the crown from Box 2 to Box 6. Put the tissue into Box 2.", "sample_id": 140, "numops": 2, "final_states": {"Box 0": ["nothing", "the wire"], "Box 1": ["nothing"], "Box 2": ["the fig", "the tissue"], "Box 3": ["the dish", "the brain"], "Box 4": ["the gift", "the computer", "the document"], "Box 5": ["the cheese", "the seed", "the beer"], "Box 6": ["the bell", "the wire", "the crown"]}}
{"sentence": "Box 0 contains the coat, Box 1 contains the wheel, Box 2 contains the magazine, Box 3 contains the boat and the dish and the plane, Box 4 contains nothing, Box 5 contains nothing, Box 6 contains the book.", "sample_id": 142, "numops": 0, "final_states": {"Box 0": ["the coat"], "Box 1": ["the wheel"], "Box 2": ["the magazine"], "Box 3": ["the plane", "the dish", "the boat"], "Box 4": ["nothing"], "Box 5": ["nothing"], "Box 6": ["the book"]}}
{"sentence": "Box 0 contains the newspaper and the painting, Box 1 contains the bone and the gift and the stone, Box 2 contains the cash and the tissue, Box 3 contains the hat and the pot and the tape, Box 4 contains nothing, Box 5 contains the bag, Box 6 contains the bill and the string. Remove the bag from Box 5. Put the beer into Box 4. Remove the bone and the gift and the stone from Box 1. Remove the beer from Box 4. Remove the hat and the pot and the tape from Box 3. Put the camera into Box 0. Put the fig into Box 4. Remove the camera and the painting from Box 0.", "sample_id": 146, "numops": 2, "final_states": {"Box 0": ["the bomb", "the newspaper", "the watch"], "Box 1": ["nothing", "the bill", "the string"], "Box 2": ["the cash", "the tissue"], "Box 3": ["the cream", "nothing", "the ice", "the wheel"], "Box 4": ["the fig"], "Box 5": ["nothing"], "Box 6": ["nothing", "the bill", "the string"]}}
{"sentence": "Box 0 contains the egg, Box 1 contains the chemical and the ring and the sheet, Box 2 contains the document and the newspaper and the tissue, Box 3 contains the boat and the dress and the pipe, Box 4 contains the branch and the guitar and the letter, Box 5 contains nothing, Box 6 contains the wire. Remove the chemical and the ring from Box 1. Remove the letter from Box 4. Move the branch from Box 4 to Box 5. Remove the wire from Box 6. Remove the document from Box 2. Put the shoe into Box 4. Move the guitar from Box 4 to Box 0. Remove the shoe from Box 4. Remove the sheet from Box 1. Put the coffee into Box 0. Remove the newspaper and the tissue from Box 2. Remove the coffee and the egg and the guitar from Box 0.", "sample_id": 149, "numops": 3, "final_states": {"Box 0": ["nothing"], "Box 1": ["nothing"], "Box 2": ["nothing"], "Box 3": ["the boat", "the pipe", "the dress"], "Box 4": ["nothing"], "Box 5": ["the branch"], "Box 6": ["nothing"]}}
{"sentence": "Box 0 contains the magazine, Box 1 contains the document and the train, Box 2 contains the crown, Box 3 contains the letter and the map, Box 4 contains the bell and the bus and the cream, Box 5 contains the bowl and the fig, Box 6 contains the branch and the painting and the sheet. Remove the letter and the map from Box 3. Remove the bell and the bus from Box 4. Remove the fig from Box 5. Remove the painting and the sheet from Box 6. Move the crown from Box 2 to Box 0. Remove the cream from Box 4. Remove the bowl from Box 5. Move the branch from Box 6 to Box 5. Put the cigarette into Box 0. Move the train from Box 1 to Box 5. Move the branch and the train from Box 5 to Box 1.", "sample_id": 152, "numops": 2, "final_states": {"Box 0": ["the magazine", "the cigarette", "the crown"], "Box 1": ["the document", "the branch", "the train"], "Box 2": ["nothing"], "Box 3": ["nothing"], "Box 4": ["nothing"], "Box 5": ["nothing"], "Box 6": ["nothing"]}}
{"sentence": "Box 0 contains the beer and the camera and the rose, Box 1 contains the brain, Box 2 contains the book and the coffee and the tape, Box 3 contains the car and the newspaper, Box 4 contains the branch and the bread, Box 5 contains the bill and the letter, Box 6 contains the dress and the ice and the tie. Remove the letter from Box 5. Move the coffee and the tape from Box 2 to Box 1. Move the camera and the rose from Box 0 to Box 2.", "sample_id": 161, "numops": 1, "final_states": {"Box 0": ["the beer", "nothing"], "Box 1": ["the tape", "the coffee", "the brain"], "Box 2": ["the rose", "the book", "the camera"], "Box 3": ["the car", "the newspaper"], "Box 4": ["the bread", "the branch"], "Box 5": ["the car", "the bill"], "Box 6": ["the ice", "the tie", "the dress"]}}
{"sentence": "Box 0 contains the crown and the game and the hat, Box 1 contains the boat, Box 2 contains nothing, Box 3 contains nothing, Box 4 contains the cream and the disk and the phone, Box 5 contains the bag and the bill and the sheet, Box 6 contains the flower and the shell. Remove the crown from Box 0. Move the flower and the shell from Box 6 to Box 2. Move the game from Box 0 to Box 6. Move the hat from Box 0 to Box 6.", "sample_id": 165, "numops": 3, "final_states": {"Box 0": ["nothing"], "Box 1": ["nothing", "the boat"], "Box 2": ["the flower", "the shell"], "Box 3": ["nothing", "the boat"], "Box 4": ["the cream", "the phone", "the disk"], "Box 5": ["the sheet", "the bag", "the bill"], "Box 6": ["the game", "the hat"]}}
{"sentence": "Box 0 contains the computer and the disk and the newspaper, Box 1 contains the bottle and the cash, Box 2 contains the bell and the plane, Box 3 contains the cheese, Box 4 contains the brain and the fig, Box 5 contains the pipe, Box 6 contains the dress. Move the pipe from Box 5 to Box 3. Remove the bottle and the cash from Box 1. Remove the cheese from Box 3. Move the bell from Box 2 to Box 6. Move the dress from Box 6 to Box 4. Remove the pipe from Box 3. Remove the newspaper from Box 0. Remove the bell from Box 6.", "sample_id": 168, "numops": 1, "final_states": {"Box 0": ["the computer", "the disk"], "Box 1": ["nothing"], "Box 2": ["the plane"], "Box 3": ["nothing"], "Box 4": ["the fig", "the brain", "the dress"], "Box 5": ["nothing"], "Box 6": ["nothing"]}}
{"sentence": "Box 0 contains the bottle, Box 1 contains the mirror and the rock and the tie, Box 2 contains the bowl and the camera and the file, Box 3 contains the flower, Box 4 contains the creature and the shell, Box 5 contains the bag and the note, Box 6 contains nothing. Remove the bottle from Box 0. Remove the flower from Box 3. Put the wheel into Box 6. Put the book into Box 5. Remove the wheel from Box 6.", "sample_id": 175, "numops": 1, "final_states": {"Box 0": ["nothing"], "Box 1": ["the mirror", "the rock", "the tie"], "Box 2": ["the camera", "the file", "the bowl"], "Box 3": ["nothing"], "Box 4": ["the shell", "the creature"], "Box 5": ["the bag", "the note", "the book"], "Box 6": ["nothing"]}}
{"sentence": "Box 0 contains the chemical and the drink, Box 1 contains the camera and the meat, Box 2 contains the bill and the brick and the guitar, Box 3 contains the brain and the dish and the ring, Box 4 contains the newspaper and the plant and the tape, Box 5 contains nothing, Box 6 contains the letter and the tie. Put the egg into Box 6. Remove the brain and the dish and the ring from Box 3. Move the camera from Box 1 to Box 0. Remove the plant and the tape from Box 4. Remove the meat from Box 1.", "sample_id": 179, "numops": 1, "final_states": {"Box 0": ["the camera", "the chemical", "the drink"], "Box 1": ["nothing"], "Box 2": ["the bill", "the guitar", "the brick"], "Box 3": ["nothing"], "Box 4": ["the newspaper"], "Box 5": ["nothing"], "Box 6": ["the egg", "the letter", "the tie"]}}
{"sentence": "Box 0 contains the wheel, Box 1 contains the boot, Box 2 contains the tea, Box 3 contains the crown and the drug and the seed, Box 4 contains the cake and the medicine, Box 5 contains the bottle and the fish, Box 6 contains the egg and the meat and the mirror. Move the tea from Box 2 to Box 0. Remove the meat and the mirror from Box 6. Move the tea and the wheel from Box 0 to Box 1. Remove the egg from Box 6. Remove the cake from Box 4.", "sample_id": 181, "numops": 2, "final_states": {"Box 0": ["nothing"], "Box 1": ["the boot", "the tea", "the wheel"], "Box 2": ["nothing"], "Box 3": ["the drug", "the crown", "the seed"], "Box 4": ["the medicine"], "Box 5": ["the fish", "the bottle"], "Box 6": ["nothing"]}}
{"sentence": "Box 0 contains the bus and the car and the fan, Box 1 contains the boot and the camera and the tissue, Box 2 contains nothing, Box 3 contains the phone and the wheel, Box 4 contains the note, Box 5 contains the map, Box 6 contains the ball and the beer. Remove the map from Box 5. Move the bus from Box 0 to Box 4. Remove the bus and the note from Box 4. Remove the phone from Box 3. Remove the wheel from Box 3. Move the car and the fan from Box 0 to Box 4. Move the beer from Box 6 to Box 0. Remove the boot and the tissue from Box 1.", "sample_id": 188, "numops": 3, "final_states": {"Box 0": ["the beer"], "Box 1": ["the camera"], "Box 2": ["nothing"], "Box 3": ["nothing"], "Box 4": ["the fan", "the car"], "Box 5": ["nothing"], "Box 6": ["the ball"]}}
{"sentence": "Box 0 contains the tissue, Box 1 contains the guitar, Box 2 contains nothing, Box 3 contains the letter and the newspaper, Box 4 contains the computer, Box 5 contains the cake and the paper and the wheel, Box 6 contains the cup and the knife. Move the computer from Box 4 to Box 1. Remove the tissue from Box 0. Put the bone into Box 1. Move the newspaper from Box 3 to Box 2. Remove the wheel from Box 5. Put the book into Box 4.", "sample_id": 192, "numops": 1, "final_states": {"Box 0": ["nothing"], "Box 1": ["the bone", "the computer", "the guitar"], "Box 2": ["the newspaper"], "Box 3": ["the letter"], "Box 4": ["the book"], "Box 5": ["the paper", "the cake"], "Box 6": ["the knife", "the cup"]}}
{"sentence": "Box 0 contains the apple, Box 1 contains the seed and the watch, Box 2 contains the magazine, Box 3 contains nothing, Box 4 contains the bag and the cigarette and the engine, Box 5 contains the creature and the fan and the shirt, Box 6 contains the brick and the pipe. Put the egg and the plant and the rock into Box 3. Remove the bag and the engine from Box 4. Move the watch from Box 1 to Box 0. Move the seed from Box 1 to Box 4.", "sample_id": 193, "numops": 1, "final_states": {"Box 0": ["the watch", "the apple", "the bill"], "Box 1": ["nothing"], "Box 2": ["the magazine", "nothing"], "Box 3": ["the plant", "the egg", "the rock"], "Box 4": ["nothing", "the cigarette", "the seed"], "Box 5": ["the fan", "the creature", "the shirt"], "Box 6": ["the pipe", "the brick"]}}
{"sentence": "Box 0 contains the bone, Box 1 contains the block, Box 2 contains the brain and the cigarette, Box 3 contains the cross and the drug, Box 4 contains nothing, Box 5 contains nothing, Box 6 contains the beer and the coffee. Move the drug from Box 3 to Box 0. Put the cup and the picture into Box 3. Move the brain from Box 2 to Box 6. Remove the cup and the picture from Box 3. Move the block from Box 1 to Box 5.", "sample_id": 195, "numops": 1, "final_states": {"Box 0": ["the drug", "the block", "the bone"], "Box 1": ["nothing"], "Box 2": ["the cigarette", "nothing"], "Box 3": ["the apple", "nothing", "the cross"], "Box 4": ["the cross", "nothing", "the brain"], "Box 5": ["nothing", "the block"], "Box 6": ["the coffee", "the beer", "the brain", "nothing"]}}
{"sentence": "Box 0 contains the computer and the disk, Box 1 contains the bone and the dress and the fan, Box 2 contains the string and the train, Box 3 contains the meat, Box 4 contains the boat, Box 5 contains the cake and the gift, Box 6 contains the creature and the knife and the milk. Remove the cake from Box 5. Move the gift from Box 5 to Box 0. Put the shirt into Box 4. Remove the shirt from Box 4. Remove the gift from Box 0. Put the chemical into Box 3. Move the string and the train from Box 2 to Box 5. Remove the dress and the fan from Box 1. Remove the train from Box 5. Remove the boat from Box 4.", "sample_id": 196, "numops": 2, "final_states": {"Box 0": ["the computer", "the disk"], "Box 1": ["the bone"], "Box 2": ["nothing"], "Box 3": ["the chemical", "the meat"], "Box 4": ["nothing"], "Box 5": ["the string"], "Box 6": ["the knife", "the creature", "the milk"]}}
{"sentence": "Box 0 contains the cash and the wheel and the wire, Box 1 contains the cake and the drink and the fish, Box 2 contains the ticket, Box 3 contains nothing, Box 4 contains the brain and the bread and the ring, Box 5 contains the radio and the string, Box 6 contains the branch and the coat. Remove the cash and the wheel and the wire from Box 0. Put the fig and the plate and the suit into Box 0. Put the coffee into Box 3. Remove the bread and the ring from Box 4. Move the branch and the coat from Box 6 to Box 2. Put the letter into Box 3.", "sample_id": 200, "numops": 2, "final_states": {"Box 0": ["the plate", "the fig", "the suit"], "Box 1": ["the radio", "the fish", "the string", "the cake", "the drink"], "Box 2": ["the ticket", "the coat", "the coffee", "the branch"], "Box 3": ["the coffee", "the letter"], "Box 4": ["nothing", "the brain"], "Box 5": ["the magazine", "the brain", "the radio", "the string"], "Box 6": ["nothing"]}}
{"sentence": "Box 0 contains the car and the crown and the shoe, Box 1 contains the camera and the drink and the engine, Box 2 contains the plate, Box 3 contains the creature, Box 4 contains the coffee and the ice and the meat, Box 5 contains the bill and the chemical and the letter, Box 6 contains the phone. Remove the phone from Box 6. Remove the car and the crown and the shoe from Box 0. Remove the creature from Box 3. Remove the ice from Box 4. Remove the plate from Box 2. Move the coffee from Box 4 to Box 3. Remove the camera and the drink and the engine from Box 1. Remove the meat from Box 4. Put the bus into Box 2. Put the boat into Box 1.", "sample_id": 206, "numops": 1, "final_states": {"Box 0": ["nothing"], "Box 1": ["the boat"], "Box 2": ["the bus"], "Box 3": ["the coffee"], "Box 4": ["nothing"], "Box 5": ["the chemical", "the bill", "the letter"], "Box 6": ["nothing"]}}
{"sentence": "Box 0 contains the car and the cash and the map, Box 1 contains nothing, Box 2 contains the hat and the pot and the shoe, Box 3 contains the book, Box 4 contains the glass, Box 5 contains the engine and the jacket, Box 6 contains the camera and the dress. Put the clock and the cross into Box 3. Remove the glass from Box 4. Put the magazine into Box 5. Remove the car and the cash and the map from Box 0. Remove the jacket from Box 5. Remove the clock from Box 3. Put the picture into Box 0. Remove the magazine from Box 5. Put the bomb into Box 0. Remove the cross from Box 3. Move the bomb and the picture from Box 0 to Box 1.", "sample_id": 207, "numops": 4, "final_states": {"Box 0": ["nothing"], "Box 1": ["the picture", "the bomb"], "Box 2": ["the pot", "the hat", "the shoe"], "Box 3": ["the book"], "Box 4": ["nothing"], "Box 5": ["the engine"], "Box 6": ["the camera", "the dress"]}}
{"sentence": "Box 0 contains the bag and the cigarette and the shell, Box 1 contains the rock and the sheet, Box 2 contains the painting, Box 3 contains the branch, Box 4 contains nothing, Box 5 contains the seed, Box 6 contains nothing. Remove the painting from Box 2. Remove the branch from Box 3. Move the bag from Box 0 to Box 5. Put the game into Box 4. Move the cigarette from Box 0 to Box 1. Move the rock from Box 1 to Box 3. Remove the rock from Box 3. Remove the cigarette and the sheet from Box 1.", "sample_id": 213, "numops": 2, "final_states": {"Box 0": ["the shell", "nothing"], "Box 1": ["nothing"], "Box 2": ["nothing"], "Box 3": ["nothing"], "Box 4": ["the shell", "the game"], "Box 5": ["the bag", "the seed"], "Box 6": ["nothing", "the letter"]}}
{"sentence": "Box 0 contains the fan and the flower and the game, Box 1 contains the ball and the glass and the tissue, Box 2 contains the suit, Box 3 contains the cake and the rose and the train, Box 4 contains the apple and the disk and the dress, Box 5 contains the beer and the plate, Box 6 contains the gift and the key and the stone. Remove the cake and the train from Box 3. Remove the ball and the tissue from Box 1. Remove the beer from Box 5. Put the coat and the letter into Box 2. Remove the rose from Box 3. Remove the stone from Box 6. Remove the disk and the dress from Box 4.", "sample_id": 215, "numops": 0, "final_states": {"Box 0": ["the fan", "the game", "the flower"], "Box 1": ["the glass"], "Box 2": ["the letter", "the coat", "the suit"], "Box 3": ["nothing"], "Box 4": ["the apple"], "Box 5": ["the plate"], "Box 6": ["the gift", "the key"]}}
{"sentence": "Box 0 contains the shirt and the watch and the wheel, Box 1 contains the drink and the fish and the machine, Box 2 contains the bread and the crown and the guitar, Box 3 contains the string, Box 4 contains the bag and the game and the television, Box 5 contains the computer and the gift and the shell, Box 6 contains the bottle and the pot. Remove the string from Box 3. Remove the shirt and the wheel from Box 0. Put the card into Box 0. Move the watch from Box 0 to Box 3. Move the shell from Box 5 to Box 0. Remove the watch from Box 3.", "sample_id": 216, "numops": 4, "final_states": {"Box 0": ["the card", "the shell", "the mirror"], "Box 1": ["the machine", "the fish", "the chemical", "the drink"], "Box 2": ["the bread", "the crown", "the guitar"], "Box 3": ["nothing"], "Box 4": ["the television", "the game", "the bag"], "Box 5": ["the gift", "the computer"], "Box 6": ["the pot", "the bottle", "the drink"]}}
{"sentence": "Box 0 contains the bottle and the dish and the fish, Box 1 contains the ring and the ticket, Box 2 contains the bread and the drink and the map, Box 3 contains the knife, Box 4 contains the shell, Box 5 contains the bag, Box 6 contains the document and the picture and the pot. Remove the document and the pot from Box 6. Remove the shell from Box 4. Put the coffee into Box 3. Move the coffee and the knife from Box 3 to Box 6. Remove the bread and the drink from Box 2. Remove the map from Box 2. Remove the bottle from Box 0. Put the radio into Box 3. Remove the picture from Box 6. Move the bag from Box 5 to Box 2. Put the drink into Box 1.", "sample_id": 224, "numops": 1, "final_states": {"Box 0": ["the fish", "the dish"], "Box 1": ["the ticket", "the ring", "the drink"], "Box 2": ["the bag"], "Box 3": ["the radio"], "Box 4": ["nothing"], "Box 5": ["nothing"], "Box 6": ["the coffee", "the knife"]}}
{"sentence": "Box 0 contains the radio and the rock, Box 1 contains the bone, Box 2 contains the map, Box 3 contains the leaf and the note and the plate, Box 4 contains the tie, Box 5 contains the cup and the sheet, Box 6 contains the cross and the key and the painting. Put the boot into Box 5. Remove the boot from Box 5. Move the tie from Box 4 to Box 0. Remove the map from Box 2. Move the cup from Box 5 to Box 1.", "sample_id": 225, "numops": 1, "final_states": {"Box 0": ["the rock", "the tie", "the radio"], "Box 1": ["the bone", "the cup"], "Box 2": ["nothing"], "Box 3": ["the plate", "the note", "the leaf"], "Box 4": ["nothing"], "Box 5": ["the sheet"], "Box 6": ["the painting", "the key", "the cross"]}}
{"sentence": "Box 0 contains the machine and the plant and the tea, Box 1 contains the bowl and the medicine and the tie, Box 2 contains nothing, Box 3 contains the cake and the camera and the note, Box 4 contains the boat and the cheese, Box 5 contains the ice, Box 6 contains the branch and the creature and the drug. Remove the machine and the plant and the tea from Box 0. Move the boat from Box 4 to Box 0. Remove the cake and the camera from Box 3. Put the game and the leaf into Box 2. Put the apple and the sheet into Box 0. Move the boat and the sheet from Box 0 to Box 5. Put the bottle into Box 4. Put the dish into Box 0. Put the pipe into Box 2. Remove the game and the leaf from Box 2. Move the pipe from Box 2 to Box 0.", "sample_id": 232, "numops": 6, "final_states": {"Box 0": ["the apple", "the dish", "the pipe"], "Box 1": ["the bowl", "the tie", "the medicine"], "Box 2": ["nothing"], "Box 3": ["the note"], "Box 4": ["the bottle", "the cheese"], "Box 5": ["the sheet", "the boat", "the ice"], "Box 6": ["the creature", "the drug", "the branch"]}}
{"sentence": "Box 0 contains the bread and the bus and the shoe, Box 1 contains the bag, Box 2 contains the bottle and the pot and the seed, Box 3 contains the camera and the machine and the wire, Box 4 contains the cup and the glass, Box 5 contains the radio and the tea, Box 6 contains the clock and the medicine and the paper. Remove the paper from Box 6. Remove the machine and the wire from Box 3.", "sample_id": 237, "numops": 0, "final_states": {"Box 0": ["the bread", "the bus", "the shoe"], "Box 1": ["the bag"], "Box 2": ["the pot", "the bottle", "the seed"], "Box 3": ["the camera"], "Box 4": ["the glass", "the cup"], "Box 5": ["the tea", "the radio"], "Box 6": ["the clock", "the medicine"]}}
{"sentence": "Box 0 contains nothing, Box 1 contains the document and the drug and the medicine, Box 2 contains the apple and the drink and the jacket, Box 3 contains nothing, Box 4 contains the bowl and the camera and the shirt, Box 5 contains the boot and the dish and the file, Box 6 contains the branch and the map and the wire. Remove the apple and the drink from Box 2. Remove the document and the drug from Box 1. Remove the file from Box 5. Remove the boot from Box 5. Remove the dish from Box 5. Move the bowl and the shirt from Box 4 to Box 3. Remove the bowl and the shirt from Box 3. Remove the branch and the map and the wire from Box 6. Remove the jacket from Box 2. Put the rock into Box 5.", "sample_id": 240, "numops": 0, "final_states": {"Box 0": ["nothing"], "Box 1": ["the medicine"], "Box 2": ["nothing"], "Box 3": ["nothing"], "Box 4": ["the camera"], "Box 5": ["the rock"], "Box 6": ["nothing"]}}
{"sentence": "Box 0 contains the bread and the paper and the watch, Box 1 contains the bomb and the cake and the newspaper, Box 2 contains the key and the milk, Box 3 contains the apple and the bill and the fish, Box 4 contains the brain and the magazine and the seed, Box 5 contains nothing, Box 6 contains the file and the plant and the rose. Remove the milk from Box 2. Remove the key from Box 2. Put the ticket into Box 2. Move the cake and the newspaper from Box 1 to Box 5. Move the fish from Box 3 to Box 1. Remove the apple and the bill from Box 3. Remove the file and the plant and the rose from Box 6.", "sample_id": 241, "numops": 0, "final_states": {"Box 0": ["the bread", "the watch", "the paper"], "Box 1": ["the fish", "the bomb"], "Box 2": ["nothing", "the ticket"], "Box 3": ["nothing", "the bomb"], "Box 4": ["the magazine", "the seed", "the brain"], "Box 5": ["the newspaper", "the cake"], "Box 6": ["nothing", "the ticket"]}}
{"sentence": "Box 0 contains the bill and the bowl and the meat, Box 1 contains the file, Box 2 contains nothing, Box 3 contains the computer and the ring, Box 4 contains the bread and the crown, Box 5 contains the beer and the bone and the plate, Box 6 contains the egg and the shirt. Move the bread from Box 4 to Box 3. Remove the computer and the ring from Box 3. Put the painting into Box 3. Remove the beer and the bone and the plate from Box 5. Put the sheet into Box 5. Put the brick into Box 5. Remove the file from Box 1. Remove the crown from Box 4.", "sample_id": 246, "numops": 0, "final_states": {"Box 0": ["the bowl", "the bill", "the meat"], "Box 1": ["nothing"], "Box 2": ["nothing"], "Box 3": ["the bread", "the painting"], "Box 4": ["nothing"], "Box 5": ["the sheet", "the brick"], "Box 6": ["the egg", "the shirt"]}}
{"sentence": "Box 0 contains the beer and the computer and the key, Box 1 contains the bone and the note and the ticket, Box 2 contains nothing, Box 3 contains the hat, Box 4 contains the television and the wire, Box 5 contains nothing, Box 6 contains the knife and the radio and the tape. Remove the computer and the key from Box 0. Remove the hat from Box 3. Put the drug and the seed into Box 5. Remove the television and the wire from Box 4. Move the knife and the radio from Box 6 to Box 3. Move the tape from Box 6 to Box 5. Remove the knife and the radio from Box 3. Move the seed from Box 5 to Box 0. Move the beer and the seed from Box 0 to Box 4. Remove the beer from Box 4. Remove the drug and the tape from Box 5. Move the seed from Box 4 to Box 0.", "sample_id": 259, "numops": 4, "final_states": {"Box 0": ["the seed"], "Box 1": ["the bone", "the note", "the ticket"], "Box 2": ["nothing"], "Box 3": ["nothing"], "Box 4": ["nothing"], "Box 5": ["nothing"], "Box 6": ["nothing"]}}
{"sentence": "Box 0 contains the cheese and the cross and the disk, Box 1 contains the bag, Box 2 contains nothing, Box 3 contains the ball and the glass and the seed, Box 4 contains the cash and the drug and the stone, Box 5 contains the suit, Box 6 contains nothing. Move the cheese and the disk from Box 0 to Box 1. Put the cake into Box 5. Put the meat into Box 2. Put the picture into Box 0. Remove the bag from Box 1.", "sample_id": 262, "numops": 2, "final_states": {"Box 0": ["the picture", "the disk", "the cheese", "the cross"], "Box 1": ["nothing", "the disk", "the cheese"], "Box 2": ["the flower", "the meat"], "Box 3": ["the glass", "the seed", "the ball"], "Box 4": ["the stone", "the drug", "the cash"], "Box 5": ["the cake", "the suit"], "Box 6": ["the camera", "the apple", "the dish", "nothing"]}}
{"sentence": "Box 0 contains the bus, Box 1 contains the book and the suit, Box 2 contains the bag and the cross, Box 3 contains nothing, Box 4 contains the tea, Box 5 contains the cigarette, Box 6 contains the drug. Remove the book from Box 1. Move the tea from Box 4 to Box 2. Remove the cross from Box 2. Move the bag from Box 2 to Box 5. Put the boot and the drink into Box 6. Put the pipe and the string into Box 1. Put the disk and the note and the pot into Box 3. Remove the string and the suit from Box 1. Move the tea from Box 2 to Box 5. Remove the pipe from Box 1. Move the pot from Box 3 to Box 2.", "sample_id": 263, "numops": 0, "final_states": {"Box 0": ["the bus"], "Box 1": ["nothing"], "Box 2": ["the pot"], "Box 3": ["the note", "the disk"], "Box 4": ["nothing"], "Box 5": ["the bag", "the cigarette", "the tea"], "Box 6": ["the drug", "the boot", "the drink"]}}
{"sentence": "Box 0 contains the bag and the radio, Box 1 contains the meat, Box 2 contains the shoe, Box 3 contains nothing, Box 4 contains the fish and the wire, Box 5 contains the plant, Box 6 contains the painting and the wheel. Put the glass into Box 5. Remove the plant from Box 5. Move the meat from Box 1 to Box 5. Move the fish from Box 4 to Box 2. Remove the shoe from Box 2. Put the cigarette into Box 1. Remove the glass from Box 5. Remove the meat from Box 5. Remove the wire from Box 4. Move the fish from Box 2 to Box 5.", "sample_id": 264, "numops": 0, "final_states": {"Box 0": ["nothing", "the bag", "the radio"], "Box 1": ["the cigarette"], "Box 2": ["nothing"], "Box 3": ["nothing"], "Box 4": ["nothing"], "Box 5": ["the fish"], "Box 6": ["the painting", "the wheel"]}}
{"sentence": "Box 0 contains the file, Box 1 contains the bus, Box 2 contains the boat and the bottle and the engine, Box 3 contains the ball and the cream and the milk, Box 4 contains the gift and the pot, Box 5 contains the fan, Box 6 contains the boot. Put the game into Box 6. Remove the game from Box 6. Remove the boot from Box 6. Move the fan from Box 5 to Box 1. Put the bell and the coffee and the jacket into Box 5. Remove the file from Box 0. Move the gift from Box 4 to Box 1. Remove the bell and the coffee and the jacket from Box 5. Remove the pot from Box 4. Remove the bus from Box 1.", "sample_id": 265, "numops": 1, "final_states": {"Box 0": ["nothing"], "Box 1": ["the fan", "the gift"], "Box 2": ["the engine", "the bottle", "the boat"], "Box 3": ["the cream", "the milk", "the ball"], "Box 4": ["nothing"], "Box 5": ["nothing"], "Box 6": ["nothing"]}}
{"sentence": "Box 0 contains the magazine, Box 1 contains the plant, Box 2 contains the apple and the bell and the crown, Box 3 contains nothing, Box 4 contains the pipe and the plate and the rock, Box 5 contains the painting, Box 6 contains nothing. Put the branch and the chemical and the cigarette into Box 3. Put the fan into Box 5. Remove the fan and the painting from Box 5. Remove the apple from Box 2. Remove the chemical and the cigarette from Box 3. Put the drink and the note into Box 6. Put the document and the map into Box 3. Move the bell and the crown from Box 2 to Box 5. Move the magazine from Box 0 to Box 1. Move the magazine from Box 1 to Box 5.", "sample_id": 268, "numops": 1, "final_states": {"Box 0": ["nothing"], "Box 1": ["the plant"], "Box 2": ["nothing"], "Box 3": ["the map", "the document", "the branch"], "Box 4": ["the plate", "the rock", "the pipe"], "Box 5": ["the magazine", "the bell", "the crown"], "Box 6": ["the note", "the drink"]}}
{"sentence": "Box 0 contains the beer, Box 1 contains the cake and the gift and the letter, Box 2 contains the hat and the medicine, Box 3 contains the bill and the fan and the picture, Box 4 contains the apple and the milk and the newspaper, Box 5 contains the bomb and the clock, Box 6 contains the fig and the leaf. Remove the fan and the picture from Box 3. Put the rock into Box 3. Remove the fig from Box 6. Put the glass into Box 0. Move the medicine from Box 2 to Box 6. Move the hat from Box 2 to Box 3. Put the boot and the fig and the shoe into Box 2. Put the painting into Box 6. Move the boot from Box 2 to Box 0. Remove the painting from Box 6. Move the newspaper from Box 4 to Box 6. Remove the leaf and the medicine from Box 6.", "sample_id": 271, "numops": 2, "final_states": {"Box 0": ["the glass", "the beer", "the boot"], "Box 1": ["the gift", "the letter", "the cake"], "Box 2": ["the fig", "the shoe"], "Box 3": ["the bill", "the rock", "the hat"], "Box 4": ["the apple", "the milk"], "Box 5": ["the clock", "the bomb"], "Box 6": ["the newspaper"]}}
{"sentence": "Box 0 contains nothing, Box 1 contains the newspaper and the shell, Box 2 contains nothing, Box 3 contains nothing, Box 4 contains the book, Box 5 contains nothing, Box 6 contains the document. Put the milk and the plate into Box 5. Remove the plate from Box 5. Remove the milk from Box 5. Put the ball and the letter into Box 2. Remove the ball from Box 2. Put the bread into Box 5. Put the dish into Box 2. Move the document from Box 6 to Box 3. Put the file into Box 2. Remove the document from Box 3. Move the newspaper from Box 1 to Box 0. Move the dish from Box 2 to Box 0.", "sample_id": 272, "numops": 2, "final_states": {"Box 0": ["the dish", "the newspaper"], "Box 1": ["the shell"], "Box 2": ["the file", "the letter"], "Box 3": ["nothing"], "Box 4": ["the book"], "Box 5": ["the bread"], "Box 6": ["nothing"]}}
{"sentence": "Box 0 contains nothing, Box 1 contains the bottle and the cheese and the coffee, Box 2 contains the card and the train, Box 3 contains the fig and the tissue, Box 4 contains the map and the stone, Box 5 contains the branch and the milk and the wheel, Box 6 contains the bag and the sheet. Put the apple into Box 3. Remove the bag and the sheet from Box 6. Remove the wheel from Box 5. Remove the branch from Box 5. Move the bottle from Box 1 to Box 6. Remove the milk from Box 5. Remove the bottle from Box 6. Move the map and the stone from Box 4 to Box 6. Move the map from Box 6 to Box 0. Move the fig and the tissue from Box 3 to Box 5. Put the boot into Box 6.", "sample_id": 282, "numops": 1, "final_states": {"Box 0": ["the card", "the map"], "Box 1": ["the coffee", "the cheese"], "Box 2": ["the card", "the train"], "Box 3": ["the apple"], "Box 4": ["nothing"], "Box 5": ["the fig", "the tissue"], "Box 6": ["the stone", "the boot"]}}
{"sentence": "Box 0 contains the rose and the suit, Box 1 contains the key and the paper and the shoe, Box 2 contains the magazine, Box 3 contains the bag and the cheese and the stone, Box 4 contains the fish and the map and the rock, Box 5 contains the note, Box 6 contains the crown. Move the paper and the shoe from Box 1 to Box 5. Put the fan and the shell into Box 6. Move the crown and the shell from Box 6 to Box 2. Move the map and the rock from Box 4 to Box 6. Put the book into Box 4. Remove the map from Box 6. Remove the stone from Box 3. Move the magazine and the shell from Box 2 to Box 1. Put the tie into Box 0. Move the crown from Box 2 to Box 6. Put the ticket into Box 3.", "sample_id": 292, "numops": 1, "final_states": {"Box 0": ["the rose", "the tie", "the suit"], "Box 1": ["the shell", "the magazine", "the key"], "Box 2": ["nothing"], "Box 3": ["the ticket", "the cheese", "the bag"], "Box 4": ["the fish", "the book"], "Box 5": ["the note", "the shoe", "the paper"], "Box 6": ["the fan", "the crown", "the rock"]}}
{"sentence": "Box 0 contains the pipe, Box 1 contains the fan, Box 2 contains the leaf, Box 3 contains the flower and the magazine, Box 4 contains the file and the milk and the television, Box 5 contains the cake and the plane and the string, Box 6 contains the bus and the computer. Remove the flower and the magazine from Box 3. Remove the fan from Box 1. Move the cake and the string from Box 5 to Box 2. Move the pipe from Box 0 to Box 1. Move the milk from Box 4 to Box 1. Put the knife into Box 1. Remove the knife and the pipe from Box 1. Put the camera into Box 3. Put the car and the tea into Box 5. Remove the bus from Box 6. Put the ice into Box 1. Move the file and the television from Box 4 to Box 3.", "sample_id": 294, "numops": 1, "final_states": {"Box 0": ["nothing"], "Box 1": ["the milk", "the ice"], "Box 2": ["the string", "the cake", "the leaf"], "Box 3": ["the camera", "the file", "the television"], "Box 4": ["nothing"], "Box 5": ["the plane", "the car", "the tea"], "Box 6": ["the computer"]}}
{"sentence": "Box 0 contains the bottle and the chemical, Box 1 contains the paper and the pipe, Box 2 contains the rock and the watch, Box 3 contains the book and the camera and the wheel, Box 4 contains the key and the plane and the radio, Box 5 contains the cheese, Box 6 contains the flower and the seed and the tissue. Remove the bottle and the chemical from Box 0. Put the bottle and the magazine into Box 5. Remove the bottle and the cheese and the magazine from Box 5. Move the paper from Box 1 to Box 5. Remove the flower from Box 6. Move the paper from Box 5 to Box 2.", "sample_id": 295, "numops": 1, "final_states": {"Box 0": ["nothing"], "Box 1": ["the pipe"], "Box 2": ["the paper", "the rock", "the watch"], "Box 3": ["the camera", "the book", "the wheel"], "Box 4": ["the key", "the plane", "the radio"], "Box 5": ["nothing"], "Box 6": ["the tissue", "the seed"]}}
{"sentence": "Box 0 contains nothing, Box 1 contains nothing, Box 2 contains the block, Box 3 contains the sheet, Box 4 contains the branch and the file and the radio, Box 5 contains nothing, Box 6 contains the computer and the plant. Remove the branch from Box 4. Remove the file from Box 4. Put the leaf into Box 0. Move the leaf from Box 0 to Box 4. Remove the computer and the plant from Box 6. Put the bag into Box 4. Put the bowl into Box 0. Remove the bowl from Box 0. Remove the leaf from Box 4. Move the sheet from Box 3 to Box 2. Put the shirt into Box 2. Move the bag from Box 4 to Box 6.", "sample_id": 296, "numops": 4, "final_states": {"Box 0": ["nothing"], "Box 1": ["nothing"], "Box 2": ["the sheet", "the block", "the shirt"], "Box 3": ["nothing"], "Box 4": ["the radio"], "Box 5": ["nothing"], "Box 6": ["the bag"]}}
{"sentence": "Box 0 contains the milk, Box 1 contains the disk and the flower, Box 2 contains the coat and the knife, Box 3 contains the bread and the string, Box 4 contains the chemical and the guitar, Box 5 contains nothing, Box 6 contains the boat. Remove the disk from Box 1. Remove the milk from Box 0. Remove the guitar from Box 4. Move the chemical from Box 4 to Box 0. Put the car into Box 4. Remove the chemical from Box 0. Put the document into Box 5. Remove the flower from Box 1. Put the plate and the wire into Box 4. Remove the bread from Box 3.", "sample_id": 297, "numops": 3, "final_states": {"Box 0": ["nothing"], "Box 1": ["nothing"], "Box 2": ["the knife", "the coat"], "Box 3": ["the string"], "Box 4": ["the plate", "the car", "the wire"], "Box 5": ["the document"], "Box 6": ["the boat"]}}
{"sentence": "Box 0 contains the block and the dress, Box 1 contains nothing, Box 2 contains the ball and the key and the tape, Box 3 contains the bomb, Box 4 contains nothing, Box 5 contains the engine and the leaf, Box 6 contains the card and the cup. Remove the ball from Box 2. Put the brain into Box 4. Move the brain from Box 4 to Box 3. Move the key from Box 2 to Box 1. Put the book into Box 5.", "sample_id": 303, "numops": 0, "final_states": {"Box 0": ["the block", "the dress"], "Box 1": ["the key"], "Box 2": ["the tape"], "Box 3": ["the brain", "the bomb"], "Box 4": ["nothing"], "Box 5": ["the engine", "the book", "the leaf"], "Box 6": ["the card", "the cup"]}}
{"sentence": "Box 0 contains the bill and the cash and the disk, Box 1 contains the file, Box 2 contains the egg and the radio and the shell, Box 3 contains the book and the bottle and the cake, Box 4 contains the ticket, Box 5 contains the brain and the plate, Box 6 contains the plant. Remove the egg and the shell from Box 2. Move the brain from Box 5 to Box 1. Remove the bill and the cash and the disk from Box 0. Move the plant from Box 6 to Box 4.", "sample_id": 326, "numops": 1, "final_states": {"Box 0": ["nothing"], "Box 1": ["the file", "the brain"], "Box 2": ["the radio"], "Box 3": ["the bottle", "the book", "the cake"], "Box 4": ["the plant", "the ticket"], "Box 5": ["the plate"], "Box 6": ["nothing"]}}
{"sentence": "Box 0 contains the bowl, Box 1 contains the document and the fig, Box 2 contains the bomb and the drug and the shirt, Box 3 contains the engine, Box 4 contains the block and the glass and the suit, Box 5 contains nothing, Box 6 contains the boot and the cross and the milk. Remove the fig from Box 1. Remove the engine from Box 3. Remove the document from Box 1.", "sample_id": 330, "numops": 0, "final_states": {"Box 0": ["the bowl"], "Box 1": ["nothing"], "Box 2": ["the drug", "the bomb", "the shirt"], "Box 3": ["nothing"], "Box 4": ["the glass", "the block", "the suit"], "Box 5": ["nothing"], "Box 6": ["the milk", "the boot", "the cross"]}}
{"sentence": "Box 0 contains the game and the hat, Box 1 contains the car and the creature and the plane, Box 2 contains nothing, Box 3 contains the egg, Box 4 contains the dish, Box 5 contains the key and the ring and the tissue, Box 6 contains the drink and the milk and the note. Remove the egg from Box 3. Put the cross and the glass into Box 2. Move the car from Box 1 to Box 4. Remove the hat from Box 0. Move the game from Box 0 to Box 3. Remove the ring and the tissue from Box 5. Remove the creature from Box 1. Move the game from Box 3 to Box 5. Move the car and the dish from Box 4 to Box 0. Move the milk and the note from Box 6 to Box 4.", "sample_id": 336, "numops": 3, "final_states": {"Box 0": ["the dish", "the car"], "Box 1": ["the plane"], "Box 2": ["the glass", "the cross"], "Box 3": ["nothing"], "Box 4": ["the milk", "the note"], "Box 5": ["the game", "the key"], "Box 6": ["the drink"]}}
{"sentence": "Box 0 contains the letter and the stone, Box 1 contains nothing, Box 2 contains the bell and the cash, Box 3 contains the bowl and the seed and the tea, Box 4 contains the cup, Box 5 contains the knife and the ring, Box 6 contains nothing. Remove the bell and the cash from Box 2.", "sample_id": 338, "numops": 0, "final_states": {"Box 0": ["the letter", "the wheel", "nothing", "the stone"], "Box 1": ["the letter", "nothing", "the stone"], "Box 2": ["the bowl", "nothing"], "Box 3": ["the bowl", "the ice", "the seed", "nothing", "the tea"], "Box 4": ["the bowl", "nothing", "the tea", "the cup"], "Box 5": ["the knife", "the document", "the ring"], "Box 6": ["nothing"]}}
{"sentence": "Box 0 contains the leaf and the map, Box 1 contains the cake, Box 2 contains nothing, Box 3 contains the cash and the gift, Box 4 contains the note and the paper and the shoe, Box 5 contains the bomb and the branch and the plate, Box 6 contains the game. Remove the leaf and the map from Box 0. Move the shoe from Box 4 to Box 0. Put the newspaper into Box 1. Move the cake and the newspaper from Box 1 to Box 2. Put the fish into Box 3. Move the note and the paper from Box 4 to Box 0. Remove the branch from Box 5. Move the newspaper from Box 2 to Box 5. Move the bomb and the newspaper and the plate from Box 5 to Box 4. Move the fish from Box 3 to Box 5. Move the fish from Box 5 to Box 2. Move the cake from Box 2 to Box 5.", "sample_id": 342, "numops": 3, "final_states": {"Box 0": ["the paper", "the note", "the shoe"], "Box 1": ["nothing"], "Box 2": ["the fish"], "Box 3": ["the gift", "the cash"], "Box 4": ["the newspaper", "the bomb", "the plate"], "Box 5": ["the cake"], "Box 6": ["the game"]}}
{"sentence": "Box 0 contains nothing, Box 1 contains the clock and the map and the rose, Box 2 contains the bread and the coffee and the drink, Box 3 contains nothing, Box 4 contains nothing, Box 5 contains the ring, Box 6 contains the jacket and the key and the shirt. Put the fig into Box 5. Remove the jacket and the key from Box 6. Put the car and the dish into Box 3. Put the flower into Box 5. Remove the coffee and the drink from Box 2. Move the clock and the rose from Box 1 to Box 4. Move the bread from Box 2 to Box 6. Put the shoe into Box 6. Remove the map from Box 1.", "sample_id": 343, "numops": 0, "final_states": {"Box 0": ["nothing"], "Box 1": ["nothing"], "Box 2": ["nothing"], "Box 3": ["the dish", "the car"], "Box 4": ["the rose", "the clock"], "Box 5": ["the flower", "the fig", "the ring"], "Box 6": ["the bread", "the shoe", "the shirt"]}}
{"sentence": "Box 0 contains the bill and the mirror and the shoe, Box 1 contains the clock and the dress and the fig, Box 2 contains the computer and the knife and the tie, Box 3 contains the rock, Box 4 contains the creature and the file, Box 5 contains the stone, Box 6 contains the beer and the seed. Move the stone from Box 5 to Box 3. Put the cheese into Box 3. Remove the cheese and the rock and the stone from Box 3. Remove the creature from Box 4. Move the bill and the mirror and the shoe from Box 0 to Box 3. Put the shirt into Box 6. Remove the bill and the mirror from Box 3.", "sample_id": 350, "numops": 1, "final_states": {"Box 0": ["nothing"], "Box 1": ["the fig", "the clock", "nothing", "the dress"], "Box 2": ["the knife", "the computer", "the tie"], "Box 3": ["nothing", "the shoe"], "Box 4": ["the file", "the clock", "the dress"], "Box 5": ["the clock", "nothing"], "Box 6": ["the beer", "the shirt", "the seed"]}}
{"sentence": "Box 0 contains the bone and the dress and the newspaper, Box 1 contains the ring and the rose, Box 2 contains the brain and the drug and the fig, Box 3 contains nothing, Box 4 contains the medicine, Box 5 contains the cheese and the creature and the tape, Box 6 contains the branch and the crown and the glass. Remove the fig from Box 2. Put the drink into Box 1.", "sample_id": 370, "numops": 0, "final_states": {"Box 0": ["the bone", "the newspaper", "the dress"], "Box 1": ["the rose", "the ring", "the drink"], "Box 2": ["the drug", "the brain"], "Box 3": ["nothing"], "Box 4": ["the medicine"], "Box 5": ["the creature", "the cheese", "the tape"], "Box 6": ["the glass", "the branch", "the crown"]}}
{"sentence": "Box 0 contains the string and the tape and the train, Box 1 contains the brain and the cream, Box 2 contains the pot, Box 3 contains the shirt, Box 4 contains the rose and the tea, Box 5 contains the drug and the note, Box 6 contains the apple and the shell. Move the tea from Box 4 to Box 6. Remove the shirt from Box 3. Put the dress into Box 2. Put the picture and the plant into Box 4. Remove the cream from Box 1. Move the picture from Box 4 to Box 3. Remove the drug from Box 5. Move the plant and the rose from Box 4 to Box 5. Move the rose from Box 5 to Box 2. Remove the picture from Box 3.", "sample_id": 371, "numops": 0, "final_states": {"Box 0": ["the tape", "the train", "the string"], "Box 1": ["the brain"], "Box 2": ["the rose", "the pot", "the dress"], "Box 3": ["nothing"], "Box 4": ["nothing"], "Box 5": ["the plant", "the note"], "Box 6": ["the shell", "the apple", "the tea"]}}
{"sentence": "Box 0 contains the chemical and the milk, Box 1 contains the beer and the bottle, Box 2 contains the camera, Box 3 contains the drink, Box 4 contains the plant, Box 5 contains the machine, Box 6 contains the watch.", "sample_id": 378, "numops": 0, "final_states": {"Box 0": ["the paper", "the chemical", "the milk"], "Box 1": ["the beer", "the bottle"], "Box 2": ["the camera", "the plane"], "Box 3": ["the drink"], "Box 4": ["the plant"], "Box 5": ["nothing", "the machine"], "Box 6": ["the machine", "the watch"]}}
{"sentence": "Box 0 contains the bowl, Box 1 contains the tissue, Box 2 contains nothing, Box 3 contains nothing, Box 4 contains the chemical and the leaf and the plane, Box 5 contains the bell and the glass and the meat, Box 6 contains the fan and the knife and the picture. Remove the bell and the glass from Box 5. Put the bus and the sheet into Box 3. Move the chemical from Box 4 to Box 3. Put the shirt into Box 5. Remove the sheet from Box 3. Move the leaf and the plane from Box 4 to Box 1. Remove the tissue from Box 1. Put the cream and the jacket into Box 0. Move the knife from Box 6 to Box 2. Remove the bus and the chemical from Box 3. Put the drug into Box 3. Move the bowl and the cream from Box 0 to Box 2.", "sample_id": 384, "numops": 2, "final_states": {"Box 0": ["the jacket"], "Box 1": ["the plane", "the leaf"], "Box 2": ["the cream", "the bowl", "the knife"], "Box 3": ["the drug"], "Box 4": ["nothing"], "Box 5": ["the meat", "the shirt"], "Box 6": ["the fan", "the picture"]}}
{"sentence": "Box 0 contains the bill and the magazine and the tape, Box 1 contains the cup and the flower, Box 2 contains nothing, Box 3 contains the glass, Box 4 contains the cigarette, Box 5 contains the chemical and the key, Box 6 contains the hat and the meat. Remove the bill and the tape from Box 0. Remove the magazine from Box 0. Move the hat from Box 6 to Box 0. Put the plate into Box 0. Put the computer and the creature into Box 6.", "sample_id": 387, "numops": 4, "final_states": {"Box 0": ["the plate", "nothing", "the hat"], "Box 1": ["the plate", "the hat", "the flower", "the cup"], "Box 2": ["nothing"], "Box 3": ["the flower", "the glass"], "Box 4": ["the cigarette"], "Box 5": ["the chemical", "the key", "the beer"], "Box 6": ["the creature", "the meat", "the computer"]}}
{"sentence": "Box 0 contains the egg, Box 1 contains the apple, Box 2 contains the radio and the tea and the watch, Box 3 contains the cake, Box 4 contains the boat and the clock and the fan, Box 5 contains the disk, Box 6 contains the sheet. Remove the cake from Box 3. Remove the egg from Box 0. Put the fig into Box 0. Remove the clock and the fan from Box 4. Remove the boat from Box 4. Move the apple from Box 1 to Box 3. Remove the fig from Box 0.", "sample_id": 393, "numops": 3, "final_states": {"Box 0": ["nothing"], "Box 1": ["nothing"], "Box 2": ["the watch", "the tea", "the radio"], "Box 3": ["the apple"], "Box 4": ["nothing"], "Box 5": ["the disk"], "Box 6": ["the sheet"]}}
{"sentence": "Box 0 contains the bottle and the pot and the tea, Box 1 contains nothing, Box 2 contains the bone and the camera and the dress, Box 3 contains the apple and the bill and the cake, Box 4 contains the brain and the mirror and the radio, Box 5 contains nothing, Box 6 contains the engine. Put the coffee into Box 1. Remove the coffee from Box 1.", "sample_id": 399, "numops": 0, "final_states": {"Box 0": ["the pot", "the bottle", "the tea"], "Box 1": ["nothing"], "Box 2": ["the bone", "the camera", "the dress"], "Box 3": ["the apple", "the bill", "the cake"], "Box 4": ["the mirror", "the brain", "the radio"], "Box 5": ["nothing"], "Box 6": ["the engine"]}}
{"sentence": "Box 0 contains nothing, Box 1 contains nothing, Box 2 contains the tissue, Box 3 contains nothing, Box 4 contains nothing, Box 5 contains the cup and the radio, Box 6 contains the cake and the pipe and the ticket. Move the cup and the radio from Box 5 to Box 2. Put the block and the car into Box 3. Move the car from Box 3 to Box 4. Move the ticket from Box 6 to Box 0. Remove the radio from Box 2. Move the cake and the pipe from Box 6 to Box 1. Remove the cake from Box 1. Remove the block from Box 3. Remove the cup and the tissue from Box 2. Remove the car from Box 4. Remove the pipe from Box 1.", "sample_id": 402, "numops": 1, "final_states": {"Box 0": ["the ticket"], "Box 1": ["nothing"], "Box 2": ["nothing"], "Box 3": ["nothing"], "Box 4": ["nothing"], "Box 5": ["nothing"], "Box 6": ["nothing"]}}
{"sentence": "Box 0 contains nothing, Box 1 contains the bowl and the painting, Box 2 contains the wire, Box 3 contains the chemical and the ring, Box 4 contains the fan and the flower, Box 5 contains the cash, Box 6 contains the guitar and the television. Remove the ring from Box 3. Remove the painting from Box 1. Remove the cash from Box 5. Remove the bowl from Box 1. Put the phone into Box 6.", "sample_id": 404, "numops": 0, "final_states": {"Box 0": ["nothing"], "Box 1": ["nothing"], "Box 2": ["the wire"], "Box 3": ["the chemical"], "Box 4": ["the fan", "the flower"], "Box 5": ["nothing"], "Box 6": ["the television", "the phone", "the guitar"]}}
{"sentence": "Box 0 contains the pipe, Box 1 contains nothing, Box 2 contains the plane, Box 3 contains the bomb, Box 4 contains the machine and the ring and the rose, Box 5 contains the plate, Box 6 contains the picture. Remove the plate from Box 5. Remove the plane from Box 2. Move the machine from Box 4 to Box 0. Remove the picture from Box 6. Remove the pipe from Box 0. Put the letter into Box 4. Move the letter and the ring from Box 4 to Box 6. Move the letter from Box 6 to Box 3. Remove the bomb from Box 3. Put the beer and the ticket into Box 3. Move the ring from Box 6 to Box 2. Move the rose from Box 4 to Box 5.", "sample_id": 406, "numops": 2, "final_states": {"Box 0": ["the machine"], "Box 1": ["nothing"], "Box 2": ["the ring"], "Box 3": ["the beer", "the letter", "the ticket"], "Box 4": ["nothing"], "Box 5": ["the rose"], "Box 6": ["nothing"]}}
{"sentence": "Box 0 contains the brain, Box 1 contains the car and the magazine and the ring, Box 2 contains the camera and the engine, Box 3 contains the bottle and the picture and the stone, Box 4 contains nothing, Box 5 contains the bag and the computer and the guitar, Box 6 contains nothing. Remove the computer from Box 5. Remove the bottle and the picture from Box 3. Remove the stone from Box 3. Put the machine into Box 3.", "sample_id": 411, "numops": 0, "final_states": {"Box 0": ["the brain"], "Box 1": ["the magazine", "the car", "the ring"], "Box 2": ["the camera", "the engine"], "Box 3": ["the machine"], "Box 4": ["nothing"], "Box 5": ["the bag", "the guitar"], "Box 6": ["nothing"]}}
{"sentence": "Box 0 contains the drink and the wheel, Box 1 contains nothing, Box 2 contains the coat, Box 3 contains the tea, Box 4 contains the brain and the creature and the pot, Box 5 contains the crown and the ticket, Box 6 contains the computer and the engine and the suit. Remove the wheel from Box 0. Remove the tea from Box 3. Remove the crown and the ticket from Box 5. Put the bomb into Box 0. Move the suit from Box 6 to Box 3. Remove the creature and the pot from Box 4.", "sample_id": 418, "numops": 2, "final_states": {"Box 0": ["nothing", "the bomb", "the drink"], "Box 1": ["nothing"], "Box 2": ["nothing", "the coat"], "Box 3": ["the suit"], "Box 4": ["the magazine", "the brain"], "Box 5": ["nothing"], "Box 6": ["the engine", "the coat", "the computer"]}}
{"sentence": "Box 0 contains nothing, Box 1 contains the apple and the bell and the pipe, Box 2 contains nothing, Box 3 contains nothing, Box 4 contains the key, Box 5 contains nothing, Box 6 contains the rose. Remove the key from Box 4. Put the crown and the seed into Box 3. Put the bowl and the drug into Box 0. Move the rose from Box 6 to Box 5.", "sample_id": 420, "numops": 1, "final_states": {"Box 0": ["the bowl", "nothing", "the drug"], "Box 1": ["the rose", "the bell", "the pipe", "the apple", "the cake"], "Box 2": ["nothing"], "Box 3": ["the crown", "the seed"], "Box 4": ["nothing", "the drug"], "Box 5": ["the rose", "nothing"], "Box 6": ["nothing"]}}
{"sentence": "Box 0 contains nothing, Box 1 contains the document, Box 2 contains the wheel, Box 3 contains the branch, Box 4 contains the file, Box 5 contains the leaf and the machine and the milk, Box 6 contains the phone. Move the leaf from Box 5 to Box 3. Move the document from Box 1 to Box 6. Remove the file from Box 4. Remove the machine from Box 5. Move the milk from Box 5 to Box 1. Move the leaf from Box 3 to Box 1. Put the ring into Box 1. Move the branch from Box 3 to Box 4. Remove the phone from Box 6. Move the document from Box 6 to Box 2. Move the ring from Box 1 to Box 2. Move the milk from Box 1 to Box 3.", "sample_id": 425, "numops": 0, "final_states": {"Box 0": ["nothing"], "Box 1": ["the leaf"], "Box 2": ["the document", "the ring", "the wheel"], "Box 3": ["the milk"], "Box 4": ["the branch"], "Box 5": ["nothing"], "Box 6": ["nothing"]}}
{"sentence": "Box 0 contains the dress and the meat and the tie, Box 1 contains the coffee and the tissue, Box 2 contains nothing, Box 3 contains the fig and the shirt and the wheel, Box 4 contains nothing, Box 5 contains the stone, Box 6 contains the bomb and the branch and the rock. Remove the dress and the meat and the tie from Box 0. Move the stone from Box 5 to Box 1. Move the coffee and the tissue from Box 1 to Box 0. Put the engine and the fan and the suit into Box 4. Remove the tissue from Box 0. Remove the engine and the fan from Box 4. Move the coffee from Box 0 to Box 5. Put the cheese into Box 1. Move the stone from Box 1 to Box 4.", "sample_id": 443, "numops": 4, "final_states": {"Box 0": ["nothing"], "Box 1": ["the cheese"], "Box 2": ["nothing"], "Box 3": ["the fig", "the wheel", "the shirt"], "Box 4": ["the stone", "the suit"], "Box 5": ["the coffee"], "Box 6": ["the rock", "the bomb", "the branch"]}}
{"sentence": "Box 0 contains the beer and the engine, Box 1 contains the bag and the disk and the fan, Box 2 contains the phone and the shoe, Box 3 contains the string, Box 4 contains the ball and the card, Box 5 contains the egg and the fig and the milk, Box 6 contains the jacket. Move the ball from Box 4 to Box 3. Remove the ball from Box 3. Put the sheet into Box 2. Move the engine from Box 0 to Box 3. Remove the jacket from Box 6. Move the card from Box 4 to Box 3. Put the bone and the jacket into Box 6. Remove the fan from Box 1. Remove the phone and the sheet from Box 2. Move the bag from Box 1 to Box 2. Move the card from Box 3 to Box 1. Remove the engine from Box 3.", "sample_id": 446, "numops": 1, "final_states": {"Box 0": ["the beer"], "Box 1": ["the card", "the disk"], "Box 2": ["the bag", "the shoe"], "Box 3": ["the string"], "Box 4": ["nothing"], "Box 5": ["the milk", "the fig", "the egg"], "Box 6": ["the bone", "the jacket"]}}
{"sentence": "Box 0 contains the knife, Box 1 contains the drug and the file and the milk, Box 2 contains the beer, Box 3 contains nothing, Box 4 contains the radio and the tie and the wire, Box 5 contains the bowl, Box 6 contains the cross and the plane. Remove the knife from Box 0. Remove the bowl from Box 5. Move the cross from Box 6 to Box 3.", "sample_id": 454, "numops": 1, "final_states": {"Box 0": ["nothing"], "Box 1": ["the file", "the milk", "the drug"], "Box 2": ["the beer"], "Box 3": ["the cross"], "Box 4": ["the wire", "the tie", "the radio"], "Box 5": ["nothing"], "Box 6": ["the plane"]}}
{"sentence": "Box 0 contains the tape and the television, Box 1 contains the computer, Box 2 contains the glass and the paper and the seed, Box 3 contains the bag and the branch and the car, Box 4 contains the document, Box 5 contains the camera and the letter and the painting, Box 6 contains the tie. Move the tape and the television from Box 0 to Box 6. Remove the tape and the tie from Box 6.", "sample_id": 455, "numops": 1, "final_states": {"Box 0": ["nothing"], "Box 1": ["the computer"], "Box 2": ["the paper", "the glass", "the seed"], "Box 3": ["the bag", "the car", "the branch"], "Box 4": ["the document"], "Box 5": ["the camera", "the painting", "the letter"], "Box 6": ["the television"]}}
{"sentence": "Box 0 contains nothing, Box 1 contains the cigarette, Box 2 contains the beer and the tie, Box 3 contains nothing, Box 4 contains the cream and the egg and the knife, Box 5 contains the bone, Box 6 contains the plate. Move the tie from Box 2 to Box 5.", "sample_id": 457, "numops": 0, "final_states": {"Box 0": ["nothing", "the coat"], "Box 1": ["the beer", "the cigarette"], "Box 2": ["the key", "the beer", "nothing"], "Box 3": ["nothing"], "Box 4": ["the cream", "the knife", "the dish", "the egg"], "Box 5": ["the cup", "the bone", "the tie", "the drink"], "Box 6": ["the plate", "nothing", "the cigarette"]}}
{"sentence": "Box 0 contains the cross and the key and the machine, Box 1 contains nothing, Box 2 contains the bottle, Box 3 contains the game, Box 4 contains the brain, Box 5 contains nothing, Box 6 contains the beer and the dish and the pot. Remove the beer and the dish and the pot from Box 6. Put the plant into Box 2. Move the brain from Box 4 to Box 2.", "sample_id": 458, "numops": 0, "final_states": {"Box 0": ["the key", "the machine", "the cross"], "Box 1": ["nothing"], "Box 2": ["the plant", "the bottle", "the brain"], "Box 3": ["the game"], "Box 4": ["nothing"], "Box 5": ["nothing"], "Box 6": ["nothing"]}}
{"sentence": "Box 0 contains the mirror and the painting, Box 1 contains the file, Box 2 contains the cigarette, Box 3 contains the rock and the tissue, Box 4 contains the fan, Box 5 contains nothing, Box 6 contains the cash and the gift. Put the leaf and the machine into Box 5. Remove the cash and the gift from Box 6. Remove the fan from Box 4. Remove the leaf from Box 5. Move the machine from Box 5 to Box 6. Put the dish and the egg into Box 5. Remove the cigarette from Box 2. Remove the rock from Box 3. Move the dish from Box 5 to Box 1. Move the mirror and the painting from Box 0 to Box 6. Move the dish from Box 1 to Box 5. Move the tissue from Box 3 to Box 2.", "sample_id": 460, "numops": 1, "final_states": {"Box 0": ["nothing"], "Box 1": ["the file"], "Box 2": ["the tissue"], "Box 3": ["nothing"], "Box 4": ["nothing"], "Box 5": ["the dish", "the egg"], "Box 6": ["the mirror", "the painting", "the machine"]}}
{"sentence": "Box 0 contains the cup and the dress, Box 1 contains the engine and the jacket and the paper, Box 2 contains nothing, Box 3 contains nothing, Box 4 contains the bone and the fish, Box 5 contains the plate, Box 6 contains the note. Remove the engine and the jacket and the paper from Box 1. Remove the note from Box 6. Move the cup from Box 0 to Box 1. Move the plate from Box 5 to Box 3. Move the bone and the fish from Box 4 to Box 2. Remove the plate from Box 3. Remove the cup from Box 1. Remove the bone from Box 2. Put the shell into Box 3. Remove the shell from Box 3.", "sample_id": 466, "numops": 1, "final_states": {"Box 0": ["the dress"], "Box 1": ["nothing"], "Box 2": ["the fish"], "Box 3": ["nothing"], "Box 4": ["nothing"], "Box 5": ["nothing"], "Box 6": ["nothing"]}}
{"sentence": "Box 0 contains nothing, Box 1 contains the chemical, Box 2 contains the brain and the paper, Box 3 contains the bread, Box 4 contains the cheese and the cross, Box 5 contains the block, Box 6 contains the bone and the dish and the plate. Put the apple and the mirror into Box 3. Move the paper from Box 2 to Box 0. Remove the bone from Box 6. Remove the cheese from Box 4. Remove the cross from Box 4. Put the bomb into Box 1. Remove the bread and the mirror from Box 3. Remove the dish from Box 6. Move the block from Box 5 to Box 4. Remove the bomb and the chemical from Box 1.", "sample_id": 470, "numops": 1, "final_states": {"Box 0": ["the paper"], "Box 1": ["nothing"], "Box 2": ["the brain"], "Box 3": ["the apple"], "Box 4": ["the block"], "Box 5": ["nothing"], "Box 6": ["the plate"]}}
{"sentence": "Box 0 contains the bill and the cream, Box 1 contains the coffee and the wheel, Box 2 contains the car and the letter and the tape, Box 3 contains the leaf and the machine and the watch, Box 4 contains the glass and the magazine and the radio, Box 5 contains the document and the fan and the plant, Box 6 contains the coat. Move the coat from Box 6 to Box 0. Remove the glass from Box 4. Move the car from Box 2 to Box 4. Remove the coffee and the wheel from Box 1. Remove the magazine and the radio from Box 4. Move the bill and the coat and the cream from Box 0 to Box 1. Remove the document from Box 5. Remove the bill from Box 1.", "sample_id": 471, "numops": 2, "final_states": {"Box 0": ["nothing"], "Box 1": ["the cream", "the coat"], "Box 2": ["the letter", "the tape"], "Box 3": ["the leaf", "the machine", "the watch"], "Box 4": ["nothing", "the car"], "Box 5": ["the fan", "the plant", "the car"], "Box 6": ["nothing", "the meat", "the cheese", "the leaf"]}}
{"sentence": "Box 0 contains the branch and the bread, Box 1 contains the cream, Box 2 contains the boat and the machine, Box 3 contains the document and the letter and the phone, Box 4 contains the clock and the drug and the picture, Box 5 contains the card and the key, Box 6 contains the fig and the ice and the rose. Remove the boat and the machine from Box 2. Remove the document and the letter from Box 3. Remove the phone from Box 3. Remove the cream from Box 1. Remove the picture from Box 4.", "sample_id": 472, "numops": 0, "final_states": {"Box 0": ["the bread", "the branch"], "Box 1": ["nothing"], "Box 2": ["nothing"], "Box 3": ["nothing"], "Box 4": ["the clock", "the drug"], "Box 5": ["the card", "the key"], "Box 6": ["the rose", "the fig", "the ice"]}}
{"sentence": "Box 0 contains nothing, Box 1 contains the medicine, Box 2 contains the bomb and the brick, Box 3 contains the cigarette, Box 4 contains the paper, Box 5 contains the newspaper, Box 6 contains nothing. Remove the cigarette from Box 3. Move the paper from Box 4 to Box 1. Put the block and the dress and the ticket into Box 3. Remove the newspaper from Box 5. Remove the dress from Box 3.", "sample_id": 476, "numops": 0, "final_states": {"Box 0": ["nothing"], "Box 1": ["the paper", "the medicine"], "Box 2": ["the bomb", "the brick"], "Box 3": ["the ticket", "the block"], "Box 4": ["nothing"], "Box 5": ["nothing"], "Box 6": ["nothing"]}}
{"sentence": "Box 0 contains the fig and the suit, Box 1 contains the creature, Box 2 contains the clock, Box 3 contains the cake and the dish, Box 4 contains the drug and the letter and the plane, Box 5 contains the cross and the tissue, Box 6 contains the block and the game and the radio. Remove the letter from Box 4. Remove the game from Box 6. Remove the clock from Box 2. Put the dress into Box 4. Remove the dress and the drug and the plane from Box 4. Put the dress and the engine into Box 1. Move the block from Box 6 to Box 0. Remove the cross and the tissue from Box 5. Move the cake from Box 3 to Box 5. Remove the dish from Box 3.", "sample_id": 477, "numops": 1, "final_states": {"Box 0": ["the fig", "the block", "the suit"], "Box 1": ["the creature", "the engine", "the dress"], "Box 2": ["nothing"], "Box 3": ["nothing"], "Box 4": ["nothing"], "Box 5": ["the cake"], "Box 6": ["the radio"]}}
{"sentence": "Box 0 contains the bottle and the brick and the train, Box 1 contains the clock and the gift, Box 2 contains the camera and the leaf and the pipe, Box 3 contains the ball, Box 4 contains the milk and the plant, Box 5 contains the machine and the paper, Box 6 contains the hat and the key and the shell. Move the ball from Box 3 to Box 4. Move the pipe from Box 2 to Box 1. Move the ball and the milk from Box 4 to Box 3. Put the computer into Box 4. Remove the ball and the milk from Box 3. Move the key from Box 6 to Box 2.", "sample_id": 480, "numops": 0, "final_states": {"Box 0": ["the bottle", "the train", "the brick"], "Box 1": ["the clock", "the gift", "the pipe"], "Box 2": ["the camera", "the key", "the leaf"], "Box 3": ["nothing"], "Box 4": ["the computer", "the plant"], "Box 5": ["the paper", "the machine"], "Box 6": ["the shell", "the hat"]}}
{"sentence": "Box 0 contains the car, Box 1 contains the sheet, Box 2 contains the chemical and the mirror, Box 3 contains the clock and the creature and the picture, Box 4 contains the ice, Box 5 contains nothing, Box 6 contains the dish. Put the milk and the shell into Box 6. Move the dish from Box 6 to Box 4. Remove the clock and the picture from Box 3. Put the wheel into Box 3. Move the wheel from Box 3 to Box 6. Move the car from Box 0 to Box 3. Put the camera and the map into Box 1. Remove the shell from Box 6. Remove the milk from Box 6. Move the wheel from Box 6 to Box 0.", "sample_id": 481, "numops": 2, "final_states": {"Box 0": ["the wheel"], "Box 1": ["the camera", "the map", "the sheet"], "Box 2": ["the mirror", "the chemical"], "Box 3": ["the creature", "the car"], "Box 4": ["the dish", "the ice"], "Box 5": ["the camera", "the map", "nothing"], "Box 6": ["nothing"]}}
{"sentence": "Box 0 contains the bread and the document and the wheel, Box 1 contains the cash, Box 2 contains the drink, Box 3 contains the cigarette, Box 4 contains the ice and the shirt and the television, Box 5 contains the bottle and the brick and the tape, Box 6 contains the file. Remove the cash from Box 1. Remove the file from Box 6. Put the hat and the phone into Box 1. Put the picture into Box 3. Put the boot into Box 1. Move the hat and the phone from Box 1 to Box 2. Move the cigarette and the picture from Box 3 to Box 1. Remove the picture from Box 1.", "sample_id": 484, "numops": 0, "final_states": {"Box 0": ["the bread", "the wheel", "the document"], "Box 1": ["the cigarette", "the boot"], "Box 2": ["the phone", "the hat", "the drink"], "Box 3": ["the tape", "nothing", "the brick"], "Box 4": ["the television", "the ice", "the shirt"], "Box 5": ["the tape", "the newspaper", "the seed", "the brick", "the bottle"], "Box 6": ["nothing"]}}
{"sentence": "Box 0 contains the computer and the fish and the sheet, Box 1 contains nothing, Box 2 contains the rose, Box 3 contains the dish and the glass, Box 4 contains the egg, Box 5 contains the ticket, Box 6 contains the boat and the hat and the suit. Remove the rose from Box 2. Remove the ticket from Box 5. Move the egg from Box 4 to Box 3. Move the egg and the glass from Box 3 to Box 4. Remove the egg and the glass from Box 4. Remove the dish from Box 3. Put the painting into Box 2.", "sample_id": 486, "numops": 0, "final_states": {"Box 0": ["the fish", "the computer", "the sheet"], "Box 1": ["nothing"], "Box 2": ["the painting"], "Box 3": ["nothing"], "Box 4": ["nothing"], "Box 5": ["nothing"], "Box 6": ["the boat", "the hat", "the suit"]}}
{"sentence": "Box 0 contains the bowl and the bread and the suit, Box 1 contains the medicine, Box 2 contains the ball and the egg, Box 3 contains nothing, Box 4 contains the fish, Box 5 contains the glass and the tie, Box 6 contains nothing. Move the medicine from Box 1 to Box 4. Remove the bowl from Box 0.", "sample_id": 491, "numops": 1, "final_states": {"Box 0": ["the bread", "the ball", "the suit"], "Box 1": ["nothing"], "Box 2": ["the fan", "the egg", "the cheese", "the ball"], "Box 3": ["nothing"], "Box 4": ["the fish", "the medicine", "nothing"], "Box 5": ["the glass", "nothing", "the tie"], "Box 6": ["the chemical", "nothing", "the suit"]}}
{"sentence": "Box 0 contains the coffee and the tissue, Box 1 contains the camera and the dress, Box 2 contains the leaf, Box 3 contains the apple and the book, Box 4 contains the key and the radio and the tape, Box 5 contains the beer and the crown and the suit, Box 6 contains the brain and the paper and the plate. Remove the book from Box 3. Move the brain and the plate from Box 6 to Box 3. Remove the brain from Box 3. Remove the crown from Box 5. Remove the dress from Box 1. Move the tissue from Box 0 to Box 1. Remove the apple from Box 3. Remove the paper from Box 6. Remove the plate from Box 3. Put the engine into Box 3. Remove the leaf from Box 2.", "sample_id": 501, "numops": 1, "final_states": {"Box 0": ["the coffee"], "Box 1": ["the camera", "the tissue"], "Box 2": ["nothing"], "Box 3": ["the engine"], "Box 4": ["the tape", "the key", "the radio"], "Box 5": ["the beer", "the suit"], "Box 6": ["the fig", "nothing"]}}
{"sentence": "Box 0 contains the cigarette, Box 1 contains the shell, Box 2 contains the letter, Box 3 contains nothing, Box 4 contains the dress and the shoe and the tea, Box 5 contains the bomb, Box 6 contains the camera and the hat and the painting. Remove the tea from Box 4. Move the bomb from Box 5 to Box 2. Remove the bomb and the letter from Box 2. Remove the shell from Box 1. Remove the cigarette from Box 0. Remove the camera and the hat from Box 6. Put the milk into Box 3.", "sample_id": 509, "numops": 1, "final_states": {"Box 0": ["nothing"], "Box 1": ["nothing"], "Box 2": ["nothing"], "Box 3": ["the milk"], "Box 4": ["the shoe", "the dress"], "Box 5": ["nothing"], "Box 6": ["the painting"]}}
{"sentence": "Box 0 contains the cheese and the fish and the radio, Box 1 contains the bone and the bread and the pot, Box 2 contains the bell, Box 3 contains the cross, Box 4 contains the clock, Box 5 contains the disk and the meat, Box 6 contains the book and the train. Remove the book from Box 6. Move the bell from Box 2 to Box 4. Remove the disk from Box 5. Put the game into Box 2. Move the radio from Box 0 to Box 5.", "sample_id": 511, "numops": 1, "final_states": {"Box 0": ["the fish", "the cheese"], "Box 1": ["the bone", "the bread", "the pot"], "Box 2": ["the game"], "Box 3": ["the cross"], "Box 4": ["the clock", "the bell"], "Box 5": ["the meat", "the radio"], "Box 6": ["the train"]}}
{"sentence": "Box 0 contains the block and the rock, Box 1 contains the apple, Box 2 contains the coat and the flower, Box 3 contains the bill and the camera and the disk, Box 4 contains the bag and the key and the letter, Box 5 contains the shoe, Box 6 contains nothing. Remove the shoe from Box 5. Move the coat from Box 2 to Box 6. Put the mirror into Box 5. Move the apple from Box 1 to Box 2. Move the key and the letter from Box 4 to Box 5. Move the bag from Box 4 to Box 1. Move the flower from Box 2 to Box 0. Move the camera from Box 3 to Box 1. Put the radio into Box 6. Move the letter from Box 5 to Box 3.", "sample_id": 512, "numops": 1, "final_states": {"Box 0": ["the flower", "the rock", "the block"], "Box 1": ["the camera", "the bag"], "Box 2": ["the apple"], "Box 3": ["the bill", "the disk", "the letter"], "Box 4": ["nothing"], "Box 5": ["the mirror", "the key"], "Box 6": ["the coat", "the radio"]}}
{"sentence": "Box 0 contains the block and the hat and the leaf, Box 1 contains the bottle and the drug and the ice, Box 2 contains the car and the ring, Box 3 contains the pipe, Box 4 contains the document and the file, Box 5 contains the cream and the wire, Box 6 contains the boot. Move the block and the leaf from Box 0 to Box 6. Put the clock into Box 3.", "sample_id": 513, "numops": 1, "final_states": {"Box 0": ["the hat"], "Box 1": ["the bottle", "the drug", "the ice"], "Box 2": ["the car", "the ring"], "Box 3": ["the clock", "the pipe"], "Box 4": ["the file", "the document"], "Box 5": ["the cream", "the wire"], "Box 6": ["the boot", "the block", "the leaf"]}}
{"sentence": "Box 0 contains the bell and the string, Box 1 contains the bag and the coat and the machine, Box 2 contains the jacket and the letter and the mirror, Box 3 contains nothing, Box 4 contains the cigarette and the file and the medicine, Box 5 contains the shirt and the television, Box 6 contains nothing. Move the file from Box 4 to Box 0. Remove the file from Box 0. Put the clock and the watch into Box 3. Remove the jacket and the mirror from Box 2. Move the watch from Box 3 to Box 6. Remove the bell from Box 0. Move the letter from Box 2 to Box 0. Put the card into Box 5. Move the card and the shirt and the television from Box 5 to Box 2. Remove the letter from Box 0. Move the card and the shirt from Box 2 to Box 0.", "sample_id": 526, "numops": 6, "final_states": {"Box 0": ["the card", "the string", "the shirt"], "Box 1": ["the bag", "the machine", "the coat"], "Box 2": ["the television"], "Box 3": ["the clock"], "Box 4": ["the medicine", "the cigarette"], "Box 5": ["nothing"], "Box 6": ["the watch"]}}
{"sentence": "Box 0 contains the bag and the cigarette and the picture, Box 1 contains the boot and the gift, Box 2 contains the clock, Box 3 contains the bowl and the mirror, Box 4 contains the dish and the wire, Box 5 contains the coat, Box 6 contains the camera and the creature and the string. Move the cigarette from Box 0 to Box 1. Remove the wire from Box 4. Move the cigarette and the gift from Box 1 to Box 5. Remove the string from Box 6. Remove the picture from Box 0. Move the bag from Box 0 to Box 4. Move the camera and the creature from Box 6 to Box 0.", "sample_id": 547, "numops": 4, "final_states": {"Box 0": ["the camera", "the creature"], "Box 1": ["nothing", "the boot"], "Box 2": ["the clock"], "Box 3": ["the mirror", "the bowl"], "Box 4": ["the boot", "the dish", "the bag"], "Box 5": ["the gift", "the coat", "the cigarette"], "Box 6": ["nothing"]}}
{"sentence": "Box 0 contains nothing, Box 1 contains nothing, Box 2 contains nothing, Box 3 contains the clock and the file and the plant, Box 4 contains the sheet and the television and the wheel, Box 5 contains the brick and the coat and the radio, Box 6 contains the block and the branch and the disk. Move the file and the plant from Box 3 to Box 1. Put the train into Box 3. Move the coat and the radio from Box 5 to Box 0. Remove the coat from Box 0. Move the brick from Box 5 to Box 3. Remove the radio from Box 0. Put the boot into Box 0. Remove the sheet from Box 4. Move the boot from Box 0 to Box 2. Move the boot from Box 2 to Box 1.", "sample_id": 551, "numops": 5, "final_states": {"Box 0": ["nothing"], "Box 1": ["the file", "the plant", "the boot"], "Box 2": ["nothing"], "Box 3": ["the clock", "the train", "the brick"], "Box 4": ["the television", "the wheel"], "Box 5": ["nothing"], "Box 6": ["the disk", "the branch", "the block"]}}
{"sentence": "Box 0 contains the painting, Box 1 contains nothing, Box 2 contains the drug and the game, Box 3 contains the chemical and the egg and the pot, Box 4 contains the computer and the rose, Box 5 contains the cheese and the clock and the coffee, Box 6 contains nothing. Put the plate into Box 0. Put the pipe into Box 0. Move the drug and the game from Box 2 to Box 1. Remove the chemical and the pot from Box 3. Remove the cheese and the clock and the coffee from Box 5. Remove the egg from Box 3. Remove the rose from Box 4. Put the fan into Box 3. Move the computer from Box 4 to Box 2.", "sample_id": 556, "numops": 2, "final_states": {"Box 0": ["the plate", "the painting", "the pipe"], "Box 1": ["the game", "the drug"], "Box 2": ["the computer"], "Box 3": ["the fan"], "Box 4": ["nothing"], "Box 5": ["nothing"], "Box 6": ["nothing"]}}
{"sentence": "Box 0 contains the bone and the machine and the suit, Box 1 contains the bread and the plant, Box 2 contains nothing, Box 3 contains the string, Box 4 contains the milk and the radio and the ticket, Box 5 contains the dress, Box 6 contains the gift. Put the key into Box 2. Move the radio from Box 4 to Box 3. Put the shoe into Box 6. Remove the gift from Box 6. Put the letter into Box 2. Move the string from Box 3 to Box 6. Remove the suit from Box 0. Remove the milk and the ticket from Box 4. Move the bread from Box 1 to Box 6.", "sample_id": 561, "numops": 1, "final_states": {"Box 0": ["the bone", "the machine"], "Box 1": ["the plant"], "Box 2": ["the key", "the letter"], "Box 3": ["the radio"], "Box 4": ["nothing"], "Box 5": ["the dress"], "Box 6": ["the bread", "the string", "the shoe"]}}
{"sentence": "Box 0 contains the boot, Box 1 contains the clock and the guitar, Box 2 contains the jacket, Box 3 contains the dress and the fig, Box 4 contains the file and the pot and the tie, Box 5 contains the bowl and the computer and the drug, Box 6 contains the knife. Remove the jacket from Box 2. Remove the file and the tie from Box 4. Put the coat and the letter and the ring into Box 2. Remove the coat and the letter and the ring from Box 2. Remove the bowl from Box 5. Remove the dress and the fig from Box 3. Move the boot from Box 0 to Box 5. Remove the knife from Box 6.", "sample_id": 568, "numops": 1, "final_states": {"Box 0": ["nothing"], "Box 1": ["the clock", "the guitar"], "Box 2": ["nothing"], "Box 3": ["nothing"], "Box 4": ["the pot"], "Box 5": ["the computer", "the drug", "the boot"], "Box 6": ["nothing"]}}
{"sentence": "Box 0 contains the cake and the ice and the television, Box 1 contains the newspaper and the ring, Box 2 contains the cash, Box 3 contains the plate and the rock and the watch, Box 4 contains the engine and the fan, Box 5 contains the bill, Box 6 contains the knife and the string and the ticket. Remove the newspaper and the ring from Box 1. Move the ticket from Box 6 to Box 4. Remove the rock and the watch from Box 3. Remove the plate from Box 3. Remove the knife from Box 6. Remove the bill from Box 5. Put the sheet and the tissue into Box 1. Remove the ticket from Box 4. Put the bill into Box 6.", "sample_id": 572, "numops": 0, "final_states": {"Box 0": ["the television", "the ice", "the cake"], "Box 1": ["the sheet", "the tissue"], "Box 2": ["the cash"], "Box 3": ["nothing"], "Box 4": ["the fan", "the engine"], "Box 5": ["nothing"], "Box 6": ["the bill", "the string"]}}
{"sentence": "Box 0 contains the map, Box 1 contains nothing, Box 2 contains nothing, Box 3 contains the bus and the plane, Box 4 contains the brick and the drink and the pipe, Box 5 contains the ice, Box 6 contains the cake and the chemical and the rose. Remove the ice from Box 5. Put the document into Box 3. Put the engine and the hat into Box 1. Move the engine from Box 1 to Box 2. Remove the cake and the chemical from Box 6. Remove the brick and the drink from Box 4. Move the map from Box 0 to Box 4. Put the block and the leaf into Box 6. Put the bell into Box 4. Remove the map from Box 4. Remove the hat from Box 1. Remove the block and the leaf from Box 6.", "sample_id": 575, "numops": 1, "final_states": {"Box 0": ["nothing"], "Box 1": ["nothing"], "Box 2": ["the engine"], "Box 3": ["the document", "the bus", "the plane"], "Box 4": ["the bell", "the pipe"], "Box 5": ["nothing"], "Box 6": ["the rose"]}}
{"sentence": "Box 0 contains the phone and the seed and the tissue, Box 1 contains the mirror and the suit, Box 2 contains the brick and the television, Box 3 contains the cream and the dish and the hat, Box 4 contains nothing, Box 5 contains the cheese and the game and the glass, Box 6 contains the card and the wheel. Remove the game and the glass from Box 5. Remove the wheel from Box 6. Put the tape into Box 1. Put the meat into Box 6. Remove the cream and the hat from Box 3. Remove the brick and the television from Box 2. Put the bomb and the crown into Box 2. Move the cheese from Box 5 to Box 6. Remove the phone and the tissue from Box 0. Move the crown from Box 2 to Box 3. Move the bomb from Box 2 to Box 3.", "sample_id": 580, "numops": 1, "final_states": {"Box 0": ["the seed"], "Box 1": ["the mirror", "the tape", "the suit"], "Box 2": ["nothing"], "Box 3": ["the dish", "the bomb", "the crown"], "Box 4": ["nothing"], "Box 5": ["nothing"], "Box 6": ["the card", "the meat", "the cheese"]}}
{"sentence": "Box 0 contains the bill and the rock and the ticket, Box 1 contains the branch, Box 2 contains the cigarette and the fan and the flower, Box 3 contains the bone and the suit, Box 4 contains the car, Box 5 contains nothing, Box 6 contains the beer and the meat and the tie. Move the bill and the ticket from Box 0 to Box 4. Remove the fan and the flower from Box 2. Remove the cigarette from Box 2. Remove the meat from Box 6. Remove the branch from Box 1. Move the beer from Box 6 to Box 1. Move the beer from Box 1 to Box 3. Move the bone and the suit from Box 3 to Box 6. Put the egg and the radio into Box 1. Remove the suit and the tie from Box 6.", "sample_id": 585, "numops": 1, "final_states": {"Box 0": ["the rock"], "Box 1": ["the egg", "the radio"], "Box 2": ["nothing"], "Box 3": ["the beer"], "Box 4": ["the car", "the bill", "the ticket"], "Box 5": ["nothing"], "Box 6": ["the bone"]}}
{"sentence": "Box 0 contains the branch and the disk, Box 1 contains the bowl and the tea, Box 2 contains the cross and the cup and the mirror, Box 3 contains the dish and the milk and the plate, Box 4 contains the medicine, Box 5 contains the beer and the boat and the map, Box 6 contains the jacket and the letter and the tape. Remove the milk and the plate from Box 3. Move the disk from Box 0 to Box 4. Move the beer from Box 5 to Box 1. Move the jacket and the tape from Box 6 to Box 0. Move the disk from Box 4 to Box 5. Move the tape from Box 0 to Box 3. Move the cross from Box 2 to Box 4. Remove the beer and the tea from Box 1. Move the branch from Box 0 to Box 2. Move the bowl from Box 1 to Box 6.", "sample_id": 588, "numops": 4, "final_states": {"Box 0": ["nothing", "the jacket"], "Box 1": ["nothing"], "Box 2": ["the mirror", "the branch", "the cup"], "Box 3": ["the dish", "the tape"], "Box 4": ["the medicine", "the cross"], "Box 5": ["the map", "the boat", "the disk"], "Box 6": ["the bowl", "the letter"]}}
{"sentence": "Box 0 contains the game and the knife and the map, Box 1 contains the magazine and the note and the string, Box 2 contains nothing, Box 3 contains the seed, Box 4 contains the egg, Box 5 contains the apple and the bomb and the rock, Box 6 contains nothing. Remove the seed from Box 3. Move the string from Box 1 to Box 4. Move the string from Box 4 to Box 3. Put the machine into Box 6. Move the string from Box 3 to Box 4. Remove the egg from Box 4. Remove the note from Box 1. Move the game from Box 0 to Box 3. Put the cigarette and the painting into Box 4.", "sample_id": 589, "numops": 1, "final_states": {"Box 0": ["the knife", "the map"], "Box 1": ["the magazine"], "Box 2": ["nothing"], "Box 3": ["the game"], "Box 4": ["the painting", "the cigarette", "the string"], "Box 5": ["the apple", "the bomb", "the rock"], "Box 6": ["the machine"]}}
{"sentence": "Box 0 contains the coat and the medicine, Box 1 contains the apple and the guitar and the shell, Box 2 contains the bag and the drink and the tie, Box 3 contains the machine and the paper and the watch, Box 4 contains the camera and the seed, Box 5 contains the clock, Box 6 contains the computer and the note and the plant. Move the tie from Box 2 to Box 0.", "sample_id": 597, "numops": 1, "final_states": {"Box 0": ["the medicine", "the coat", "the paper", "the tie"], "Box 1": ["the shell", "the apple", "the guitar"], "Box 2": ["the bag", "the drink"], "Box 3": ["the machine", "the watch", "the paper"], "Box 4": ["the seed", "the camera", "the clock"], "Box 5": ["the clock", "nothing"], "Box 6": ["the note", "the computer", "the plant"]}}
{"sentence": "Box 0 contains the coat and the fan, Box 1 contains the jacket and the paper, Box 2 contains the tape, Box 3 contains the bowl and the cross and the key, Box 4 contains nothing, Box 5 contains the television, Box 6 contains nothing. Put the cash and the medicine into Box 6. Move the jacket and the paper from Box 1 to Box 5. Remove the medicine from Box 6. Put the string into Box 0. Remove the coat and the string from Box 0. Put the rose into Box 2. Move the rose from Box 2 to Box 6. Move the cash from Box 6 to Box 2. Remove the rose from Box 6. Remove the television from Box 5. Remove the cross from Box 3. Remove the paper from Box 5.", "sample_id": 598, "numops": 2, "final_states": {"Box 0": ["the fan"], "Box 1": ["nothing"], "Box 2": ["the cash", "the tape"], "Box 3": ["the bowl", "the key"], "Box 4": ["nothing"], "Box 5": ["the jacket"], "Box 6": ["nothing"]}}
{"sentence": "Box 0 contains the chemical and the cup, Box 1 contains the book and the game and the magazine, Box 2 contains the boat and the fig and the hat, Box 3 contains the car and the seed and the suit, Box 4 contains the drug and the leaf and the painting, Box 5 contains nothing, Box 6 contains nothing. Remove the book and the magazine from Box 1. Remove the chemical from Box 0. Put the bread and the mirror into Box 6. Move the mirror from Box 6 to Box 1. Remove the game from Box 1. Put the plane into Box 1. Remove the fig and the hat from Box 2. Remove the bread from Box 6. Put the bus and the cheese into Box 5. Move the cup from Box 0 to Box 1. Remove the cup from Box 1.", "sample_id": 602, "numops": 2, "final_states": {"Box 0": ["nothing"], "Box 1": ["the mirror", "the plane"], "Box 2": ["the boat"], "Box 3": ["the suit", "the car", "the seed"], "Box 4": ["the painting", "the drug", "the leaf"], "Box 5": ["the bus", "the cheese"], "Box 6": ["nothing"]}}
{"sentence": "Box 0 contains the phone and the ticket, Box 1 contains the document and the pipe and the shirt, Box 2 contains the boot and the brain and the guitar, Box 3 contains the knife and the stone, Box 4 contains the card and the cross and the fig, Box 5 contains the watch, Box 6 contains the drug. Remove the drug from Box 6. Remove the brain and the guitar from Box 2. Move the document from Box 1 to Box 0. Move the phone from Box 0 to Box 2. Remove the watch from Box 5. Move the card and the cross from Box 4 to Box 6. Put the jacket into Box 1. Put the crown into Box 6. Move the document from Box 0 to Box 4. Remove the card and the cross and the crown from Box 6.", "sample_id": 608, "numops": 3, "final_states": {"Box 0": ["the ticket"], "Box 1": ["the shirt", "the pipe", "the jacket"], "Box 2": ["the phone", "the boot"], "Box 3": ["the knife", "the stone"], "Box 4": ["the fig", "the document", "nothing"], "Box 5": ["nothing"], "Box 6": ["nothing"]}}
{"sentence": "Box 0 contains the boat and the car and the milk, Box 1 contains the ball and the boot and the glass, Box 2 contains nothing, Box 3 contains the drink, Box 4 contains the bowl and the leaf and the tape, Box 5 contains the string and the suit, Box 6 contains the clock and the wire.", "sample_id": 622, "numops": 0, "final_states": {"Box 0": ["the milk", "the car", "the boat"], "Box 1": ["the glass", "the boot", "the ball"], "Box 2": ["nothing"], "Box 3": ["the drink"], "Box 4": ["the bowl", "the tape", "the leaf"], "Box 5": ["the suit", "the string"], "Box 6": ["the clock", "the wire"]}}
{"sentence": "Box 0 contains the fish, Box 1 contains the newspaper and the painting, Box 2 contains the bag and the coffee, Box 3 contains the bone and the clock and the phone, Box 4 contains the crown and the seed, Box 5 contains the creature and the flower and the ticket, Box 6 contains the apple and the bowl and the plane. Put the bomb and the ring into Box 0. Remove the crown and the seed from Box 4. Remove the creature and the flower from Box 5. Remove the fish from Box 0. Put the milk into Box 4. Move the bomb from Box 0 to Box 4. Move the ticket from Box 5 to Box 1. Move the ticket from Box 1 to Box 5. Move the newspaper and the painting from Box 1 to Box 0.", "sample_id": 624, "numops": 4, "final_states": {"Box 0": ["the painting", "the newspaper", "the ring"], "Box 1": ["nothing"], "Box 2": ["the coffee", "the bag"], "Box 3": ["the bone", "the clock", "the phone"], "Box 4": ["the milk", "the bomb"], "Box 5": ["the ticket"], "Box 6": ["the apple", "the bowl", "the plane"]}}
{"sentence": "Box 0 contains the flower and the game and the rock, Box 1 contains the beer, Box 2 contains the clock and the jacket and the radio, Box 3 contains the apple and the gift, Box 4 contains the file and the plate and the wheel, Box 5 contains the bowl, Box 6 contains the egg and the ice and the shirt. Move the beer from Box 1 to Box 5. Move the beer from Box 5 to Box 3. Put the coffee into Box 1. Move the flower and the rock from Box 0 to Box 1. Remove the file and the wheel from Box 4. Move the bowl from Box 5 to Box 4. Remove the game from Box 0. Remove the apple and the gift from Box 3. Move the beer from Box 3 to Box 4. Remove the coffee and the flower from Box 1. Remove the ice and the shirt from Box 6. Move the bowl from Box 4 to Box 6.", "sample_id": 625, "numops": 2, "final_states": {"Box 0": ["nothing"], "Box 1": ["the rock"], "Box 2": ["the clock", "the radio", "the jacket"], "Box 3": ["nothing"], "Box 4": ["the plate", "the beer"], "Box 5": ["nothing"], "Box 6": ["the bowl", "the egg"]}}
{"sentence": "Box 0 contains the magazine, Box 1 contains the disk, Box 2 contains the apple and the painting and the wire, Box 3 contains nothing, Box 4 contains the boot and the cup and the radio, Box 5 contains the camera and the cream and the guitar, Box 6 contains the card and the file. Move the magazine from Box 0 to Box 1. Move the file from Box 6 to Box 3. Move the guitar from Box 5 to Box 1. Put the book and the cross into Box 3. Remove the book and the cross from Box 3. Remove the magazine from Box 1. Put the mirror into Box 1. Remove the file from Box 3.", "sample_id": 629, "numops": 1, "final_states": {"Box 0": ["nothing"], "Box 1": ["the mirror", "the guitar", "the disk"], "Box 2": ["the apple", "the painting", "the wire"], "Box 3": ["nothing"], "Box 4": ["the boot", "the cup", "the radio"], "Box 5": ["the camera", "the cream"], "Box 6": ["the card"]}}
{"sentence": "Box 0 contains the note, Box 1 contains the plate and the tea, Box 2 contains the document, Box 3 contains the branch and the cross, Box 4 contains the coffee and the drug, Box 5 contains the newspaper, Box 6 contains the flower and the sheet. Put the picture and the ticket into Box 2. Move the note from Box 0 to Box 6. Put the key into Box 1. Move the tea from Box 1 to Box 5. Put the disk into Box 5. Move the key and the plate from Box 1 to Box 0. Remove the ticket from Box 2. Remove the coffee and the drug from Box 4. Remove the branch and the cross from Box 3. Put the letter into Box 2. Move the letter from Box 2 to Box 3.", "sample_id": 632, "numops": 2, "final_states": {"Box 0": ["the plate", "the key"], "Box 1": ["nothing"], "Box 2": ["the document", "the picture"], "Box 3": ["the letter"], "Box 4": ["nothing"], "Box 5": ["the newspaper", "the disk", "the tea"], "Box 6": ["the flower", "the sheet", "the note"]}}
{"sentence": "Box 0 contains nothing, Box 1 contains the coat and the drug, Box 2 contains the disk and the medicine and the picture, Box 3 contains the shell, Box 4 contains the block and the boat, Box 5 contains the wire, Box 6 contains the beer and the dish and the painting. Put the engine and the ring into Box 5. Remove the shell from Box 3. Remove the beer and the painting from Box 6. Remove the picture from Box 2. Put the hat and the paper and the phone into Box 3. Put the boot and the computer into Box 0. Remove the hat and the paper from Box 3. Move the phone from Box 3 to Box 4.", "sample_id": 638, "numops": 1, "final_states": {"Box 0": ["the computer", "the boot"], "Box 1": ["the drug", "the coat"], "Box 2": ["the medicine", "the disk"], "Box 3": ["nothing"], "Box 4": ["the phone", "the boat", "the block"], "Box 5": ["the engine", "the wire", "the ring"], "Box 6": ["the dish"]}}
{"sentence": "Box 0 contains the brick, Box 1 contains the bag and the boat and the coffee, Box 2 contains the boot and the cigarette and the watch, Box 3 contains the card and the engine and the milk, Box 4 contains the computer and the drug and the seed, Box 5 contains the ball and the bottle and the pot, Box 6 contains the map and the wire. Move the card from Box 3 to Box 6. Remove the drug and the seed from Box 4. Remove the engine and the milk from Box 3. Move the watch from Box 2 to Box 4. Put the block into Box 3. Put the dress and the jacket into Box 0. Remove the bag and the coffee from Box 1. Move the block from Box 3 to Box 2. Remove the bottle from Box 5. Put the machine into Box 5.", "sample_id": 646, "numops": 1, "final_states": {"Box 0": ["the brick", "the jacket", "the dress"], "Box 1": ["the boat"], "Box 2": ["the boot", "the block", "the cigarette"], "Box 3": ["nothing", "the pipe"], "Box 4": ["the computer", "the watch"], "Box 5": ["the machine", "the pot", "the ball"], "Box 6": ["the card", "the map", "the wire"]}}
{"sentence": "Box 0 contains the apple and the drug and the engine, Box 1 contains the newspaper, Box 2 contains nothing, Box 3 contains the cheese and the hat, Box 4 contains the ball, Box 5 contains the bowl, Box 6 contains the book. Move the newspaper from Box 1 to Box 3. Move the ball from Box 4 to Box 1. Remove the cheese and the newspaper from Box 3. Put the suit into Box 2. Move the drug and the engine from Box 0 to Box 3. Remove the ball from Box 1. Move the book from Box 6 to Box 0. Put the bag and the dress into Box 6. Move the apple from Box 0 to Box 6. Move the suit from Box 2 to Box 5. Move the bag from Box 6 to Box 2. Put the branch into Box 6.", "sample_id": 653, "numops": 3, "final_states": {"Box 0": ["the book"], "Box 1": ["nothing"], "Box 2": ["the bag"], "Box 3": ["the engine", "the drug", "the hat"], "Box 4": ["nothing"], "Box 5": ["the bowl", "the suit"], "Box 6": ["the apple", "the branch", "the dress"]}}
{"sentence": "Box 0 contains the drink and the plane and the shell, Box 1 contains nothing, Box 2 contains the cake and the painting, Box 3 contains nothing, Box 4 contains the bone and the magazine and the radio, Box 5 contains the chemical and the plant and the tape, Box 6 contains the flower and the suit and the wire. Move the bone from Box 4 to Box 3. Remove the chemical and the plant from Box 5. Move the bone from Box 3 to Box 4. Remove the drink and the plane and the shell from Box 0. Remove the tape from Box 5. Put the knife and the leaf into Box 5. Remove the knife from Box 5.", "sample_id": 663, "numops": 1, "final_states": {"Box 0": ["nothing"], "Box 1": ["nothing"], "Box 2": ["the painting", "the cake"], "Box 3": ["nothing"], "Box 4": ["the bone", "the magazine", "the radio"], "Box 5": ["the leaf"], "Box 6": ["the flower", "the wire", "the suit"]}}
{"sentence": "Box 0 contains the ball and the cheese and the key, Box 1 contains the paper, Box 2 contains the fig and the knife and the rose, Box 3 contains the file and the fish and the rock, Box 4 contains the picture, Box 5 contains the book and the car and the medicine, Box 6 contains the sheet. Remove the file from Box 3. Remove the key from Box 0. Move the ball from Box 0 to Box 3. Remove the ball and the fish from Box 3. Remove the sheet from Box 6. Move the paper from Box 1 to Box 3. Remove the picture from Box 4. Remove the cheese from Box 0. Move the fig from Box 2 to Box 1. Move the car and the medicine from Box 5 to Box 4. Remove the fig from Box 1. Put the engine into Box 3.", "sample_id": 667, "numops": 3, "final_states": {"Box 0": ["nothing"], "Box 1": ["nothing"], "Box 2": ["the rose", "the knife"], "Box 3": ["the paper", "the engine", "the rock"], "Box 4": ["the medicine", "the car"], "Box 5": ["the book"], "Box 6": ["nothing"]}}
{"sentence": "Box 0 contains the computer and the cream and the glass, Box 1 contains nothing, Box 2 contains the flower and the rose, Box 3 contains the card and the egg and the plate, Box 4 contains the brick and the seed, Box 5 contains the document and the pipe, Box 6 contains the dress and the guitar. Move the rose from Box 2 to Box 1. Move the rose from Box 1 to Box 2. Move the brick and the seed from Box 4 to Box 1. Move the cream from Box 0 to Box 2. Remove the card and the egg and the plate from Box 3. Remove the brick from Box 1. Move the computer and the glass from Box 0 to Box 4. Put the knife into Box 4.", "sample_id": 669, "numops": 2, "final_states": {"Box 0": ["nothing"], "Box 1": ["the seed"], "Box 2": ["the flower", "the cream", "the rose"], "Box 3": ["nothing"], "Box 4": ["the glass", "the computer", "the knife"], "Box 5": ["the document", "the pipe"], "Box 6": ["the guitar", "the dress"]}}
{"sentence": "Box 0 contains nothing, Box 1 contains the bone, Box 2 contains the meat, Box 3 contains the car and the plate and the stone, Box 4 contains the boot and the fig and the jacket, Box 5 contains the ball and the creature and the shirt, Box 6 contains the crown and the glass and the guitar. Put the dish into Box 0. Remove the shirt from Box 5. Move the bone from Box 1 to Box 2. Remove the boot and the fig from Box 4. Put the branch and the document and the file into Box 1. Remove the crown from Box 6. Remove the document from Box 1. Move the dish from Box 0 to Box 4. Remove the dish from Box 4. Remove the meat from Box 2. Put the boat into Box 0. Remove the stone from Box 3.", "sample_id": 672, "numops": 3, "final_states": {"Box 0": ["the boat"], "Box 1": ["the file", "the branch"], "Box 2": ["the bone"], "Box 3": ["the plate", "the car"], "Box 4": ["the jacket"], "Box 5": ["the creature", "the ball"], "Box 6": ["the glass", "the guitar"]}}
{"sentence": "Box 0 contains the cigarette, Box 1 contains the document, Box 2 contains the shirt, Box 3 contains the cream and the drink and the plant, Box 4 contains the branch and the ice, Box 5 contains the watch, Box 6 contains the car and the machine and the meat. Remove the cigarette from Box 0. Remove the cream and the plant from Box 3. Remove the document from Box 1. Put the chemical into Box 1. Remove the chemical from Box 1. Remove the watch from Box 5. Remove the ice from Box 4. Move the meat from Box 6 to Box 2. Move the meat and the shirt from Box 2 to Box 1. Put the bill into Box 5. Remove the meat from Box 1.", "sample_id": 681, "numops": 1, "final_states": {"Box 0": ["nothing"], "Box 1": ["the shirt"], "Box 2": ["nothing"], "Box 3": ["the drink"], "Box 4": ["the branch"], "Box 5": ["the bill"], "Box 6": ["the car", "the machine"]}}
{"sentence": "Box 0 contains the document and the string, Box 1 contains the plane and the stone and the television, Box 2 contains the boot and the bottle and the ring, Box 3 contains the key and the medicine, Box 4 contains the machine, Box 5 contains nothing, Box 6 contains the dress. Move the machine from Box 4 to Box 3. Remove the plane from Box 1.", "sample_id": 691, "numops": 0, "final_states": {"Box 0": ["the document", "the string"], "Box 1": ["the television", "the stone"], "Box 2": ["the bottle", "the boot", "the ring"], "Box 3": ["the key", "the machine", "the medicine"], "Box 4": ["nothing"], "Box 5": ["nothing"], "Box 6": ["the dress"]}}
{"sentence": "Box 0 contains the shell, Box 1 contains nothing, Box 2 contains the dish and the letter and the plant, Box 3 contains the cake and the machine and the note, Box 4 contains the block and the drink and the flower, Box 5 contains the gift, Box 6 contains the cheese and the ice and the train. Remove the gift from Box 5. Remove the drink from Box 4. Move the dish from Box 2 to Box 1. Remove the block from Box 4. Move the cake and the machine and the note from Box 3 to Box 5. Move the flower from Box 4 to Box 0. Remove the letter from Box 2. Remove the machine and the note from Box 5. Move the flower and the shell from Box 0 to Box 5.", "sample_id": 695, "numops": 2, "final_states": {"Box 0": ["the flower", "nothing", "the cake"], "Box 1": ["the dish"], "Box 2": ["the plant"], "Box 3": ["nothing"], "Box 4": ["the shell", "nothing"], "Box 5": ["the flower", "the cake", "nothing", "the shell"], "Box 6": ["the ice", "the cheese", "the train"]}}
{"sentence": "Box 0 contains the map and the television and the wire, Box 1 contains the bottle and the coat, Box 2 contains the boot and the drink and the fan, Box 3 contains the dress, Box 4 contains the plant, Box 5 contains the egg and the medicine, Box 6 contains nothing. Remove the dress from Box 3.", "sample_id": 696, "numops": 0, "final_states": {"Box 0": ["the map", "the television", "the wire"], "Box 1": ["the map", "the coat", "the bottle"], "Box 2": ["the fan", "the boot", "the drink"], "Box 3": ["nothing"], "Box 4": ["the plant"], "Box 5": ["the medicine", "the egg"], "Box 6": ["the computer", "nothing"]}}
{"sentence": "Box 0 contains the beer and the coffee and the wheel, Box 1 contains the cake and the rock and the tissue, Box 2 contains the boot and the drug and the leaf, Box 3 contains the magazine, Box 4 contains the brick and the cigarette, Box 5 contains the shoe, Box 6 contains nothing. Remove the boot from Box 2. Put the pot into Box 4. Move the coffee from Box 0 to Box 5. Move the wheel from Box 0 to Box 2. Remove the beer from Box 0. Move the rock from Box 1 to Box 5. Remove the tissue from Box 1. Move the brick from Box 4 to Box 1. Move the wheel from Box 2 to Box 0.", "sample_id": 702, "numops": 4, "final_states": {"Box 0": ["the wheel"], "Box 1": ["the cake", "the brick"], "Box 2": ["the drug", "the leaf"], "Box 3": ["the magazine"], "Box 4": ["the pot", "the cigarette"], "Box 5": ["the coffee", "the rock", "the shoe"], "Box 6": ["nothing"]}}
{"sentence": "Box 0 contains the bag and the bill and the fig, Box 1 contains the paper, Box 2 contains the dress, Box 3 contains the book and the drug, Box 4 contains the bread and the medicine and the shirt, Box 5 contains nothing, Box 6 contains the picture. Move the bill and the fig from Box 0 to Box 6. Remove the book and the drug from Box 3. Move the dress from Box 2 to Box 5. Move the bag from Box 0 to Box 3. Put the cheese and the train into Box 1. Remove the cheese and the train from Box 1. Move the bill and the fig from Box 6 to Box 5. Remove the bill from Box 5. Remove the picture from Box 6. Put the guitar into Box 1. Remove the bag from Box 3.", "sample_id": 723, "numops": 2, "final_states": {"Box 0": ["nothing"], "Box 1": ["the paper", "the guitar"], "Box 2": ["nothing"], "Box 3": ["nothing"], "Box 4": ["the bread", "the medicine", "the shirt"], "Box 5": ["the fig", "the dress"], "Box 6": ["nothing"]}}
{"sentence": "Box 0 contains the guitar and the magazine, Box 1 contains the fig and the sheet, Box 2 contains the tea, Box 3 contains the bell and the cross and the watch, Box 4 contains the cheese and the fish and the phone, Box 5 contains the brick, Box 6 contains the drink and the painting and the ring. Put the cash into Box 5.", "sample_id": 730, "numops": 0, "final_states": {"Box 0": ["the magazine", "the guitar"], "Box 1": ["the fig", "the sheet"], "Box 2": ["the tea"], "Box 3": ["the bell", "the watch", "the cross"], "Box 4": ["the fish", "the phone", "the cheese"], "Box 5": ["the cash", "the brick"], "Box 6": ["the painting", "the ring", "the drink"]}}
{"sentence": "Box 0 contains the beer and the cup and the phone, Box 1 contains the boat and the seed and the shirt, Box 2 contains the wire, Box 3 contains the mirror and the suit, Box 4 contains the bread and the key and the plane, Box 5 contains the car and the ticket, Box 6 contains the drink. Remove the boat and the shirt from Box 1. Put the file into Box 1. Remove the file and the seed from Box 1. Remove the drink from Box 6. Remove the mirror from Box 3. Remove the wire from Box 2.", "sample_id": 731, "numops": 0, "final_states": {"Box 0": ["the phone", "the beer", "the cup"], "Box 1": ["nothing"], "Box 2": ["nothing"], "Box 3": ["the suit"], "Box 4": ["the bread", "the key", "the plane"], "Box 5": ["the picture", "the ticket", "the car"], "Box 6": ["nothing"]}}
{"sentence": "Box 0 contains the cigarette and the pipe, Box 1 contains the book and the magazine and the stone, Box 2 contains the flower, Box 3 contains the medicine and the paper and the rock, Box 4 contains the block, Box 5 contains nothing, Box 6 contains the cake and the engine. Put the computer into Box 2. Move the block from Box 4 to Box 2. Move the block from Box 2 to Box 6. Remove the medicine and the paper and the rock from Box 3. Put the bill and the brick and the cream into Box 5. Move the stone from Box 1 to Box 2. Put the bread into Box 4.", "sample_id": 754, "numops": 0, "final_states": {"Box 0": ["the cigarette", "the pipe"], "Box 1": ["the magazine", "the book"], "Box 2": ["the flower", "the computer", "the stone"], "Box 3": ["nothing"], "Box 4": ["the bread"], "Box 5": ["the cream", "the bill", "the brick"], "Box 6": ["the cake", "the engine", "the block"]}}
{"sentence": "Box 0 contains the card and the leaf, Box 1 contains nothing, Box 2 contains the apple and the picture, Box 3 contains the bag and the hat and the wheel, Box 4 contains the bottle and the drink and the tape, Box 5 contains the brick and the plant and the wire, Box 6 contains the rose. Move the bag and the hat from Box 3 to Box 6. Remove the brick from Box 5. Move the hat from Box 6 to Box 1. Move the hat from Box 1 to Box 3. Remove the picture from Box 2. Put the milk into Box 5. Put the egg into Box 3. Remove the leaf from Box 0. Move the plant and the wire from Box 5 to Box 2. Move the milk from Box 5 to Box 1. Remove the bottle and the tape from Box 4.", "sample_id": 762, "numops": 1, "final_states": {"Box 0": ["the card"], "Box 1": ["the milk"], "Box 2": ["the apple", "the plant", "the wire"], "Box 3": ["the egg", "the hat", "the wheel"], "Box 4": ["the drink"], "Box 5": ["nothing"], "Box 6": ["the rose", "the bag"]}}
{"sentence": "Box 0 contains nothing, Box 1 contains the computer, Box 2 contains the leaf and the picture and the rose, Box 3 contains the bus and the hat, Box 4 contains the dish, Box 5 contains the guitar and the jacket, Box 6 contains the disk and the seed. Remove the disk from Box 6. Remove the seed from Box 6. Move the computer from Box 1 to Box 6. Remove the guitar and the jacket from Box 5. Move the picture from Box 2 to Box 0. Put the bag and the radio into Box 5.", "sample_id": 764, "numops": 1, "final_states": {"Box 0": ["the picture", "the wire"], "Box 1": ["the cream", "nothing"], "Box 2": ["the rose", "the dress", "the computer", "the bag", "the leaf"], "Box 3": ["the bus", "the hat"], "Box 4": ["the dish"], "Box 5": ["the bag", "the radio"], "Box 6": ["the computer", "nothing"]}}
{"sentence": "Box 0 contains the cross and the drug and the fan, Box 1 contains the bag and the meat and the tissue, Box 2 contains the brick and the coffee and the paper, Box 3 contains the bread, Box 4 contains the bottle and the radio, Box 5 contains the bone and the drink and the wheel, Box 6 contains the jacket and the ticket. Remove the bone from Box 5. Move the ticket from Box 6 to Box 3. Remove the coffee and the paper from Box 2. Move the drug and the fan from Box 0 to Box 6. Put the computer into Box 5. Remove the brick from Box 2. Put the brick into Box 3. Put the tie into Box 4. Move the bottle from Box 4 to Box 0. Remove the computer and the drink from Box 5.", "sample_id": 766, "numops": 2, "final_states": {"Box 0": ["the bottle", "the cross"], "Box 1": ["the bag", "the meat", "the tissue"], "Box 2": ["nothing"], "Box 3": ["the bread", "the ticket", "the brick"], "Box 4": ["the tie", "the radio"], "Box 5": ["the wheel"], "Box 6": ["the fan", "the drug", "the jacket"]}}
{"sentence": "Box 0 contains the block and the disk, Box 1 contains the boot and the brain, Box 2 contains the chemical and the phone and the seed, Box 3 contains the fig and the mirror and the pot, Box 4 contains nothing, Box 5 contains the cross and the sheet and the shell, Box 6 contains the cheese and the dish and the painting. Put the tissue into Box 4. Remove the tissue from Box 4. Remove the chemical and the phone from Box 2. Remove the cross from Box 5. Remove the sheet from Box 5. Remove the seed from Box 2. Move the shell from Box 5 to Box 0. Remove the disk and the shell from Box 0. Move the block from Box 0 to Box 1. Put the bowl and the ticket into Box 2. Put the train into Box 4. Put the car and the shoe into Box 5.", "sample_id": 767, "numops": 3, "final_states": {"Box 0": ["nothing"], "Box 1": ["the brain", "the boot", "the block"], "Box 2": ["the bowl", "the ticket"], "Box 3": ["the mirror", "the fig", "the pot"], "Box 4": ["the train"], "Box 5": ["the car", "the shoe"], "Box 6": ["the painting", "the dish", "the cheese"]}}
{"sentence": "Box 0 contains the plant, Box 1 contains the bomb and the bowl, Box 2 contains the drink and the seed, Box 3 contains the bone and the coffee and the painting, Box 4 contains the clock and the leaf, Box 5 contains the radio and the shoe and the stone, Box 6 contains nothing.", "sample_id": 770, "numops": 0, "final_states": {"Box 0": ["the plant"], "Box 1": ["the bowl", "the bomb"], "Box 2": ["the seed", "the drink"], "Box 3": ["the bone", "the painting", "the coffee"], "Box 4": ["the clock", "the leaf"], "Box 5": ["the stone", "the shoe", "the radio"], "Box 6": ["nothing"]}}
{"sentence": "Box 0 contains the seed, Box 1 contains the dress, Box 2 contains the picture, Box 3 contains the bowl and the computer, Box 4 contains the bomb and the tea, Box 5 contains nothing, Box 6 contains the cigarette. Move the dress from Box 1 to Box 5. Put the stone into Box 4. Remove the picture from Box 2. Remove the dress from Box 5. Put the radio into Box 1. Remove the radio from Box 1. Remove the seed from Box 0. Put the drink into Box 5. Move the stone and the tea from Box 4 to Box 6. Put the coat into Box 3. Put the seed into Box 4.", "sample_id": 773, "numops": 1, "final_states": {"Box 0": ["nothing"], "Box 1": ["nothing"], "Box 2": ["nothing"], "Box 3": ["the bowl", "the coat", "the computer"], "Box 4": ["the bomb", "the seed"], "Box 5": ["the drink"], "Box 6": ["the cigarette", "the stone", "the tea"]}}
{"sentence": "Box 0 contains nothing, Box 1 contains nothing, Box 2 contains the file and the map and the ticket, Box 3 contains the bag and the drug and the flower, Box 4 contains the wheel, Box 5 contains the picture and the plate and the stone, Box 6 contains the dish and the phone. Remove the dish from Box 6. Move the picture and the plate and the stone from Box 5 to Box 1. Remove the wheel from Box 4. Put the cigarette and the note into Box 5. Move the note from Box 5 to Box 6. Put the radio into Box 5. Remove the note and the phone from Box 6. Remove the radio from Box 5.", "sample_id": 778, "numops": 0, "final_states": {"Box 0": ["nothing"], "Box 1": ["the plate", "the picture", "the stone"], "Box 2": ["the file", "the map", "the ticket"], "Box 3": ["the drug", "the flower", "the bag"], "Box 4": ["nothing"], "Box 5": ["the cigarette", "nothing"], "Box 6": ["nothing"]}}
{"sentence": "Box 0 contains the wheel, Box 1 contains the disk and the guitar and the letter, Box 2 contains the bread and the fan and the map, Box 3 contains the branch and the picture, Box 4 contains the apple and the bell and the boat, Box 5 contains the coat and the jacket and the tea, Box 6 contains the hat. Move the branch and the picture from Box 3 to Box 6. Remove the bread and the fan and the map from Box 2. Move the branch from Box 6 to Box 2. Put the pipe into Box 0. Remove the apple and the boat from Box 4. Remove the bell from Box 4. Remove the coat from Box 5. Remove the picture from Box 6. Remove the branch from Box 2. Remove the pipe and the wheel from Box 0. Move the guitar from Box 1 to Box 0. Move the tea from Box 5 to Box 6.", "sample_id": 786, "numops": 3, "final_states": {"Box 0": ["the guitar"], "Box 1": ["the disk", "the letter"], "Box 2": ["nothing"], "Box 3": ["nothing"], "Box 4": ["nothing"], "Box 5": ["the jacket"], "Box 6": ["the tea", "the hat"]}}
{"sentence": "Box 0 contains the note, Box 1 contains nothing, Box 2 contains the ball, Box 3 contains nothing, Box 4 contains the bus and the camera and the radio, Box 5 contains the cream and the tie, Box 6 contains the document. Move the bus and the camera and the radio from Box 4 to Box 1. Put the mirror into Box 0. Move the document from Box 6 to Box 0. Remove the bus and the radio from Box 1. Put the bell and the jacket into Box 6. Put the plate into Box 3. Move the jacket from Box 6 to Box 4. Remove the plate from Box 3. Move the ball from Box 2 to Box 1. Put the bill into Box 5. Put the computer into Box 2. Put the ring into Box 1.", "sample_id": 789, "numops": 2, "final_states": {"Box 0": ["the mirror", "the document", "the note"], "Box 1": ["the camera", "the ring", "the ball"], "Box 2": ["the computer"], "Box 3": ["nothing"], "Box 4": ["the jacket"], "Box 5": ["the cream", "the bill", "the tie"], "Box 6": ["the bell"]}}
{"sentence": "Box 0 contains the rock, Box 1 contains the bill and the flower and the guitar, Box 2 contains the branch and the medicine and the mirror, Box 3 contains the bowl and the map, Box 4 contains the ball and the boat and the bread, Box 5 contains the glass and the painting, Box 6 contains the card and the crown and the shirt. Remove the rock from Box 0. Remove the branch and the medicine and the mirror from Box 2. Move the bowl from Box 3 to Box 0. Put the plane into Box 0. Remove the map from Box 3. Remove the plane from Box 0. Remove the bowl from Box 0. Put the brick into Box 2. Put the document and the note into Box 3. Move the bill from Box 1 to Box 2. Move the note from Box 3 to Box 0.", "sample_id": 793, "numops": 6, "final_states": {"Box 0": ["the note"], "Box 1": ["the flower", "the guitar"], "Box 2": ["the bill", "the brick"], "Box 3": ["the document", "nothing"], "Box 4": ["the bread", "the boat", "the ball"], "Box 5": ["the glass", "the painting"], "Box 6": ["the card", "the crown", "the shirt"]}}
{"sentence": "Box 0 contains the rose, Box 1 contains the document and the sheet, Box 2 contains the engine and the painting, Box 3 contains the bell, Box 4 contains the ball and the clock and the seed, Box 5 contains the cross and the tape, Box 6 contains the card and the cash. Move the bell from Box 3 to Box 0. Put the block and the key into Box 3. Move the painting from Box 2 to Box 5. Remove the engine from Box 2. Remove the ball and the clock and the seed from Box 4. Move the card from Box 6 to Box 1. Remove the cash from Box 6. Put the fig into Box 6. Put the picture and the tissue into Box 2.", "sample_id": 796, "numops": 1, "final_states": {"Box 0": ["the rose", "the bell"], "Box 1": ["the card", "the sheet", "the document"], "Box 2": ["the picture", "the tissue"], "Box 3": ["the key", "the block"], "Box 4": ["the picture", "nothing"], "Box 5": ["the tape", "the painting", "the cross"], "Box 6": ["the fig"]}}
{"sentence": "Box 0 contains the bell and the shirt, Box 1 contains nothing, Box 2 contains the coat, Box 3 contains nothing, Box 4 contains the ice and the magazine and the stone, Box 5 contains the camera and the tape, Box 6 contains the map and the mirror. Remove the ice and the magazine from Box 4. Move the stone from Box 4 to Box 0. Move the coat from Box 2 to Box 1. Remove the bell and the shirt from Box 0. Move the camera and the tape from Box 5 to Box 0. Put the flower into Box 2. Remove the flower from Box 2. Remove the camera from Box 0. Put the cash and the wire into Box 4. Move the map from Box 6 to Box 3. Put the branch into Box 5. Put the bomb into Box 0.", "sample_id": 800, "numops": 5, "final_states": {"Box 0": ["the stone", "the bomb", "the tape"], "Box 1": ["the coat"], "Box 2": ["nothing"], "Box 3": ["the map"], "Box 4": ["the cash", "the wire"], "Box 5": ["the branch"], "Box 6": ["the mirror"]}}
{"sentence": "Box 0 contains the crown and the picture, Box 1 contains the bone and the cheese and the clock, Box 2 contains the egg and the gift and the medicine, Box 3 contains the letter, Box 4 contains nothing, Box 5 contains the flower, Box 6 contains the computer. Remove the egg and the gift and the medicine from Box 2. Move the bone and the cheese and the clock from Box 1 to Box 4. Move the flower from Box 5 to Box 3. Put the boot and the plane into Box 6. Remove the bone and the cheese from Box 4. Move the boot from Box 6 to Box 4. Move the picture from Box 0 to Box 3. Move the plane from Box 6 to Box 4.", "sample_id": 804, "numops": 1, "final_states": {"Box 0": ["the crown"], "Box 1": ["nothing"], "Box 2": ["nothing"], "Box 3": ["the flower", "the picture", "the letter"], "Box 4": ["the clock", "the plane", "the boot"], "Box 5": ["nothing"], "Box 6": ["the computer"]}}
{"sentence": "Box 0 contains the bus and the watch, Box 1 contains nothing, Box 2 contains the dress and the note and the sheet, Box 3 contains the bowl and the computer and the paper, Box 4 contains the boat and the dish and the television, Box 5 contains the boot and the rose, Box 6 contains nothing. Remove the bus from Box 0. Move the boot and the rose from Box 5 to Box 0. Remove the boot and the rose and the watch from Box 0. Put the bag into Box 0. Remove the boat and the television from Box 4. Move the dish from Box 4 to Box 1. Remove the dress and the note from Box 2. Remove the bag from Box 0. Move the paper from Box 3 to Box 0. Remove the paper from Box 0.", "sample_id": 805, "numops": 7, "final_states": {"Box 0": ["nothing"], "Box 1": ["the dish"], "Box 2": ["the sheet", "the boot"], "Box 3": ["the bowl", "the computer"], "Box 4": ["nothing"], "Box 5": ["nothing"], "Box 6": ["nothing"]}}
{"sentence": "Box 0 contains the block and the clock and the computer, Box 1 contains the creature and the fan and the paper, Box 2 contains the guitar and the wheel, Box 3 contains the jacket and the string and the television, Box 4 contains nothing, Box 5 contains the bomb, Box 6 contains the game. Move the bomb from Box 5 to Box 4. Remove the jacket from Box 3. Remove the bomb from Box 4. Put the shoe into Box 5. Move the fan from Box 1 to Box 4. Remove the shoe from Box 5. Put the apple into Box 2. Remove the apple and the guitar and the wheel from Box 2.", "sample_id": 807, "numops": 0, "final_states": {"Box 0": ["the clock", "the computer", "the block"], "Box 1": ["the paper", "the creature"], "Box 2": ["nothing"], "Box 3": ["the television", "the string"], "Box 4": ["the fan"], "Box 5": ["nothing"], "Box 6": ["the game"]}}
{"sentence": "Box 0 contains the brain and the cigarette, Box 1 contains the cheese and the chemical, Box 2 contains the bowl and the tie, Box 3 contains the guitar, Box 4 contains the camera, Box 5 contains the creature and the ice, Box 6 contains the bomb and the shirt and the shoe. Remove the ice from Box 5. Move the shirt from Box 6 to Box 3. Remove the bowl from Box 2. Move the cigarette from Box 0 to Box 6. Remove the creature from Box 5. Remove the shirt from Box 3. Remove the guitar from Box 3. Move the camera from Box 4 to Box 1. Move the brain from Box 0 to Box 2. Put the card and the paper and the plant into Box 3. Put the train into Box 0.", "sample_id": 813, "numops": 3, "final_states": {"Box 0": ["the train"], "Box 1": ["the camera", "the chemical", "the cheese"], "Box 2": ["the brain", "the tie"], "Box 3": ["the card", "the plant", "the paper"], "Box 4": ["nothing"], "Box 5": ["nothing"], "Box 6": ["the cigarette", "the bomb", "the shoe"]}}
{"sentence": "Box 0 contains the cheese and the guitar and the string, Box 1 contains nothing, Box 2 contains the brick and the clock and the tea, Box 3 contains the drug, Box 4 contains the apple, Box 5 contains nothing, Box 6 contains the newspaper. Put the milk into Box 3. Remove the tea from Box 2. Move the string from Box 0 to Box 1.", "sample_id": 815, "numops": 1, "final_states": {"Box 0": ["the guitar", "the cheese"], "Box 1": ["the camera", "the string"], "Box 2": ["the clock", "nothing", "the brick"], "Box 3": ["the drug", "the milk"], "Box 4": ["the apple", "nothing"], "Box 5": ["nothing"], "Box 6": ["the fig", "the newspaper"]}}
{"sentence": "Box 0 contains the hat, Box 1 contains the cream and the drug, Box 2 contains the bottle and the glass and the medicine, Box 3 contains the document and the machine and the mirror, Box 4 contains the meat and the tissue, Box 5 contains the file, Box 6 contains the key and the sheet. Remove the document and the machine from Box 3. Move the meat and the tissue from Box 4 to Box 5. Remove the mirror from Box 3. Remove the key from Box 6. Remove the sheet from Box 6. Move the hat from Box 0 to Box 6. Put the knife into Box 4. Move the bottle from Box 2 to Box 1. Remove the knife from Box 4. Move the bottle from Box 1 to Box 4. Put the note into Box 6.", "sample_id": 817, "numops": 1, "final_states": {"Box 0": ["nothing"], "Box 1": ["the cream", "the drug"], "Box 2": ["the glass", "the medicine"], "Box 3": ["nothing"], "Box 4": ["the bottle"], "Box 5": ["the file", "the meat", "the tissue"], "Box 6": ["the note", "the hat"]}}
{"sentence": "Box 0 contains the note, Box 1 contains the leaf and the map, Box 2 contains nothing, Box 3 contains the bell and the computer and the suit, Box 4 contains the cake and the ring and the rose, Box 5 contains the cigarette and the cross, Box 6 contains the ball and the machine and the television. Remove the bell from Box 3. Put the phone into Box 1. Remove the note from Box 0.", "sample_id": 818, "numops": 1, "final_states": {"Box 0": ["nothing"], "Box 1": ["the map", "the phone", "the leaf"], "Box 2": ["nothing"], "Box 3": ["the computer", "the suit"], "Box 4": ["the rose", "the cake", "nothing", "the ring"], "Box 5": ["the cigarette", "the cross"], "Box 6": ["the television", "the machine", "the ball"]}}
{"sentence": "Box 0 contains the book and the brick, Box 1 contains the bus and the crown and the plant, Box 2 contains the apple and the drug and the wire, Box 3 contains the file, Box 4 contains the game, Box 5 contains the paper and the ring, Box 6 contains the milk and the watch. Remove the bus from Box 1.", "sample_id": 825, "numops": 0, "final_states": {"Box 0": ["nothing", "the book", "the brick"], "Box 1": ["the plant", "nothing", "the crown"], "Box 2": ["the drug", "the apple", "the wire"], "Box 3": ["the file", "nothing"], "Box 4": ["the game", "nothing"], "Box 5": ["the paper", "nothing", "the ring"], "Box 6": ["the painting", "the milk", "the watch"]}}
{"sentence": "Box 0 contains the glass and the seed and the sheet, Box 1 contains the book, Box 2 contains nothing, Box 3 contains the disk and the medicine, Box 4 contains the magazine, Box 5 contains the picture, Box 6 contains the card. Put the crown into Box 4. Move the magazine from Box 4 to Box 3. Remove the book from Box 1. Remove the crown from Box 4. Move the picture from Box 5 to Box 1. Move the seed and the sheet from Box 0 to Box 2. Move the card from Box 6 to Box 2. Remove the seed from Box 2.", "sample_id": 828, "numops": 1, "final_states": {"Box 0": ["the glass", "the picture"], "Box 1": ["the glass", "the picture", "nothing"], "Box 2": ["the card", "the sheet", "the document"], "Box 3": ["the medicine", "the magazine", "the disk"], "Box 4": ["nothing"], "Box 5": ["nothing"], "Box 6": ["nothing"]}}
{"sentence": "Box 0 contains nothing, Box 1 contains the block and the cheese and the note, Box 2 contains the cake and the cross, Box 3 contains nothing, Box 4 contains nothing, Box 5 contains the clock, Box 6 contains the bottle and the flower. Move the cake from Box 2 to Box 3. Remove the cross from Box 2. Move the flower from Box 6 to Box 4. Move the bottle from Box 6 to Box 0. Put the book into Box 4. Remove the bottle from Box 0. Move the cake from Box 3 to Box 2. Move the flower from Box 4 to Box 6.", "sample_id": 832, "numops": 2, "final_states": {"Box 0": ["nothing"], "Box 1": ["the note", "the block", "the cheese"], "Box 2": ["the cake"], "Box 3": ["nothing"], "Box 4": ["the fan", "the book", "the shirt"], "Box 5": ["the clock"], "Box 6": ["the flower"]}}
{"sentence": "Box 0 contains nothing, Box 1 contains the dish and the television and the tie, Box 2 contains nothing, Box 3 contains the bus, Box 4 contains nothing, Box 5 contains the medicine and the plant and the sheet, Box 6 contains the pipe. Remove the bus from Box 3. Move the pipe from Box 6 to Box 2. Remove the medicine from Box 5. Move the pipe from Box 2 to Box 4. Move the plant from Box 5 to Box 4. Remove the sheet from Box 5. Put the hat and the leaf into Box 0.", "sample_id": 834, "numops": 1, "final_states": {"Box 0": ["the hat", "the leaf"], "Box 1": ["the television", "the dish", "the tie"], "Box 2": ["nothing"], "Box 3": ["nothing"], "Box 4": ["the plant", "the pipe"], "Box 5": ["nothing"], "Box 6": ["nothing"]}}
{"sentence": "Box 0 contains the plant, Box 1 contains the bill and the cigarette and the creature, Box 2 contains the beer and the cash and the cup, Box 3 contains the jacket and the key and the shoe, Box 4 contains the television, Box 5 contains the computer and the ticket, Box 6 contains the car. Move the creature from Box 1 to Box 5. Remove the computer and the creature from Box 5. Remove the television from Box 4. Put the suit into Box 1. Remove the beer and the cash from Box 2. Remove the cup from Box 2. Remove the key and the shoe from Box 3. Move the car from Box 6 to Box 3. Remove the car from Box 3. Move the plant from Box 0 to Box 5. Remove the plant and the ticket from Box 5. Put the leaf into Box 5.", "sample_id": 836, "numops": 1, "final_states": {"Box 0": ["nothing"], "Box 1": ["the cigarette", "the bill", "the suit"], "Box 2": ["nothing"], "Box 3": ["the jacket"], "Box 4": ["nothing"], "Box 5": ["the leaf"], "Box 6": ["nothing"]}}
{"sentence": "Box 0 contains the letter, Box 1 contains nothing, Box 2 contains the bell and the dress, Box 3 contains the chemical and the sheet and the string, Box 4 contains the crown and the plane and the tape, Box 5 contains the beer, Box 6 contains nothing. Put the bus and the train into Box 6. Put the cream into Box 6. Remove the chemical from Box 3. Move the beer from Box 5 to Box 0. Remove the sheet from Box 3. Put the bill and the shirt into Box 3. Remove the bus from Box 6. Put the mirror into Box 6. Put the apple into Box 2. Move the dress from Box 2 to Box 1. Move the dress from Box 1 to Box 0.", "sample_id": 838, "numops": 2, "final_states": {"Box 0": ["the beer", "the letter", "the dress"], "Box 1": ["nothing"], "Box 2": ["the apple", "the bell"], "Box 3": ["the string", "the bill", "the shirt"], "Box 4": ["the plane", "the crown", "the tape"], "Box 5": ["nothing"], "Box 6": ["the mirror", "the cream", "the train"]}}
{"sentence": "Box 0 contains nothing, Box 1 contains the bomb and the cup, Box 2 contains the clock and the jacket and the wire, Box 3 contains the picture, Box 4 contains nothing, Box 5 contains the chemical and the medicine and the rock, Box 6 contains the pipe. Put the drug into Box 0. Remove the bomb from Box 1. Remove the chemical and the rock from Box 5. Put the train and the watch into Box 5. Remove the medicine and the train from Box 5. Put the string into Box 6. Put the ball and the egg into Box 0. Move the pipe and the string from Box 6 to Box 5.", "sample_id": 842, "numops": 2, "final_states": {"Box 0": ["the egg", "the drug", "the ball"], "Box 1": ["the cup"], "Box 2": ["the clock", "the wire", "the jacket"], "Box 3": ["the picture"], "Box 4": ["nothing"], "Box 5": ["the watch", "the pipe", "the string"], "Box 6": ["nothing"]}}
{"sentence": "Box 0 contains the camera and the chemical and the milk, Box 1 contains nothing, Box 2 contains the book and the radio, Box 3 contains the phone, Box 4 contains the bus and the clock and the computer, Box 5 contains the beer, Box 6 contains nothing. Put the ring into Box 3. Remove the book and the radio from Box 2. Put the sheet into Box 2.", "sample_id": 844, "numops": 0, "final_states": {"Box 0": ["the camera", "the chemical", "the milk"], "Box 1": ["nothing"], "Box 2": ["the sheet"], "Box 3": ["the phone", "the ring"], "Box 4": ["the clock", "the computer", "the bus"], "Box 5": ["the beer"], "Box 6": ["nothing"]}}
{"sentence": "Box 0 contains the block and the sheet and the tape, Box 1 contains the note, Box 2 contains nothing, Box 3 contains nothing, Box 4 contains nothing, Box 5 contains the brick, Box 6 contains the drug and the game. Move the note from Box 1 to Box 6. Put the flower into Box 4. Move the note from Box 6 to Box 1. Move the game from Box 6 to Box 5. Put the computer and the shoe into Box 2. Remove the drug from Box 6. Move the flower from Box 4 to Box 5. Put the paper and the shirt into Box 6. Remove the note from Box 1.", "sample_id": 846, "numops": 0, "final_states": {"Box 0": ["the sheet", "the block", "the tape"], "Box 1": ["nothing"], "Box 2": ["the computer", "the shoe"], "Box 3": ["nothing"], "Box 4": ["nothing"], "Box 5": ["the flower", "the game", "the brick"], "Box 6": ["the paper", "the shirt"]}}
{"sentence": "Box 0 contains nothing, Box 1 contains the file and the plane, Box 2 contains the crown, Box 3 contains the picture and the shirt, Box 4 contains the plate and the radio, Box 5 contains nothing, Box 6 contains the television and the ticket. Move the shirt from Box 3 to Box 2. Remove the crown and the shirt from Box 2. Remove the ticket from Box 6. Move the picture from Box 3 to Box 6. Put the apple and the coffee and the wire into Box 5. Move the file from Box 1 to Box 6. Remove the picture and the television from Box 6. Remove the file from Box 6. Move the plane from Box 1 to Box 6.", "sample_id": 847, "numops": 0, "final_states": {"Box 0": ["nothing"], "Box 1": ["the glass", "nothing", "the dress"], "Box 2": ["the plane", "nothing"], "Box 3": ["nothing"], "Box 4": ["the plate", "the radio"], "Box 5": ["the coffee", "the apple", "the wire"], "Box 6": ["the plane", "nothing"]}}
{"sentence": "Box 0 contains the cash and the crown and the cup, Box 1 contains the brain and the chemical and the glass, Box 2 contains the drink, Box 3 contains nothing, Box 4 contains nothing, Box 5 contains the wire, Box 6 contains the ticket. Move the cash from Box 0 to Box 2. Move the cash and the drink from Box 2 to Box 4. Remove the glass from Box 1. Move the crown from Box 0 to Box 1. Remove the crown from Box 1. Remove the cup from Box 0. Remove the ticket from Box 6. Move the drink from Box 4 to Box 1. Put the clock into Box 0. Move the cash from Box 4 to Box 2. Remove the clock from Box 0. Remove the wire from Box 5.", "sample_id": 848, "numops": 5, "final_states": {"Box 0": ["nothing"], "Box 1": ["the chemical", "the brain", "the drink"], "Box 2": ["the cash"], "Box 3": ["nothing"], "Box 4": ["nothing"], "Box 5": ["nothing"], "Box 6": ["nothing"]}}
{"sentence": "Box 0 contains the coffee and the rock, Box 1 contains nothing, Box 2 contains nothing, Box 3 contains the crown and the picture and the plane, Box 4 contains the television, Box 5 contains the glass and the phone, Box 6 contains the creature and the ticket. Put the ring into Box 1. Move the ring from Box 1 to Box 6. Remove the picture from Box 3.", "sample_id": 849, "numops": 0, "final_states": {"Box 0": ["the coffee", "the rock"], "Box 1": ["nothing"], "Box 2": ["nothing"], "Box 3": ["the plane", "the crown"], "Box 4": ["the television"], "Box 5": ["the glass", "the phone"], "Box 6": ["the creature", "the ticket", "the ring"]}}
{"sentence": "Box 0 contains nothing, Box 1 contains the brick and the ice and the suit, Box 2 contains the book and the dish and the fig, Box 3 contains nothing, Box 4 contains nothing, Box 5 contains the painting and the train, Box 6 contains the camera and the tape and the tie. Move the tape from Box 6 to Box 5. Put the ticket into Box 3. Put the jacket into Box 0. Remove the brick from Box 1. Remove the book and the dish and the fig from Box 2. Remove the train from Box 5. Put the plant into Box 2. Move the plant from Box 2 to Box 1.", "sample_id": 852, "numops": 1, "final_states": {"Box 0": ["the jacket"], "Box 1": ["the plant", "the ice", "the suit"], "Box 2": ["nothing", "the block"], "Box 3": ["the painting", "the ticket"], "Box 4": ["nothing"], "Box 5": ["the painting", "the tape"], "Box 6": ["the camera", "nothing", "the tie"]}}
{"sentence": "Box 0 contains the car, Box 1 contains the clock and the drug and the stone, Box 2 contains the block and the bread and the fish, Box 3 contains nothing, Box 4 contains the chemical and the cream and the crown, Box 5 contains the dress and the magazine, Box 6 contains the boat and the bone. Remove the drug and the stone from Box 1. Move the bone from Box 6 to Box 1. Remove the clock from Box 1. Move the magazine from Box 5 to Box 1. Remove the chemical and the cream and the crown from Box 4.", "sample_id": 857, "numops": 0, "final_states": {"Box 0": ["the boat", "the car"], "Box 1": ["the bone", "the magazine", "nothing"], "Box 2": ["the bread", "the block", "the fish"], "Box 3": ["nothing"], "Box 4": ["nothing"], "Box 5": ["the note", "the dress"], "Box 6": ["the bone", "the picture", "the boat", "the rock"]}}
{"sentence": "Box 0 contains the dress and the flower and the map, Box 1 contains the cup, Box 2 contains the bell and the egg and the jacket, Box 3 contains the cream and the document, Box 4 contains the cross and the fan, Box 5 contains nothing, Box 6 contains the cake and the plane. Put the shoe into Box 1. Move the plane from Box 6 to Box 5. Move the document from Box 3 to Box 6. Move the bell and the jacket from Box 2 to Box 3. Move the bell and the jacket from Box 3 to Box 2.", "sample_id": 858, "numops": 0, "final_states": {"Box 0": ["the flower", "the map", "the dress"], "Box 1": ["the cup", "the shoe"], "Box 2": ["the bell", "the egg", "the jacket"], "Box 3": ["the cream"], "Box 4": ["the fan", "the cross"], "Box 5": ["the plane"], "Box 6": ["the document", "the cake"]}}
{"sentence": "Box 0 contains the bottle and the picture, Box 1 contains the bowl and the rose, Box 2 contains the letter and the shirt and the television, Box 3 contains the brain and the branch and the sheet, Box 4 contains the block and the cigarette and the drink, Box 5 contains nothing, Box 6 contains the engine. Put the book into Box 0.", "sample_id": 869, "numops": 1, "final_states": {"Box 0": ["the picture", "the bottle", "the book"], "Box 1": ["the rose", "the bowl"], "Box 2": ["the television", "the letter", "the shirt"], "Box 3": ["the sheet", "the brain", "the branch"], "Box 4": ["the cigarette", "the block", "the drink"], "Box 5": ["nothing"], "Box 6": ["the engine"]}}
{"sentence": "Box 0 contains the bomb, Box 1 contains nothing, Box 2 contains nothing, Box 3 contains the flower and the gift and the guitar, Box 4 contains the drink, Box 5 contains the newspaper and the painting and the radio, Box 6 contains the dish. Remove the flower and the guitar from Box 3. Remove the drink from Box 4. Remove the newspaper from Box 5. Move the gift from Box 3 to Box 1. Remove the radio from Box 5. Remove the painting from Box 5. Remove the dish from Box 6. Put the note and the seed into Box 5. Move the gift from Box 1 to Box 4. Put the string into Box 6. Remove the string from Box 6.", "sample_id": 872, "numops": 0, "final_states": {"Box 0": ["the bomb"], "Box 1": ["nothing"], "Box 2": ["nothing"], "Box 3": ["nothing"], "Box 4": ["the gift"], "Box 5": ["the note", "the seed"], "Box 6": ["nothing"]}}
{"sentence": "Box 0 contains the chemical, Box 1 contains the ball and the tie, Box 2 contains the bread, Box 3 contains the plane, Box 4 contains nothing, Box 5 contains the boot, Box 6 contains the card and the clock and the plate. Remove the ball from Box 1. Remove the card and the clock and the plate from Box 6. Move the boot from Box 5 to Box 6. Remove the plane from Box 3. Move the chemical from Box 0 to Box 5. Move the bread from Box 2 to Box 6. Remove the tie from Box 1. Put the creature and the ice into Box 1. Move the chemical from Box 5 to Box 4. Put the note and the tissue into Box 5. Put the television into Box 5. Remove the boot from Box 6.", "sample_id": 878, "numops": 1, "final_states": {"Box 0": ["nothing"], "Box 1": ["the creature", "the ice"], "Box 2": ["nothing"], "Box 3": ["nothing"], "Box 4": ["the chemical"], "Box 5": ["the television", "the note", "the tissue"], "Box 6": ["the bread"]}}
{"sentence": "Box 0 contains the computer and the crown, Box 1 contains the beer and the sheet and the train, Box 2 contains the clock and the leaf, Box 3 contains the picture and the shoe and the tie, Box 4 contains the glass and the plate and the suit, Box 5 contains nothing, Box 6 contains the ticket. Move the shoe from Box 3 to Box 6. Move the picture from Box 3 to Box 6. Remove the sheet and the train from Box 1. Remove the leaf from Box 2. Remove the computer and the crown from Box 0. Put the ball into Box 3. Remove the suit from Box 4. Put the newspaper into Box 2. Put the mirror into Box 0. Remove the beer from Box 1. Put the chemical into Box 3. Remove the ball and the chemical and the tie from Box 3.", "sample_id": 887, "numops": 2, "final_states": {"Box 0": ["the mirror"], "Box 1": ["nothing"], "Box 2": ["the clock", "the newspaper"], "Box 3": ["nothing"], "Box 4": ["the plate", "the glass"], "Box 5": ["nothing"], "Box 6": ["the picture", "the ticket", "the shoe"]}}
{"sentence": "Box 0 contains nothing, Box 1 contains the egg and the letter, Box 2 contains the knife and the shell and the train, Box 3 contains the brick and the jacket and the mirror, Box 4 contains the document and the radio, Box 5 contains the disk, Box 6 contains the bottle and the coat and the computer. Remove the knife and the shell and the train from Box 2. Remove the egg from Box 1. Put the newspaper into Box 2. Put the pipe and the ring into Box 0. Move the computer from Box 6 to Box 0. Remove the coat from Box 6. Move the brick and the mirror from Box 3 to Box 1. Remove the pipe from Box 0. Put the egg into Box 2.", "sample_id": 891, "numops": 3, "final_states": {"Box 0": ["the computer", "the ring"], "Box 1": ["the mirror", "the letter", "the brick"], "Box 2": ["the newspaper", "the egg"], "Box 3": ["the jacket"], "Box 4": ["the document", "the radio"], "Box 5": ["the disk"], "Box 6": ["the bottle"]}}
{"sentence": "Box 0 contains the bus and the wheel, Box 1 contains the cross, Box 2 contains the note and the shirt, Box 3 contains the suit and the tie, Box 4 contains the brain and the string, Box 5 contains the cash and the crown, Box 6 contains the cream and the seed. Move the tie from Box 3 to Box 6. Remove the note from Box 2. Put the jacket into Box 4. Move the brain from Box 4 to Box 0. Remove the suit from Box 3. Put the bill and the card and the drink into Box 3. Move the brain from Box 0 to Box 4.", "sample_id": 894, "numops": 2, "final_states": {"Box 0": ["the bus", "the wheel"], "Box 1": ["the cross"], "Box 2": ["the shirt"], "Box 3": ["the card", "the bill", "the drink"], "Box 4": ["the jacket", "the brain", "the string"], "Box 5": ["nothing", "the cash", "the crown"], "Box 6": ["the cream", "the seed", "the tie"]}}
{"sentence": "Box 0 contains the branch and the ticket, Box 1 contains nothing, Box 2 contains the bag and the brain and the knife, Box 3 contains the file and the milk, Box 4 contains the block and the watch, Box 5 contains nothing, Box 6 contains the key. Remove the watch from Box 4. Remove the bag and the brain and the knife from Box 2. Remove the key from Box 6. Move the file from Box 3 to Box 0. Move the milk from Box 3 to Box 4. Put the picture into Box 5. Remove the block from Box 4. Move the ticket from Box 0 to Box 6. Put the cheese into Box 3. Remove the branch and the file from Box 0. Move the picture from Box 5 to Box 2. Put the brick into Box 1.", "sample_id": 896, "numops": 3, "final_states": {"Box 0": ["nothing"], "Box 1": ["the brick"], "Box 2": ["the picture"], "Box 3": ["the cheese"], "Box 4": ["the milk"], "Box 5": ["nothing"], "Box 6": ["the ticket"]}}
{"sentence": "Box 0 contains the wire, Box 1 contains the bag and the boat and the leaf, Box 2 contains the seed, Box 3 contains the chemical and the file, Box 4 contains the painting, Box 5 contains the watch, Box 6 contains the glass. Move the glass from Box 6 to Box 3. Put the clock and the letter into Box 4. Put the coffee into Box 2. Move the coffee from Box 2 to Box 0. Remove the chemical and the file and the glass from Box 3. Remove the watch from Box 5. Move the wire from Box 0 to Box 2. Put the jacket into Box 3. Put the disk into Box 6.", "sample_id": 899, "numops": 2, "final_states": {"Box 0": ["the coffee", "the painting", "the letter"], "Box 1": ["the bag", "the boat", "the leaf"], "Box 2": ["the wire", "the seed"], "Box 3": ["the jacket"], "Box 4": ["the clock", "the painting", "the letter"], "Box 5": ["nothing"], "Box 6": ["the disk"]}}
{"sentence": "Box 0 contains the chemical and the clock, Box 1 contains nothing, Box 2 contains nothing, Box 3 contains the dress and the hat, Box 4 contains the beer and the letter, Box 5 contains the apple and the tape and the ticket, Box 6 contains the cup and the picture. Move the letter from Box 4 to Box 2. Remove the beer from Box 4. Put the knife into Box 6.", "sample_id": 901, "numops": 0, "final_states": {"Box 0": ["the chemical", "the clock"], "Box 1": ["nothing"], "Box 2": ["the letter"], "Box 3": ["the hat", "the dress"], "Box 4": ["nothing"], "Box 5": ["the apple", "the ticket", "the tape"], "Box 6": ["the knife", "the picture", "the cup"]}}
{"sentence": "Box 0 contains the coat and the cross and the wire, Box 1 contains the shirt, Box 2 contains the ticket and the wheel, Box 3 contains nothing, Box 4 contains the radio, Box 5 contains the branch and the hat and the phone, Box 6 contains nothing. Move the phone from Box 5 to Box 2. Remove the hat from Box 5.", "sample_id": 904, "numops": 0, "final_states": {"Box 0": ["the wire", "the coat", "the cross"], "Box 1": ["the shirt"], "Box 2": ["the phone", "the ticket", "the wheel"], "Box 3": ["nothing"], "Box 4": ["the radio"], "Box 5": ["the branch"], "Box 6": ["nothing"]}}
{"sentence": "Box 0 contains the note, Box 1 contains the boat and the branch and the television, Box 2 contains the computer and the picture, Box 3 contains nothing, Box 4 contains the cup, Box 5 contains the bag and the beer and the milk, Box 6 contains the hat and the watch. Move the cup from Box 4 to Box 0. Remove the note from Box 0. Put the ball into Box 6. Move the picture from Box 2 to Box 0. Put the cream into Box 4. Remove the branch from Box 1. Remove the beer from Box 5.", "sample_id": 916, "numops": 3, "final_states": {"Box 0": ["the picture", "the cup"], "Box 1": ["the television", "the boat"], "Box 2": ["the computer"], "Box 3": ["nothing"], "Box 4": ["the cream", "the machine"], "Box 5": ["the bag", "the milk"], "Box 6": ["the ball", "the hat", "the watch"]}}
{"sentence": "Box 0 contains the bus and the leaf and the ring, Box 1 contains nothing, Box 2 contains the key and the tie, Box 3 contains the cake and the chemical and the watch, Box 4 contains the coat and the paper and the tissue, Box 5 contains the string and the ticket, Box 6 contains the cheese and the cigarette. Move the ticket from Box 5 to Box 2. Remove the leaf from Box 0.", "sample_id": 918, "numops": 1, "final_states": {"Box 0": ["the bus", "the ring"], "Box 1": ["nothing"], "Box 2": ["the key", "the ticket", "the tie"], "Box 3": ["the chemical", "the cake", "the watch"], "Box 4": ["the paper", "the coat", "the tissue"], "Box 5": ["the string"], "Box 6": ["the cigarette", "the cheese"]}}
{"sentence": "Box 0 contains nothing, Box 1 contains the coat and the creature, Box 2 contains the cross and the jacket and the knife, Box 3 contains the pot and the ring, Box 4 contains the ball and the glass and the phone, Box 5 contains the drink and the hat and the picture, Box 6 contains the tie. Put the guitar into Box 0. Move the coat and the creature from Box 1 to Box 0. Remove the tie from Box 6.", "sample_id": 920, "numops": 2, "final_states": {"Box 0": ["the creature", "the coat", "the guitar"], "Box 1": ["the bone", "nothing", "the car", "the drug"], "Box 2": ["the knife", "the cross", "the jacket"], "Box 3": ["the pot", "the ring"], "Box 4": ["the glass", "the phone", "the ball"], "Box 5": ["the picture", "the hat", "the drink"], "Box 6": ["the plane", "nothing", "the newspaper"]}}
{"sentence": "Box 0 contains the glass and the note and the string, Box 1 contains the bus and the medicine and the suit, Box 2 contains the guitar and the magazine and the shirt, Box 3 contains the boat and the camera and the car, Box 4 contains the tape and the ticket, Box 5 contains the fig, Box 6 contains the newspaper and the pipe. Put the chemical into Box 6. Remove the guitar and the shirt from Box 2. Move the fig from Box 5 to Box 2. Remove the fig from Box 2. Remove the bus and the suit from Box 1. Move the magazine from Box 2 to Box 5.", "sample_id": 923, "numops": 0, "final_states": {"Box 0": ["the glass", "the note", "the string"], "Box 1": ["the medicine", "the beer"], "Box 2": ["nothing", "the ticket"], "Box 3": ["the camera", "the car", "the boat"], "Box 4": ["the ticket", "the tape"], "Box 5": ["the magazine", "the watch", "nothing"], "Box 6": ["the newspaper", "the pipe", "the chemical"]}}
{"sentence": "Box 0 contains the coffee and the engine and the fan, Box 1 contains the cash and the ice, Box 2 contains the cheese, Box 3 contains the bell and the crown and the picture, Box 4 contains the drink, Box 5 contains the machine, Box 6 contains the letter. Put the egg into Box 5. Move the cheese from Box 2 to Box 4. Remove the bell from Box 3. Remove the engine from Box 0. Move the coffee from Box 0 to Box 6. Put the document into Box 3. Remove the coffee and the letter from Box 6. Move the egg from Box 5 to Box 2. Move the cheese and the drink from Box 4 to Box 6. Remove the egg from Box 2.", "sample_id": 935, "numops": 2, "final_states": {"Box 0": ["the fan"], "Box 1": ["the cash", "the ice"], "Box 2": ["nothing"], "Box 3": ["the document", "the picture", "the crown"], "Box 4": ["nothing"], "Box 5": ["the machine"], "Box 6": ["the cheese", "the drink"]}}
{"sentence": "Box 0 contains the plane and the seed, Box 1 contains the pipe, Box 2 contains the engine and the tissue, Box 3 contains the picture and the string, Box 4 contains the bomb and the cheese, Box 5 contains the brick and the tie, Box 6 contains the flower and the key. Move the string from Box 3 to Box 1. Put the tape into Box 3. Move the engine from Box 2 to Box 4. Move the tissue from Box 2 to Box 3. Remove the cheese from Box 4. Remove the plane and the seed from Box 0. Remove the tape and the tissue from Box 3. Remove the pipe and the string from Box 1.", "sample_id": 940, "numops": 1, "final_states": {"Box 0": ["the apple", "nothing", "the tea"], "Box 1": ["nothing"], "Box 2": ["nothing"], "Box 3": ["the television", "the picture"], "Box 4": ["the engine", "the bomb"], "Box 5": ["the tie", "the brick"], "Box 6": ["the flower", "the key"]}}
{"sentence": "Box 0 contains the bell and the phone, Box 1 contains the note and the rock, Box 2 contains the dish and the egg and the rose, Box 3 contains the ice and the tissue, Box 4 contains the ring, Box 5 contains the boat and the meat and the pot, Box 6 contains the map. Move the note from Box 1 to Box 3. Remove the ring from Box 4. Put the suit into Box 6. Remove the ice and the note and the tissue from Box 3. Remove the rock from Box 1. Put the apple into Box 3. Remove the meat from Box 5. Move the apple from Box 3 to Box 6. Move the rose from Box 2 to Box 3.", "sample_id": 943, "numops": 0, "final_states": {"Box 0": ["the phone", "the bell"], "Box 1": ["nothing"], "Box 2": ["the dish", "the egg"], "Box 3": ["the rose"], "Box 4": ["nothing"], "Box 5": ["the pot", "the boat"], "Box 6": ["the apple", "the map", "the suit"]}}
{"sentence": "Box 0 contains the cross and the egg, Box 1 contains the bomb and the card, Box 2 contains nothing, Box 3 contains nothing, Box 4 contains the branch and the stone, Box 5 contains the clock and the tie, Box 6 contains the creature. Remove the creature from Box 6. Put the coffee into Box 1. Move the egg from Box 0 to Box 3. Put the wire into Box 4. Put the seed into Box 3. Move the cross from Box 0 to Box 3. Remove the branch and the stone and the wire from Box 4. Put the beer into Box 2. Remove the cross and the egg from Box 3. Remove the seed from Box 3. Move the tie from Box 5 to Box 3. Move the bomb and the coffee from Box 1 to Box 0.", "sample_id": 947, "numops": 3, "final_states": {"Box 0": ["the coffee", "the bomb"], "Box 1": ["the card"], "Box 2": ["the beer"], "Box 3": ["the tie"], "Box 4": ["nothing"], "Box 5": ["the clock"], "Box 6": ["nothing"]}}
{"sentence": "Box 0 contains the meat, Box 1 contains the cigarette and the rock, Box 2 contains the bus and the milk and the picture, Box 3 contains the boat, Box 4 contains the car and the fish and the string, Box 5 contains nothing, Box 6 contains the pipe and the radio. Remove the meat from Box 0. Remove the string from Box 4. Remove the boat from Box 3. Remove the pipe and the radio from Box 6. Move the rock from Box 1 to Box 3. Remove the cigarette from Box 1. Put the apple and the creature and the plate into Box 6. Move the rock from Box 3 to Box 1. Put the drink and the glass into Box 1. Remove the apple from Box 6. Put the card into Box 3. Put the dish into Box 5.", "sample_id": 958, "numops": 1, "final_states": {"Box 0": ["nothing"], "Box 1": ["the glass", "the rock", "the drink"], "Box 2": ["the picture", "the bus", "the milk"], "Box 3": ["the card"], "Box 4": ["the fish", "the car"], "Box 5": ["the dish"], "Box 6": ["the plate", "the creature"]}}
{"sentence": "Box 0 contains nothing, Box 1 contains the picture, Box 2 contains the ball, Box 3 contains the cream and the leaf and the train, Box 4 contains the bottle, Box 5 contains the creature, Box 6 contains the dress. Move the dress from Box 6 to Box 1. Put the boat into Box 2. Remove the bottle from Box 4. Remove the cream from Box 3.", "sample_id": 959, "numops": 0, "final_states": {"Box 0": ["nothing"], "Box 1": ["the picture", "the dress"], "Box 2": ["the boat", "the ball"], "Box 3": ["the train", "the leaf"], "Box 4": ["nothing"], "Box 5": ["the creature"], "Box 6": ["nothing"]}}
{"sentence": "Box 0 contains the bell and the document, Box 1 contains the cross and the medicine and the radio, Box 2 contains the beer and the machine, Box 3 contains the wire, Box 4 contains the string, Box 5 contains the apple and the bottle, Box 6 contains the bomb and the pot and the tape. Remove the bell and the document from Box 0. Remove the wire from Box 3. Put the dress into Box 0. Move the apple and the bottle from Box 5 to Box 3. Remove the machine from Box 2. Put the shell into Box 2. Remove the string from Box 4. Move the apple from Box 3 to Box 4.", "sample_id": 968, "numops": 2, "final_states": {"Box 0": ["the dress"], "Box 1": ["the medicine", "the cross", "the radio"], "Box 2": ["the shell", "the bomb", "the tape", "the beer"], "Box 3": ["the bottle"], "Box 4": ["the apple"], "Box 5": ["the flower", "the cream", "nothing", "the drink"], "Box 6": ["the pot", "the bomb", "the tape"]}}
{"sentence": "Box 0 contains the brain and the newspaper and the rock, Box 1 contains the wheel, Box 2 contains the bag and the block and the map, Box 3 contains the bus and the gift and the radio, Box 4 contains the plant, Box 5 contains the string, Box 6 contains the chemical and the clock. Put the plane into Box 5. Move the wheel from Box 1 to Box 4. Put the file into Box 6. Remove the string from Box 5. Move the bag from Box 2 to Box 1. Remove the bus and the gift and the radio from Box 3. Remove the plane from Box 5. Remove the block from Box 2. Put the watch into Box 2. Move the chemical from Box 6 to Box 5.", "sample_id": 969, "numops": 0, "final_states": {"Box 0": ["the newspaper", "the brain", "the rock"], "Box 1": ["the bag"], "Box 2": ["the map", "the watch"], "Box 3": ["nothing"], "Box 4": ["the plant", "the wheel"], "Box 5": ["the chemical"], "Box 6": ["the file", "the clock"]}}
{"sentence": "Box 0 contains the knife, Box 1 contains the ball and the cigarette and the coat, Box 2 contains the card and the fig and the ring, Box 3 contains the bag and the camera and the gift, Box 4 contains the clock and the tie, Box 5 contains nothing, Box 6 contains nothing. Remove the card from Box 2. Remove the fig from Box 2. Move the clock from Box 4 to Box 2. Move the coat from Box 1 to Box 6. Remove the tie from Box 4. Move the knife from Box 0 to Box 4. Remove the knife from Box 4. Put the knife into Box 1. Put the car and the pot into Box 5. Move the cigarette from Box 1 to Box 4. Remove the cigarette from Box 4.", "sample_id": 971, "numops": 1, "final_states": {"Box 0": ["nothing"], "Box 1": ["the knife", "the ball"], "Box 2": ["the clock", "the ring"], "Box 3": ["the gift", "the camera", "the bag"], "Box 4": ["nothing"], "Box 5": ["the pot", "the car"], "Box 6": ["the coat"]}}
{"sentence": "Box 0 contains the seed, Box 1 contains the cake and the document and the television, Box 2 contains the glass and the plane, Box 3 contains nothing, Box 4 contains the bone and the cheese and the coffee, Box 5 contains the ball, Box 6 contains the book and the disk and the tissue. Put the shell into Box 5. Move the disk from Box 6 to Box 0. Put the map into Box 0. Put the flower into Box 6. Move the document and the television from Box 1 to Box 3. Remove the shell from Box 5. Remove the bone and the coffee from Box 4. Move the glass and the plane from Box 2 to Box 1. Remove the document and the television from Box 3. Put the paper and the television into Box 5. Move the cheese from Box 4 to Box 3.", "sample_id": 979, "numops": 2, "final_states": {"Box 0": ["the map", "the disk", "the seed"], "Box 1": ["the glass", "the plane", "the cake"], "Box 2": ["nothing"], "Box 3": ["the cheese"], "Box 4": ["nothing"], "Box 5": ["the paper", "the television", "the ball"], "Box 6": ["the flower", "the book", "the tissue"]}}
{"sentence": "Box 0 contains the guitar and the magazine and the picture, Box 1 contains the plate, Box 2 contains the bell and the branch and the medicine, Box 3 contains the boat and the key and the paper, Box 4 contains the cup and the tea and the wheel, Box 5 contains the bill, Box 6 contains the shirt. Move the shirt from Box 6 to Box 1. Remove the bell and the branch from Box 2. Put the drug into Box 1. Put the watch into Box 6. Remove the watch from Box 6. Move the cup and the tea from Box 4 to Box 5.", "sample_id": 980, "numops": 0, "final_states": {"Box 0": ["the rose", "the picture", "the magazine", "the guitar"], "Box 1": ["the plate", "the drug", "the shirt"], "Box 2": ["the painting", "the medicine", "the plane", "the pot"], "Box 3": ["the paper", "the key", "the boat"], "Box 4": ["the wheel"], "Box 5": ["the bill", "the tea", "the cup"], "Box 6": ["the magazine", "nothing"]}}
{"sentence": "Box 0 contains nothing, Box 1 contains nothing, Box 2 contains the meat, Box 3 contains the fan, Box 4 contains the bell, Box 5 contains the map, Box 6 contains the bottle and the car and the document.", "sample_id": 982, "numops": 0, "final_states": {"Box 0": ["nothing"], "Box 1": ["the glass", "the creature", "the clock", "nothing"], "Box 2": ["the cigarette", "the creature", "the meat"], "Box 3": ["the fan", "nothing"], "Box 4": ["the bell"], "Box 5": ["the map", "nothing"], "Box 6": ["the document", "the bottle", "the car", "nothing"]}}
{"sentence": "Box 0 contains nothing, Box 1 contains the coat and the key, Box 2 contains the bag, Box 3 contains nothing, Box 4 contains the cash and the ring, Box 5 contains the gift, Box 6 contains the television. Remove the cash and the ring from Box 4. Move the key from Box 1 to Box 4. Move the coat from Box 1 to Box 5. Move the bag from Box 2 to Box 3. Remove the coat from Box 5. Remove the gift from Box 5. Put the apple and the mirror and the plane into Box 1. Move the mirror from Box 1 to Box 4. Move the apple and the plane from Box 1 to Box 0. Remove the apple and the plane from Box 0.", "sample_id": 985, "numops": 2, "final_states": {"Box 0": ["nothing"], "Box 1": ["nothing"], "Box 2": ["nothing"], "Box 3": ["the bag"], "Box 4": ["the mirror", "the key"], "Box 5": ["nothing"], "Box 6": ["the television", "the cup"]}}
{"sentence": "Box 0 contains the shell, Box 1 contains the book and the magazine and the rose, Box 2 contains the knife and the tape, Box 3 contains the fig and the mirror, Box 4 contains nothing, Box 5 contains the dress, Box 6 contains the drug and the jacket. Remove the shell from Box 0. Move the book and the magazine and the rose from Box 1 to Box 4. Move the jacket from Box 6 to Box 1. Remove the rose from Box 4. Move the dress from Box 5 to Box 2. Put the card and the string into Box 5. Move the jacket from Box 1 to Box 0. Move the jacket from Box 0 to Box 4. Put the cake into Box 0. Remove the book and the jacket and the magazine from Box 4. Put the ball into Box 6.", "sample_id": 992, "numops": 4, "final_states": {"Box 0": ["the cake"], "Box 1": ["nothing"], "Box 2": ["the knife", "the tape", "the dress"], "Box 3": ["the mirror", "the fig"], "Box 4": ["nothing"], "Box 5": ["the card", "the string"], "Box 6": ["the drug", "the ball"]}}
{"sentence": "Box 0 contains the boat and the leaf, Box 1 contains the cash, Box 2 contains nothing, Box 3 contains the key and the map and the picture, Box 4 contains the ring, Box 5 contains the coffee, Box 6 contains the chemical and the guitar. Put the fish into Box 6. Remove the ring from Box 4. Put the bottle into Box 4. Move the fish from Box 6 to Box 0. Put the pot into Box 5. Remove the guitar from Box 6. Move the chemical from Box 6 to Box 5. Remove the coffee from Box 5. Remove the chemical and the pot from Box 5. Move the map and the picture from Box 3 to Box 5.", "sample_id": 993, "numops": 1, "final_states": {"Box 0": ["the fish", "the boat", "the leaf"], "Box 1": ["the cash"], "Box 2": ["nothing"], "Box 3": ["the map", "the key"], "Box 4": ["the bottle"], "Box 5": ["the map", "the picture"], "Box 6": ["nothing"]}}
{"sentence": "Box 0 contains the bread and the letter and the ticket, Box 1 contains the cash and the paper and the string, Box 2 contains the bowl and the fig and the plate, Box 3 contains the block and the tea, Box 4 contains the brick and the gift, Box 5 contains the engine and the flower and the milk, Box 6 contains nothing.", "sample_id": 1009, "numops": 0, "final_states": {"Box 0": ["the bread", "the letter", "the ticket"], "Box 1": ["the paper", "the cash", "the string"], "Box 2": ["the plate", "the fig", "the bowl"], "Box 3": ["the tea", "the block"], "Box 4": ["the gift", "the brick"], "Box 5": ["the flower", "the engine", "the milk"], "Box 6": ["nothing"]}}
{"sentence": "Box 0 contains the dish and the document, Box 1 contains the coffee and the ice, Box 2 contains the branch and the ring, Box 3 contains nothing, Box 4 contains the cream and the meat and the plant, Box 5 contains the bus and the sheet, Box 6 contains the bottle and the disk and the phone. Move the dish from Box 0 to Box 1. Remove the branch and the ring from Box 2. Put the creature and the ring into Box 3. Move the ring from Box 3 to Box 0. Remove the ring from Box 0. Put the camera and the fan into Box 0. Remove the disk and the phone from Box 6. Remove the fan from Box 0. Move the creature from Box 3 to Box 0. Put the fish into Box 5. Move the bus from Box 5 to Box 6.", "sample_id": 1011, "numops": 6, "final_states": {"Box 0": ["the camera", "the document", "the creature"], "Box 1": ["the coffee", "the dish", "the ice"], "Box 2": ["nothing"], "Box 3": ["nothing"], "Box 4": ["the cream", "the plant", "the meat"], "Box 5": ["the fish", "the sheet"], "Box 6": ["the bottle", "the bus"]}}
{"sentence": "Box 0 contains the key and the magazine, Box 1 contains the shell, Box 2 contains the shirt, Box 3 contains the map and the medicine, Box 4 contains the plane and the tape, Box 5 contains the bag and the computer, Box 6 contains the bus and the creature and the meat. Remove the creature from Box 6. Remove the map and the medicine from Box 3. Move the computer from Box 5 to Box 4.", "sample_id": 1013, "numops": 0, "final_states": {"Box 0": ["the key", "the magazine", "the bill"], "Box 1": ["the shell", "nothing"], "Box 2": ["the tape", "the shirt"], "Box 3": ["nothing"], "Box 4": ["the plane", "the tape", "the computer"], "Box 5": ["the bag"], "Box 6": ["the bus", "the meat"]}}
{"sentence": "Box 0 contains the bag, Box 1 contains the drug and the wire, Box 2 contains the branch and the leaf and the ticket, Box 3 contains the coffee and the milk and the plane, Box 4 contains nothing, Box 5 contains nothing, Box 6 contains the television. Move the wire from Box 1 to Box 6. Remove the wire from Box 6. Remove the branch from Box 2. Remove the plane from Box 3. Remove the drug from Box 1. Move the ticket from Box 2 to Box 6. Move the television and the ticket from Box 6 to Box 1. Remove the ticket from Box 1. Remove the coffee and the milk from Box 3. Put the shoe into Box 1.", "sample_id": 1029, "numops": 0, "final_states": {"Box 0": ["the shoe", "the bag", "the leaf"], "Box 1": ["the television", "the shoe"], "Box 2": ["nothing", "the leaf"], "Box 3": ["nothing"], "Box 4": ["nothing"], "Box 5": ["nothing"], "Box 6": ["nothing"]}}
{"sentence": "Box 0 contains the coffee and the egg and the string, Box 1 contains the card and the pot, Box 2 contains the disk, Box 3 contains the drug and the key, Box 4 contains the cream, Box 5 contains the block and the creature and the tea, Box 6 contains the rock. Put the map into Box 1. Move the card and the map from Box 1 to Box 4. Remove the disk from Box 2. Move the block and the creature from Box 5 to Box 6. Remove the pot from Box 1. Move the drug and the key from Box 3 to Box 2. Put the boot and the radio into Box 3. Move the radio from Box 3 to Box 5. Move the map from Box 4 to Box 5. Move the key from Box 2 to Box 3. Put the plate into Box 4.", "sample_id": 1030, "numops": 0, "final_states": {"Box 0": ["the coffee", "the egg", "the string"], "Box 1": ["nothing"], "Box 2": ["the drug"], "Box 3": ["the key", "the boot"], "Box 4": ["the card", "the cream", "the plate"], "Box 5": ["the map", "the tea", "the radio"], "Box 6": ["the creature", "the rock", "the block"]}}
{"sentence": "Box 0 contains the cross and the newspaper and the train, Box 1 contains the crown, Box 2 contains the bag and the car and the tea, Box 3 contains the note, Box 4 contains the bomb and the medicine, Box 5 contains nothing, Box 6 contains the knife and the letter. Move the note from Box 3 to Box 4. Move the bag from Box 2 to Box 5. Remove the letter from Box 6. Move the note from Box 4 to Box 5. Move the car from Box 2 to Box 1. Move the medicine from Box 4 to Box 3. Put the document into Box 5. Remove the tea from Box 2. Remove the car from Box 1. Remove the cross and the newspaper from Box 0. Move the crown from Box 1 to Box 6. Put the card into Box 1.", "sample_id": 1035, "numops": 1, "final_states": {"Box 0": ["the train"], "Box 1": ["the card"], "Box 2": ["nothing"], "Box 3": ["the medicine"], "Box 4": ["the bomb"], "Box 5": ["the document", "the bag", "the note"], "Box 6": ["the knife", "the crown"]}}
{"sentence": "Box 0 contains nothing, Box 1 contains the milk and the pipe, Box 2 contains nothing, Box 3 contains nothing, Box 4 contains nothing, Box 5 contains the magazine and the tie, Box 6 contains nothing. Remove the milk from Box 1. Put the bag and the plant into Box 0. Remove the bag from Box 0. Remove the plant from Box 0. Put the bag and the clock into Box 1. Put the fig into Box 0. Put the machine into Box 3. Put the cream into Box 3. Put the cigarette into Box 4. Remove the cigarette from Box 4. Remove the machine from Box 3.", "sample_id": 1042, "numops": 4, "final_states": {"Box 0": ["the fig"], "Box 1": ["the clock", "the bag", "the pipe"], "Box 2": ["nothing"], "Box 3": ["the cream"], "Box 4": ["nothing"], "Box 5": ["the magazine", "the tie"], "Box 6": ["nothing"]}}
{"sentence": "Box 0 contains the creature and the magazine, Box 1 contains the disk and the radio, Box 2 contains the beer and the sheet, Box 3 contains nothing, Box 4 contains nothing, Box 5 contains the ball and the fig, Box 6 contains the bell and the engine. Move the disk and the radio from Box 1 to Box 3. Put the shoe into Box 4. Put the milk into Box 2. Remove the bell from Box 6.", "sample_id": 1046, "numops": 0, "final_states": {"Box 0": ["the magazine", "the creature"], "Box 1": ["nothing"], "Box 2": ["the sheet", "the beer", "the milk"], "Box 3": ["the disk", "the radio"], "Box 4": ["the shoe"], "Box 5": ["the fig", "the ball"], "Box 6": ["the engine"]}}
{"sentence": "Box 0 contains nothing, Box 1 contains the medicine, Box 2 contains the beer and the boat and the suit, Box 3 contains the pipe, Box 4 contains the brain and the newspaper and the note, Box 5 contains the plate and the shoe, Box 6 contains the bell and the card. Remove the plate and the shoe from Box 5. Remove the newspaper and the note from Box 4. Remove the medicine from Box 1. Remove the beer and the boat from Box 2. Put the cream into Box 6. Remove the cream from Box 6. Put the bomb and the painting into Box 2. Remove the bell from Box 6. Put the bone and the gift into Box 4. Remove the pipe from Box 3. Move the bomb and the painting from Box 2 to Box 6.", "sample_id": 1049, "numops": 0, "final_states": {"Box 0": ["nothing"], "Box 1": ["nothing"], "Box 2": ["the suit"], "Box 3": ["nothing"], "Box 4": ["the bone", "the gift", "the brain"], "Box 5": ["nothing"], "Box 6": ["the card", "the painting", "the bomb"]}}
{"sentence": "Box 0 contains the machine, Box 1 contains the pipe, Box 2 contains the brain and the tie, Box 3 contains the dish and the plate, Box 4 contains the car, Box 5 contains the chemical and the rock, Box 6 contains the bag and the egg and the newspaper. Remove the machine from Box 0. Move the car from Box 4 to Box 2. Move the pipe from Box 1 to Box 3. Remove the bag from Box 6. Put the boat into Box 1. Move the chemical from Box 5 to Box 0. Put the bill into Box 5.", "sample_id": 1053, "numops": 2, "final_states": {"Box 0": ["the chemical"], "Box 1": ["the boat"], "Box 2": ["the car", "the brain", "the tie"], "Box 3": ["the plate", "the dish", "the pipe"], "Box 4": ["nothing"], "Box 5": ["the bill", "the rock"], "Box 6": ["the newspaper", "the egg"]}}
{"sentence": "Box 0 contains the file, Box 1 contains the cream and the plane and the tie, Box 2 contains the bag and the chemical and the rock, Box 3 contains the computer and the gift and the medicine, Box 4 contains the bill and the bone and the jacket, Box 5 contains the shoe, Box 6 contains the ball and the bowl. Remove the bill and the jacket from Box 4. Put the disk into Box 0.", "sample_id": 1055, "numops": 1, "final_states": {"Box 0": ["the file", "the disk"], "Box 1": ["the cream", "the plane", "the tie"], "Box 2": ["the chemical", "the bag", "the rock"], "Box 3": ["the gift", "the computer", "the medicine"], "Box 4": ["the bone"], "Box 5": ["the shoe"], "Box 6": ["the bowl", "the ball"]}}
{"sentence": "Box 0 contains nothing, Box 1 contains the leaf and the pipe, Box 2 contains the chemical and the map and the wire, Box 3 contains the cash, Box 4 contains the newspaper, Box 5 contains the book and the tie, Box 6 contains the watch. Remove the newspaper from Box 4. Move the cash from Box 3 to Box 1. Put the block into Box 4. Put the boot into Box 3. Move the leaf and the pipe from Box 1 to Box 4. Move the boot from Box 3 to Box 6. Remove the leaf from Box 4. Put the sheet into Box 0. Put the rose into Box 0. Put the engine into Box 4. Put the glass and the meat into Box 3.", "sample_id": 1060, "numops": 2, "final_states": {"Box 0": ["the rose", "the sheet"], "Box 1": ["the cash"], "Box 2": ["the chemical", "the map", "the wire"], "Box 3": ["the glass", "the meat"], "Box 4": ["the engine", "the pipe", "the block"], "Box 5": ["the book", "the tie"], "Box 6": ["the boot", "the watch"]}}
{"sentence": "Box 0 contains the brain and the coffee, Box 1 contains the fish, Box 2 contains the bag and the guitar and the paper, Box 3 contains the car and the meat, Box 4 contains the gift and the mirror, Box 5 contains the card, Box 6 contains the cream and the crown and the key. Move the fish from Box 1 to Box 0. Remove the crown and the key from Box 6. Put the phone and the plate into Box 5. Remove the phone from Box 5. Move the coffee from Box 0 to Box 3. Put the leaf into Box 1. Remove the guitar from Box 2. Move the gift from Box 4 to Box 2. Move the cream from Box 6 to Box 5.", "sample_id": 1071, "numops": 2, "final_states": {"Box 0": ["the fish", "the brain"], "Box 1": ["the leaf"], "Box 2": ["the paper", "the gift", "the bag"], "Box 3": ["the coffee", "the car", "the meat"], "Box 4": ["the mirror"], "Box 5": ["the card", "the cream", "the plate"], "Box 6": ["nothing"]}}
{"sentence": "Box 0 contains nothing, Box 1 contains the cheese and the drug and the gift, Box 2 contains nothing, Box 3 contains the radio and the wheel, Box 4 contains the apple and the dish, Box 5 contains the clock and the cup and the leaf, Box 6 contains the bus and the cross. Put the brick into Box 4. Move the cross from Box 6 to Box 3. Remove the cross and the radio from Box 3. Remove the drug from Box 1. Remove the clock from Box 5.", "sample_id": 1074, "numops": 0, "final_states": {"Box 0": ["nothing"], "Box 1": ["the gift", "the television", "the cheese"], "Box 2": ["nothing"], "Box 3": ["the wheel"], "Box 4": ["the brick", "the apple", "the dish"], "Box 5": ["the cup", "the leaf"], "Box 6": ["the bus"]}}
{"sentence": "Box 0 contains the suit, Box 1 contains the beer and the cup and the drink, Box 2 contains the dress and the string and the tea, Box 3 contains the bill and the branch and the fan, Box 4 contains the disk and the pot and the radio, Box 5 contains the bomb and the engine, Box 6 contains the card and the document. Remove the engine from Box 5. Move the string and the tea from Box 2 to Box 5. Remove the dress from Box 2. Put the mirror into Box 2. Move the cup and the drink from Box 1 to Box 2. Remove the beer from Box 1. Move the drink and the mirror from Box 2 to Box 1. Remove the bomb and the string and the tea from Box 5. Move the drink from Box 1 to Box 5. Remove the drink from Box 5. Put the magazine into Box 5.", "sample_id": 1085, "numops": 0, "final_states": {"Box 0": ["the suit"], "Box 1": ["the mirror"], "Box 2": ["nothing", "the cup"], "Box 3": ["the fan", "the bill", "the branch"], "Box 4": ["the pot", "the disk", "the radio"], "Box 5": ["the magazine"], "Box 6": ["the card", "the document"]}}
{"sentence": "Box 0 contains the boat and the cake and the magazine, Box 1 contains the game, Box 2 contains the shoe, Box 3 contains the document and the rose, Box 4 contains the cream, Box 5 contains the bowl and the guitar and the tea, Box 6 contains the bone and the egg. Put the book into Box 4. Remove the tea from Box 5. Remove the document from Box 3.", "sample_id": 1095, "numops": 0, "final_states": {"Box 0": ["the magazine", "the boat", "the cake"], "Box 1": ["the game"], "Box 2": ["the shoe"], "Box 3": ["the rose"], "Box 4": ["the cream", "the book"], "Box 5": ["the bowl", "the guitar"], "Box 6": ["the bone", "the egg"]}}
{"sentence": "Box 0 contains the plate, Box 1 contains nothing, Box 2 contains the string and the tape, Box 3 contains the engine and the glass, Box 4 contains the block and the map, Box 5 contains the brick and the bus, Box 6 contains the bill and the cream and the phone. Remove the glass from Box 3. Move the brick and the bus from Box 5 to Box 0. Remove the engine from Box 3. Remove the block from Box 4. Remove the bus and the plate from Box 0. Put the block into Box 5. Remove the map from Box 4. Remove the cream and the phone from Box 6. Move the bill from Box 6 to Box 2. Remove the bill from Box 2. Move the string from Box 2 to Box 4. Remove the brick from Box 0.", "sample_id": 1097, "numops": 3, "final_states": {"Box 0": ["nothing"], "Box 1": ["nothing"], "Box 2": ["the tape"], "Box 3": ["nothing"], "Box 4": ["the string"], "Box 5": ["the block"], "Box 6": ["nothing"]}}
{"sentence": "Box 0 contains nothing, Box 1 contains the cigarette and the hat, Box 2 contains the bowl and the stone, Box 3 contains the ice and the medicine, Box 4 contains the bag, Box 5 contains the file and the seed and the television, Box 6 contains the map. Remove the map from Box 6. Put the train into Box 1. Remove the seed and the television from Box 5. Move the cigarette from Box 1 to Box 0. Remove the file from Box 5. Remove the hat and the train from Box 1. Remove the cigarette from Box 0. Move the bag from Box 4 to Box 6. Move the bag from Box 6 to Box 5. Put the leaf into Box 5. Remove the bag from Box 5. Move the bowl and the stone from Box 2 to Box 4.", "sample_id": 1102, "numops": 2, "final_states": {"Box 0": ["nothing"], "Box 1": ["nothing"], "Box 2": ["nothing"], "Box 3": ["the medicine", "the ice"], "Box 4": ["the bowl", "the stone"], "Box 5": ["the leaf"], "Box 6": ["nothing"]}}
{"sentence": "Box 0 contains the bone and the television, Box 1 contains the drink and the fig, Box 2 contains the glass, Box 3 contains the pot, Box 4 contains the key and the plate and the shoe, Box 5 contains the beer and the egg, Box 6 contains nothing. Move the pot from Box 3 to Box 2.", "sample_id": 1103, "numops": 0, "final_states": {"Box 0": ["the bone", "the television", "nothing"], "Box 1": ["the fig", "nothing", "the drink"], "Box 2": ["the glass", "nothing", "the pot"], "Box 3": ["the paper", "the game", "nothing"], "Box 4": ["the plate", "the shoe", "the key"], "Box 5": ["the glass", "the beer", "the egg"], "Box 6": ["the cream", "nothing"]}}
{"sentence": "Box 0 contains the boot, Box 1 contains the card and the leaf, Box 2 contains nothing, Box 3 contains the plane, Box 4 contains the game and the phone, Box 5 contains the bowl and the tape and the tea, Box 6 contains the chemical and the guitar. Put the drug into Box 6. Move the drug from Box 6 to Box 0. Remove the bowl and the tape and the tea from Box 5. Put the bus into Box 1. Remove the phone from Box 4. Move the bus and the card from Box 1 to Box 2. Move the leaf from Box 1 to Box 5. Remove the game from Box 4. Move the bus from Box 2 to Box 4. Put the television into Box 3. Move the leaf from Box 5 to Box 0. Put the shoe into Box 5.", "sample_id": 1116, "numops": 2, "final_states": {"Box 0": ["the drug", "the boot", "the leaf"], "Box 1": ["nothing"], "Box 2": ["the card"], "Box 3": ["the television", "the plane"], "Box 4": ["the bus"], "Box 5": ["the shoe"], "Box 6": ["the chemical", "the guitar"]}}
{"sentence": "Box 0 contains nothing, Box 1 contains the cigarette and the suit, Box 2 contains nothing, Box 3 contains the crown, Box 4 contains the chemical and the fan, Box 5 contains the seed and the tie, Box 6 contains the bottle and the drink and the jacket. Remove the seed from Box 5. Remove the crown from Box 3. Remove the bottle and the jacket from Box 6. Put the book into Box 3.", "sample_id": 1121, "numops": 0, "final_states": {"Box 0": ["nothing"], "Box 1": ["the leaf", "the cigarette", "the suit"], "Box 2": ["nothing"], "Box 3": ["the book"], "Box 4": ["the fan", "the chemical", "nothing", "the cigarette"], "Box 5": ["the bus", "the tie"], "Box 6": ["the drink"]}}
{"sentence": "Box 0 contains the block and the computer and the cream, Box 1 contains nothing, Box 2 contains the radio, Box 3 contains the apple and the fan, Box 4 contains the tea, Box 5 contains the boot and the branch and the watch, Box 6 contains the clock. Move the fan from Box 3 to Box 1. Put the stone into Box 2. Move the clock from Box 6 to Box 2. Put the bill and the map into Box 4. Move the bill and the map and the tea from Box 4 to Box 6. Move the boot and the watch from Box 5 to Box 3. Move the radio and the stone from Box 2 to Box 1. Remove the branch from Box 5. Remove the tea from Box 6. Put the cigarette into Box 6. Move the bill and the cigarette from Box 6 to Box 4.", "sample_id": 1126, "numops": 0, "final_states": {"Box 0": ["the cream", "the computer", "the block"], "Box 1": ["the fan", "the stone", "the radio"], "Box 2": ["the clock"], "Box 3": ["the apple", "the boot", "the watch"], "Box 4": ["the cigarette", "the bill"], "Box 5": ["nothing"], "Box 6": ["the map"]}}
{"sentence": "Box 0 contains the bowl and the creature, Box 1 contains the drug and the key and the shirt, Box 2 contains nothing, Box 3 contains the gift and the paper, Box 4 contains nothing, Box 5 contains the bag and the computer and the letter, Box 6 contains the stone. Move the stone from Box 6 to Box 3. Move the bowl and the creature from Box 0 to Box 6. Put the rose into Box 6. Put the fish into Box 4. Move the bag and the letter from Box 5 to Box 4. Remove the bowl and the creature from Box 6. Remove the computer from Box 5. Move the gift and the stone from Box 3 to Box 6. Remove the rose and the stone from Box 6. Move the bag and the fish and the letter from Box 4 to Box 0. Remove the bag from Box 0.", "sample_id": 1137, "numops": 3, "final_states": {"Box 0": ["the fish", "the letter"], "Box 1": ["the drug", "the shirt", "the key"], "Box 2": ["the paper", "nothing"], "Box 3": ["the paper", "nothing"], "Box 4": ["nothing"], "Box 5": ["nothing"], "Box 6": ["the gift"]}}
{"sentence": "Box 0 contains the knife, Box 1 contains nothing, Box 2 contains the ball and the rose, Box 3 contains the suit, Box 4 contains the key and the plate and the ring, Box 5 contains the fan and the meat, Box 6 contains the file and the sheet. Move the suit from Box 3 to Box 2. Move the suit from Box 2 to Box 3. Move the sheet from Box 6 to Box 2. Remove the fan and the meat from Box 5. Remove the suit from Box 3. Move the file from Box 6 to Box 5. Remove the knife from Box 0.", "sample_id": 1138, "numops": 1, "final_states": {"Box 0": ["nothing"], "Box 1": ["nothing"], "Box 2": ["the rose", "the sheet", "the ball"], "Box 3": ["nothing"], "Box 4": ["the plate", "the key", "the ring"], "Box 5": ["the file"], "Box 6": ["nothing"]}}
{"sentence": "Box 0 contains the bread and the leaf, Box 1 contains nothing, Box 2 contains nothing, Box 3 contains the apple and the cash, Box 4 contains the bag and the chemical and the tape, Box 5 contains nothing, Box 6 contains the beer and the cigarette and the shell. Move the bag and the chemical and the tape from Box 4 to Box 5. Put the drug into Box 3. Put the drink into Box 2. Put the milk into Box 0. Remove the cigarette and the shell from Box 6. Put the boot and the rose into Box 2. Move the bag and the tape from Box 5 to Box 6. Remove the drug from Box 3.", "sample_id": 1140, "numops": 1, "final_states": {"Box 0": ["the bread", "the milk", "the leaf"], "Box 1": ["nothing"], "Box 2": ["the rose", "the boot", "the drink"], "Box 3": ["the apple", "the cash"], "Box 4": ["nothing", "the tape"], "Box 5": ["the chemical"], "Box 6": ["the bag", "the tape", "the beer"]}}
{"sentence": "Box 0 contains the computer and the pipe and the wire, Box 1 contains the bottle and the stone and the tape, Box 2 contains the crown and the letter, Box 3 contains the car and the magazine and the note, Box 4 contains the bus and the flower and the tie, Box 5 contains the cheese and the drink and the sheet, Box 6 contains the camera and the leaf and the rock. Remove the bus from Box 4. Remove the leaf and the rock from Box 6. Remove the car and the magazine from Box 3. Put the shell into Box 3. Move the crown from Box 2 to Box 4. Move the bottle from Box 1 to Box 2. Move the cheese from Box 5 to Box 3. Remove the note and the shell from Box 3. Remove the camera from Box 6. Put the egg into Box 3.", "sample_id": 1147, "numops": 0, "final_states": {"Box 0": ["the wire", "the computer", "the pipe"], "Box 1": ["the stone", "the tape"], "Box 2": ["the bottle", "the letter"], "Box 3": ["the egg", "the cheese"], "Box 4": ["the flower", "the tie", "the crown"], "Box 5": ["the sheet", "the drink"], "Box 6": ["nothing"]}}
{"sentence": "Box 0 contains the camera and the fan and the pot, Box 1 contains nothing, Box 2 contains nothing, Box 3 contains the train, Box 4 contains the clock and the fig and the tea, Box 5 contains the bill and the machine and the wire, Box 6 contains nothing. Move the pot from Box 0 to Box 1. Remove the pot from Box 1. Move the bill and the machine from Box 5 to Box 3. Move the wire from Box 5 to Box 6. Put the tissue into Box 2. Move the wire from Box 6 to Box 2. Move the clock and the fig from Box 4 to Box 5. Move the tissue and the wire from Box 2 to Box 4. Remove the clock and the fig from Box 5.", "sample_id": 1151, "numops": 1, "final_states": {"Box 0": ["the camera", "the fan"], "Box 1": ["nothing"], "Box 2": ["nothing"], "Box 3": ["the train", "the bill", "the machine"], "Box 4": ["the wire", "the tea", "the tissue"], "Box 5": ["nothing"], "Box 6": ["nothing"]}}
{"sentence": "Box 0 contains the picture and the shoe, Box 1 contains the bell and the coffee and the sheet, Box 2 contains the glass, Box 3 contains the chemical and the pot, Box 4 contains the boot, Box 5 contains nothing, Box 6 contains the document and the file and the gift. Move the bell and the sheet from Box 1 to Box 4. Put the drink into Box 0. Put the cigarette and the newspaper into Box 2. Remove the shoe from Box 0.", "sample_id": 1153, "numops": 2, "final_states": {"Box 0": ["the picture", "the drink"], "Box 1": ["the coffee"], "Box 2": ["the glass", "the cigarette", "the newspaper"], "Box 3": ["the chemical", "the pot"], "Box 4": ["the sheet", "the bell", "the boot"], "Box 5": ["nothing"], "Box 6": ["the file", "the gift", "the document"]}}
{"sentence": "Box 0 contains nothing, Box 1 contains the bus and the file, Box 2 contains the engine and the medicine and the milk, Box 3 contains the brain and the glass, Box 4 contains the bomb and the clock and the tea, Box 5 contains the cream and the paper and the wire, Box 6 contains the bread and the cup and the newspaper. Remove the engine and the medicine from Box 2. Remove the milk from Box 2. Put the bottle into Box 1. Put the dress into Box 2. Remove the bread and the cup and the newspaper from Box 6. Remove the brain and the glass from Box 3. Put the bone into Box 0. Put the coat into Box 0. Remove the clock from Box 4.", "sample_id": 1155, "numops": 2, "final_states": {"Box 0": ["the bone", "the coat"], "Box 1": ["the file", "the bottle", "the bus"], "Box 2": ["the dress"], "Box 3": ["nothing"], "Box 4": ["the bomb", "the tea"], "Box 5": ["the paper", "the cream", "the wire"], "Box 6": ["nothing"]}}
{"sentence": "Box 0 contains the bus, Box 1 contains the bowl and the dish and the suit, Box 2 contains nothing, Box 3 contains the pot, Box 4 contains the boat and the egg, Box 5 contains the boot and the drug, Box 6 contains the cigarette. Put the plate into Box 2. Remove the cigarette from Box 6. Put the key into Box 2. Put the bill into Box 5. Remove the key and the plate from Box 2. Remove the bowl from Box 1. Move the suit from Box 1 to Box 2. Remove the suit from Box 2. Remove the egg from Box 4. Move the bus from Box 0 to Box 2.", "sample_id": 1156, "numops": 1, "final_states": {"Box 0": ["nothing"], "Box 1": ["the dish"], "Box 2": ["the bus", "nothing"], "Box 3": ["the pot", "the bus"], "Box 4": ["the boat"], "Box 5": ["the drug", "the boot", "the bill"], "Box 6": ["nothing"]}}
{"sentence": "Box 0 contains the fig, Box 1 contains the newspaper and the tape, Box 2 contains the bread and the shirt, Box 3 contains the bus and the hat and the rose, Box 4 contains the bag and the boat and the suit, Box 5 contains the plane and the string, Box 6 contains the coat and the magazine. Move the bag from Box 4 to Box 5. Put the bowl into Box 4. Put the picture into Box 6. Put the gift into Box 2. Remove the bus from Box 3. Remove the tape from Box 1. Remove the hat from Box 3. Put the bus into Box 1. Remove the newspaper from Box 1. Remove the rose from Box 3.", "sample_id": 1158, "numops": 0, "final_states": {"Box 0": ["the fig"], "Box 1": ["the bus"], "Box 2": ["the bread", "the gift", "the shirt"], "Box 3": ["nothing"], "Box 4": ["the bowl", "the boat", "the suit"], "Box 5": ["the plane", "the bag", "the string"], "Box 6": ["the picture", "the magazine", "the coat"]}}
{"sentence": "Box 0 contains the card and the clock and the glass, Box 1 contains the mirror, Box 2 contains the ring, Box 3 contains the cake and the cheese, Box 4 contains the cross and the shoe and the stone, Box 5 contains the fig, Box 6 contains nothing. Remove the cake and the cheese from Box 3. Move the ring from Box 2 to Box 1. Remove the mirror and the ring from Box 1. Remove the shoe and the stone from Box 4. Put the branch and the seed into Box 5. Move the branch and the fig and the seed from Box 5 to Box 3. Put the radio into Box 5. Move the cross from Box 4 to Box 5. Move the seed from Box 3 to Box 2.", "sample_id": 1169, "numops": 0, "final_states": {"Box 0": ["the card", "the clock", "the glass"], "Box 1": ["nothing"], "Box 2": ["the seed"], "Box 3": ["the fig", "the branch"], "Box 4": ["nothing"], "Box 5": ["the radio", "the cross"], "Box 6": ["nothing"]}}
{"sentence": "Box 0 contains the clock and the pot and the tea, Box 1 contains the apple and the bone and the plate, Box 2 contains the watch, Box 3 contains the cheese, Box 4 contains the newspaper and the painting, Box 5 contains nothing, Box 6 contains the beer and the cup. Remove the watch from Box 2. Remove the cheese from Box 3. Put the bottle and the letter into Box 2.", "sample_id": 1177, "numops": 0, "final_states": {"Box 0": ["the clock", "the tea", "the pot"], "Box 1": ["the bone", "the apple", "the plate"], "Box 2": ["the bottle", "the letter"], "Box 3": ["nothing"], "Box 4": ["the painting", "the newspaper"], "Box 5": ["nothing"], "Box 6": ["the beer", "the cup"]}}
{"sentence": "Box 0 contains the drug and the fish and the shirt, Box 1 contains the mirror and the television, Box 2 contains the machine and the shoe, Box 3 contains the ring, Box 4 contains the bus and the rose and the watch, Box 5 contains the engine, Box 6 contains the ice and the pipe. Put the crown into Box 1. Put the sheet into Box 2. Move the shoe from Box 2 to Box 6. Remove the ring from Box 3. Put the beer and the car into Box 5. Remove the mirror and the television from Box 1. Move the rose and the watch from Box 4 to Box 3.", "sample_id": 1180, "numops": 0, "final_states": {"Box 0": ["the fish", "the drug", "the shirt"], "Box 1": ["the crown"], "Box 2": ["the sheet", "the machine"], "Box 3": ["the rose", "the watch"], "Box 4": ["the bus"], "Box 5": ["the engine", "the beer", "the car"], "Box 6": ["the pipe", "the ice", "the shoe"]}}
{"sentence": "Box 0 contains the paper and the shirt, Box 1 contains nothing, Box 2 contains the cream and the dish, Box 3 contains the leaf and the rock, Box 4 contains the boat and the branch and the train, Box 5 contains the coffee and the pipe and the tie, Box 6 contains nothing.", "sample_id": 1186, "numops": 0, "final_states": {"Box 0": ["the paper", "the shirt"], "Box 1": ["nothing"], "Box 2": ["the cream", "the dish"], "Box 3": ["the rock", "the leaf"], "Box 4": ["the boat", "the branch", "the train"], "Box 5": ["the coffee", "the pipe", "the tie"], "Box 6": ["nothing"]}}
{"sentence": "Box 0 contains the bell and the cigarette and the tape, Box 1 contains the picture and the string and the suit, Box 2 contains the brick and the computer, Box 3 contains the beer and the cream and the fan, Box 4 contains nothing, Box 5 contains the plate, Box 6 contains nothing. Remove the cream from Box 3. Remove the picture and the string from Box 1. Move the suit from Box 1 to Box 2. Move the plate from Box 5 to Box 6. Put the rock into Box 3. Move the computer from Box 2 to Box 1. Remove the plate from Box 6.", "sample_id": 1187, "numops": 0, "final_states": {"Box 0": ["the bell", "the cigarette", "the tape"], "Box 1": ["the computer"], "Box 2": ["the suit", "the brick"], "Box 3": ["the fan", "the beer", "the rock"], "Box 4": ["nothing"], "Box 5": ["nothing"], "Box 6": ["nothing"]}}
{"sentence": "Box 0 contains the car, Box 1 contains the bone, Box 2 contains the chemical and the cup and the hat, Box 3 contains the clock and the mirror and the string, Box 4 contains the bell and the card and the note, Box 5 contains nothing, Box 6 contains the coffee and the radio and the watch. Remove the bone from Box 1. Move the coffee from Box 6 to Box 0. Put the game into Box 0. Remove the car from Box 0. Remove the coffee and the game from Box 0. Move the mirror from Box 3 to Box 6. Remove the clock from Box 3. Remove the chemical from Box 2. Remove the string from Box 3. Move the radio from Box 6 to Box 1.", "sample_id": 1188, "numops": 4, "final_states": {"Box 0": ["nothing"], "Box 1": ["the radio"], "Box 2": ["the hat", "the cup"], "Box 3": ["nothing"], "Box 4": ["the card", "the bell", "the note"], "Box 5": ["nothing"], "Box 6": ["the mirror", "the watch"]}}
{"sentence": "Box 0 contains the brain and the crown and the fish, Box 1 contains the apple, Box 2 contains the game, Box 3 contains the gift, Box 4 contains the beer and the computer and the cross, Box 5 contains the jacket and the tea and the tie, Box 6 contains the cash and the newspaper and the plant. Remove the cash and the newspaper and the plant from Box 6. Remove the game from Box 2. Move the apple from Box 1 to Box 2. Remove the apple from Box 2. Remove the brain and the fish from Box 0. Remove the tie from Box 5. Remove the jacket from Box 5. Put the bell into Box 1. Put the apple into Box 6. Move the crown from Box 0 to Box 2. Move the apple from Box 6 to Box 0. Remove the apple from Box 0.", "sample_id": 1193, "numops": 4, "final_states": {"Box 0": ["nothing"], "Box 1": ["the bell"], "Box 2": ["the crown"], "Box 3": ["the gift"], "Box 4": ["the computer", "the beer", "the cross"], "Box 5": ["the tea"], "Box 6": ["nothing"]}}
{"sentence": "Box 0 contains the engine, Box 1 contains the bottle, Box 2 contains the letter, Box 3 contains the brain and the shoe and the ticket, Box 4 contains the egg and the map, Box 5 contains the cake and the crown and the medicine, Box 6 contains the cream and the drug. Put the gift into Box 4. Put the wheel into Box 6. Move the crown and the medicine from Box 5 to Box 2. Put the pipe into Box 1. Remove the bottle from Box 1. Remove the pipe from Box 1. Move the wheel from Box 6 to Box 1. Remove the ticket from Box 3. Remove the shoe from Box 3. Put the boat into Box 0. Move the brain from Box 3 to Box 1.", "sample_id": 1195, "numops": 1, "final_states": {"Box 0": ["the engine", "the boat"], "Box 1": ["the brain", "the wheel"], "Box 2": ["the medicine", "the letter", "the crown"], "Box 3": ["nothing"], "Box 4": ["the map", "the gift", "the egg"], "Box 5": ["the cake"], "Box 6": ["the cream", "the drug"]}}
{"sentence": "Box 0 contains the coat, Box 1 contains the card and the crown and the newspaper, Box 2 contains the shoe, Box 3 contains the brain and the chemical and the cream, Box 4 contains the wheel, Box 5 contains the fan, Box 6 contains the picture and the ticket. Move the coat from Box 0 to Box 4. Move the chemical and the cream from Box 3 to Box 2. Move the fan from Box 5 to Box 3.", "sample_id": 1197, "numops": 1, "final_states": {"Box 0": ["nothing"], "Box 1": ["the card", "the newspaper", "the crown"], "Box 2": ["the chemical", "the shoe", "the cream"], "Box 3": ["the fan", "the brain"], "Box 4": ["the coat", "the wheel"], "Box 5": ["nothing"], "Box 6": ["the picture", "the ticket"]}}
{"sentence": "Box 0 contains nothing, Box 1 contains the plate and the radio, Box 2 contains the fish, Box 3 contains the tissue, Box 4 contains nothing, Box 5 contains the boat and the ring, Box 6 contains the bill and the plant and the shell. Move the fish from Box 2 to Box 4.", "sample_id": 1200, "numops": 0, "final_states": {"Box 0": ["nothing"], "Box 1": ["the plate", "the radio"], "Box 2": ["nothing"], "Box 3": ["the tissue"], "Box 4": ["the fish"], "Box 5": ["the boat", "the ring"], "Box 6": ["the shell", "the plant", "the bill"]}}
{"sentence": "Box 0 contains the tie, Box 1 contains the bus and the cream, Box 2 contains the ball and the bill, Box 3 contains the bomb and the car, Box 4 contains the brick and the sheet and the wire, Box 5 contains the knife and the phone and the train, Box 6 contains nothing. Remove the sheet and the wire from Box 4. Move the bus and the cream from Box 1 to Box 0.", "sample_id": 1201, "numops": 1, "final_states": {"Box 0": ["the cream", "the bus", "the car", "the tie"], "Box 1": ["the magazine", "nothing", "the boat"], "Box 2": ["the bill", "the ball"], "Box 3": ["the car", "nothing", "the bomb"], "Box 4": ["nothing", "the brick"], "Box 5": ["the knife", "the phone", "the train", "nothing"], "Box 6": ["nothing"]}}
{"sentence": "Box 0 contains the bone, Box 1 contains the suit, Box 2 contains the cake and the letter and the medicine, Box 3 contains nothing, Box 4 contains the game and the gift and the hat, Box 5 contains the bell and the boat and the knife, Box 6 contains the car and the cigarette and the disk. Remove the bell and the knife from Box 5. Remove the suit from Box 1. Move the cake and the letter from Box 2 to Box 1. Put the drug and the rock into Box 0. Remove the medicine from Box 2.", "sample_id": 1205, "numops": 1, "final_states": {"Box 0": ["the bone", "the drug", "the rock"], "Box 1": ["the letter", "the cake"], "Box 2": ["nothing"], "Box 3": ["nothing"], "Box 4": ["the game", "the gift", "the hat"], "Box 5": ["the boat"], "Box 6": ["the cigarette", "the car", "the disk"]}}
{"sentence": "Box 0 contains the book and the fish and the watch, Box 1 contains the branch and the hat and the shell, Box 2 contains the bread and the seed, Box 3 contains the apple, Box 4 contains the brain and the document, Box 5 contains the crown and the plane, Box 6 contains the cup. Remove the cup from Box 6. Remove the brain and the document from Box 4. Move the seed from Box 2 to Box 4. Move the branch and the hat from Box 1 to Box 3. Remove the bread from Box 2.", "sample_id": 1207, "numops": 0, "final_states": {"Box 0": ["the fish", "the book", "the watch"], "Box 1": ["the shell"], "Box 2": ["nothing"], "Box 3": ["the apple", "the branch", "the hat"], "Box 4": ["the seed"], "Box 5": ["the plane", "the crown"], "Box 6": ["nothing"]}}
{"sentence": "Box 0 contains the dress, Box 1 contains the drug and the milk, Box 2 contains the newspaper, Box 3 contains the fig, Box 4 contains the coat and the letter and the paper, Box 5 contains the drink and the shoe, Box 6 contains the computer and the fan and the tea. Move the dress from Box 0 to Box 3. Move the fan and the tea from Box 6 to Box 0. Move the computer from Box 6 to Box 1. Move the shoe from Box 5 to Box 6. Remove the dress and the fig from Box 3. Put the disk into Box 3. Remove the computer from Box 1. Put the shirt into Box 3. Put the bill into Box 3. Remove the fan from Box 0.", "sample_id": 1208, "numops": 3, "final_states": {"Box 0": ["the tea"], "Box 1": ["the milk", "the drug"], "Box 2": ["the newspaper"], "Box 3": ["the bill", "the disk", "the shirt"], "Box 4": ["the paper", "the letter", "the coat"], "Box 5": ["the drink"], "Box 6": ["the shoe"]}}
{"sentence": "Box 0 contains the ball and the shoe, Box 1 contains the stone, Box 2 contains the sheet and the wire, Box 3 contains the book and the boot and the shirt, Box 4 contains the branch, Box 5 contains the creature, Box 6 contains the beer and the bell and the coffee. Move the stone from Box 1 to Box 5. Move the wire from Box 2 to Box 0. Remove the sheet from Box 2. Put the letter into Box 1. Remove the beer and the bell and the coffee from Box 6. Put the fig and the ring into Box 4. Move the stone from Box 5 to Box 6. Remove the creature from Box 5. Remove the stone from Box 6.", "sample_id": 1214, "numops": 1, "final_states": {"Box 0": ["the wire", "the shoe", "the ball"], "Box 1": ["the letter"], "Box 2": ["nothing"], "Box 3": ["the boot", "the book", "the shirt"], "Box 4": ["the fig", "the branch", "the ring"], "Box 5": ["nothing"], "Box 6": ["nothing"]}}
{"sentence": "Box 0 contains the block and the bottle and the wire, Box 1 contains the boot and the cheese and the leaf, Box 2 contains the meat, Box 3 contains the bomb and the game, Box 4 contains the bone and the jacket and the letter, Box 5 contains the plane, Box 6 contains the bell and the cash and the ice. Remove the cheese from Box 1. Remove the meat from Box 2. Put the cup and the shell into Box 5. Remove the bell from Box 6. Move the bomb from Box 3 to Box 2. Remove the jacket and the letter from Box 4.", "sample_id": 1217, "numops": 0, "final_states": {"Box 0": ["the bottle", "the wire", "the block"], "Box 1": ["the boot", "the leaf"], "Box 2": ["the bomb"], "Box 3": ["the game"], "Box 4": ["the bone"], "Box 5": ["the shell", "the plane", "the cup"], "Box 6": ["the cash", "the ice"]}}
{"sentence": "Box 0 contains the bell and the boat and the bus, Box 1 contains the branch and the brick and the television, Box 2 contains the card and the fan and the wire, Box 3 contains the book, Box 4 contains the ice, Box 5 contains nothing, Box 6 contains the drug and the rose. Remove the boat from Box 0. Remove the drug and the rose from Box 6. Remove the card from Box 2. Move the bell and the bus from Box 0 to Box 6. Remove the ice from Box 4. Put the paper and the tea into Box 0.", "sample_id": 1225, "numops": 3, "final_states": {"Box 0": ["the paper", "the tea"], "Box 1": ["the television", "the brick", "the branch"], "Box 2": ["the fan", "the wire"], "Box 3": ["the book"], "Box 4": ["nothing"], "Box 5": ["nothing"], "Box 6": ["the bell", "the note", "the bus", "the brain", "nothing"]}}
{"sentence": "Box 0 contains the disk, Box 1 contains the ball and the crown, Box 2 contains the shirt, Box 3 contains nothing, Box 4 contains the bottle and the egg and the leaf, Box 5 contains the block and the engine and the plane, Box 6 contains the bomb and the flower. Move the shirt from Box 2 to Box 1. Remove the bomb and the flower from Box 6. Put the car and the game into Box 2. Put the letter into Box 0. Remove the bottle and the egg from Box 4. Remove the leaf from Box 4. Put the bag and the magazine into Box 4. Remove the car and the game from Box 2. Move the disk and the letter from Box 0 to Box 6. Put the seed into Box 4. Put the rock into Box 0. Remove the letter from Box 6.", "sample_id": 1226, "numops": 3, "final_states": {"Box 0": ["the rock"], "Box 1": ["the shirt", "the crown", "the ball"], "Box 2": ["nothing"], "Box 3": ["nothing"], "Box 4": ["the magazine", "the bag", "the seed"], "Box 5": ["the plane", "the engine", "the block"], "Box 6": ["the disk"]}}
{"sentence": "Box 0 contains nothing, Box 1 contains nothing, Box 2 contains the document and the flower and the machine, Box 3 contains the cream, Box 4 contains the bone, Box 5 contains the knife and the pot, Box 6 contains the phone and the rock. Remove the bone from Box 4. Move the pot from Box 5 to Box 6. Move the rock from Box 6 to Box 1. Move the rock from Box 1 to Box 0. Remove the document and the machine from Box 2. Move the flower from Box 2 to Box 1. Put the milk and the tea into Box 1.", "sample_id": 1231, "numops": 1, "final_states": {"Box 0": ["the rock"], "Box 1": ["the milk", "the flower", "the tea"], "Box 2": ["nothing"], "Box 3": ["the cream"], "Box 4": ["the sheet", "the book", "the pipe", "nothing"], "Box 5": ["the knife", "the shoe"], "Box 6": ["the pot", "the phone", "nothing"]}}
{"sentence": "Box 0 contains the cake, Box 1 contains nothing, Box 2 contains the coffee and the tie, Box 3 contains the pipe and the rock and the shoe, Box 4 contains the bread and the egg and the meat, Box 5 contains nothing, Box 6 contains the brick. Remove the bread and the egg from Box 4. Put the note into Box 4. Put the tea into Box 1. Move the shoe from Box 3 to Box 2. Move the pipe and the rock from Box 3 to Box 5. Remove the brick from Box 6. Remove the tea from Box 1.", "sample_id": 1232, "numops": 0, "final_states": {"Box 0": ["the cake"], "Box 1": ["the coffee", "nothing"], "Box 2": ["the coffee", "the tie", "the shoe"], "Box 3": ["nothing"], "Box 4": ["the note", "the meat", "the tie"], "Box 5": ["the pipe", "the rock"], "Box 6": ["nothing"]}}
{"sentence": "Box 0 contains the beer and the picture, Box 1 contains the string, Box 2 contains the cross, Box 3 contains nothing, Box 4 contains the bowl, Box 5 contains the drink and the medicine and the rose, Box 6 contains nothing. Move the string from Box 1 to Box 4. Move the cross from Box 2 to Box 0. Put the magazine into Box 1. Put the boot and the file into Box 6. Remove the medicine and the rose from Box 5. Remove the file from Box 6. Move the bowl and the string from Box 4 to Box 1. Move the bowl and the string from Box 1 to Box 5. Move the boot from Box 6 to Box 4. Move the boot from Box 4 to Box 1. Put the flower into Box 1.", "sample_id": 1239, "numops": 1, "final_states": {"Box 0": ["the picture", "the cross", "the beer"], "Box 1": ["the magazine", "the boot", "the flower"], "Box 2": ["nothing"], "Box 3": ["nothing"], "Box 4": ["nothing"], "Box 5": ["the bowl", "the string", "the drink"], "Box 6": ["nothing"]}}
{"sentence": "Box 0 contains the car and the coat and the flower, Box 1 contains the document and the leaf, Box 2 contains the picture and the pot, Box 3 contains the file and the medicine, Box 4 contains the cheese and the radio and the ring, Box 5 contains the bottle and the seed and the sheet, Box 6 contains nothing. Put the drink into Box 1. Remove the sheet from Box 5. Remove the coat from Box 0. Put the dress into Box 3. Move the dress and the file from Box 3 to Box 6. Remove the medicine from Box 3. Put the ball into Box 5.", "sample_id": 1245, "numops": 1, "final_states": {"Box 0": ["the flower", "the car"], "Box 1": ["the document", "the leaf", "the drink"], "Box 2": ["the pot", "the picture"], "Box 3": ["nothing"], "Box 4": ["the cheese", "the ring", "the radio"], "Box 5": ["the seed", "the bottle", "the ball"], "Box 6": ["the file", "the game", "the dress"]}}
{"sentence": "Box 0 contains the camera and the chemical and the plant, Box 1 contains nothing, Box 2 contains the newspaper and the tea and the wire, Box 3 contains nothing, Box 4 contains the branch and the painting and the shell, Box 5 contains the cake and the disk and the machine, Box 6 contains the cross and the phone and the picture. Remove the chemical and the plant from Box 0. Remove the camera from Box 0. Remove the shell from Box 4. Remove the newspaper from Box 2. Move the disk from Box 5 to Box 4. Move the disk and the painting from Box 4 to Box 0. Move the disk and the painting from Box 0 to Box 4.", "sample_id": 1247, "numops": 4, "final_states": {"Box 0": ["nothing"], "Box 1": ["nothing"], "Box 2": ["the paper", "the jacket", "the flower", "the wire", "the tea"], "Box 3": ["nothing"], "Box 4": ["the disk", "the painting", "the branch"], "Box 5": ["the machine", "the cake"], "Box 6": ["the phone", "nothing", "the picture", "the cross"]}}
{"sentence": "Box 0 contains the gift, Box 1 contains the ball and the bone and the sheet, Box 2 contains the game and the map and the tissue, Box 3 contains nothing, Box 4 contains the document, Box 5 contains the key, Box 6 contains the bomb and the machine and the picture. Move the key from Box 5 to Box 0.", "sample_id": 1248, "numops": 1, "final_states": {"Box 0": ["the gift", "the brick", "the key"], "Box 1": ["the sheet", "the map", "the bone", "the ball"], "Box 2": ["the game", "the map", "the tissue"], "Box 3": ["the fish", "nothing", "the tie"], "Box 4": ["the document"], "Box 5": ["nothing"], "Box 6": ["the picture", "the bomb", "the machine"]}}
{"sentence": "Box 0 contains the cigarette, Box 1 contains the drug and the fig, Box 2 contains the brain and the pot, Box 3 contains the coffee, Box 4 contains the egg and the string and the tissue, Box 5 contains the map, Box 6 contains the boat and the plane. Put the card into Box 2. Remove the fig from Box 1. Remove the brain and the card and the pot from Box 2. Move the map from Box 5 to Box 0. Move the egg and the string and the tissue from Box 4 to Box 5. Remove the boat from Box 6. Move the map from Box 0 to Box 1. Put the ball and the sheet into Box 4. Move the drug and the map from Box 1 to Box 2. Move the plane from Box 6 to Box 1. Move the cigarette from Box 0 to Box 2. Put the bus into Box 1.", "sample_id": 1256, "numops": 3, "final_states": {"Box 0": ["nothing"], "Box 1": ["the plane", "the bus"], "Box 2": ["the map", "the cigarette", "the drug"], "Box 3": ["the coffee"], "Box 4": ["the sheet", "the ball"], "Box 5": ["the egg", "the tissue", "the string"], "Box 6": ["nothing"]}}
{"sentence": "Box 0 contains the computer and the ring, Box 1 contains the card and the key and the shirt, Box 2 contains the brick and the dish and the medicine, Box 3 contains the pipe, Box 4 contains the newspaper, Box 5 contains the bone and the paper, Box 6 contains the ticket. Remove the ticket from Box 6. Remove the newspaper from Box 4. Put the fish and the gift and the tape into Box 6. Put the drink into Box 5. Remove the pipe from Box 3. Move the brick from Box 2 to Box 4. Put the meat and the mirror into Box 4. Remove the meat and the mirror from Box 4. Remove the bone and the paper from Box 5. Move the key from Box 1 to Box 2. Remove the dish and the key from Box 2. Remove the drink from Box 5.", "sample_id": 1260, "numops": 0, "final_states": {"Box 0": ["the computer", "the ring"], "Box 1": ["the card", "the shirt"], "Box 2": ["the medicine"], "Box 3": ["nothing"], "Box 4": ["the brick"], "Box 5": ["nothing"], "Box 6": ["the fish", "the gift", "the tape"]}}
{"sentence": "Box 0 contains the meat and the plate and the sheet, Box 1 contains the brain and the gift and the wire, Box 2 contains the book, Box 3 contains the branch, Box 4 contains the cheese and the dish and the fig, Box 5 contains the card and the file, Box 6 contains the egg. Move the egg from Box 6 to Box 2. Remove the brain from Box 1. Remove the gift from Box 1. Move the meat from Box 0 to Box 5. Put the game into Box 0. Remove the plate and the sheet from Box 0. Remove the card and the meat from Box 5. Remove the book and the egg from Box 2. Remove the game from Box 0. Remove the file from Box 5. Put the magazine into Box 0. Remove the wire from Box 1.", "sample_id": 1269, "numops": 5, "final_states": {"Box 0": ["the magazine"], "Box 1": ["nothing"], "Box 2": ["nothing"], "Box 3": ["the branch"], "Box 4": ["the fig", "the dish", "the cheese"], "Box 5": ["nothing"], "Box 6": ["nothing"]}}
{"sentence": "Box 0 contains the brick and the picture, Box 1 contains nothing, Box 2 contains the pot, Box 3 contains the clock, Box 4 contains the cup and the fan and the game, Box 5 contains the ice and the suit, Box 6 contains the painting and the phone and the shell.", "sample_id": 1270, "numops": 0, "final_states": {"Box 0": ["the picture", "the brick"], "Box 1": ["nothing"], "Box 2": ["the pot"], "Box 3": ["the clock"], "Box 4": ["the fan", "the game", "the cup"], "Box 5": ["the ice", "the suit"], "Box 6": ["the shell", "the painting", "the phone"]}}
{"sentence": "Box 0 contains the apple and the leaf and the milk, Box 1 contains the beer and the branch and the pipe, Box 2 contains the bread and the clock, Box 3 contains the bell and the watch, Box 4 contains the drink and the egg, Box 5 contains the chemical and the fish and the key, Box 6 contains the camera. Remove the camera from Box 6. Remove the watch from Box 3. Remove the bread and the clock from Box 2. Move the branch and the pipe from Box 1 to Box 3. Move the beer from Box 1 to Box 6. Move the beer from Box 6 to Box 1. Remove the milk from Box 0. Put the plate into Box 1. Move the bell and the pipe from Box 3 to Box 6. Put the jacket into Box 6. Put the clock into Box 3. Put the ticket into Box 2.", "sample_id": 1278, "numops": 1, "final_states": {"Box 0": ["the apple", "the leaf"], "Box 1": ["the plate", "the beer"], "Box 2": ["the ticket"], "Box 3": ["the clock", "the branch"], "Box 4": ["the egg", "the drink"], "Box 5": ["the chemical", "the key", "the fish"], "Box 6": ["the bell", "the pipe", "the jacket"]}}
{"sentence": "Box 0 contains the watch, Box 1 contains the brain and the drink and the sheet, Box 2 contains the ball and the cup and the tie, Box 3 contains the key and the rock and the shell, Box 4 contains the computer and the disk and the note, Box 5 contains the bomb and the fish and the guitar, Box 6 contains the coffee and the cross and the tissue. Put the bread and the creature into Box 0. Remove the drink and the sheet from Box 1. Remove the bomb from Box 5. Remove the creature from Box 0. Remove the ball and the cup and the tie from Box 2. Move the tissue from Box 6 to Box 1. Move the shell from Box 3 to Box 6. Remove the guitar from Box 5. Remove the fish from Box 5.", "sample_id": 1281, "numops": 2, "final_states": {"Box 0": ["the bread", "nothing", "the watch"], "Box 1": ["the brain", "the tissue"], "Box 2": ["nothing"], "Box 3": ["the bomb", "the key", "the rock"], "Box 4": ["the note", "the computer", "the disk"], "Box 5": ["nothing"], "Box 6": ["the shell", "the cross", "the coffee"]}}
{"sentence": "Box 0 contains the computer, Box 1 contains the cheese and the sheet, Box 2 contains the document and the engine, Box 3 contains the camera and the chemical and the coffee, Box 4 contains the block and the newspaper, Box 5 contains the ball and the shirt, Box 6 contains nothing. Move the cheese from Box 1 to Box 0. Put the pot into Box 0. Remove the pot from Box 0. Put the bottle into Box 0. Remove the sheet from Box 1. Move the cheese and the computer from Box 0 to Box 1. Put the ticket into Box 4. Remove the ball from Box 5. Remove the block and the ticket from Box 4.", "sample_id": 1283, "numops": 5, "final_states": {"Box 0": ["the bottle"], "Box 1": ["the computer", "the cheese"], "Box 2": ["the document", "the engine"], "Box 3": ["the camera", "the chemical", "the coffee"], "Box 4": ["the newspaper"], "Box 5": ["the shirt"], "Box 6": ["nothing"]}}
{"sentence": "Box 0 contains the bone and the computer and the tea, Box 1 contains the leaf, Box 2 contains nothing, Box 3 contains the bread and the drink, Box 4 contains the boat and the tie, Box 5 contains the crown, Box 6 contains the flower and the hat. Put the beer and the radio into Box 5. Move the drink from Box 3 to Box 6. Remove the crown and the radio from Box 5. Put the cross into Box 5. Move the leaf from Box 1 to Box 5. Remove the beer from Box 5. Put the apple into Box 5.", "sample_id": 1290, "numops": 0, "final_states": {"Box 0": ["the bone", "the computer", "the tea"], "Box 1": ["the newspaper", "the cross", "nothing", "the leaf"], "Box 2": ["nothing"], "Box 3": ["the bread", "the note", "the coat"], "Box 4": ["the boat", "the tie"], "Box 5": ["the apple", "the leaf", "the cross"], "Box 6": ["the hat", "the flower", "the drink"]}}
{"sentence": "Box 0 contains the glass, Box 1 contains the cash and the guitar and the map, Box 2 contains nothing, Box 3 contains the drug and the machine and the shell, Box 4 contains the card and the newspaper and the tea, Box 5 contains the branch and the coat and the rock, Box 6 contains the milk and the note and the television. Put the computer into Box 0. Remove the glass from Box 0. Move the card from Box 4 to Box 2. Remove the computer from Box 0. Move the newspaper and the tea from Box 4 to Box 2. Put the wheel into Box 4. Remove the newspaper and the tea from Box 2. Move the milk and the note from Box 6 to Box 4. Put the ice into Box 0. Remove the card from Box 2. Move the machine from Box 3 to Box 6.", "sample_id": 1299, "numops": 4, "final_states": {"Box 0": ["the ice"], "Box 1": ["the map", "the cash", "the guitar"], "Box 2": ["nothing"], "Box 3": ["the shell", "the drug"], "Box 4": ["the milk", "the note", "the wheel"], "Box 5": ["the rock", "the branch", "the coat"], "Box 6": ["the television", "the machine"]}}
{"sentence": "Box 0 contains the hat and the seed, Box 1 contains the drink, Box 2 contains the block, Box 3 contains the brain and the fan and the shoe, Box 4 contains the pot, Box 5 contains the file and the rock and the train, Box 6 contains the bone and the tape. Remove the block from Box 2. Move the hat from Box 0 to Box 2. Remove the tape from Box 6. Put the milk into Box 2. Remove the milk from Box 2. Put the ball into Box 1.", "sample_id": 1303, "numops": 1, "final_states": {"Box 0": ["nothing", "the seed"], "Box 1": ["the drink", "the bone", "the ball"], "Box 2": ["the fan", "the brain", "the hat"], "Box 3": ["the fan", "the brain", "the shoe"], "Box 4": ["the pot", "the hat"], "Box 5": ["the file", "the train", "the rock"], "Box 6": ["the bone", "the ticket"]}}
{"sentence": "Box 0 contains the shell and the stone, Box 1 contains the cigarette and the disk and the shirt, Box 2 contains the bill and the wire, Box 3 contains the key, Box 4 contains the computer, Box 5 contains the ice and the paper, Box 6 contains the brick and the fan and the map. Remove the ice from Box 5. Move the bill from Box 2 to Box 4. Remove the cigarette and the disk from Box 1. Remove the wire from Box 2. Move the fan from Box 6 to Box 5. Move the key from Box 3 to Box 5. Put the branch into Box 1. Put the wheel into Box 6. Move the branch from Box 1 to Box 0. Remove the fan and the paper from Box 5. Put the beer and the brain and the mirror into Box 3.", "sample_id": 1307, "numops": 1, "final_states": {"Box 0": ["the shell", "the stone", "the branch"], "Box 1": ["the shirt"], "Box 2": ["nothing"], "Box 3": ["the mirror", "the beer", "the brain"], "Box 4": ["the computer", "the bill"], "Box 5": ["the key"], "Box 6": ["the map", "the wheel", "the brick"]}}
{"sentence": "Box 0 contains the clock and the game, Box 1 contains the fig, Box 2 contains the mirror, Box 3 contains the bill and the creature and the phone, Box 4 contains the ice and the rock, Box 5 contains the pipe, Box 6 contains the brick and the leaf. Move the mirror from Box 2 to Box 1. Put the apple into Box 1. Put the jacket into Box 5. Remove the ice and the rock from Box 4. Move the brick from Box 6 to Box 2. Move the apple from Box 1 to Box 6. Move the jacket from Box 5 to Box 2.", "sample_id": 1311, "numops": 0, "final_states": {"Box 0": ["the clock", "the game"], "Box 1": ["the mirror", "the fig"], "Box 2": ["the jacket", "the brick"], "Box 3": ["the phone", "the creature", "the bill"], "Box 4": ["nothing"], "Box 5": ["the pipe"], "Box 6": ["the apple", "the leaf"]}}
{"sentence": "Box 0 contains the boot, Box 1 contains the chemical and the creature, Box 2 contains the hat, Box 3 contains the knife and the suit and the tape, Box 4 contains the beer and the fig, Box 5 contains the bell and the disk and the ticket, Box 6 contains the picture and the radio. Remove the beer and the fig from Box 4. Move the boot from Box 0 to Box 1. Remove the boot and the chemical from Box 1. Put the book and the branch into Box 0.", "sample_id": 1315, "numops": 2, "final_states": {"Box 0": ["the branch", "the book"], "Box 1": ["the creature"], "Box 2": ["the hat"], "Box 3": ["the knife", "the tape", "the suit"], "Box 4": ["nothing"], "Box 5": ["the bell", "the disk", "the ticket"], "Box 6": ["the picture", "the radio"]}}
{"sentence": "Box 0 contains the bomb and the bus and the leaf, Box 1 contains the pot, Box 2 contains the cheese and the ring, Box 3 contains the brain and the cross, Box 4 contains the file and the flower and the knife, Box 5 contains the boot and the fish and the painting, Box 6 contains the bag and the bell and the bone. Put the dish into Box 1. Remove the brain and the cross from Box 3. Move the file and the knife from Box 4 to Box 3. Move the flower from Box 4 to Box 1. Remove the fish and the painting from Box 5. Remove the bomb and the bus from Box 0. Remove the boot from Box 5.", "sample_id": 1316, "numops": 1, "final_states": {"Box 0": ["the bowl", "the leaf"], "Box 1": ["the flower", "the pot", "the dish"], "Box 2": ["the cheese", "the ring"], "Box 3": ["the file", "the knife"], "Box 4": ["nothing"], "Box 5": ["nothing"], "Box 6": ["the bell", "the bone", "the bag"]}}
{"sentence": "Box 0 contains the apple and the fig and the seed, Box 1 contains the cigarette and the ice and the plant, Box 2 contains the bell and the cake and the coffee, Box 3 contains the tissue, Box 4 contains nothing, Box 5 contains nothing, Box 6 contains the map. Move the tissue from Box 3 to Box 4. Remove the cigarette from Box 1. Remove the bell and the cake from Box 2. Put the flower and the pot into Box 5. Put the crown into Box 6. Remove the coffee from Box 2. Move the plant from Box 1 to Box 2. Move the fig from Box 0 to Box 4. Put the radio into Box 2. Remove the tissue from Box 4. Remove the fig from Box 4.", "sample_id": 1325, "numops": 1, "final_states": {"Box 0": ["the apple", "the seed"], "Box 1": ["the ice"], "Box 2": ["the plant", "the radio"], "Box 3": ["nothing"], "Box 4": ["nothing"], "Box 5": ["the flower", "the pot"], "Box 6": ["the map", "the crown"]}}
{"sentence": "Box 0 contains the dress and the tape and the tie, Box 1 contains the picture, Box 2 contains the document and the drug and the glass, Box 3 contains the meat, Box 4 contains nothing, Box 5 contains the brain and the pipe, Box 6 contains the boat and the boot. Move the drug from Box 2 to Box 4.", "sample_id": 1330, "numops": 0, "final_states": {"Box 0": ["the television", "the bell", "the tape", "the brain", "the tie", "the dress"], "Box 1": ["the picture"], "Box 2": ["the glass", "the meat", "the document"], "Box 3": ["the drug", "the meat", "the dress"], "Box 4": ["nothing", "the drug"], "Box 5": ["the brain", "the pipe", "the tape"], "Box 6": ["the boat", "the boot"]}}
{"sentence": "Box 0 contains the fan and the television, Box 1 contains the brain and the fig, Box 2 contains the bone and the watch, Box 3 contains the apple and the coffee and the train, Box 4 contains the shell and the shirt, Box 5 contains the bill and the shoe, Box 6 contains the key and the rose. Move the key from Box 6 to Box 5. Move the rose from Box 6 to Box 0. Remove the key and the shoe from Box 5. Put the boat into Box 6. Remove the fan and the rose from Box 0.", "sample_id": 1333, "numops": 2, "final_states": {"Box 0": ["the television", "the boat", "the rock"], "Box 1": ["the fig", "the brain"], "Box 2": ["the bone", "the bill", "the watch"], "Box 3": ["the coffee", "the apple", "nothing", "the train"], "Box 4": ["the shell", "the shirt", "the coffee"], "Box 5": ["nothing", "the bill"], "Box 6": ["the fish", "the boat"]}}
{"sentence": "Box 0 contains the magazine and the suit and the television, Box 1 contains the train, Box 2 contains the pot, Box 3 contains nothing, Box 4 contains the apple and the milk, Box 5 contains the cigarette and the letter, Box 6 contains the coat and the sheet. Remove the magazine and the television from Box 0. Remove the pot from Box 2. Remove the apple from Box 4. Remove the letter from Box 5. Put the camera into Box 6. Put the picture into Box 2. Remove the camera and the sheet from Box 6. Move the coat from Box 6 to Box 5. Move the suit from Box 0 to Box 3. Move the picture from Box 2 to Box 4. Put the boot into Box 3. Put the wire into Box 4.", "sample_id": 1335, "numops": 2, "final_states": {"Box 0": ["nothing"], "Box 1": ["the train"], "Box 2": ["nothing"], "Box 3": ["the boot", "the suit"], "Box 4": ["the picture", "the milk", "the wire"], "Box 5": ["the cigarette", "the coat"], "Box 6": ["nothing"]}}
{"sentence": "Box 0 contains the picture and the tea, Box 1 contains the bag and the card, Box 2 contains the seed and the wheel, Box 3 contains the boat and the ice and the jacket, Box 4 contains the bread and the computer and the document, Box 5 contains the game, Box 6 contains the dish and the meat and the shoe. Put the pot into Box 0. Remove the picture and the pot and the tea from Box 0. Move the game from Box 5 to Box 2. Remove the card from Box 1. Remove the bag from Box 1. Move the shoe from Box 6 to Box 0. Put the bus into Box 6.", "sample_id": 1342, "numops": 3, "final_states": {"Box 0": ["the shoe"], "Box 1": ["nothing"], "Box 2": ["the game", "the wheel", "the seed"], "Box 3": ["the boat", "the ice", "the jacket"], "Box 4": ["the document", "the bread", "the computer"], "Box 5": ["nothing"], "Box 6": ["the dish", "the bus", "the meat"]}}
{"sentence": "Box 0 contains the painting, Box 1 contains the coat and the ring and the tie, Box 2 contains the camera and the file and the milk, Box 3 contains the bone and the train, Box 4 contains the magazine, Box 5 contains the bomb and the game, Box 6 contains the brick and the cigarette and the disk. Remove the file from Box 2. Move the brick from Box 6 to Box 5. Remove the magazine from Box 4. Remove the camera from Box 2. Move the milk from Box 2 to Box 4.", "sample_id": 1345, "numops": 0, "final_states": {"Box 0": ["the painting"], "Box 1": ["the ring", "the tie", "the coat"], "Box 2": ["nothing"], "Box 3": ["the bone", "the train"], "Box 4": ["the milk"], "Box 5": ["the game", "the bomb", "the brick"], "Box 6": ["the cigarette", "the disk"]}}
{"sentence": "Box 0 contains the paper, Box 1 contains the bus and the card and the tissue, Box 2 contains the creature and the phone, Box 3 contains the camera and the jacket and the shirt, Box 4 contains the bill and the map, Box 5 contains the bag and the tape, Box 6 contains nothing. Remove the bill from Box 4. Move the phone from Box 2 to Box 0. Put the glass into Box 2. Put the bread and the rock into Box 4. Put the bill into Box 2. Remove the creature and the glass from Box 2. Put the painting into Box 0. Remove the camera from Box 3. Remove the map and the rock from Box 4. Remove the card from Box 1. Move the bill from Box 2 to Box 4.", "sample_id": 1350, "numops": 2, "final_states": {"Box 0": ["the paper", "the painting", "the phone"], "Box 1": ["the bus", "the tissue"], "Box 2": ["nothing"], "Box 3": ["the shirt", "the jacket"], "Box 4": ["the bread", "the bill"], "Box 5": ["the bag", "the tape"], "Box 6": ["nothing"]}}
{"sentence": "Box 0 contains the book and the flower and the shirt, Box 1 contains the camera and the dress and the jacket, Box 2 contains the picture, Box 3 contains nothing, Box 4 contains the string, Box 5 contains the tape, Box 6 contains the fig. Remove the string from Box 4. Remove the fig from Box 6. Remove the dress and the jacket from Box 1. Move the book from Box 0 to Box 3. Move the flower from Box 0 to Box 4. Put the egg and the map into Box 0. Move the tape from Box 5 to Box 4. Put the fish into Box 4.", "sample_id": 1354, "numops": 3, "final_states": {"Box 0": ["the map", "the egg", "the shirt"], "Box 1": ["the camera"], "Box 2": ["the picture"], "Box 3": ["the book"], "Box 4": ["the flower", "the fish", "the tape"], "Box 5": ["nothing"], "Box 6": ["nothing"]}}
{"sentence": "Box 0 contains the rock and the wire, Box 1 contains the map, Box 2 contains the brick and the ice, Box 3 contains the hat, Box 4 contains the coat and the disk, Box 5 contains the rose, Box 6 contains nothing. Put the clock and the plane into Box 6. Move the rock from Box 0 to Box 6. Remove the rose from Box 5. Put the pot into Box 5. Remove the map from Box 1. Remove the pot from Box 5. Move the coat and the disk from Box 4 to Box 5. Move the brick and the ice from Box 2 to Box 0. Put the brain and the gift into Box 3. Remove the ice and the wire from Box 0. Remove the disk from Box 5. Move the hat from Box 3 to Box 5.", "sample_id": 1357, "numops": 3, "final_states": {"Box 0": ["the brick"], "Box 1": ["nothing"], "Box 2": ["nothing"], "Box 3": ["the gift", "the brain"], "Box 4": ["nothing"], "Box 5": ["the hat", "the coat"], "Box 6": ["the clock", "the plane", "the rock"]}}
{"sentence": "Box 0 contains the bus and the glass and the television, Box 1 contains nothing, Box 2 contains the flower and the phone and the wheel, Box 3 contains the medicine and the train, Box 4 contains the chemical and the disk, Box 5 contains the cash and the game and the shell, Box 6 contains nothing. Put the ring into Box 3. Put the cigarette into Box 1. Move the cigarette from Box 1 to Box 6. Remove the flower and the phone from Box 2. Remove the cigarette from Box 6. Remove the wheel from Box 2. Remove the game from Box 5. Move the bus from Box 0 to Box 6. Put the block and the cheese into Box 2. Move the ring and the train from Box 3 to Box 6.", "sample_id": 1362, "numops": 1, "final_states": {"Box 0": ["the glass", "the television"], "Box 1": ["nothing"], "Box 2": ["the cheese", "the block"], "Box 3": ["the medicine"], "Box 4": ["the chemical", "the disk"], "Box 5": ["the shell", "the cash"], "Box 6": ["the train", "the bus", "the ring"]}}
{"sentence": "Box 0 contains nothing, Box 1 contains the bag and the cream, Box 2 contains the plant and the sheet and the tape, Box 3 contains the block and the plane, Box 4 contains the boat and the clock and the crown, Box 5 contains the paper, Box 6 contains nothing. Remove the boat from Box 4. Move the crown from Box 4 to Box 0. Put the ticket into Box 4. Move the paper from Box 5 to Box 0. Put the cheese and the egg into Box 6. Remove the clock and the ticket from Box 4. Put the meat into Box 0. Put the disk into Box 5. Move the plane from Box 3 to Box 6. Remove the block from Box 3. Put the shell into Box 4.", "sample_id": 1364, "numops": 3, "final_states": {"Box 0": ["the crown", "the meat", "the paper"], "Box 1": ["the cream", "the bag"], "Box 2": ["the sheet", "the plant", "the tape"], "Box 3": ["the sheet", "the plant", "nothing"], "Box 4": ["the shell"], "Box 5": ["the disk"], "Box 6": ["the plane", "the cheese", "the egg"]}}
{"sentence": "Box 0 contains the cheese and the dish and the picture, Box 1 contains the cigarette, Box 2 contains nothing, Box 3 contains the disk and the map and the meat, Box 4 contains the boot and the flower, Box 5 contains the bag and the cross and the machine, Box 6 contains the ticket. Remove the bag and the cross and the machine from Box 5. Put the apple into Box 5. Remove the ticket from Box 6. Move the apple from Box 5 to Box 4. Remove the apple from Box 4. Put the clock into Box 2. Put the stone into Box 5. Remove the clock from Box 2. Remove the stone from Box 5. Move the flower from Box 4 to Box 5. Move the boot from Box 4 to Box 5.", "sample_id": 1368, "numops": 0, "final_states": {"Box 0": ["the dish", "the picture", "the cheese"], "Box 1": ["the cigarette"], "Box 2": ["nothing"], "Box 3": ["the map", "the meat", "the disk"], "Box 4": ["the dish", "nothing", "the cheese"], "Box 5": ["the flower", "the boot"], "Box 6": ["nothing"]}}
{"sentence": "Box 0 contains the block and the cheese and the train, Box 1 contains the apple, Box 2 contains the dress and the milk, Box 3 contains the ice and the plant, Box 4 contains the car and the seed and the tape, Box 5 contains the bus and the egg, Box 6 contains nothing. Remove the bus from Box 5. Remove the apple from Box 1. Move the car from Box 4 to Box 3. Remove the car and the ice from Box 3. Remove the tape from Box 4. Move the plant from Box 3 to Box 1. Move the seed from Box 4 to Box 2. Move the dress and the milk from Box 2 to Box 6. Remove the seed from Box 2. Put the stone into Box 5. Move the block from Box 0 to Box 3. Move the block from Box 3 to Box 1.", "sample_id": 1369, "numops": 1, "final_states": {"Box 0": ["the train", "the cheese"], "Box 1": ["the plant", "the block"], "Box 2": ["nothing"], "Box 3": ["nothing"], "Box 4": ["nothing"], "Box 5": ["the stone", "the egg"], "Box 6": ["the milk", "the dress"]}}
{"sentence": "Box 0 contains the disk and the jacket and the seed, Box 1 contains the clock and the cream and the phone, Box 2 contains the brain and the dish and the radio, Box 3 contains the document and the game, Box 4 contains the bag and the engine and the train, Box 5 contains the shell, Box 6 contains the egg. Remove the cream from Box 1. Remove the shell from Box 5. Remove the disk and the jacket and the seed from Box 0. Put the cross into Box 1. Remove the bag from Box 4. Put the fish into Box 5. Remove the engine and the train from Box 4. Remove the brain from Box 2. Put the boat and the plant into Box 4.", "sample_id": 1372, "numops": 1, "final_states": {"Box 0": ["nothing"], "Box 1": ["the clock", "the phone", "the cross"], "Box 2": ["the dish", "the radio"], "Box 3": ["the game", "the document"], "Box 4": ["the plant", "the boat"], "Box 5": ["the fish"], "Box 6": ["the egg"]}}
{"sentence": "Box 0 contains the rock, Box 1 contains the block and the dish, Box 2 contains the drink and the hat and the shirt, Box 3 contains the boot and the fig and the medicine, Box 4 contains the coat and the egg and the flower, Box 5 contains the disk and the phone, Box 6 contains nothing. Move the rock from Box 0 to Box 6. Remove the disk and the phone from Box 5. Move the drink and the hat from Box 2 to Box 5. Remove the drink from Box 5. Move the egg and the flower from Box 4 to Box 6. Move the shirt from Box 2 to Box 0. Move the hat from Box 5 to Box 1. Remove the dish and the hat from Box 1. Remove the shirt from Box 0.", "sample_id": 1376, "numops": 3, "final_states": {"Box 0": ["nothing"], "Box 1": ["the block"], "Box 2": ["nothing"], "Box 3": ["the fig", "the medicine", "the boot"], "Box 4": ["the coat"], "Box 5": ["nothing", "the ring", "the drink"], "Box 6": ["the flower", "the egg", "the rock"]}}
{"sentence": "Box 0 contains the cross and the dish and the pot, Box 1 contains nothing, Box 2 contains nothing, Box 3 contains the cigarette, Box 4 contains the shoe, Box 5 contains the mirror and the sheet, Box 6 contains the chemical and the seed and the stone. Remove the cigarette from Box 3. Put the apple and the drink into Box 4. Remove the apple and the drink and the shoe from Box 4. Put the book into Box 1. Move the book from Box 1 to Box 4. Remove the stone from Box 6. Move the dish from Box 0 to Box 1. Put the game and the magazine into Box 2. Remove the dish from Box 1. Move the book from Box 4 to Box 1. Remove the game from Box 2. Remove the magazine from Box 2.", "sample_id": 1378, "numops": 1, "final_states": {"Box 0": ["the pot", "the cross"], "Box 1": ["the book"], "Box 2": ["nothing"], "Box 3": ["nothing"], "Box 4": ["nothing"], "Box 5": ["the mirror", "the sheet"], "Box 6": ["the chemical", "the seed"]}}
{"sentence": "Box 0 contains the fish and the ice, Box 1 contains nothing, Box 2 contains the bread and the note, Box 3 contains the glass, Box 4 contains nothing, Box 5 contains the bomb and the knife, Box 6 contains the disk. Move the knife from Box 5 to Box 1. Put the cash into Box 6. Put the milk into Box 0. Remove the knife from Box 1. Remove the fish from Box 0. Remove the disk from Box 6. Put the tea into Box 6. Move the bread from Box 2 to Box 3. Move the bomb from Box 5 to Box 1. Remove the cash from Box 6. Put the apple into Box 2.", "sample_id": 1380, "numops": 2, "final_states": {"Box 0": ["the milk", "the ice"], "Box 1": ["the bomb"], "Box 2": ["the apple", "the note"], "Box 3": ["the bread", "the glass"], "Box 4": ["nothing"], "Box 5": ["nothing"], "Box 6": ["the tea"]}}
{"sentence": "Box 0 contains the block and the television and the watch, Box 1 contains the ice, Box 2 contains nothing, Box 3 contains the shirt, Box 4 contains the card and the engine, Box 5 contains the ball, Box 6 contains the brick and the knife. Put the bread into Box 2. Put the bowl into Box 1. Move the shirt from Box 3 to Box 5. Move the bowl and the ice from Box 1 to Box 2. Move the brick from Box 6 to Box 3. Put the bill and the mirror into Box 3.", "sample_id": 1381, "numops": 0, "final_states": {"Box 0": ["the television", "nothing", "the block", "the watch"], "Box 1": ["the knife", "nothing"], "Box 2": ["the bread", "the bowl", "the ice"], "Box 3": ["the mirror", "nothing", "the bill", "the brick"], "Box 4": ["the card", "the engine"], "Box 5": ["the ball", "the shirt"], "Box 6": ["the knife", "nothing", "the watch"]}}
{"sentence": "Box 0 contains the machine, Box 1 contains the phone, Box 2 contains the apple and the brain and the guitar, Box 3 contains the camera and the picture and the ticket, Box 4 contains the shoe and the suit and the tape, Box 5 contains the book and the branch and the newspaper, Box 6 contains the bus and the key. Remove the brain from Box 2. Remove the shoe from Box 4. Move the key from Box 6 to Box 0. Remove the camera and the ticket from Box 3. Move the machine from Box 0 to Box 1. Remove the suit from Box 4.", "sample_id": 1382, "numops": 2, "final_states": {"Box 0": ["the key"], "Box 1": ["the phone", "the machine"], "Box 2": ["the apple", "the guitar"], "Box 3": ["the picture"], "Box 4": ["the tape"], "Box 5": ["the branch", "the newspaper", "the book"], "Box 6": ["the bus"]}}
{"sentence": "Box 0 contains the magazine, Box 1 contains the boat, Box 2 contains the cash and the shirt, Box 3 contains the bottle and the egg, Box 4 contains the bone, Box 5 contains the cup and the phone and the plant, Box 6 contains nothing. Move the magazine from Box 0 to Box 1. Remove the boat and the magazine from Box 1. Remove the cash and the shirt from Box 2. Move the phone and the plant from Box 5 to Box 2. Put the machine and the ticket into Box 0. Move the ticket from Box 0 to Box 6. Put the crown into Box 4. Remove the bottle and the egg from Box 3. Remove the cup from Box 5. Move the plant from Box 2 to Box 1. Move the plant from Box 1 to Box 2.", "sample_id": 1383, "numops": 3, "final_states": {"Box 0": ["the machine"], "Box 1": ["nothing"], "Box 2": ["the phone", "the plant"], "Box 3": ["nothing"], "Box 4": ["the bone", "the crown"], "Box 5": ["nothing"], "Box 6": ["the ticket"]}}
{"sentence": "Box 0 contains the camera and the magazine and the shirt, Box 1 contains the card and the wheel, Box 2 contains nothing, Box 3 contains the bill and the crown and the guitar, Box 4 contains the drug and the shoe, Box 5 contains the bread and the leaf, Box 6 contains the bomb and the file and the seed. Remove the wheel from Box 1.", "sample_id": 1393, "numops": 0, "final_states": {"Box 0": ["the camera", "the magazine", "the shirt"], "Box 1": ["the card"], "Box 2": ["nothing"], "Box 3": ["the bill", "the guitar", "the crown"], "Box 4": ["the drug", "the shoe"], "Box 5": ["the bread", "the leaf"], "Box 6": ["the file", "the bomb", "the seed"]}}
{"sentence": "Box 0 contains the key, Box 1 contains the dish and the mirror, Box 2 contains the milk, Box 3 contains the drug and the plane and the shirt, Box 4 contains the computer and the ice, Box 5 contains the magazine and the seed, Box 6 contains the block and the picture. Put the drink into Box 2. Move the computer from Box 4 to Box 1. Remove the ice from Box 4. Move the drug from Box 3 to Box 2. Move the shirt from Box 3 to Box 5. Remove the plane from Box 3. Move the key from Box 0 to Box 6. Remove the block from Box 6. Move the magazine and the seed from Box 5 to Box 3. Remove the drink and the milk from Box 2. Remove the computer from Box 1.", "sample_id": 1395, "numops": 1, "final_states": {"Box 0": ["nothing"], "Box 1": ["the mirror", "the dish"], "Box 2": ["the drug"], "Box 3": ["the magazine", "the seed"], "Box 4": ["nothing"], "Box 5": ["the shirt"], "Box 6": ["the key", "the picture"]}}
{"sentence": "Box 0 contains the cash and the shoe, Box 1 contains the magazine and the pot, Box 2 contains the egg and the fan and the letter, Box 3 contains the coffee and the painting and the ticket, Box 4 contains the bomb, Box 5 contains the bottle and the machine, Box 6 contains the ball and the camera and the picture. Remove the pot from Box 1. Remove the cash and the shoe from Box 0. Move the ball and the picture from Box 6 to Box 4. Remove the letter from Box 2. Remove the camera from Box 6. Put the branch into Box 2. Remove the bottle and the machine from Box 5. Remove the coffee and the ticket from Box 3. Remove the picture from Box 4.", "sample_id": 1398, "numops": 1, "final_states": {"Box 0": ["nothing"], "Box 1": ["the magazine"], "Box 2": ["the fan", "the egg", "the branch"], "Box 3": ["the painting"], "Box 4": ["the bomb", "the ball"], "Box 5": ["nothing"], "Box 6": ["nothing"]}}
{"sentence": "Box 0 contains the bus and the cross and the tape, Box 1 contains nothing, Box 2 contains the jacket, Box 3 contains nothing, Box 4 contains the guitar and the plane, Box 5 contains the camera and the plant, Box 6 contains the fig. Remove the tape from Box 0. Remove the jacket from Box 2. Put the ball into Box 5. Move the camera from Box 5 to Box 1. Put the bill into Box 3. Remove the camera from Box 1. Move the fig from Box 6 to Box 4. Put the apple and the branch and the tea into Box 1. Move the cross from Box 0 to Box 2. Move the bill from Box 3 to Box 0.", "sample_id": 1400, "numops": 3, "final_states": {"Box 0": ["the bus", "the bill"], "Box 1": ["the apple", "the branch", "the tea"], "Box 2": ["the cross"], "Box 3": ["nothing"], "Box 4": ["the fig", "the plane", "the guitar"], "Box 5": ["the plant", "the ball"], "Box 6": ["nothing"]}}
{"sentence": "Box 0 contains the rose, Box 1 contains the brick and the fish and the shirt, Box 2 contains the ball and the pot and the watch, Box 3 contains the fan and the suit, Box 4 contains the brain and the egg and the wheel, Box 5 contains the boat and the drug, Box 6 contains the map. Put the beer into Box 3. Remove the beer and the fan and the suit from Box 3. Remove the fish and the shirt from Box 1. Move the ball from Box 2 to Box 0. Remove the map from Box 6. Remove the pot from Box 2. Put the game and the knife into Box 6. Remove the ball and the rose from Box 0. Remove the watch from Box 2. Put the computer into Box 0. Remove the brick from Box 1.", "sample_id": 1411, "numops": 3, "final_states": {"Box 0": ["the computer"], "Box 1": ["nothing"], "Box 2": ["nothing"], "Box 3": ["nothing"], "Box 4": ["the egg", "the brain", "the wheel"], "Box 5": ["the drug", "the boat"], "Box 6": ["the game", "the knife"]}}
{"sentence": "Box 0 contains the picture and the seed and the watch, Box 1 contains the crown, Box 2 contains the bus and the pot and the suit, Box 3 contains the apple and the branch and the bread, Box 4 contains the milk and the wheel, Box 5 contains the ball and the chemical, Box 6 contains the brick and the tea and the wire.", "sample_id": 1415, "numops": 0, "final_states": {"Box 0": ["the picture", "the watch", "the seed"], "Box 1": ["nothing", "the crown"], "Box 2": ["the pot", "nothing", "the bus", "the suit"], "Box 3": ["the bread", "the apple", "the branch", "the suit"], "Box 4": ["the milk", "the wheel"], "Box 5": ["the chemical", "the ball"], "Box 6": ["the note", "the wire", "the tea", "the brick"]}}
{"sentence": "Box 0 contains the bottle, Box 1 contains nothing, Box 2 contains the ball and the plant and the tea, Box 3 contains the chemical and the phone, Box 4 contains the file and the flower and the plate, Box 5 contains the meat and the note, Box 6 contains the beer and the guitar. Put the clock into Box 1. Remove the note from Box 5. Put the bowl and the drug into Box 0.", "sample_id": 1424, "numops": 1, "final_states": {"Box 0": ["the bowl", "the drug", "the bottle"], "Box 1": ["the clock", "nothing"], "Box 2": ["the plant", "the tea", "the ball"], "Box 3": ["the chemical", "the phone"], "Box 4": ["the file", "the plate", "the milk", "the flower", "the boat"], "Box 5": ["the disk", "the meat", "the shirt"], "Box 6": ["the branch", "the beer", "the guitar"]}}
{"sentence": "Box 0 contains the cash and the suit, Box 1 contains the bell and the medicine and the shoe, Box 2 contains the cake and the clock and the engine, Box 3 contains the map and the pot, Box 4 contains the fan and the mirror, Box 5 contains the block and the string and the train, Box 6 contains the disk. Remove the mirror from Box 4. Remove the fan from Box 4. Remove the cash and the suit from Box 0.", "sample_id": 1427, "numops": 1, "final_states": {"Box 0": ["nothing"], "Box 1": ["the medicine", "the bell", "the shoe"], "Box 2": ["the clock", "the engine", "the cake"], "Box 3": ["the map", "the pot"], "Box 4": ["the camera", "nothing"], "Box 5": ["the block", "the train", "the string"], "Box 6": ["the disk"]}}
{"sentence": "Box 0 contains the picture, Box 1 contains the beer and the coat and the wheel, Box 2 contains the brick and the drug and the flower, Box 3 contains nothing, Box 4 contains the bottle and the leaf and the pot, Box 5 contains the game and the newspaper, Box 6 contains the bomb and the string and the tape. Remove the picture from Box 0. Put the bell and the watch into Box 3. Remove the newspaper from Box 5. Remove the brick and the drug from Box 2. Put the computer into Box 0. Remove the string from Box 6. Put the pipe into Box 6. Remove the computer from Box 0. Put the plant into Box 3. Remove the plant from Box 3. Remove the bomb from Box 6.", "sample_id": 1429, "numops": 3, "final_states": {"Box 0": ["nothing"], "Box 1": ["the beer", "the coat", "the wheel"], "Box 2": ["the flower"], "Box 3": ["the bell", "the watch"], "Box 4": ["the pot", "the bottle", "the leaf"], "Box 5": ["the game"], "Box 6": ["the pipe", "the tape"]}}
{"sentence": "Box 0 contains the bottle and the cigarette and the engine, Box 1 contains the suit, Box 2 contains the fan, Box 3 contains nothing, Box 4 contains the painting, Box 5 contains the camera and the mirror, Box 6 contains the branch and the computer and the egg. Move the painting from Box 4 to Box 3. Move the painting from Box 3 to Box 5. Remove the camera and the mirror from Box 5. Remove the engine from Box 0. Put the train into Box 4. Move the painting from Box 5 to Box 3.", "sample_id": 1434, "numops": 1, "final_states": {"Box 0": ["the bottle", "the cigarette"], "Box 1": ["the suit"], "Box 2": ["the fan"], "Box 3": ["the painting"], "Box 4": ["the train"], "Box 5": ["nothing"], "Box 6": ["the computer", "the egg", "the branch"]}}
{"sentence": "Box 0 contains nothing, Box 1 contains the television, Box 2 contains the tea, Box 3 contains the bread and the coat, Box 4 contains nothing, Box 5 contains the plane, Box 6 contains the disk. Move the tea from Box 2 to Box 4. Move the plane from Box 5 to Box 1. Remove the disk from Box 6. Move the tea from Box 4 to Box 2. Put the tie and the tissue into Box 6. Remove the tea from Box 2. Put the boat into Box 3. Put the fig and the shell into Box 5. Put the card into Box 6.", "sample_id": 1436, "numops": 0, "final_states": {"Box 0": ["nothing"], "Box 1": ["the television", "the plane"], "Box 2": ["nothing"], "Box 3": ["the bread", "the boat", "the coat"], "Box 4": ["nothing"], "Box 5": ["the shell", "the fig"], "Box 6": ["the card", "the tie", "the tissue"]}}
{"sentence": "Box 0 contains the chemical, Box 1 contains the brick and the engine and the glass, Box 2 contains the ball and the fan and the painting, Box 3 contains the machine, Box 4 contains nothing, Box 5 contains the beer and the stone and the ticket, Box 6 contains the bottle and the game. Remove the machine from Box 3. Move the bottle and the game from Box 6 to Box 4. Remove the game from Box 4. Put the disk into Box 4. Move the brick and the engine from Box 1 to Box 3. Remove the brick and the engine from Box 3. Remove the chemical from Box 0. Move the glass from Box 1 to Box 0. Remove the glass from Box 0. Put the medicine into Box 3. Move the medicine from Box 3 to Box 1. Move the stone from Box 5 to Box 6.", "sample_id": 1438, "numops": 3, "final_states": {"Box 0": ["nothing"], "Box 1": ["the medicine"], "Box 2": ["the fan", "the painting", "the ball"], "Box 3": ["nothing"], "Box 4": ["the bottle", "the disk"], "Box 5": ["the beer", "the ticket"], "Box 6": ["the stone"]}}
{"sentence": "Box 0 contains the egg and the tea, Box 1 contains the painting and the phone and the watch, Box 2 contains the string, Box 3 contains the car and the medicine and the paper, Box 4 contains the ice, Box 5 contains the boat, Box 6 contains nothing. Remove the watch from Box 1. Remove the string from Box 2. Remove the painting and the phone from Box 1. Put the pot into Box 4. Remove the ice and the pot from Box 4. Put the suit into Box 1. Remove the tea from Box 0. Put the pot into Box 1. Remove the egg from Box 0. Move the medicine from Box 3 to Box 1. Put the meat into Box 2.", "sample_id": 1439, "numops": 2, "final_states": {"Box 0": ["nothing"], "Box 1": ["the pot", "the medicine", "the suit"], "Box 2": ["the meat"], "Box 3": ["the paper", "the car"], "Box 4": ["nothing"], "Box 5": ["the boat"], "Box 6": ["nothing"]}}
{"sentence": "Box 0 contains the cream and the painting, Box 1 contains the apple and the bag and the milk, Box 2 contains the drink and the sheet, Box 3 contains the plane, Box 4 contains the phone, Box 5 contains the meat and the note, Box 6 contains the branch and the document and the tea. Put the bowl and the key into Box 4. Move the branch from Box 6 to Box 5. Remove the painting from Box 0. Put the tape into Box 0. Move the drink and the sheet from Box 2 to Box 3. Move the tea from Box 6 to Box 2. Remove the apple and the bag from Box 1. Put the brain into Box 0. Move the phone from Box 4 to Box 6. Remove the key from Box 4. Move the milk from Box 1 to Box 6.", "sample_id": 1444, "numops": 3, "final_states": {"Box 0": ["the cream", "the brain", "the tape"], "Box 1": ["nothing"], "Box 2": ["the tea"], "Box 3": ["the sheet", "the plane", "the drink"], "Box 4": ["the bowl"], "Box 5": ["the note", "the branch", "the meat"], "Box 6": ["the document", "the milk", "the phone"]}}
{"sentence": "Box 0 contains the coat, Box 1 contains the bomb and the train, Box 2 contains the book and the magazine, Box 3 contains the chemical, Box 4 contains the cake and the phone and the seed, Box 5 contains the cross and the hat and the mirror, Box 6 contains the fish and the glass. Remove the train from Box 1. Move the glass from Box 6 to Box 2. Remove the coat from Box 0. Put the key into Box 6. Remove the phone from Box 4. Put the fig into Box 1. Put the bread and the creature into Box 0. Remove the hat from Box 5. Remove the fish and the key from Box 6. Remove the cross and the mirror from Box 5. Move the fig from Box 1 to Box 5.", "sample_id": 1445, "numops": 2, "final_states": {"Box 0": ["the bread", "the creature"], "Box 1": ["the bomb"], "Box 2": ["the glass", "the magazine", "the book"], "Box 3": ["the chemical"], "Box 4": ["the cake", "the seed"], "Box 5": ["the fig"], "Box 6": ["nothing"]}}
{"sentence": "Box 0 contains the apple and the shell and the television, Box 1 contains the brick and the mirror and the plane, Box 2 contains the rock, Box 3 contains the coffee and the train, Box 4 contains nothing, Box 5 contains the clock and the fan, Box 6 contains nothing. Put the dish into Box 4.", "sample_id": 1449, "numops": 0, "final_states": {"Box 0": ["the shell", "the apple", "the television"], "Box 1": ["the mirror", "the plane", "the brick"], "Box 2": ["the rock"], "Box 3": ["the coffee", "the train"], "Box 4": ["the dish"], "Box 5": ["the fan", "the clock"], "Box 6": ["nothing"]}}
{"sentence": "Box 0 contains the ball and the tape and the television, Box 1 contains the clock and the cross, Box 2 contains the paper and the rose, Box 3 contains the key, Box 4 contains the drug and the tea, Box 5 contains the branch and the card, Box 6 contains the gift. Move the gift from Box 6 to Box 5. Move the card and the gift from Box 5 to Box 3. Move the clock from Box 1 to Box 5. Move the card from Box 3 to Box 4. Remove the tape from Box 0. Move the branch and the clock from Box 5 to Box 6. Remove the card and the tea from Box 4. Remove the gift from Box 3. Put the boat into Box 1. Move the key from Box 3 to Box 2. Move the drug from Box 4 to Box 1. Put the cash and the tea into Box 4.", "sample_id": 1451, "numops": 1, "final_states": {"Box 0": ["the television", "the ball"], "Box 1": ["the drug", "the boat", "the cross"], "Box 2": ["the paper", "the key", "the rose"], "Box 3": ["nothing"], "Box 4": ["the cash", "the tea"], "Box 5": ["nothing"], "Box 6": ["the clock", "the branch"]}}
{"sentence": "Box 0 contains the bill and the fig and the pipe, Box 1 contains the train, Box 2 contains the machine and the phone, Box 3 contains the meat and the plant, Box 4 contains the boat and the leaf, Box 5 contains nothing, Box 6 contains the drug and the paper. Remove the phone from Box 2. Move the drug and the paper from Box 6 to Box 1. Put the television into Box 3. Move the bill and the fig from Box 0 to Box 2. Remove the drug and the paper and the train from Box 1. Put the jacket into Box 4. Remove the bill and the fig from Box 2.", "sample_id": 1454, "numops": 1, "final_states": {"Box 0": ["nothing", "the pipe"], "Box 1": ["the television", "nothing", "the meat"], "Box 2": ["the fish", "the machine"], "Box 3": ["the television", "the plant", "the meat"], "Box 4": ["the jacket", "the boat", "the leaf"], "Box 5": ["nothing"], "Box 6": ["nothing"]}}
{"sentence": "Box 0 contains the book and the fan and the radio, Box 1 contains the bus and the crown and the suit, Box 2 contains the leaf and the shell and the stone, Box 3 contains the apple and the hat and the plane, Box 4 contains the brain and the card and the cigarette, Box 5 contains the seed, Box 6 contains the disk and the painting and the sheet. Remove the fan from Box 0. Remove the plane from Box 3. Remove the leaf and the stone from Box 2. Remove the cigarette from Box 4. Move the brain and the card from Box 4 to Box 2. Remove the seed from Box 5. Put the bowl and the pot into Box 4. Remove the apple from Box 3. Remove the crown from Box 1. Move the brain and the card from Box 2 to Box 3. Remove the bowl from Box 4. Remove the suit from Box 1.", "sample_id": 1456, "numops": 1, "final_states": {"Box 0": ["the book", "the radio"], "Box 1": ["the bus"], "Box 2": ["the shell"], "Box 3": ["the card", "the brain", "the hat"], "Box 4": ["the pot"], "Box 5": ["nothing"], "Box 6": ["the painting", "the sheet", "the disk"]}}
{"sentence": "Box 0 contains the machine and the medicine and the tea, Box 1 contains the magazine and the phone, Box 2 contains the bone and the egg and the file, Box 3 contains the map and the radio, Box 4 contains the brain, Box 5 contains the bell and the meat, Box 6 contains the card and the cross. Remove the radio from Box 3. Move the card from Box 6 to Box 4. Move the meat from Box 5 to Box 4. Put the flower into Box 6. Put the boat into Box 3. Move the boat from Box 3 to Box 1. Move the tea from Box 0 to Box 3. Move the map and the tea from Box 3 to Box 5. Move the bell from Box 5 to Box 3. Remove the flower from Box 6. Remove the bell from Box 3.", "sample_id": 1457, "numops": 1, "final_states": {"Box 0": ["the medicine", "the machine"], "Box 1": ["the phone", "the magazine", "the boat"], "Box 2": ["the file", "the bone", "the egg"], "Box 3": ["nothing"], "Box 4": ["the card", "the meat", "the brain"], "Box 5": ["the map", "the tea"], "Box 6": ["the cross"]}}
{"sentence": "Box 0 contains nothing, Box 1 contains the letter and the shoe and the train, Box 2 contains the document, Box 3 contains the bus, Box 4 contains the cash and the fish, Box 5 contains nothing, Box 6 contains the paper and the stone. Put the camera and the chemical into Box 3. Remove the document from Box 2. Remove the letter and the shoe from Box 1. Move the train from Box 1 to Box 6. Remove the camera and the chemical from Box 3. Remove the paper and the train from Box 6. Move the bus from Box 3 to Box 6. Remove the bus from Box 6.", "sample_id": 1465, "numops": 0, "final_states": {"Box 0": ["nothing", "the stone"], "Box 1": ["nothing"], "Box 2": ["nothing"], "Box 3": ["nothing"], "Box 4": ["the fish", "the cash"], "Box 5": ["nothing"], "Box 6": ["the game", "the stone"]}}
{"sentence": "Box 0 contains the bomb and the card and the fig, Box 1 contains the cigarette and the map and the shoe, Box 2 contains nothing, Box 3 contains the bill and the creature, Box 4 contains nothing, Box 5 contains the magazine, Box 6 contains nothing. Move the map from Box 1 to Box 4. Remove the magazine from Box 5. Put the plant into Box 4. Remove the creature from Box 3.", "sample_id": 1467, "numops": 0, "final_states": {"Box 0": ["the card", "the fig", "the bomb"], "Box 1": ["the cigarette", "the shoe"], "Box 2": ["nothing"], "Box 3": ["the bill"], "Box 4": ["the map", "the plant"], "Box 5": ["nothing"], "Box 6": ["nothing"]}}
{"sentence": "Box 0 contains nothing, Box 1 contains the guitar and the picture and the suit, Box 2 contains the cake and the pot and the sheet, Box 3 contains the computer, Box 4 contains the card and the meat and the plant, Box 5 contains the newspaper and the radio and the wheel, Box 6 contains the engine and the letter. Remove the sheet from Box 2. Remove the pot from Box 2. Remove the computer from Box 3. Put the television into Box 3. Remove the newspaper and the wheel from Box 5. Move the cake from Box 2 to Box 5. Remove the guitar from Box 1. Move the engine from Box 6 to Box 3.", "sample_id": 1469, "numops": 0, "final_states": {"Box 0": ["nothing"], "Box 1": ["the picture", "the suit"], "Box 2": ["nothing"], "Box 3": ["the television", "the engine"], "Box 4": ["the card", "the plant", "the meat"], "Box 5": ["the cake", "the radio"], "Box 6": ["the letter"]}}
{"sentence": "Box 0 contains nothing, Box 1 contains the card and the milk and the painting, Box 2 contains the book and the cake and the guitar, Box 3 contains the chemical, Box 4 contains the letter and the ticket, Box 5 contains the camera and the gift and the pot, Box 6 contains the coffee and the drink and the tie. Remove the chemical from Box 3. Remove the ticket from Box 4. Remove the drink from Box 6. Remove the coffee from Box 6. Put the branch and the tissue into Box 6. Remove the card and the milk from Box 1. Remove the cake from Box 2. Remove the branch and the tie and the tissue from Box 6. Remove the painting from Box 1. Remove the gift and the pot from Box 5. Put the gift into Box 4. Put the crown into Box 6.", "sample_id": 1473, "numops": 0, "final_states": {"Box 0": ["nothing"], "Box 1": ["nothing"], "Box 2": ["the guitar", "the book"], "Box 3": ["nothing"], "Box 4": ["the gift", "the letter"], "Box 5": ["the camera"], "Box 6": ["the crown"]}}
{"sentence": "Box 0 contains the book and the phone and the picture, Box 1 contains the knife and the painting, Box 2 contains the bottle and the magazine, Box 3 contains the bell and the note, Box 4 contains the brain and the mirror and the newspaper, Box 5 contains the coat, Box 6 contains the beer and the stone. Remove the coat from Box 5. Move the knife from Box 1 to Box 2. Move the stone from Box 6 to Box 5. Move the beer from Box 6 to Box 3. Remove the stone from Box 5.", "sample_id": 1478, "numops": 0, "final_states": {"Box 0": ["the phone", "the picture", "the book"], "Box 1": ["the painting", "the wire"], "Box 2": ["the knife", "the magazine", "the bottle", "nothing"], "Box 3": ["the bell", "the note", "the beer"], "Box 4": ["the mirror", "the newspaper", "the brain"], "Box 5": ["the fig", "nothing"], "Box 6": ["the mirror", "the magazine", "the bottle", "nothing"]}}
{"sentence": "Box 0 contains nothing, Box 1 contains the book, Box 2 contains the ball and the glass, Box 3 contains the tissue, Box 4 contains the cash and the letter and the seed, Box 5 contains the flower and the game and the leaf, Box 6 contains the bowl and the bread and the phone. Remove the book from Box 1. Remove the glass from Box 2. Remove the bread from Box 6. Move the cash and the seed from Box 4 to Box 0.", "sample_id": 1480, "numops": 1, "final_states": {"Box 0": ["the flower", "the cash", "the seed"], "Box 1": ["the shell", "nothing", "the tape"], "Box 2": ["nothing", "the ball"], "Box 3": ["nothing", "the tissue"], "Box 4": ["the letter", "the seed"], "Box 5": ["the flower", "the game", "the leaf"], "Box 6": ["the bowl", "the phone"]}}
{"sentence": "Box 0 contains the ring and the suit, Box 1 contains the book and the knife, Box 2 contains the plate and the tie, Box 3 contains nothing, Box 4 contains the bread and the brick and the cup, Box 5 contains the magazine and the shell, Box 6 contains the rock and the shirt and the string. Put the crown into Box 2. Move the bread from Box 4 to Box 5. Remove the knife from Box 1. Remove the rock and the shirt from Box 6. Remove the string from Box 6. Remove the shell from Box 5. Move the book from Box 1 to Box 5. Move the bread from Box 5 to Box 6. Remove the magazine from Box 5. Remove the bread from Box 6. Put the game and the rock into Box 5. Remove the crown and the plate and the tie from Box 2.", "sample_id": 1487, "numops": 0, "final_states": {"Box 0": ["the ring", "the suit"], "Box 1": ["nothing"], "Box 2": ["nothing"], "Box 3": ["nothing"], "Box 4": ["the cup", "the brick"], "Box 5": ["the game", "the rock", "the book"], "Box 6": ["nothing"]}}
{"sentence": "Box 0 contains the boat and the dish and the leaf, Box 1 contains nothing, Box 2 contains the bottle and the newspaper, Box 3 contains the block and the clock and the wire, Box 4 contains the disk, Box 5 contains the boot and the brain and the bread, Box 6 contains the beer and the suit. Remove the boot from Box 5. Move the brain and the bread from Box 5 to Box 1. Remove the boat and the leaf from Box 0.", "sample_id": 1490, "numops": 1, "final_states": {"Box 0": ["the dish"], "Box 1": ["the bread", "the brain"], "Box 2": ["the bottle", "the newspaper"], "Box 3": ["the clock", "the wire", "the block"], "Box 4": ["the disk"], "Box 5": ["nothing"], "Box 6": ["the beer", "the suit"]}}
{"sentence": "Box 0 contains the boat, Box 1 contains the document and the ice and the mirror, Box 2 contains the branch and the cash and the seed, Box 3 contains the shell, Box 4 contains nothing, Box 5 contains the block and the bottle and the dish, Box 6 contains nothing. Move the boat from Box 0 to Box 6. Move the boat from Box 6 to Box 4. Remove the shell from Box 3. Move the document from Box 1 to Box 4. Remove the mirror from Box 1. Remove the document from Box 4. Put the wire into Box 3. Move the branch and the seed from Box 2 to Box 1. Remove the ice and the seed from Box 1. Put the cheese into Box 6. Remove the wire from Box 3. Move the boat from Box 4 to Box 0.", "sample_id": 1492, "numops": 2, "final_states": {"Box 0": ["the boat"], "Box 1": ["the branch"], "Box 2": ["the cash"], "Box 3": ["nothing"], "Box 4": ["nothing"], "Box 5": ["the dish", "the bottle", "the block"], "Box 6": ["the cheese"]}}
{"sentence": "Box 0 contains the cross, Box 1 contains the wheel, Box 2 contains nothing, Box 3 contains the fig and the rock and the shirt, Box 4 contains nothing, Box 5 contains the computer and the letter and the medicine, Box 6 contains the leaf and the phone and the tea. Put the cigarette and the pipe into Box 1. Put the television into Box 0. Put the drink into Box 2. Remove the television from Box 0. Remove the computer and the letter and the medicine from Box 5. Move the cigarette and the wheel from Box 1 to Box 5. Put the card and the egg into Box 0. Remove the cross from Box 0. Put the bag into Box 4. Remove the card from Box 0. Move the egg from Box 0 to Box 4.", "sample_id": 1510, "numops": 6, "final_states": {"Box 0": ["nothing", "the tea", "the leaf"], "Box 1": ["the pipe"], "Box 2": ["the drink"], "Box 3": ["the fig", "the shirt", "the rock"], "Box 4": ["the bag", "the egg"], "Box 5": ["the cigarette", "the wheel"], "Box 6": ["the phone", "the tea", "the leaf"]}}
{"sentence": "Box 0 contains the bus and the game and the plate, Box 1 contains the fig, Box 2 contains the letter and the machine and the rock, Box 3 contains the pot, Box 4 contains nothing, Box 5 contains the plant, Box 6 contains the coffee and the egg and the plane. Move the pot from Box 3 to Box 5. Put the coat into Box 3. Put the branch into Box 5. Put the camera into Box 4. Remove the branch from Box 5. Remove the camera from Box 4. Remove the game from Box 0. Move the coat from Box 3 to Box 1. Move the bus and the plate from Box 0 to Box 4. Remove the bus and the plate from Box 4. Remove the letter and the machine and the rock from Box 2. Move the fig from Box 1 to Box 2.", "sample_id": 1513, "numops": 2, "final_states": {"Box 0": ["nothing"], "Box 1": ["the coat"], "Box 2": ["the fig"], "Box 3": ["nothing"], "Box 4": ["nothing"], "Box 5": ["the pot", "the plant"], "Box 6": ["the coffee", "the plane", "the egg"]}}
{"sentence": "Box 0 contains the clock and the tape, Box 1 contains the drink and the note and the watch, Box 2 contains the cross and the radio and the train, Box 3 contains the book and the pot, Box 4 contains the newspaper, Box 5 contains the beer and the medicine, Box 6 contains the ball and the cheese and the gift. Remove the drink from Box 1. Remove the book from Box 3. Remove the tape from Box 0. Put the apple and the fig into Box 3. Remove the gift from Box 6. Move the cross from Box 2 to Box 6. Remove the pot from Box 3. Move the apple and the fig from Box 3 to Box 0.", "sample_id": 1517, "numops": 2, "final_states": {"Box 0": ["the apple", "the clock", "the fig"], "Box 1": ["the note", "the watch"], "Box 2": ["the train", "the radio"], "Box 3": ["nothing"], "Box 4": ["the newspaper"], "Box 5": ["the medicine", "the beer"], "Box 6": ["the cross", "the cheese", "the ball"]}}
{"sentence": "Box 0 contains the cigarette and the dress and the string, Box 1 contains the disk and the stone, Box 2 contains nothing, Box 3 contains nothing, Box 4 contains the bread and the fig and the tape, Box 5 contains nothing, Box 6 contains the watch. Move the tape from Box 4 to Box 2. Move the bread and the fig from Box 4 to Box 3. Remove the bread and the fig from Box 3. Remove the tape from Box 2. Remove the watch from Box 6. Move the cigarette and the dress and the string from Box 0 to Box 3. Put the cup and the engine into Box 5. Remove the string from Box 3. Move the cup from Box 5 to Box 2. Remove the dress from Box 3. Move the cup from Box 2 to Box 0.", "sample_id": 1525, "numops": 2, "final_states": {"Box 0": ["the cup"], "Box 1": ["the stone", "the disk"], "Box 2": ["nothing"], "Box 3": ["the cigarette"], "Box 4": ["nothing"], "Box 5": ["the engine"], "Box 6": ["nothing"]}}
{"sentence": "Box 0 contains the beer and the bread and the dress, Box 1 contains the apple, Box 2 contains the ball and the pipe and the watch, Box 3 contains the clock and the crown, Box 4 contains the brain and the fan and the tissue, Box 5 contains the glass and the tea, Box 6 contains the gift and the television. Remove the watch from Box 2. Move the apple from Box 1 to Box 2. Put the branch into Box 1. Remove the apple and the pipe from Box 2. Remove the crown from Box 3. Put the fig into Box 5. Remove the ball from Box 2. Remove the clock from Box 3. Move the branch from Box 1 to Box 2.", "sample_id": 1530, "numops": 0, "final_states": {"Box 0": ["the bread", "the beer", "the dress"], "Box 1": ["nothing"], "Box 2": ["the picture", "the branch"], "Box 3": ["nothing"], "Box 4": ["the fan", "the brain", "the tissue"], "Box 5": ["the fig", "the glass", "the tea"], "Box 6": ["the gift", "the television", "the magazine"]}}
{"sentence": "Box 0 contains the coat, Box 1 contains the boat and the wire, Box 2 contains the cash, Box 3 contains the plate, Box 4 contains the milk and the sheet, Box 5 contains the ball and the bomb and the creature, Box 6 contains the rose. Put the ice and the plant into Box 6. Put the map into Box 3. Remove the wire from Box 1. Remove the coat from Box 0. Remove the sheet from Box 4. Remove the bomb from Box 5. Move the boat from Box 1 to Box 0. Move the boat from Box 0 to Box 4. Remove the plant and the rose from Box 6. Move the cash from Box 2 to Box 6. Move the ball and the creature from Box 5 to Box 0. Put the document and the ticket into Box 2.", "sample_id": 1536, "numops": 4, "final_states": {"Box 0": ["the creature", "the ball"], "Box 1": ["nothing"], "Box 2": ["the document", "the ticket"], "Box 3": ["the plate", "the map"], "Box 4": ["the milk", "the boat"], "Box 5": ["nothing"], "Box 6": ["the cash", "the ice"]}}
{"sentence": "Box 0 contains the plant and the sheet, Box 1 contains the coffee and the leaf and the stone, Box 2 contains nothing, Box 3 contains the fish, Box 4 contains the bomb and the cross and the key, Box 5 contains the card and the ticket, Box 6 contains the tie. Remove the tie from Box 6. Put the plane into Box 6. Remove the plane from Box 6. Remove the fish from Box 3. Move the stone from Box 1 to Box 0. Put the boat and the letter into Box 6. Move the cross from Box 4 to Box 1. Move the boat and the letter from Box 6 to Box 3. Move the plant from Box 0 to Box 4. Move the cross from Box 1 to Box 6.", "sample_id": 1538, "numops": 2, "final_states": {"Box 0": ["the sheet", "the stone"], "Box 1": ["the coffee", "the leaf"], "Box 2": ["nothing"], "Box 3": ["the boat", "the letter"], "Box 4": ["the bomb", "the key", "the plant"], "Box 5": ["the card", "the ticket", "the cross"], "Box 6": ["nothing", "the cross"]}}
{"sentence": "Box 0 contains the jacket and the ring, Box 1 contains the car and the file and the medicine, Box 2 contains the boot and the computer and the machine, Box 3 contains nothing, Box 4 contains the pipe, Box 5 contains nothing, Box 6 contains the crown. Remove the medicine from Box 1. Remove the car from Box 1. Put the fig into Box 4. Remove the crown from Box 6. Put the bell into Box 3. Put the milk into Box 3. Move the jacket and the ring from Box 0 to Box 6. Move the bell from Box 3 to Box 1. Remove the milk from Box 3. Put the hat and the seed into Box 3. Move the hat from Box 3 to Box 5. Remove the fig from Box 4.", "sample_id": 1541, "numops": 1, "final_states": {"Box 0": ["nothing"], "Box 1": ["the file", "the bell"], "Box 2": ["the computer", "the boot", "the machine"], "Box 3": ["the seed"], "Box 4": ["the pipe"], "Box 5": ["the hat"], "Box 6": ["the ring", "the jacket"]}}
{"sentence": "Box 0 contains the ball, Box 1 contains the coat and the drink and the pot, Box 2 contains the drug and the egg and the plate, Box 3 contains the cup, Box 4 contains the car and the cash and the newspaper, Box 5 contains the apple and the bus and the stone, Box 6 contains the bone and the ice and the medicine. Remove the cup from Box 3. Remove the bone and the medicine from Box 6. Move the car from Box 4 to Box 0.", "sample_id": 1544, "numops": 1, "final_states": {"Box 0": ["the car", "the ball"], "Box 1": ["the coat", "the pot", "the drink"], "Box 2": ["the plate", "the bowl", "the drug", "the egg"], "Box 3": ["nothing"], "Box 4": ["the cash", "the newspaper"], "Box 5": ["the apple", "the bus", "the stone"], "Box 6": ["nothing", "the ice"]}}
{"sentence": "Box 0 contains nothing, Box 1 contains the plane and the pot and the sheet, Box 2 contains the cup and the tissue, Box 3 contains the dish and the guitar and the plate, Box 4 contains the gift and the plant and the shell, Box 5 contains the book and the cake and the paper, Box 6 contains the ice. Put the car into Box 0. Put the cheese into Box 6. Remove the book and the paper from Box 5. Move the car from Box 0 to Box 5. Put the coffee into Box 0. Move the ice from Box 6 to Box 5. Remove the guitar and the plate from Box 3. Remove the cake from Box 5. Put the bomb into Box 5. Move the car from Box 5 to Box 2.", "sample_id": 1545, "numops": 3, "final_states": {"Box 0": ["the coffee"], "Box 1": ["the sheet", "the plane", "the pot"], "Box 2": ["the car", "the cup", "the tissue"], "Box 3": ["the dish"], "Box 4": ["the shell", "the gift", "the plant"], "Box 5": ["the bomb", "the ice", "the chemical"], "Box 6": ["the wire", "the cheese"]}}
{"sentence": "Box 0 contains the card and the clock, Box 1 contains the camera and the cash and the computer, Box 2 contains the bottle and the chemical and the key, Box 3 contains nothing, Box 4 contains the creature and the document, Box 5 contains the car and the coffee, Box 6 contains the bomb and the leaf and the tie. Move the bottle from Box 2 to Box 5. Move the coffee from Box 5 to Box 4. Remove the computer from Box 1. Remove the camera and the cash from Box 1. Remove the bomb and the tie from Box 6. Move the bottle and the car from Box 5 to Box 6. Put the meat and the painting into Box 1. Remove the coffee from Box 4. Move the creature and the document from Box 4 to Box 5. Remove the clock from Box 0. Move the card from Box 0 to Box 5.", "sample_id": 1550, "numops": 2, "final_states": {"Box 0": ["nothing"], "Box 1": ["the painting", "the meat"], "Box 2": ["the chemical", "the key"], "Box 3": ["nothing"], "Box 4": ["nothing"], "Box 5": ["the card", "the document", "the creature"], "Box 6": ["the bottle", "the car", "the leaf"]}}
{"sentence": "Box 0 contains nothing, Box 1 contains the chemical and the clock, Box 2 contains the watch, Box 3 contains the dress and the plant and the sheet, Box 4 contains the document and the fig and the string, Box 5 contains nothing, Box 6 contains the gift and the newspaper and the tissue. Remove the clock from Box 1. Put the ice into Box 1. Put the bowl into Box 2. Remove the document from Box 4. Remove the gift and the newspaper and the tissue from Box 6. Remove the ice from Box 1. Move the watch from Box 2 to Box 1.", "sample_id": 1551, "numops": 0, "final_states": {"Box 0": ["nothing"], "Box 1": ["the chemical", "the watch"], "Box 2": ["the bowl"], "Box 3": ["the sheet", "the plant", "the dress"], "Box 4": ["the fig", "the string"], "Box 5": ["nothing"], "Box 6": ["nothing"]}}
{"sentence": "Box 0 contains the bomb, Box 1 contains the bag and the bell, Box 2 contains the cream and the drug and the picture, Box 3 contains the letter and the rose and the tea, Box 4 contains the flower and the wire, Box 5 contains the coffee and the paper and the sheet, Box 6 contains the cash and the fig and the gift. Remove the flower and the wire from Box 4. Remove the paper and the sheet from Box 5. Remove the fig from Box 6. Remove the bomb from Box 0. Put the tape into Box 1. Move the coffee from Box 5 to Box 0. Remove the coffee from Box 0. Remove the picture from Box 2. Put the medicine into Box 4. Move the medicine from Box 4 to Box 6. Move the cream from Box 2 to Box 5.", "sample_id": 1558, "numops": 3, "final_states": {"Box 0": ["nothing"], "Box 1": ["the bell", "the bag", "the tape"], "Box 2": ["the drug"], "Box 3": ["the rose", "the letter", "the tea"], "Box 4": ["nothing"], "Box 5": ["the cream"], "Box 6": ["the gift", "the cash", "the medicine"]}}
{"sentence": "Box 0 contains the tea, Box 1 contains the ice, Box 2 contains the dress, Box 3 contains the fish and the gift and the tape, Box 4 contains the shell, Box 5 contains the block and the clock, Box 6 contains the train. Move the ice from Box 1 to Box 6. Move the dress from Box 2 to Box 5. Remove the clock and the dress from Box 5. Move the fish and the gift from Box 3 to Box 0. Move the block from Box 5 to Box 4. Move the tape from Box 3 to Box 1. Move the tea from Box 0 to Box 4. Put the tissue into Box 2. Move the ice and the train from Box 6 to Box 5. Remove the ice from Box 5.", "sample_id": 1559, "numops": 2, "final_states": {"Box 0": ["the fish", "the gift"], "Box 1": ["the tape"], "Box 2": ["the tissue"], "Box 3": ["nothing"], "Box 4": ["the shell", "the tea", "the block"], "Box 5": ["the train"], "Box 6": ["nothing"]}}
{"sentence": "Box 0 contains the boot and the chemical and the shirt, Box 1 contains the bomb and the television, Box 2 contains the dress and the fan and the phone, Box 3 contains the wheel, Box 4 contains the coffee, Box 5 contains the fig, Box 6 contains the ball and the block and the cheese. Remove the cheese from Box 6. Move the bomb and the television from Box 1 to Box 4. Remove the block from Box 6. Move the bomb and the coffee and the television from Box 4 to Box 1. Remove the ball from Box 6.", "sample_id": 1561, "numops": 0, "final_states": {"Box 0": ["the chemical", "the boot", "the shirt"], "Box 1": ["the coffee", "the television", "the bomb"], "Box 2": ["the fan", "the phone", "the dress"], "Box 3": ["the wheel"], "Box 4": ["nothing"], "Box 5": ["the fig"], "Box 6": ["nothing"]}}
{"sentence": "Box 0 contains the document, Box 1 contains the dress and the radio, Box 2 contains the suit, Box 3 contains the bill, Box 4 contains the pipe, Box 5 contains the cup and the magazine and the plant, Box 6 contains nothing. Put the shell and the wheel into Box 0. Remove the suit from Box 2. Remove the pipe from Box 4.", "sample_id": 1566, "numops": 1, "final_states": {"Box 0": ["the shell", "the wheel", "the document"], "Box 1": ["the gift", "the radio", "the note", "the crown", "the dress"], "Box 2": ["nothing"], "Box 3": ["nothing", "the bill"], "Box 4": ["nothing"], "Box 5": ["the plant", "the magazine", "the cup"], "Box 6": ["nothing"]}}
{"sentence": "Box 0 contains the bottle, Box 1 contains the pipe, Box 2 contains the dish and the game, Box 3 contains nothing, Box 4 contains the plate, Box 5 contains the car and the painting and the plant, Box 6 contains the milk. Put the picture into Box 2. Remove the picture from Box 2. Move the dish and the game from Box 2 to Box 1. Remove the dish and the game and the pipe from Box 1. Move the bottle from Box 0 to Box 4. Remove the plant from Box 5. Put the engine into Box 5. Remove the car from Box 5. Put the coffee and the medicine into Box 0. Remove the milk from Box 6. Remove the engine from Box 5.", "sample_id": 1573, "numops": 2, "final_states": {"Box 0": ["the coffee", "the medicine"], "Box 1": ["nothing"], "Box 2": ["nothing"], "Box 3": ["nothing"], "Box 4": ["the plate", "the bottle"], "Box 5": ["the painting"], "Box 6": ["nothing"]}}
{"sentence": "Box 0 contains the book and the game and the tea, Box 1 contains the drug and the note and the ring, Box 2 contains nothing, Box 3 contains the string, Box 4 contains the tissue, Box 5 contains the bell, Box 6 contains the television. Move the drug and the ring from Box 1 to Box 2. Remove the string from Box 3. Remove the bell from Box 5. Put the milk into Box 5. Remove the television from Box 6. Remove the tissue from Box 4. Move the game from Box 0 to Box 4. Put the shell into Box 2.", "sample_id": 1581, "numops": 1, "final_states": {"Box 0": ["the book", "the tea"], "Box 1": ["the note"], "Box 2": ["the shell", "the drug", "the ring"], "Box 3": ["nothing"], "Box 4": ["the game"], "Box 5": ["the milk"], "Box 6": ["nothing"]}}
{"sentence": "Box 0 contains the pot, Box 1 contains the flower, Box 2 contains nothing, Box 3 contains the game and the watch, Box 4 contains the cross and the phone and the tea, Box 5 contains the cheese and the ticket, Box 6 contains the cake. Put the creature into Box 2. Move the pot from Box 0 to Box 5. Move the pot from Box 5 to Box 1. Remove the cake from Box 6. Move the phone and the tea from Box 4 to Box 0. Move the cheese from Box 5 to Box 3. Move the ticket from Box 5 to Box 2. Remove the cheese and the game and the watch from Box 3. Move the phone from Box 0 to Box 3. Put the glass into Box 3.", "sample_id": 1586, "numops": 3, "final_states": {"Box 0": ["the tea"], "Box 1": ["the flower", "the pot"], "Box 2": ["the creature", "the ticket"], "Box 3": ["the glass", "the phone"], "Box 4": ["the cross"], "Box 5": ["nothing"], "Box 6": ["nothing"]}}
{"sentence": "Box 0 contains the pipe, Box 1 contains the bone and the glass and the wire, Box 2 contains the letter and the radio, Box 3 contains the car, Box 4 contains the document and the engine and the knife, Box 5 contains the chemical, Box 6 contains the bomb and the book and the game. Remove the pipe from Box 0. Put the brain and the plane into Box 5. Move the letter and the radio from Box 2 to Box 3. Remove the bone and the wire from Box 1. Move the brain and the chemical from Box 5 to Box 0. Remove the brain and the chemical from Box 0. Remove the engine from Box 4. Remove the car and the letter from Box 3. Move the plane from Box 5 to Box 0. Move the bomb from Box 6 to Box 5.", "sample_id": 1588, "numops": 4, "final_states": {"Box 0": ["the plane"], "Box 1": ["the glass"], "Box 2": ["nothing"], "Box 3": ["the radio"], "Box 4": ["the knife", "the document"], "Box 5": ["the bomb"], "Box 6": ["the game", "the book"]}}
{"sentence": "Box 0 contains the mirror and the plane, Box 1 contains the cheese and the disk and the tissue, Box 2 contains the pipe and the watch, Box 3 contains the flower and the shirt, Box 4 contains the book and the tea, Box 5 contains the drug, Box 6 contains the ice. Put the leaf into Box 6. Remove the flower and the shirt from Box 3. Remove the ice and the leaf from Box 6.", "sample_id": 1598, "numops": 0, "final_states": {"Box 0": ["the mirror", "the plane"], "Box 1": ["the disk", "the cheese", "the tissue"], "Box 2": ["the pipe", "the watch"], "Box 3": ["nothing"], "Box 4": ["the book", "the tea"], "Box 5": ["the drug"], "Box 6": ["nothing"]}}
{"sentence": "Box 0 contains the magazine, Box 1 contains the boot and the cheese and the chemical, Box 2 contains nothing, Box 3 contains the bowl and the glass and the hat, Box 4 contains the branch and the drug and the egg, Box 5 contains the tie, Box 6 contains the pipe and the stone. Move the boot and the cheese and the chemical from Box 1 to Box 2. Remove the stone from Box 6. Put the meat and the string into Box 6. Put the medicine into Box 1. Remove the tie from Box 5. Remove the medicine from Box 1. Put the cup into Box 1. Remove the magazine from Box 0. Move the cup from Box 1 to Box 5.", "sample_id": 1599, "numops": 1, "final_states": {"Box 0": ["nothing"], "Box 1": ["nothing", "the rock"], "Box 2": ["the boot", "the cheese", "the chemical"], "Box 3": ["the glass", "the bowl", "nothing", "the hat"], "Box 4": ["the drug", "the egg", "the branch"], "Box 5": ["the cup"], "Box 6": ["the pipe", "the meat", "the string"]}}
{"sentence": "Box 0 contains the bomb and the drug, Box 1 contains the bill and the cup and the plant, Box 2 contains the branch and the card and the pot, Box 3 contains the coffee and the shell and the train, Box 4 contains the picture and the rose, Box 5 contains the egg, Box 6 contains the cash and the key and the phone. Remove the picture and the rose from Box 4. Remove the egg from Box 5. Move the drug from Box 0 to Box 4. Move the coffee from Box 3 to Box 5.", "sample_id": 1606, "numops": 1, "final_states": {"Box 0": ["the bomb"], "Box 1": ["the plant", "the bill", "the cup"], "Box 2": ["the card", "the pot", "the branch"], "Box 3": ["the shell", "the drug", "the train"], "Box 4": ["nothing", "the drug"], "Box 5": ["the coffee", "nothing"], "Box 6": ["the phone", "the key", "the cash"]}}
{"sentence": "Box 0 contains the camera and the phone and the shirt, Box 1 contains the game and the ice, Box 2 contains nothing, Box 3 contains the painting, Box 4 contains the bottle and the computer and the tape, Box 5 contains the drug, Box 6 contains the shell and the shoe. Move the ice from Box 1 to Box 5. Put the brain into Box 3. Remove the computer and the tape from Box 4. Put the paper into Box 1. Move the ice from Box 5 to Box 1. Remove the brain from Box 3. Remove the camera and the phone and the shirt from Box 0. Remove the drug from Box 5. Put the chemical and the seed into Box 0. Put the rose into Box 3. Put the bomb and the milk into Box 5. Move the bottle from Box 4 to Box 5.", "sample_id": 1608, "numops": 2, "final_states": {"Box 0": ["the chemical", "the seed"], "Box 1": ["the paper", "the game", "the ice"], "Box 2": ["nothing"], "Box 3": ["the rose", "the painting"], "Box 4": ["nothing"], "Box 5": ["the milk", "the bottle", "the bomb"], "Box 6": ["the shell", "the shoe"]}}
{"sentence": "Box 0 contains the branch and the drug, Box 1 contains the gift and the seed, Box 2 contains the crown, Box 3 contains the brain and the suit, Box 4 contains the watch, Box 5 contains the book and the pot and the shell, Box 6 contains the coat and the dish. Put the jacket into Box 4. Remove the branch and the drug from Box 0. Remove the jacket from Box 4. Remove the gift from Box 1. Remove the watch from Box 4. Put the dress into Box 6. Move the shell from Box 5 to Box 4. Move the shell from Box 4 to Box 3.", "sample_id": 1612, "numops": 1, "final_states": {"Box 0": ["nothing"], "Box 1": ["the seed"], "Box 2": ["the crown"], "Box 3": ["the shell", "the brain", "the suit"], "Box 4": ["nothing"], "Box 5": ["the pot", "the book"], "Box 6": ["the dish", "the coat", "the dress"]}}
{"sentence": "Box 0 contains the ticket, Box 1 contains the brick and the glass and the tea, Box 2 contains the beer and the painting and the radio, Box 3 contains the bus, Box 4 contains the clock, Box 5 contains the disk and the medicine, Box 6 contains the book and the mirror and the stone. Remove the ticket from Box 0. Put the drug into Box 5. Remove the brick and the glass and the tea from Box 1. Remove the stone from Box 6. Move the drug and the medicine from Box 5 to Box 4. Remove the drug and the medicine from Box 4. Remove the beer and the painting and the radio from Box 2. Remove the book from Box 6. Move the mirror from Box 6 to Box 0. Move the mirror from Box 0 to Box 3.", "sample_id": 1614, "numops": 3, "final_states": {"Box 0": ["nothing"], "Box 1": ["nothing"], "Box 2": ["nothing"], "Box 3": ["the mirror", "the bus"], "Box 4": ["the clock"], "Box 5": ["the disk"], "Box 6": ["nothing"]}}
{"sentence": "Box 0 contains nothing, Box 1 contains the cup and the leaf and the tie, Box 2 contains the dress and the game, Box 3 contains the brick and the camera and the file, Box 4 contains the book, Box 5 contains the cross, Box 6 contains the map and the stone. Remove the dress from Box 2. Remove the camera and the file from Box 3. Remove the brick from Box 3. Put the brick into Box 5. Remove the cross from Box 5. Put the block into Box 2. Remove the book from Box 4. Move the stone from Box 6 to Box 4. Put the creature into Box 2. Remove the creature from Box 2. Remove the cup and the leaf from Box 1. Remove the map from Box 6.", "sample_id": 1615, "numops": 0, "final_states": {"Box 0": ["nothing"], "Box 1": ["the tie"], "Box 2": ["the game", "the block"], "Box 3": ["nothing"], "Box 4": ["the stone"], "Box 5": ["the brick"], "Box 6": ["nothing"]}}
{"sentence": "Box 0 contains the fan and the tape, Box 1 contains the shell, Box 2 contains nothing, Box 3 contains the bomb and the radio, Box 4 contains the fish and the ring, Box 5 contains the computer, Box 6 contains the plane. Move the fish and the ring from Box 4 to Box 5. Remove the fish from Box 5. Remove the plane from Box 6. Remove the radio from Box 3. Move the fan and the tape from Box 0 to Box 6. Remove the fan from Box 6. Put the shirt into Box 4. Put the tea into Box 4. Put the shoe into Box 3. Move the tea from Box 4 to Box 5.", "sample_id": 1619, "numops": 1, "final_states": {"Box 0": ["the tape", "nothing", "the shirt"], "Box 1": ["the shell"], "Box 2": ["nothing"], "Box 3": ["the bomb", "the shoe"], "Box 4": ["nothing", "the shirt"], "Box 5": ["the computer", "the tea", "the ring"], "Box 6": ["nothing", "the tape"]}}
{"sentence": "Box 0 contains the chemical and the magazine, Box 1 contains the wire, Box 2 contains the boat and the book and the drink, Box 3 contains the ball and the fan and the gift, Box 4 contains the dish, Box 5 contains the file, Box 6 contains nothing. Remove the ball from Box 3. Remove the boat and the book from Box 2. Move the magazine from Box 0 to Box 1. Remove the magazine and the wire from Box 1. Put the ticket into Box 1. Move the dish from Box 4 to Box 1. Put the watch into Box 4. Move the dish and the ticket from Box 1 to Box 4. Move the drink from Box 2 to Box 6. Move the file from Box 5 to Box 2.", "sample_id": 1628, "numops": 1, "final_states": {"Box 0": ["the chemical"], "Box 1": ["nothing"], "Box 2": ["the file"], "Box 3": ["the fan", "the gift"], "Box 4": ["the dish", "the ticket", "the watch"], "Box 5": ["nothing"], "Box 6": ["the drink"]}}
{"sentence": "Box 0 contains nothing, Box 1 contains the cash and the hat, Box 2 contains the car and the phone and the sheet, Box 3 contains the crown, Box 4 contains the document and the medicine, Box 5 contains the jacket and the machine and the tape, Box 6 contains the cream. Remove the car and the sheet from Box 2. Put the picture into Box 4. Put the boat into Box 3. Move the cream from Box 6 to Box 1. Move the phone from Box 2 to Box 6.", "sample_id": 1633, "numops": 0, "final_states": {"Box 0": ["the phone", "nothing"], "Box 1": ["the cream", "nothing", "the cash", "the hat"], "Box 2": ["the bottle", "the boot", "the watch", "nothing"], "Box 3": ["the rose", "the boat", "the crown"], "Box 4": ["the document", "the picture", "the medicine"], "Box 5": ["the machine", "the tape", "the jacket"], "Box 6": ["the phone", "nothing"]}}
{"sentence": "Box 0 contains the magazine and the phone and the watch, Box 1 contains nothing, Box 2 contains the chemical, Box 3 contains the cross, Box 4 contains nothing, Box 5 contains the machine and the train, Box 6 contains nothing. Remove the chemical from Box 2. Remove the train from Box 5. Put the document into Box 6. Move the machine from Box 5 to Box 3. Move the magazine and the watch from Box 0 to Box 4. Remove the cross and the machine from Box 3. Remove the document from Box 6. Move the phone from Box 0 to Box 5.", "sample_id": 1649, "numops": 2, "final_states": {"Box 0": ["nothing"], "Box 1": ["nothing"], "Box 2": ["nothing"], "Box 3": ["nothing"], "Box 4": ["the magazine", "the watch"], "Box 5": ["the phone"], "Box 6": ["nothing"]}}
{"sentence": "Box 0 contains the coat and the flower, Box 1 contains the tape and the wheel, Box 2 contains the cup and the leaf and the medicine, Box 3 contains the chemical and the gift, Box 4 contains the creature and the dress and the meat, Box 5 contains nothing, Box 6 contains the key.", "sample_id": 1653, "numops": 0, "final_states": {"Box 0": ["the flower", "the coat"], "Box 1": ["the wheel", "the tape"], "Box 2": ["the medicine", "the cup", "the leaf"], "Box 3": ["the chemical", "the gift"], "Box 4": ["the creature", "the meat", "the dress"], "Box 5": ["nothing"], "Box 6": ["the key"]}}
{"sentence": "Box 0 contains the meat, Box 1 contains the computer and the creature and the drink, Box 2 contains the bone and the cigarette and the drug, Box 3 contains nothing, Box 4 contains the egg and the gift and the radio, Box 5 contains the hat and the milk and the seed, Box 6 contains the plant. Remove the drink from Box 1. Move the hat and the seed from Box 5 to Box 3. Remove the plant from Box 6.", "sample_id": 1654, "numops": 0, "final_states": {"Box 0": ["the meat"], "Box 1": ["the computer", "the creature"], "Box 2": ["the bone", "the cigarette", "the drug"], "Box 3": ["the hat", "the seed"], "Box 4": ["the gift", "the egg", "the radio"], "Box 5": ["the milk"], "Box 6": ["nothing"]}}
{"sentence": "Box 0 contains the jacket and the tape, Box 1 contains the ring, Box 2 contains the dish, Box 3 contains the drink, Box 4 contains the ball and the fan and the file, Box 5 contains the ice and the radio, Box 6 contains the leaf and the string.", "sample_id": 1655, "numops": 0, "final_states": {"Box 0": ["the jacket", "the tape"], "Box 1": ["nothing", "the ring"], "Box 2": ["the dish", "nothing"], "Box 3": ["nothing", "the drink"], "Box 4": ["the fan", "the file", "nothing", "the ball"], "Box 5": ["nothing", "the ice", "the radio"], "Box 6": ["the dish", "the string", "the leaf"]}}
{"sentence": "Box 0 contains the radio, Box 1 contains the map and the tea, Box 2 contains the file and the medicine and the tape, Box 3 contains the brick and the disk and the wheel, Box 4 contains the bomb and the shell, Box 5 contains the bowl and the plane, Box 6 contains the bill and the fish and the letter. Move the brick from Box 3 to Box 1. Remove the plane from Box 5. Move the medicine from Box 2 to Box 3. Remove the bowl from Box 5. Remove the tape from Box 2. Remove the radio from Box 0.", "sample_id": 1660, "numops": 1, "final_states": {"Box 0": ["nothing"], "Box 1": ["the map", "the tea", "the brick"], "Box 2": ["the file"], "Box 3": ["the medicine", "the disk", "the wheel"], "Box 4": ["the shell", "the bomb"], "Box 5": ["nothing"], "Box 6": ["the fish", "the bill", "the letter"]}}
{"sentence": "Box 0 contains the camera and the note and the suit, Box 1 contains the bell, Box 2 contains the ice and the mirror, Box 3 contains nothing, Box 4 contains the bottle, Box 5 contains the game and the painting and the pipe, Box 6 contains the brain and the tissue. Put the drink into Box 6. Move the painting from Box 5 to Box 3. Move the bell from Box 1 to Box 4. Move the painting from Box 3 to Box 5. Remove the game and the painting and the pipe from Box 5. Move the bottle from Box 4 to Box 5. Remove the bottle from Box 5. Move the ice and the mirror from Box 2 to Box 5.", "sample_id": 1670, "numops": 0, "final_states": {"Box 0": ["the note", "the camera", "the suit"], "Box 1": ["nothing"], "Box 2": ["nothing"], "Box 3": ["the computer", "nothing", "the medicine"], "Box 4": ["the knife", "the bell"], "Box 5": ["the mirror", "nothing", "the ice"], "Box 6": ["the tissue", "the brain", "the drink"]}}
{"sentence": "Box 0 contains the magazine and the painting, Box 1 contains the cross, Box 2 contains the camera and the cup, Box 3 contains the bone and the wheel, Box 4 contains the cheese and the disk and the milk, Box 5 contains the brain and the document and the picture, Box 6 contains the glass. Put the leaf into Box 3. Put the coat and the plate into Box 6. Move the cup from Box 2 to Box 1. Remove the camera from Box 2. Remove the bone and the leaf from Box 3. Move the cross and the cup from Box 1 to Box 2. Remove the plate from Box 6. Remove the wheel from Box 3.", "sample_id": 1672, "numops": 0, "final_states": {"Box 0": ["the painting", "the magazine"], "Box 1": ["nothing"], "Box 2": ["the picture", "the cross", "the brain", "the cup"], "Box 3": ["nothing"], "Box 4": ["the milk", "the cheese", "the disk"], "Box 5": ["the document", "the brain", "the picture"], "Box 6": ["the glass", "the coat"]}}
{"sentence": "Box 0 contains the boot and the bread, Box 1 contains the block and the clock and the fan, Box 2 contains the plant, Box 3 contains the book and the cheese and the ring, Box 4 contains the shoe, Box 5 contains nothing, Box 6 contains the cross and the gift and the key. Remove the boot from Box 0. Move the cross and the key from Box 6 to Box 0. Remove the bread from Box 0. Move the shoe from Box 4 to Box 5. Move the plant from Box 2 to Box 0. Remove the fan from Box 1. Put the tea into Box 5. Move the clock from Box 1 to Box 2. Move the gift from Box 6 to Box 1. Remove the block and the gift from Box 1. Put the apple into Box 1.", "sample_id": 1677, "numops": 4, "final_states": {"Box 0": ["the key", "the plant", "the cross"], "Box 1": ["the apple"], "Box 2": ["the clock"], "Box 3": ["the ring", "the book", "the cheese"], "Box 4": ["nothing"], "Box 5": ["the tea", "the shoe"], "Box 6": ["nothing"]}}
{"sentence": "Box 0 contains the crown and the gift, Box 1 contains the bag and the map and the plane, Box 2 contains the ball and the coffee and the painting, Box 3 contains the camera and the tissue, Box 4 contains nothing, Box 5 contains the drug and the medicine and the picture, Box 6 contains the bowl and the bread and the train. Put the shell into Box 0. Remove the gift and the shell from Box 0. Move the map and the plane from Box 1 to Box 0. Put the mirror into Box 3. Remove the bowl and the bread and the train from Box 6. Remove the bag from Box 1. Remove the ball and the painting from Box 2. Put the beer and the letter into Box 6. Put the ball and the shoe into Box 1. Remove the crown and the plane from Box 0.", "sample_id": 1686, "numops": 4, "final_states": {"Box 0": ["the map"], "Box 1": ["the shoe", "the ball"], "Box 2": ["the coffee"], "Box 3": ["the camera", "the mirror", "the tissue"], "Box 4": ["nothing"], "Box 5": ["the medicine", "the drug", "the picture"], "Box 6": ["the beer", "the letter"]}}
{"sentence": "Box 0 contains the bell, Box 1 contains the bread and the drink and the engine, Box 2 contains the bone, Box 3 contains the cigarette and the ring, Box 4 contains the cake and the newspaper and the phone, Box 5 contains the bowl and the crown, Box 6 contains the plant. Move the bowl from Box 5 to Box 3.", "sample_id": 1692, "numops": 0, "final_states": {"Box 0": ["the bell"], "Box 1": ["the bread", "the engine", "the drink"], "Box 2": ["the bone"], "Box 3": ["the bowl", "the cigarette", "the ring"], "Box 4": ["the phone", "the newspaper", "the cake"], "Box 5": ["the crown"], "Box 6": ["the plant"]}}
{"sentence": "Box 0 contains nothing, Box 1 contains the egg and the medicine and the wheel, Box 2 contains the file and the tie, Box 3 contains nothing, Box 4 contains the boot and the suit, Box 5 contains the fig and the seed, Box 6 contains the beer and the meat. Move the file from Box 2 to Box 5. Remove the beer from Box 6. Put the watch into Box 4. Put the drug and the guitar into Box 3. Move the egg and the wheel from Box 1 to Box 6. Put the brick and the coffee into Box 2. Remove the medicine from Box 1. Remove the coffee and the tie from Box 2. Remove the suit and the watch from Box 4. Remove the boot from Box 4. Move the egg and the meat from Box 6 to Box 2. Remove the wheel from Box 6.", "sample_id": 1701, "numops": 0, "final_states": {"Box 0": ["nothing"], "Box 1": ["nothing"], "Box 2": ["the egg", "the meat", "the brick"], "Box 3": ["the drug", "the guitar"], "Box 4": ["nothing"], "Box 5": ["the file", "the fig", "the seed"], "Box 6": ["nothing"]}}
{"sentence": "Box 0 contains the shoe, Box 1 contains nothing, Box 2 contains the branch and the shell, Box 3 contains the cream and the fan and the map, Box 4 contains the book and the car and the mirror, Box 5 contains the pipe and the string, Box 6 contains the milk and the newspaper and the rose. Remove the book from Box 4. Remove the mirror from Box 4. Remove the fan and the map from Box 3. Remove the pipe from Box 5. Remove the car from Box 4. Remove the shoe from Box 0. Put the key into Box 2. Remove the cream from Box 3. Put the fig into Box 5. Move the milk and the newspaper and the rose from Box 6 to Box 3.", "sample_id": 1708, "numops": 1, "final_states": {"Box 0": ["nothing"], "Box 1": ["nothing"], "Box 2": ["the shell", "the key", "the branch"], "Box 3": ["the newspaper", "the milk", "the rose"], "Box 4": ["nothing"], "Box 5": ["the fig", "the string"], "Box 6": ["nothing"]}}
{"sentence": "Box 0 contains nothing, Box 1 contains the bomb and the ice and the wheel, Box 2 contains the picture, Box 3 contains the boat and the cross, Box 4 contains the card, Box 5 contains the book and the coat and the note, Box 6 contains the cream and the egg and the key. Remove the cross from Box 3. Move the picture from Box 2 to Box 3. Move the book from Box 5 to Box 3. Remove the cream and the egg and the key from Box 6. Remove the boat and the book from Box 3. Move the picture from Box 3 to Box 2. Move the note from Box 5 to Box 2. Remove the note from Box 2. Move the coat from Box 5 to Box 4. Put the game into Box 3.", "sample_id": 1710, "numops": 0, "final_states": {"Box 0": ["the game", "nothing"], "Box 1": ["the bomb", "the ice", "the wheel"], "Box 2": ["the picture", "the newspaper", "the apple"], "Box 3": ["the game", "nothing"], "Box 4": ["the card", "the coat"], "Box 5": ["nothing"], "Box 6": ["nothing"]}}
{"sentence": "Box 0 contains the milk, Box 1 contains the clock and the cross, Box 2 contains the game and the letter, Box 3 contains the book and the cup, Box 4 contains nothing, Box 5 contains the ball, Box 6 contains the medicine and the television. Move the game from Box 2 to Box 1. Move the milk from Box 0 to Box 6. Move the book from Box 3 to Box 2. Remove the ball from Box 5. Remove the letter from Box 2. Put the fig into Box 2. Move the book and the fig from Box 2 to Box 4. Remove the cup from Box 3. Put the coat into Box 5.", "sample_id": 1723, "numops": 1, "final_states": {"Box 0": ["nothing"], "Box 1": ["the game", "the cross", "the clock"], "Box 2": ["nothing", "the note"], "Box 3": ["nothing", "the cross"], "Box 4": ["the fig", "the book"], "Box 5": ["the camera", "the coat"], "Box 6": ["the television", "the medicine", "the milk"]}}
{"sentence": "Box 0 contains the brick and the wire, Box 1 contains the cigarette and the jacket, Box 2 contains the bell and the bone, Box 3 contains the milk and the tie and the wheel, Box 4 contains the ball and the newspaper and the tape, Box 5 contains the bus, Box 6 contains the chemical and the rock and the suit. Remove the bus from Box 5. Remove the jacket from Box 1. Move the newspaper and the tape from Box 4 to Box 5. Remove the bell from Box 2. Remove the milk and the wheel from Box 3.", "sample_id": 1727, "numops": 0, "final_states": {"Box 0": ["the wire", "the brick"], "Box 1": ["the cigarette"], "Box 2": ["the bone"], "Box 3": ["the tie"], "Box 4": ["the ball"], "Box 5": ["the newspaper", "the tape"], "Box 6": ["the chemical", "the rock", "the suit"]}}
{"sentence": "Box 0 contains the cake and the crown and the knife, Box 1 contains the note, Box 2 contains the coat and the medicine and the shirt, Box 3 contains the bag and the magazine and the tissue, Box 4 contains the ice, Box 5 contains the gift and the painting and the shell, Box 6 contains nothing. Move the shell from Box 5 to Box 1. Remove the ice from Box 4. Move the shirt from Box 2 to Box 1. Put the card into Box 4. Move the magazine and the tissue from Box 3 to Box 4. Remove the tissue from Box 4.", "sample_id": 1729, "numops": 0, "final_states": {"Box 0": ["the knife", "the crown", "the cake"], "Box 1": ["the shell", "the note", "the shirt"], "Box 2": ["the medicine", "the coat", "the pot", "the tissue"], "Box 3": ["the bag"], "Box 4": ["the card", "the medicine", "the magazine", "nothing"], "Box 5": ["the painting", "the gift"], "Box 6": ["nothing", "the note"]}}
{"sentence": "Box 0 contains the bag, Box 1 contains the coffee and the tape, Box 2 contains the cheese and the drug and the picture, Box 3 contains nothing, Box 4 contains the drink and the note, Box 5 contains the ball, Box 6 contains the machine and the tie. Remove the bag from Box 0. Put the ice into Box 6. Put the bag and the plant into Box 0. Move the cheese and the picture from Box 2 to Box 3. Remove the machine from Box 6. Remove the note from Box 4. Move the ice from Box 6 to Box 0. Move the drug from Box 2 to Box 6.", "sample_id": 1731, "numops": 3, "final_states": {"Box 0": ["the ice", "the plant", "the bag"], "Box 1": ["the coffee", "the tape"], "Box 2": ["nothing"], "Box 3": ["the picture", "the cheese", "the tie"], "Box 4": ["nothing", "the drink"], "Box 5": ["the ball"], "Box 6": ["nothing", "the drug", "the tie"]}}
{"sentence": "Box 0 contains the camera and the fan and the note, Box 1 contains the leaf and the plate, Box 2 contains the mirror, Box 3 contains the drug, Box 4 contains the coffee and the dress, Box 5 contains the key and the pipe, Box 6 contains the egg and the hat. Remove the drug from Box 3. Remove the mirror from Box 2. Put the ticket into Box 3. Move the leaf and the plate from Box 1 to Box 3. Put the magazine into Box 6. Remove the ticket from Box 3. Move the key from Box 5 to Box 4.", "sample_id": 1737, "numops": 0, "final_states": {"Box 0": ["the camera", "the fan", "the note"], "Box 1": ["nothing"], "Box 2": ["nothing", "the cup"], "Box 3": ["the plate", "the leaf"], "Box 4": ["the coffee", "the key", "the dress"], "Box 5": ["the pipe"], "Box 6": ["the magazine", "the hat", "the egg"]}}
{"sentence": "Box 0 contains nothing, Box 1 contains the disk and the drink and the fig, Box 2 contains nothing, Box 3 contains the block and the shirt, Box 4 contains the bus and the key and the rose, Box 5 contains the crown and the painting and the wheel, Box 6 contains the boot and the cigarette. Move the crown and the wheel from Box 5 to Box 2. Put the letter into Box 2. Remove the painting from Box 5. Move the disk from Box 1 to Box 0. Remove the disk from Box 0. Remove the boot and the cigarette from Box 6. Remove the letter and the wheel from Box 2. Remove the block from Box 3. Remove the bus from Box 4. Put the ice into Box 4. Remove the shirt from Box 3. Put the wheel into Box 2.", "sample_id": 1742, "numops": 2, "final_states": {"Box 0": ["nothing"], "Box 1": ["the fig", "the drink"], "Box 2": ["the crown", "the wheel"], "Box 3": ["nothing"], "Box 4": ["the rose", "the key", "the ice"], "Box 5": ["nothing"], "Box 6": ["nothing"]}}
{"sentence": "Box 0 contains the boot and the key and the pipe, Box 1 contains the branch and the drug and the meat, Box 2 contains the fig and the radio and the tissue, Box 3 contains the machine and the painting and the watch, Box 4 contains the crown and the plate and the pot, Box 5 contains the bag and the cross and the disk, Box 6 contains the leaf and the letter and the shell. Remove the watch from Box 3. Remove the pot from Box 4. Remove the meat from Box 1. Put the bell into Box 4. Put the sheet into Box 3. Remove the drug from Box 1. Remove the boot and the pipe from Box 0. Move the fig from Box 2 to Box 1.", "sample_id": 1745, "numops": 1, "final_states": {"Box 0": ["the key"], "Box 1": ["the fig", "the branch"], "Box 2": ["the radio", "the tissue"], "Box 3": ["the sheet", "the machine", "the painting"], "Box 4": ["the plate", "the bell", "the crown", "the leaf"], "Box 5": ["the cross", "the bag", "the disk"], "Box 6": ["the shell", "the letter", "the leaf"]}}
{"sentence": "Box 0 contains the creature and the tissue, Box 1 contains the fish, Box 2 contains the drink and the radio, Box 3 contains the bag and the cup and the plant, Box 4 contains the map and the painting and the tape, Box 5 contains the glass and the mirror and the phone, Box 6 contains the ball and the brick and the jacket. Remove the bag and the cup from Box 3. Remove the brick and the jacket from Box 6. Move the fish from Box 1 to Box 2.", "sample_id": 1750, "numops": 0, "final_states": {"Box 0": ["nothing", "the creature", "the tissue", "the shirt"], "Box 1": ["nothing", "the bill"], "Box 2": ["the radio", "the fish", "the drink"], "Box 3": ["the creature", "the shirt", "the plant", "nothing", "the tissue"], "Box 4": ["the map", "the painting", "the tape"], "Box 5": ["the mirror", "the glass", "the phone"], "Box 6": ["nothing", "the ball"]}}
{"sentence": "Box 0 contains the apple and the fig and the ice, Box 1 contains the branch and the creature and the egg, Box 2 contains the bone and the watch, Box 3 contains the file and the television, Box 4 contains the crown, Box 5 contains nothing, Box 6 contains the engine and the phone. Remove the watch from Box 2. Remove the file from Box 3. Move the engine and the phone from Box 6 to Box 5. Move the crown from Box 4 to Box 5. Remove the apple and the fig from Box 0. Remove the ice from Box 0.", "sample_id": 1753, "numops": 2, "final_states": {"Box 0": ["nothing"], "Box 1": ["the creature", "the egg", "the branch"], "Box 2": ["the bone"], "Box 3": ["the television"], "Box 4": ["nothing"], "Box 5": ["the phone", "the engine", "the crown"], "Box 6": ["nothing"]}}
{"sentence": "Box 0 contains the document and the engine, Box 1 contains the plant and the tape and the tissue, Box 2 contains nothing, Box 3 contains the bone, Box 4 contains the card, Box 5 contains nothing, Box 6 contains nothing. Remove the bone from Box 3. Remove the document and the engine from Box 0. Put the bomb into Box 3. Remove the bomb from Box 3. Put the cheese and the milk and the train into Box 0. Put the sheet into Box 3. Move the card from Box 4 to Box 5. Remove the milk from Box 0. Remove the sheet from Box 3. Put the clock and the engine into Box 4.", "sample_id": 1755, "numops": 3, "final_states": {"Box 0": ["the train", "the cheese"], "Box 1": ["the plant", "the tissue", "the tape"], "Box 2": ["nothing"], "Box 3": ["nothing"], "Box 4": ["the clock", "the engine"], "Box 5": ["the card"], "Box 6": ["nothing"]}}
{"sentence": "Box 0 contains the flower and the magazine, Box 1 contains the leaf and the shell, Box 2 contains the apple and the glass and the tea, Box 3 contains the drug, Box 4 contains the bill and the clock and the tissue, Box 5 contains the knife and the phone and the rose, Box 6 contains the cigarette and the sheet and the shoe. Remove the magazine from Box 0. Remove the tea from Box 2. Remove the tissue from Box 4. Remove the knife and the rose from Box 5. Remove the cigarette and the sheet and the shoe from Box 6. Move the shell from Box 1 to Box 3. Put the boat into Box 6. Move the drug from Box 3 to Box 5. Remove the glass from Box 2. Put the letter and the map into Box 6. Remove the flower from Box 0.", "sample_id": 1760, "numops": 2, "final_states": {"Box 0": ["nothing"], "Box 1": ["the leaf"], "Box 2": ["the apple"], "Box 3": ["the shell"], "Box 4": ["the clock", "the bill"], "Box 5": ["the phone", "the drug"], "Box 6": ["the map", "the boat", "the letter"]}}
{"sentence": "Box 0 contains the painting, Box 1 contains the camera, Box 2 contains nothing, Box 3 contains the newspaper and the television and the train, Box 4 contains the coffee, Box 5 contains nothing, Box 6 contains the dish and the ice and the phone. Remove the painting from Box 0. Put the creature into Box 2. Put the apple into Box 2. Remove the apple and the creature from Box 2. Move the newspaper from Box 3 to Box 2. Remove the train from Box 3. Move the phone from Box 6 to Box 5. Move the ice from Box 6 to Box 3. Move the phone from Box 5 to Box 1. Remove the newspaper from Box 2. Put the file into Box 3.", "sample_id": 1763, "numops": 1, "final_states": {"Box 0": ["nothing"], "Box 1": ["the camera", "the phone"], "Box 2": ["nothing"], "Box 3": ["the file", "the television", "the ice"], "Box 4": ["the coffee"], "Box 5": ["nothing"], "Box 6": ["the dish"]}}
{"sentence": "Box 0 contains nothing, Box 1 contains the card and the cigarette and the painting, Box 2 contains the cup and the knife, Box 3 contains the hat and the mirror, Box 4 contains nothing, Box 5 contains the dish and the gift and the watch, Box 6 contains the cheese. Remove the card from Box 1. Move the dish and the watch from Box 5 to Box 6. Remove the mirror from Box 3. Remove the cigarette from Box 1. Remove the gift from Box 5. Remove the hat from Box 3. Put the string into Box 1. Move the cheese from Box 6 to Box 1. Put the seed into Box 3. Move the seed from Box 3 to Box 6. Remove the cup from Box 2.", "sample_id": 1780, "numops": 0, "final_states": {"Box 0": ["nothing"], "Box 1": ["the painting", "the cheese", "the string"], "Box 2": ["the knife"], "Box 3": ["nothing"], "Box 4": ["nothing"], "Box 5": ["nothing"], "Box 6": ["the dish", "the watch", "the seed"]}}
{"sentence": "Box 0 contains the bowl and the drug, Box 1 contains the crown and the leaf and the newspaper, Box 2 contains the dish and the painting, Box 3 contains the watch, Box 4 contains the boot and the document and the map, Box 5 contains the bill and the seed and the wire, Box 6 contains the cigarette and the fan. Remove the crown and the leaf and the newspaper from Box 1. Move the painting from Box 2 to Box 3. Move the bill from Box 5 to Box 1. Remove the boot and the document from Box 4. Put the newspaper into Box 6. Put the bomb and the brain into Box 4. Put the rose into Box 1. Remove the bomb and the brain from Box 4. Move the cigarette and the newspaper from Box 6 to Box 4. Remove the wire from Box 5. Remove the newspaper from Box 4.", "sample_id": 1790, "numops": 0, "final_states": {"Box 0": ["the bowl", "the drug"], "Box 1": ["the rose", "the bill"], "Box 2": ["the dish"], "Box 3": ["the painting", "the watch"], "Box 4": ["the map", "the cigarette"], "Box 5": ["the seed"], "Box 6": ["the fan"]}}
{"sentence": "Box 0 contains the apple and the paper and the rock, Box 1 contains the block and the plate and the wire, Box 2 contains the bus and the note and the shirt, Box 3 contains the boot and the meat, Box 4 contains the map, Box 5 contains the bill and the card and the flower, Box 6 contains the mirror and the ticket and the watch. Remove the block and the wire from Box 1.", "sample_id": 1792, "numops": 0, "final_states": {"Box 0": ["the paper", "the apple", "the rock"], "Box 1": ["the plate"], "Box 2": ["the bus", "the note", "the shirt"], "Box 3": ["the boot", "the meat"], "Box 4": ["the map"], "Box 5": ["the card", "the bill", "the flower"], "Box 6": ["the mirror", "the ticket", "the watch"]}}
{"sentence": "Box 0 contains the boat and the medicine, Box 1 contains nothing, Box 2 contains the computer and the crown and the tape, Box 3 contains the egg and the string, Box 4 contains the branch and the drug and the radio, Box 5 contains the rock, Box 6 contains the beer and the letter. Move the rock from Box 5 to Box 3. Move the drug from Box 4 to Box 1. Remove the letter from Box 6. Move the medicine from Box 0 to Box 1. Move the branch and the radio from Box 4 to Box 0. Move the crown from Box 2 to Box 4. Remove the drug and the medicine from Box 1. Remove the crown from Box 4. Move the radio from Box 0 to Box 4. Put the ticket into Box 2.", "sample_id": 1794, "numops": 3, "final_states": {"Box 0": ["the boat", "the branch"], "Box 1": ["nothing", "the radio"], "Box 2": ["the ticket", "the tape", "the computer"], "Box 3": ["the egg", "the rock", "the string"], "Box 4": ["nothing", "the radio"], "Box 5": ["nothing"], "Box 6": ["the beer", "nothing"]}}
{"sentence": "Box 0 contains the beer and the guitar and the mirror, Box 1 contains nothing, Box 2 contains the cheese and the pipe and the sheet, Box 3 contains the coat and the knife, Box 4 contains the cream and the fan and the fish, Box 5 contains nothing, Box 6 contains the disk and the tissue. Remove the coat and the knife from Box 3. Move the fish from Box 4 to Box 6.", "sample_id": 1796, "numops": 0, "final_states": {"Box 0": ["the mirror", "the beer", "the guitar"], "Box 1": ["nothing"], "Box 2": ["the sheet", "the pipe", "the cheese"], "Box 3": ["nothing"], "Box 4": ["the fan", "the cream"], "Box 5": ["nothing"], "Box 6": ["the fish", "the disk", "the tissue"]}}
{"sentence": "Box 0 contains the ice and the plant, Box 1 contains the cream and the meat and the pot, Box 2 contains the cigarette and the crown, Box 3 contains the phone and the shoe, Box 4 contains the file and the map, Box 5 contains nothing, Box 6 contains the car. Remove the car from Box 6. Remove the plant from Box 0. Move the ice from Box 0 to Box 4. Move the crown from Box 2 to Box 0. Move the cigarette from Box 2 to Box 0. Put the beer into Box 6. Remove the phone from Box 3. Put the pipe into Box 0. Put the bread into Box 5. Remove the ice from Box 4.", "sample_id": 1804, "numops": 5, "final_states": {"Box 0": ["the pipe", "the crown", "the cigarette"], "Box 1": ["the cream", "the meat", "the pot"], "Box 2": ["nothing"], "Box 3": ["the shoe"], "Box 4": ["the file", "the map"], "Box 5": ["the bread"], "Box 6": ["the beer"]}}
{"sentence": "Box 0 contains the cash and the machine, Box 1 contains the cheese and the document and the drink, Box 2 contains nothing, Box 3 contains the plane, Box 4 contains the seed and the sheet and the string, Box 5 contains the note, Box 6 contains the rock. Put the fig into Box 2. Move the note from Box 5 to Box 2. Remove the seed and the sheet from Box 4. Move the rock from Box 6 to Box 0. Move the rock from Box 0 to Box 4. Remove the fig from Box 2. Put the magazine into Box 2. Remove the magazine and the note from Box 2. Put the coat into Box 2.", "sample_id": 1806, "numops": 2, "final_states": {"Box 0": ["the cash", "the machine"], "Box 1": ["the document", "the cheese", "the drink"], "Box 2": ["the coat"], "Box 3": ["the plane"], "Box 4": ["the rock", "the tea", "the string"], "Box 5": ["the cheese", "the document", "nothing"], "Box 6": ["nothing"]}}
{"sentence": "Box 0 contains the cup and the television and the tissue, Box 1 contains the shoe, Box 2 contains the cigarette and the seed and the tie, Box 3 contains the guitar and the key and the ticket, Box 4 contains the drug and the mirror, Box 5 contains the watch, Box 6 contains the glass. Remove the key from Box 3. Move the mirror from Box 4 to Box 5. Move the ticket from Box 3 to Box 4. Move the watch from Box 5 to Box 4. Remove the shoe from Box 1. Move the guitar from Box 3 to Box 5.", "sample_id": 1807, "numops": 0, "final_states": {"Box 0": ["the television", "the cup", "the tissue"], "Box 1": ["nothing", "the drug"], "Box 2": ["the cigarette", "the tie", "the seed"], "Box 3": ["nothing"], "Box 4": ["the drug", "the ticket", "the watch"], "Box 5": ["the mirror", "the guitar"], "Box 6": ["the glass", "nothing"]}}
{"sentence": "Box 0 contains the bread and the guitar and the pot, Box 1 contains the cream and the disk, Box 2 contains the bag and the shell, Box 3 contains the clock and the stone, Box 4 contains the creature and the milk, Box 5 contains the car and the cigarette and the gift, Box 6 contains the cross. Remove the cross from Box 6. Remove the shell from Box 2. Move the cream from Box 1 to Box 2. Remove the clock from Box 3. Remove the bag from Box 2. Move the guitar and the pot from Box 0 to Box 3. Put the brain and the computer into Box 2. Remove the disk from Box 1.", "sample_id": 1814, "numops": 1, "final_states": {"Box 0": ["the bread"], "Box 1": ["nothing"], "Box 2": ["the cream", "the computer", "the brain"], "Box 3": ["the pot", "the stone", "the guitar"], "Box 4": ["the creature", "the milk"], "Box 5": ["the gift", "the cigarette", "the car"], "Box 6": ["nothing"]}}
{"sentence": "Box 0 contains the meat and the tea, Box 1 contains the bottle and the computer and the disk, Box 2 contains the file, Box 3 contains the boot and the drug and the jacket, Box 4 contains the cross, Box 5 contains the book and the cigarette and the fig, Box 6 contains the car and the watch. Move the cross from Box 4 to Box 0. Remove the bottle from Box 1.", "sample_id": 1817, "numops": 1, "final_states": {"Box 0": ["the tea", "the meat", "the cross"], "Box 1": ["the computer", "the disk"], "Box 2": ["the file"], "Box 3": ["the drug", "the boot", "the jacket"], "Box 4": ["nothing"], "Box 5": ["the fig", "the cigarette", "the book"], "Box 6": ["the car", "the watch"]}}
{"sentence": "Box 0 contains the card and the hat, Box 1 contains the fish, Box 2 contains the bomb, Box 3 contains the branch and the car and the mirror, Box 4 contains nothing, Box 5 contains the creature and the watch, Box 6 contains the flower and the ice and the shoe. Move the ice and the shoe from Box 6 to Box 4. Remove the fish from Box 1. Move the shoe from Box 4 to Box 6. Remove the bomb from Box 2. Remove the card from Box 0. Move the flower and the shoe from Box 6 to Box 2.", "sample_id": 1820, "numops": 1, "final_states": {"Box 0": ["the hat"], "Box 1": ["nothing"], "Box 2": ["the flower", "the shoe"], "Box 3": ["the mirror", "the car", "the branch"], "Box 4": ["the ice"], "Box 5": ["the creature", "the watch"], "Box 6": ["nothing"]}}
{"sentence": "Box 0 contains the string, Box 1 contains the bus and the flower and the leaf, Box 2 contains nothing, Box 3 contains the bell, Box 4 contains the camera and the picture, Box 5 contains the ball and the book and the drink, Box 6 contains nothing. Remove the ball from Box 5. Remove the string from Box 0. Put the ticket into Box 0. Put the dress into Box 5. Remove the book and the dress and the drink from Box 5. Move the bus from Box 1 to Box 0. Put the jacket into Box 2. Put the meat into Box 0. Move the meat from Box 0 to Box 6. Move the flower and the leaf from Box 1 to Box 3. Remove the ticket from Box 0.", "sample_id": 1828, "numops": 6, "final_states": {"Box 0": ["the bus"], "Box 1": ["nothing"], "Box 2": ["the camera", "the jacket"], "Box 3": ["the bell", "the flower", "the leaf"], "Box 4": ["the camera", "the picture"], "Box 5": ["nothing"], "Box 6": ["the meat"]}}
{"sentence": "Box 0 contains nothing, Box 1 contains the boat and the jacket, Box 2 contains the apple, Box 3 contains nothing, Box 4 contains the bottle and the pot, Box 5 contains the bell, Box 6 contains the ball and the picture and the shoe. Move the bell from Box 5 to Box 2. Move the bottle and the pot from Box 4 to Box 3. Put the dress and the meat and the mirror into Box 4. Remove the apple and the bell from Box 2. Put the string into Box 5. Put the pipe and the plate into Box 2. Move the jacket from Box 1 to Box 3. Move the bottle from Box 3 to Box 1.", "sample_id": 1838, "numops": 0, "final_states": {"Box 0": ["nothing"], "Box 1": ["the bottle", "the boat"], "Box 2": ["the plate", "the pipe"], "Box 3": ["the pot", "the jacket"], "Box 4": ["the mirror", "nothing", "the meat", "the dress"], "Box 5": ["nothing", "the string"], "Box 6": ["the picture", "the shoe", "the ball"]}}
{"sentence": "Box 0 contains the guitar and the picture, Box 1 contains nothing, Box 2 contains the branch and the flower and the painting, Box 3 contains the seed, Box 4 contains the boot and the ring, Box 5 contains the cake and the document, Box 6 contains the dress. Move the flower from Box 2 to Box 4. Remove the dress from Box 6. Move the seed from Box 3 to Box 2. Move the boot from Box 4 to Box 6. Move the ring from Box 4 to Box 1. Remove the flower from Box 4. Remove the ring from Box 1. Move the guitar and the picture from Box 0 to Box 3. Remove the picture from Box 3. Put the bell and the tie into Box 0. Remove the boot from Box 6.", "sample_id": 1840, "numops": 2, "final_states": {"Box 0": ["the bell", "the tie"], "Box 1": ["nothing"], "Box 2": ["the painting", "the branch", "the seed"], "Box 3": ["the guitar"], "Box 4": ["nothing"], "Box 5": ["the document", "the cake"], "Box 6": ["nothing"]}}
{"sentence": "Box 0 contains nothing, Box 1 contains the coat, Box 2 contains the cheese, Box 3 contains nothing, Box 4 contains the knife and the mirror and the plate, Box 5 contains the painting, Box 6 contains the block and the rose. Remove the coat from Box 1. Remove the knife and the mirror and the plate from Box 4. Move the painting from Box 5 to Box 3. Put the guitar and the jacket and the letter into Box 0. Move the letter from Box 0 to Box 1. Move the rose from Box 6 to Box 5. Remove the letter from Box 1. Move the block from Box 6 to Box 2. Put the cup into Box 0. Remove the rose from Box 5.", "sample_id": 1841, "numops": 3, "final_states": {"Box 0": ["the guitar", "the cup", "the jacket"], "Box 1": ["nothing"], "Box 2": ["the cheese", "the block"], "Box 3": ["the painting"], "Box 4": ["nothing"], "Box 5": ["nothing"], "Box 6": ["nothing"]}}
{"sentence": "Box 0 contains the fig, Box 1 contains the cream and the paper, Box 2 contains the bag and the file, Box 3 contains the car and the ring and the ticket, Box 4 contains the fish and the pot, Box 5 contains the coat and the coffee, Box 6 contains the boot and the knife. Put the egg into Box 0. Remove the fig from Box 0. Move the coat from Box 5 to Box 6. Move the coffee from Box 5 to Box 0. Remove the paper from Box 1. Put the bottle and the jacket into Box 1. Remove the cream from Box 1. Move the coat from Box 6 to Box 1. Move the bag from Box 2 to Box 4. Remove the car and the ring and the ticket from Box 3. Remove the bag from Box 4. Put the creature into Box 3.", "sample_id": 1844, "numops": 3, "final_states": {"Box 0": ["the coffee", "the egg"], "Box 1": ["the bottle", "the coat", "the jacket"], "Box 2": ["the file"], "Box 3": ["the creature"], "Box 4": ["the fish", "the pot"], "Box 5": ["nothing"], "Box 6": ["the knife", "the boot"]}}
{"sentence": "Box 0 contains the bell and the jacket, Box 1 contains the newspaper and the sheet, Box 2 contains the flower and the milk, Box 3 contains the bread and the machine, Box 4 contains the drug and the tape, Box 5 contains the apple and the meat, Box 6 contains nothing. Remove the bread from Box 3. Remove the flower and the milk from Box 2. Move the drug and the tape from Box 4 to Box 3. Remove the sheet from Box 1. Move the newspaper from Box 1 to Box 0. Remove the meat from Box 5. Put the ice into Box 5. Put the chemical and the disk and the picture into Box 2. Put the letter into Box 5. Put the tea into Box 1. Put the cream and the pipe into Box 1. Remove the cream from Box 1.", "sample_id": 1850, "numops": 1, "final_states": {"Box 0": ["the bell", "the newspaper", "the jacket"], "Box 1": ["the pipe", "the tea"], "Box 2": ["the chemical", "the picture", "the disk"], "Box 3": ["the drug", "the machine", "the tape"], "Box 4": ["nothing"], "Box 5": ["the apple", "the ice", "the letter"], "Box 6": ["nothing"]}}
{"sentence": "Box 0 contains nothing, Box 1 contains the guitar and the knife, Box 2 contains the cross, Box 3 contains the branch, Box 4 contains nothing, Box 5 contains the apple and the bill and the magazine, Box 6 contains the bone and the leaf and the tape. Remove the knife from Box 1. Move the cross from Box 2 to Box 4. Move the cross from Box 4 to Box 3. Move the cross from Box 3 to Box 4. Remove the branch from Box 3.", "sample_id": 1855, "numops": 0, "final_states": {"Box 0": ["nothing"], "Box 1": ["the guitar"], "Box 2": ["nothing"], "Box 3": ["nothing"], "Box 4": ["the cross"], "Box 5": ["the apple", "the magazine", "the bill"], "Box 6": ["the bone", "the tape", "the leaf"]}}
{"sentence": "Box 0 contains the glass and the television, Box 1 contains the guitar and the knife, Box 2 contains the jacket, Box 3 contains the drug and the medicine, Box 4 contains the bag and the dish and the flower, Box 5 contains the note, Box 6 contains nothing. Move the drug and the medicine from Box 3 to Box 6. Put the leaf into Box 2. Move the knife from Box 1 to Box 3. Remove the television from Box 0. Move the leaf from Box 2 to Box 1. Move the dish from Box 4 to Box 3. Move the note from Box 5 to Box 0. Remove the glass and the note from Box 0. Put the plane into Box 3. Move the guitar from Box 1 to Box 5.", "sample_id": 1863, "numops": 3, "final_states": {"Box 0": ["nothing"], "Box 1": ["the leaf"], "Box 2": ["the jacket"], "Box 3": ["the knife", "the dish", "the plane"], "Box 4": ["the flower", "the bag"], "Box 5": ["the guitar"], "Box 6": ["the medicine", "the drug"]}}
{"sentence": "Box 0 contains the bowl and the glass and the ring, Box 1 contains the computer and the disk, Box 2 contains the ice, Box 3 contains the coat and the file and the painting, Box 4 contains the bomb, Box 5 contains the bus and the magazine and the meat, Box 6 contains the cigarette and the seed. Remove the bowl and the glass and the ring from Box 0. Move the disk from Box 1 to Box 0.", "sample_id": 1867, "numops": 2, "final_states": {"Box 0": ["nothing", "the disk"], "Box 1": ["the magazine", "the engine", "the computer"], "Box 2": ["the shell", "the ice", "the machine", "the disk"], "Box 3": ["the file", "the painting", "the coat", "the coffee", "the fish"], "Box 4": ["the bomb", "the ice", "the apple"], "Box 5": ["the magazine", "the meat", "the bus"], "Box 6": ["the cigarette", "the seed"]}}
{"sentence": "Box 0 contains the file, Box 1 contains the bell and the newspaper and the paper, Box 2 contains the document and the fan, Box 3 contains the beer and the train, Box 4 contains the engine and the flower and the game, Box 5 contains nothing, Box 6 contains the drink. Remove the file from Box 0. Remove the engine from Box 4. Put the bread into Box 4. Remove the bread from Box 4.", "sample_id": 1870, "numops": 1, "final_states": {"Box 0": ["the fan", "nothing"], "Box 1": ["the paper", "the bell", "the newspaper", "nothing"], "Box 2": ["the fan", "the document", "nothing"], "Box 3": ["the beer", "the train"], "Box 4": ["the flower", "the game", "nothing"], "Box 5": ["nothing", "the drink"], "Box 6": ["the game", "nothing", "the bill", "the drink"]}}
{"sentence": "Box 0 contains the beer and the gift, Box 1 contains the boat and the crown and the jacket, Box 2 contains the ice and the meat, Box 3 contains the bread, Box 4 contains the dress and the tea and the ticket, Box 5 contains the cup and the milk, Box 6 contains the drug and the magazine and the pot. Remove the magazine and the pot from Box 6. Move the bread from Box 3 to Box 5. Remove the dress from Box 4. Put the plate into Box 0. Remove the ice from Box 2. Remove the meat from Box 2. Move the ticket from Box 4 to Box 2. Put the chemical and the seed into Box 3. Remove the cup from Box 5. Put the bill into Box 6.", "sample_id": 1881, "numops": 1, "final_states": {"Box 0": ["the plate", "the gift", "the beer"], "Box 1": ["the crown", "the jacket", "the boat"], "Box 2": ["the ticket"], "Box 3": ["the chemical", "the seed"], "Box 4": ["the tea"], "Box 5": ["the bread", "the milk"], "Box 6": ["the drug", "the bill"]}}
{"sentence": "Box 0 contains the mirror and the shirt and the string, Box 1 contains nothing, Box 2 contains the camera and the drink, Box 3 contains the bottle and the shoe and the television, Box 4 contains the cash and the newspaper, Box 5 contains the phone and the tissue, Box 6 contains the boat and the cheese and the letter. Remove the boat and the cheese from Box 6. Put the fish into Box 2. Remove the cash and the newspaper from Box 4. Remove the phone from Box 5. Move the drink and the fish from Box 2 to Box 4. Put the bowl and the tea into Box 5. Move the camera from Box 2 to Box 4. Remove the television from Box 3. Remove the mirror and the shirt from Box 0. Remove the camera and the drink from Box 4.", "sample_id": 1882, "numops": 1, "final_states": {"Box 0": ["the string"], "Box 1": ["nothing"], "Box 2": ["nothing"], "Box 3": ["the bottle", "the shoe"], "Box 4": ["the fish"], "Box 5": ["the bowl", "the tea", "the tissue"], "Box 6": ["the letter"]}}
{"sentence": "Box 0 contains the bag and the plant, Box 1 contains the car and the dish and the game, Box 2 contains the rose, Box 3 contains the branch and the stone and the television, Box 4 contains the meat, Box 5 contains the dress and the gift and the watch, Box 6 contains the hat and the shirt. Move the dish from Box 1 to Box 0. Move the meat from Box 4 to Box 2. Remove the television from Box 3. Move the gift from Box 5 to Box 3. Move the dress from Box 5 to Box 6. Move the branch and the gift from Box 3 to Box 5.", "sample_id": 1883, "numops": 1, "final_states": {"Box 0": ["the dish", "the bag", "the plant"], "Box 1": ["the game", "the car"], "Box 2": ["the rose", "the meat"], "Box 3": ["the stone"], "Box 4": ["nothing"], "Box 5": ["the gift", "the branch", "the watch"], "Box 6": ["the shirt", "the hat", "the dress"]}}
{"sentence": "Box 0 contains the ticket, Box 1 contains the cup and the watch, Box 2 contains the fish and the leaf and the newspaper, Box 3 contains the coffee, Box 4 contains the camera and the glass and the milk, Box 5 contains the chemical and the letter, Box 6 contains the bill and the brain and the pipe. Put the boot into Box 1. Remove the bill and the brain and the pipe from Box 6. Remove the boot from Box 1. Move the coffee from Box 3 to Box 6. Move the newspaper from Box 2 to Box 0. Remove the chemical and the letter from Box 5.", "sample_id": 1885, "numops": 1, "final_states": {"Box 0": ["the newspaper", "the ticket"], "Box 1": ["the cup", "the watch"], "Box 2": ["the fish", "the leaf"], "Box 3": ["nothing"], "Box 4": ["the camera", "the glass", "the milk"], "Box 5": ["nothing"], "Box 6": ["the coffee"]}}
{"sentence": "Box 0 contains nothing, Box 1 contains the document and the fan and the fig, Box 2 contains the clock and the magazine and the newspaper, Box 3 contains the apple and the cash and the tape, Box 4 contains the bag and the knife and the plane, Box 5 contains the branch and the ring, Box 6 contains the cup. Move the branch and the ring from Box 5 to Box 0. Remove the clock and the newspaper from Box 2. Put the cross into Box 6. Remove the magazine from Box 2. Put the rose into Box 6. Remove the cross and the cup from Box 6. Remove the rose from Box 6. Move the ring from Box 0 to Box 5. Put the meat into Box 2. Remove the bag and the knife and the plane from Box 4. Remove the apple and the cash and the tape from Box 3. Put the plane into Box 4.", "sample_id": 1887, "numops": 2, "final_states": {"Box 0": ["the branch"], "Box 1": ["the fan", "the fig", "the document"], "Box 2": ["the meat"], "Box 3": ["nothing"], "Box 4": ["the plane"], "Box 5": ["the ring"], "Box 6": ["nothing"]}}
{"sentence": "Box 0 contains the car and the jacket and the suit, Box 1 contains the boot and the watch, Box 2 contains the chemical and the painting, Box 3 contains the brain and the milk, Box 4 contains the fan, Box 5 contains nothing, Box 6 contains the fish and the ring and the tape. Put the bag into Box 5. Remove the fan from Box 4. Move the bag from Box 5 to Box 2. Put the crown into Box 1. Put the bus into Box 5. Remove the brain and the milk from Box 3. Move the watch from Box 1 to Box 5. Move the crown from Box 1 to Box 5. Remove the car and the jacket from Box 0. Remove the boot from Box 1. Move the bag and the chemical and the painting from Box 2 to Box 4.", "sample_id": 1890, "numops": 1, "final_states": {"Box 0": ["the suit"], "Box 1": ["nothing"], "Box 2": ["nothing"], "Box 3": ["nothing"], "Box 4": ["the painting", "the chemical", "the bag"], "Box 5": ["the bus", "the crown", "the watch"], "Box 6": ["the fish", "the ring", "the tape"]}}
{"sentence": "Box 0 contains the computer and the plate, Box 1 contains the tissue, Box 2 contains the cash and the pipe, Box 3 contains the beer, Box 4 contains nothing, Box 5 contains the meat, Box 6 contains the knife and the stone and the tape. Remove the tape from Box 6. Put the rock and the wheel into Box 5. Put the coat into Box 2. Remove the knife from Box 6. Remove the tissue from Box 1. Put the suit into Box 0. Move the beer from Box 3 to Box 6. Put the milk into Box 6. Remove the coat from Box 2. Put the leaf and the picture into Box 4. Remove the beer and the stone from Box 6.", "sample_id": 1892, "numops": 1, "final_states": {"Box 0": ["the plate", "the computer", "the suit"], "Box 1": ["nothing"], "Box 2": ["the cash", "the pipe"], "Box 3": ["nothing"], "Box 4": ["the picture", "the leaf"], "Box 5": ["the rock", "the meat", "the wheel"], "Box 6": ["the milk"]}}
{"sentence": "Box 0 contains the computer and the machine, Box 1 contains nothing, Box 2 contains nothing, Box 3 contains the suit, Box 4 contains the apple and the clock and the leaf, Box 5 contains the car and the cross, Box 6 contains the plate. Move the plate from Box 6 to Box 2. Put the stone into Box 3. Move the clock and the leaf from Box 4 to Box 2.", "sample_id": 1906, "numops": 0, "final_states": {"Box 0": ["the computer", "the machine"], "Box 1": ["nothing"], "Box 2": ["the plate", "the clock", "the stone", "the leaf"], "Box 3": ["the stone", "the suit"], "Box 4": ["the apple", "the document"], "Box 5": ["the car", "the cross"], "Box 6": ["nothing", "the branch"]}}
{"sentence": "Box 0 contains the brain and the seed, Box 1 contains the jacket, Box 2 contains the bomb and the computer and the shoe, Box 3 contains the medicine and the tea, Box 4 contains the ball and the disk, Box 5 contains the bus and the glass and the watch, Box 6 contains the pot.", "sample_id": 1908, "numops": 0, "final_states": {"Box 0": ["the brain", "the seed"], "Box 1": ["the jacket"], "Box 2": ["the computer", "the bomb", "the shoe"], "Box 3": ["the medicine", "the tea"], "Box 4": ["the disk", "the ball"], "Box 5": ["the glass", "the bus", "the watch"], "Box 6": ["the pot"]}}
{"sentence": "Box 0 contains the beer and the cheese and the flower, Box 1 contains the gift and the radio and the tape, Box 2 contains the string and the tie, Box 3 contains the picture, Box 4 contains the wire, Box 5 contains the creature, Box 6 contains the brain and the camera and the rock. Move the tape from Box 1 to Box 3. Remove the string from Box 2. Remove the picture from Box 3. Move the rock from Box 6 to Box 5. Move the tie from Box 2 to Box 5.", "sample_id": 1914, "numops": 0, "final_states": {"Box 0": ["the flower", "the beer", "the cheese"], "Box 1": ["the gift", "the radio"], "Box 2": ["nothing"], "Box 3": ["the tape"], "Box 4": ["the wire"], "Box 5": ["the creature", "the rock", "the tie"], "Box 6": ["the camera", "the brain"]}}
{"sentence": "Box 0 contains nothing, Box 1 contains the rock, Box 2 contains the cup and the flower and the knife, Box 3 contains the cake and the leaf, Box 4 contains the cream and the paper, Box 5 contains the coffee, Box 6 contains nothing. Remove the leaf from Box 3. Remove the cake from Box 3.", "sample_id": 1915, "numops": 0, "final_states": {"Box 0": ["nothing"], "Box 1": ["nothing", "the rock"], "Box 2": ["the flower", "the knife", "the cup"], "Box 3": ["nothing"], "Box 4": ["the card", "the cream", "the paper"], "Box 5": ["the coffee"], "Box 6": ["nothing"]}}
{"sentence": "Box 0 contains the car and the engine and the jacket, Box 1 contains nothing, Box 2 contains the cake, Box 3 contains the bowl and the fig and the sheet, Box 4 contains the computer and the creature and the string, Box 5 contains nothing, Box 6 contains nothing. Move the creature and the string from Box 4 to Box 1. Move the engine from Box 0 to Box 6. Move the bowl and the fig from Box 3 to Box 6. Remove the cake from Box 2. Move the creature from Box 1 to Box 2. Move the sheet from Box 3 to Box 4.", "sample_id": 1918, "numops": 1, "final_states": {"Box 0": ["the car", "the jacket"], "Box 1": ["the string"], "Box 2": ["the creature"], "Box 3": ["nothing"], "Box 4": ["the sheet", "the computer"], "Box 5": ["nothing"], "Box 6": ["the fig", "the bowl", "the engine"]}}
{"sentence": "Box 0 contains the chemical and the plate, Box 1 contains the ball, Box 2 contains the brick and the document and the engine, Box 3 contains the milk and the train, Box 4 contains the cake and the newspaper, Box 5 contains the rose, Box 6 contains the fan and the map and the shell. Put the card into Box 0. Move the rose from Box 5 to Box 1. Remove the chemical and the plate from Box 0. Move the map from Box 6 to Box 4. Remove the ball and the rose from Box 1. Put the egg into Box 6. Remove the card from Box 0. Remove the cake and the map from Box 4.", "sample_id": 1921, "numops": 3, "final_states": {"Box 0": ["nothing"], "Box 1": ["nothing"], "Box 2": ["the engine", "the brick", "the document"], "Box 3": ["the magazine", "the milk", "the train"], "Box 4": ["the newspaper"], "Box 5": ["nothing", "the milk"], "Box 6": ["the fan", "the shell", "the egg"]}}
{"sentence": "Box 0 contains the dress and the string and the tea, Box 1 contains nothing, Box 2 contains the coat and the phone, Box 3 contains the drug and the knife, Box 4 contains nothing, Box 5 contains the map and the pipe and the tie, Box 6 contains the picture. Remove the picture from Box 6. Remove the drug from Box 3. Remove the map and the tie from Box 5. Move the pipe from Box 5 to Box 3. Put the bell and the clock into Box 6. Remove the phone from Box 2.", "sample_id": 1925, "numops": 0, "final_states": {"Box 0": ["the string", "the tea", "the dress"], "Box 1": ["nothing"], "Box 2": ["nothing", "the coat"], "Box 3": ["the knife", "the gift", "the pipe", "the brick", "nothing"], "Box 4": ["nothing"], "Box 5": ["nothing"], "Box 6": ["the clock", "the bell"]}}
{"sentence": "Box 0 contains nothing, Box 1 contains the cash and the meat and the painting, Box 2 contains the car, Box 3 contains nothing, Box 4 contains the bowl and the clock and the seed, Box 5 contains nothing, Box 6 contains the engine and the guitar and the leaf. Put the coat and the newspaper into Box 3. Remove the painting from Box 1. Remove the bowl and the seed from Box 4. Put the glass into Box 0. Remove the glass from Box 0. Move the clock from Box 4 to Box 5. Put the train into Box 4. Remove the train from Box 4. Remove the guitar from Box 6. Put the shoe into Box 1. Remove the car from Box 2.", "sample_id": 1932, "numops": 2, "final_states": {"Box 0": ["nothing"], "Box 1": ["the cash", "the meat", "the shoe"], "Box 2": ["nothing"], "Box 3": ["the newspaper", "the coat"], "Box 4": ["nothing"], "Box 5": ["the clock"], "Box 6": ["the engine", "the leaf"]}}
{"sentence": "Box 0 contains the dress and the key, Box 1 contains nothing, Box 2 contains the mirror and the tape and the train, Box 3 contains the block and the car, Box 4 contains the fig and the watch, Box 5 contains the bread and the rock, Box 6 contains the bag and the note and the rose. Remove the watch from Box 4. Move the fig from Box 4 to Box 1. Put the computer into Box 0. Remove the rose from Box 6. Remove the car from Box 3. Put the hat into Box 4. Remove the mirror and the train from Box 2. Move the fig from Box 1 to Box 2. Move the hat from Box 4 to Box 2. Move the fig and the hat and the tape from Box 2 to Box 4.", "sample_id": 1933, "numops": 1, "final_states": {"Box 0": ["the key", "the computer", "the dress"], "Box 1": ["nothing", "the wire"], "Box 2": ["nothing"], "Box 3": ["the block"], "Box 4": ["the fig", "the hat", "the tape"], "Box 5": ["the bread", "the rock"], "Box 6": ["the bag", "the note"]}}
{"sentence": "Box 0 contains nothing, Box 1 contains the dress and the key and the plate, Box 2 contains nothing, Box 3 contains the game and the tie and the train, Box 4 contains the jacket and the shell, Box 5 contains the computer and the crown and the suit, Box 6 contains the disk and the wheel. Put the chemical and the egg into Box 0. Put the shirt into Box 6. Put the pot into Box 4. Put the cash and the meat and the paper into Box 2. Remove the egg from Box 0. Remove the dress from Box 1. Remove the chemical from Box 0. Put the cigarette into Box 0.", "sample_id": 1944, "numops": 4, "final_states": {"Box 0": ["the cigarette"], "Box 1": ["the plate", "the key", "the suit"], "Box 2": ["the meat", "the paper", "the cash"], "Box 3": ["the train", "the game", "the tie"], "Box 4": ["the shell", "the jacket", "the pot"], "Box 5": ["the crown", "the computer", "nothing", "the suit"], "Box 6": ["the shirt", "the wheel", "the disk"]}}
{"sentence": "Box 0 contains the bag and the beer and the file, Box 1 contains nothing, Box 2 contains the camera and the radio, Box 3 contains nothing, Box 4 contains the plane and the shirt and the wire, Box 5 contains the string, Box 6 contains the bottle and the tea. Move the string from Box 5 to Box 6. Move the plane from Box 4 to Box 3. Move the plane from Box 3 to Box 5. Remove the plane from Box 5. Remove the shirt from Box 4. Move the beer from Box 0 to Box 5. Remove the string from Box 6. Remove the camera from Box 2. Put the picture into Box 4. Move the tea from Box 6 to Box 5. Put the gift into Box 6. Remove the radio from Box 2.", "sample_id": 1947, "numops": 1, "final_states": {"Box 0": ["the file", "the bag"], "Box 1": ["nothing"], "Box 2": ["nothing"], "Box 3": ["nothing"], "Box 4": ["the picture", "the wire"], "Box 5": ["the beer", "the tea"], "Box 6": ["the gift", "the bottle"]}}
{"sentence": "Box 0 contains the egg, Box 1 contains the ticket, Box 2 contains the car and the gift and the shoe, Box 3 contains the document and the suit, Box 4 contains the computer and the crown, Box 5 contains the knife and the pot and the shell, Box 6 contains the branch and the machine and the tea. Remove the crown from Box 4. Move the egg from Box 0 to Box 3. Move the machine from Box 6 to Box 0. Remove the car and the shoe from Box 2. Move the document and the suit from Box 3 to Box 2. Remove the ticket from Box 1. Remove the computer from Box 4. Remove the egg from Box 3.", "sample_id": 1951, "numops": 2, "final_states": {"Box 0": ["the machine"], "Box 1": ["nothing"], "Box 2": ["the gift", "the document", "the suit"], "Box 3": ["nothing"], "Box 4": ["nothing"], "Box 5": ["the shell", "the knife", "the pot"], "Box 6": ["the branch", "the tea"]}}
{"sentence": "Box 0 contains the tissue, Box 1 contains the document and the fig and the wheel, Box 2 contains the brick and the camera and the cream, Box 3 contains nothing, Box 4 contains the flower and the glass and the milk, Box 5 contains the boot and the coffee, Box 6 contains the cup and the paper. Remove the document and the fig from Box 1. Remove the milk from Box 4. Remove the cup and the paper from Box 6. Move the wheel from Box 1 to Box 3. Put the engine and the ring into Box 1. Move the tissue from Box 0 to Box 5.", "sample_id": 1960, "numops": 1, "final_states": {"Box 0": ["nothing"], "Box 1": ["the engine", "the ring"], "Box 2": ["the camera", "the cream", "the brick"], "Box 3": ["the wheel"], "Box 4": ["the flower", "the glass"], "Box 5": ["the coffee", "the boot", "the tissue"], "Box 6": ["nothing"]}}
{"sentence": "Box 0 contains the cigarette and the crown, Box 1 contains the medicine and the plate, Box 2 contains the cup and the disk and the note, Box 3 contains the document and the egg, Box 4 contains the bell and the drug, Box 5 contains nothing, Box 6 contains the phone and the rock. Move the egg from Box 3 to Box 4. Move the medicine and the plate from Box 1 to Box 3. Put the bag and the ring and the tissue into Box 1. Remove the ring from Box 1. Remove the cup and the disk from Box 2. Move the note from Box 2 to Box 5. Remove the note from Box 5. Move the rock from Box 6 to Box 5. Move the rock from Box 5 to Box 0.", "sample_id": 1968, "numops": 1, "final_states": {"Box 0": ["the cigarette", "the rock", "the crown"], "Box 1": ["the bag", "the tissue"], "Box 2": ["nothing"], "Box 3": ["the plate", "the document", "the medicine"], "Box 4": ["the egg", "the bell", "the drug"], "Box 5": ["nothing"], "Box 6": ["the phone"]}}
{"sentence": "Box 0 contains the bottle and the document, Box 1 contains the key, Box 2 contains the cake, Box 3 contains the ball and the crown, Box 4 contains the bell and the computer, Box 5 contains the game, Box 6 contains nothing. Move the game from Box 5 to Box 6. Put the fan into Box 4. Remove the cake from Box 2. Move the bell and the computer from Box 4 to Box 1. Move the ball from Box 3 to Box 4. Put the shell into Box 2. Put the chemical into Box 3. Move the game from Box 6 to Box 4. Remove the bottle and the document from Box 0. Remove the game from Box 4.", "sample_id": 1970, "numops": 1, "final_states": {"Box 0": ["nothing"], "Box 1": ["the computer", "the bell", "the key"], "Box 2": ["the shell"], "Box 3": ["the chemical", "the crown"], "Box 4": ["the fan", "the ball"], "Box 5": ["nothing"], "Box 6": ["nothing"]}}
{"sentence": "Box 0 contains the cake and the painting, Box 1 contains the knife, Box 2 contains the bus and the cheese and the seed, Box 3 contains the letter, Box 4 contains the ticket, Box 5 contains the medicine, Box 6 contains the crown and the phone. Move the painting from Box 0 to Box 1. Move the ticket from Box 4 to Box 3. Remove the phone from Box 6. Remove the crown from Box 6. Put the dish into Box 5. Move the cake from Box 0 to Box 6. Remove the cake from Box 6. Move the knife from Box 1 to Box 5. Move the dish and the medicine from Box 5 to Box 6. Move the knife from Box 5 to Box 4. Put the bread and the flower into Box 0. Move the bus and the seed from Box 2 to Box 4.", "sample_id": 1977, "numops": 3, "final_states": {"Box 0": ["the flower", "the bread"], "Box 1": ["the painting"], "Box 2": ["the cheese"], "Box 3": ["the letter", "the ticket"], "Box 4": ["the knife", "the bus", "the seed"], "Box 5": ["nothing"], "Box 6": ["the dish", "the medicine"]}}
{"sentence": "Box 0 contains nothing, Box 1 contains the plant and the seed, Box 2 contains nothing, Box 3 contains the crown and the newspaper and the television, Box 4 contains nothing, Box 5 contains the bag and the hat and the picture, Box 6 contains the bottle and the document and the pot. Put the branch into Box 2. Remove the plant and the seed from Box 1. Remove the bottle from Box 6.", "sample_id": 1981, "numops": 0, "final_states": {"Box 0": ["the television", "the newspaper", "the crown", "nothing"], "Box 1": ["the hat", "the pot", "nothing"], "Box 2": ["nothing", "the branch"], "Box 3": ["the television", "the newspaper", "the crown", "nothing"], "Box 4": ["nothing"], "Box 5": ["the picture", "the hat", "the bag"], "Box 6": ["the pot", "the document", "nothing", "the sheet"]}}
{"sentence": "Box 0 contains nothing, Box 1 contains the string, Box 2 contains the shirt, Box 3 contains the coffee and the file and the wire, Box 4 contains the cash and the suit and the tape, Box 5 contains the brick and the radio and the tea, Box 6 contains the paper. Remove the cash and the suit and the tape from Box 4. Remove the string from Box 1. Remove the brick and the radio and the tea from Box 5. Put the brick into Box 0. Put the document and the note and the train into Box 5. Remove the shirt from Box 2. Move the coffee and the file from Box 3 to Box 2.", "sample_id": 1987, "numops": 1, "final_states": {"Box 0": ["the brick"], "Box 1": ["nothing"], "Box 2": ["the coffee", "the file"], "Box 3": ["the wire"], "Box 4": ["nothing"], "Box 5": ["the document", "the note", "the train"], "Box 6": ["the paper"]}}
{"sentence": "Box 0 contains the bone and the branch and the wire, Box 1 contains the coat and the radio, Box 2 contains the crown and the milk and the suit, Box 3 contains nothing, Box 4 contains the boot and the hat and the rose, Box 5 contains the computer and the medicine and the rock, Box 6 contains the egg. Remove the computer from Box 5. Move the rose from Box 4 to Box 1. Remove the milk and the suit from Box 2. Put the cake into Box 5.", "sample_id": 1989, "numops": 0, "final_states": {"Box 0": ["the bone", "the wire", "the branch"], "Box 1": ["the rose", "the coat", "the radio"], "Box 2": ["the crown"], "Box 3": ["nothing"], "Box 4": ["the boot", "the hat"], "Box 5": ["the medicine", "the rock", "the cake"], "Box 6": ["the egg"]}}
{"sentence": "Box 0 contains the key and the magazine, Box 1 contains the shell, Box 2 contains the fan and the plate, Box 3 contains the medicine, Box 4 contains the book and the cash and the coffee, Box 5 contains the beer and the game, Box 6 contains the file. Move the beer and the game from Box 5 to Box 6. Move the book and the coffee from Box 4 to Box 3. Remove the plate from Box 2. Remove the cash from Box 4. Remove the shell from Box 1. Move the coffee from Box 3 to Box 2. Put the boot into Box 5. Remove the book from Box 3. Move the boot from Box 5 to Box 4. Remove the magazine from Box 0.", "sample_id": 1990, "numops": 1, "final_states": {"Box 0": ["the key"], "Box 1": ["nothing"], "Box 2": ["the coffee", "the fan"], "Box 3": ["the medicine"], "Box 4": ["the boot"], "Box 5": ["nothing"], "Box 6": ["the file", "the game", "the beer"]}}
{"sentence": "Box 0 contains nothing, Box 1 contains the bowl and the gift and the rose, Box 2 contains the jacket, Box 3 contains the glass and the rock, Box 4 contains nothing, Box 5 contains the meat, Box 6 contains nothing. Put the drug into Box 3. Remove the meat from Box 5.", "sample_id": 1998, "numops": 0, "final_states": {"Box 0": ["nothing"], "Box 1": ["the rose", "the gift", "the bowl"], "Box 2": ["the jacket"], "Box 3": ["the glass", "the drug", "the rock"], "Box 4": ["nothing"], "Box 5": ["nothing"], "Box 6": ["nothing"]}}
{"sentence": "Box 0 contains nothing, Box 1 contains the fan and the fig and the tissue, Box 2 contains the seed, Box 3 contains the cross, Box 4 contains nothing, Box 5 contains the card and the disk, Box 6 contains nothing. Move the fig from Box 1 to Box 0. Put the coat into Box 4. Put the cigarette into Box 0. Remove the coat from Box 4. Move the seed from Box 2 to Box 5. Remove the cross from Box 3. Remove the disk and the seed from Box 5. Move the cigarette from Box 0 to Box 3. Remove the card from Box 5. Put the train into Box 5. Move the fig from Box 0 to Box 2. Move the fan from Box 1 to Box 0.", "sample_id": 2010, "numops": 5, "final_states": {"Box 0": ["the fan"], "Box 1": ["the tissue"], "Box 2": ["the fig"], "Box 3": ["the cigarette"], "Box 4": ["nothing"], "Box 5": ["the train"], "Box 6": ["nothing"]}}
{"sentence": "Box 0 contains nothing, Box 1 contains the bell and the bill and the brain, Box 2 contains the camera, Box 3 contains the crown and the pipe, Box 4 contains the knife and the phone and the plant, Box 5 contains the glass and the key and the television, Box 6 contains the cross and the flower and the jacket. Put the guitar into Box 2.", "sample_id": 2014, "numops": 0, "final_states": {"Box 0": ["nothing"], "Box 1": ["the brain", "the bell", "the bill"], "Box 2": ["the camera", "the guitar"], "Box 3": ["the pipe", "the crown"], "Box 4": ["the knife", "the phone", "the plant"], "Box 5": ["the television", "the glass", "the key"], "Box 6": ["the flower", "the jacket", "the cross"]}}
{"sentence": "Box 0 contains the key and the map and the watch, Box 1 contains the milk and the picture and the plate, Box 2 contains the card and the guitar and the ring, Box 3 contains the letter and the paper, Box 4 contains the bomb and the leaf, Box 5 contains the chemical and the gift and the magazine, Box 6 contains the dress and the train.", "sample_id": 2023, "numops": 0, "final_states": {"Box 0": ["the map", "the key", "the magazine", "the watch"], "Box 1": ["the plate", "the picture", "the milk"], "Box 2": ["the card", "the guitar", "the ring"], "Box 3": ["the plate", "the letter", "the paper"], "Box 4": ["the bomb", "the document", "the leaf"], "Box 5": ["the gift", "the magazine", "the ticket", "the chemical"], "Box 6": ["nothing", "the train", "the dress"]}}
{"sentence": "Box 0 contains the crown, Box 1 contains the cake and the cup and the picture, Box 2 contains the tie, Box 3 contains the computer and the rose and the tissue, Box 4 contains the egg, Box 5 contains the document and the fish, Box 6 contains the plate. Remove the tie from Box 2. Move the rose and the tissue from Box 3 to Box 0. Put the bus and the drink into Box 6. Remove the cake and the cup from Box 1. Remove the crown and the rose from Box 0. Remove the tissue from Box 0. Put the card and the ice into Box 3.", "sample_id": 2026, "numops": 3, "final_states": {"Box 0": ["nothing"], "Box 1": ["the picture"], "Box 2": ["nothing"], "Box 3": ["the card", "the computer", "the ice"], "Box 4": ["the egg"], "Box 5": ["the fish", "the document"], "Box 6": ["the plate", "the bus", "the drink"]}}
{"sentence": "Box 0 contains the ball, Box 1 contains the radio, Box 2 contains the clock and the map and the note, Box 3 contains the coat, Box 4 contains the bottle and the bus and the pipe, Box 5 contains the bag and the phone and the tissue, Box 6 contains the computer and the meat and the shoe. Move the coat from Box 3 to Box 1. Remove the coat and the radio from Box 1. Remove the bus and the pipe from Box 4. Move the map and the note from Box 2 to Box 0. Move the map from Box 0 to Box 1. Remove the note from Box 0. Move the map from Box 1 to Box 2. Remove the bag and the phone and the tissue from Box 5. Put the apple and the flower into Box 0. Remove the ball and the flower from Box 0. Move the meat from Box 6 to Box 3.", "sample_id": 2029, "numops": 5, "final_states": {"Box 0": ["the apple"], "Box 1": ["nothing"], "Box 2": ["the clock", "the map"], "Box 3": ["the meat"], "Box 4": ["the bottle"], "Box 5": ["nothing"], "Box 6": ["the computer", "the shoe"]}}
{"sentence": "Box 0 contains the note and the suit, Box 1 contains nothing, Box 2 contains nothing, Box 3 contains the glass, Box 4 contains the document and the newspaper and the tape, Box 5 contains the clock and the wheel, Box 6 contains the stone. Move the glass from Box 3 to Box 2. Remove the clock and the wheel from Box 5. Move the newspaper from Box 4 to Box 1.", "sample_id": 2032, "numops": 0, "final_states": {"Box 0": ["the note", "the suit"], "Box 1": ["the phone", "the drug", "the newspaper"], "Box 2": ["the glass"], "Box 3": ["nothing", "the stone", "the tape"], "Box 4": ["the document", "nothing", "the tape"], "Box 5": ["nothing"], "Box 6": ["the document", "the stone", "the note"]}}
{"sentence": "Box 0 contains the chemical and the disk and the tie, Box 1 contains the shoe, Box 2 contains the pot and the train, Box 3 contains the suit, Box 4 contains the boat and the bone and the fig, Box 5 contains the brain and the game and the television, Box 6 contains the car and the key and the pipe.", "sample_id": 2035, "numops": 0, "final_states": {"Box 0": ["the chemical", "the disk", "the tie"], "Box 1": ["the shoe"], "Box 2": ["the pot", "the train"], "Box 3": ["the suit"], "Box 4": ["the bone", "the fig", "the boat"], "Box 5": ["the game", "the television", "the brain"], "Box 6": ["the key", "the car", "the pipe"]}}
{"sentence": "Box 0 contains the picture and the tape, Box 1 contains the engine and the phone and the watch, Box 2 contains the train, Box 3 contains the boot and the bowl and the tissue, Box 4 contains the cheese and the document and the leaf, Box 5 contains the machine, Box 6 contains the bag. Remove the machine from Box 5. Remove the picture and the tape from Box 0. Move the bag from Box 6 to Box 5. Move the engine from Box 1 to Box 2. Remove the boot and the bowl from Box 3. Move the train from Box 2 to Box 0. Remove the bag from Box 5. Remove the engine from Box 2. Move the phone from Box 1 to Box 5. Put the branch into Box 5. Move the train from Box 0 to Box 5.", "sample_id": 2036, "numops": 3, "final_states": {"Box 0": ["nothing"], "Box 1": ["the watch"], "Box 2": ["nothing"], "Box 3": ["the tissue"], "Box 4": ["the document", "the cheese", "the leaf"], "Box 5": ["the phone", "the branch", "the train"], "Box 6": ["nothing"]}}
{"sentence": "Box 0 contains the phone, Box 1 contains the cake, Box 2 contains the bone, Box 3 contains the car and the drink and the machine, Box 4 contains the cheese and the ice and the medicine, Box 5 contains the bag and the dress and the plant, Box 6 contains nothing.", "sample_id": 2039, "numops": 0, "final_states": {"Box 0": ["the phone"], "Box 1": ["the cake"], "Box 2": ["the bone"], "Box 3": ["the car", "the machine", "the drink"], "Box 4": ["the medicine", "the ice", "the cheese"], "Box 5": ["the plant", "the bag", "the dress"], "Box 6": ["nothing"]}}
{"sentence": "Box 0 contains nothing, Box 1 contains the coat and the drug, Box 2 contains nothing, Box 3 contains nothing, Box 4 contains nothing, Box 5 contains the computer and the cross and the pipe, Box 6 contains the glass. Remove the computer and the cross from Box 5.", "sample_id": 2043, "numops": 0, "final_states": {"Box 0": ["nothing", "the dress"], "Box 1": ["nothing", "the drug", "the coat"], "Box 2": ["the file", "nothing", "the drug", "the coat"], "Box 3": ["the glass", "nothing"], "Box 4": ["nothing"], "Box 5": ["the bread", "the milk", "the pipe"], "Box 6": ["the bone", "the glass"]}}
{"sentence": "Box 0 contains the seed and the train, Box 1 contains the ball and the flower and the shell, Box 2 contains the bottle and the plant and the radio, Box 3 contains nothing, Box 4 contains the bag and the jacket, Box 5 contains the map and the picture, Box 6 contains nothing. Remove the bottle from Box 2. Put the fig into Box 4. Put the computer into Box 2. Remove the computer and the plant and the radio from Box 2. Put the note into Box 6. Move the note from Box 6 to Box 3. Move the fig and the jacket from Box 4 to Box 6.", "sample_id": 2045, "numops": 0, "final_states": {"Box 0": ["the train", "the seed"], "Box 1": ["the flower", "the shell", "the ball"], "Box 2": ["nothing"], "Box 3": ["the note"], "Box 4": ["the bag"], "Box 5": ["the map", "the picture"], "Box 6": ["the fig", "the jacket"]}}
{"sentence": "Box 0 contains the pipe, Box 1 contains the disk and the shell, Box 2 contains the cream and the key, Box 3 contains the card and the letter, Box 4 contains the fan and the string and the wheel, Box 5 contains the coat and the egg and the rose, Box 6 contains the knife and the plate. Put the machine into Box 6. Put the seed into Box 3. Remove the seed from Box 3. Remove the knife from Box 6. Remove the fan and the string from Box 4. Remove the pipe from Box 0. Remove the letter from Box 3. Remove the card from Box 3. Put the camera and the medicine and the paper into Box 3.", "sample_id": 2046, "numops": 1, "final_states": {"Box 0": ["nothing"], "Box 1": ["the shell", "the disk"], "Box 2": ["the cream", "the key"], "Box 3": ["the medicine", "the paper", "the camera"], "Box 4": ["the cream", "the ring", "the wheel"], "Box 5": ["the rose", "the coat", "the egg"], "Box 6": ["the plate", "the machine"]}}
{"sentence": "Box 0 contains nothing, Box 1 contains the bone and the glass, Box 2 contains the drink and the mirror, Box 3 contains the apple and the tie and the wheel, Box 4 contains the ball and the letter and the string, Box 5 contains the creature and the guitar and the sheet, Box 6 contains the seed. Move the mirror from Box 2 to Box 1. Remove the seed from Box 6. Move the wheel from Box 3 to Box 6. Put the bag and the branch into Box 2. Move the branch and the drink from Box 2 to Box 0. Remove the tie from Box 3. Remove the apple from Box 3. Remove the branch and the drink from Box 0.", "sample_id": 2048, "numops": 2, "final_states": {"Box 0": ["nothing"], "Box 1": ["the bone", "the glass", "the mirror"], "Box 2": ["the bag"], "Box 3": ["nothing"], "Box 4": ["the string", "the letter", "the ball"], "Box 5": ["the sheet", "the creature", "the guitar"], "Box 6": ["the wheel"]}}
{"sentence": "Box 0 contains the leaf, Box 1 contains the block and the rose, Box 2 contains the book and the car, Box 3 contains the pot, Box 4 contains the apple, Box 5 contains the brain and the clock and the egg, Box 6 contains the coffee. Remove the block and the rose from Box 1. Put the phone into Box 0. Move the brain and the egg from Box 5 to Box 1. Move the coffee from Box 6 to Box 1. Remove the apple from Box 4. Move the pot from Box 3 to Box 6. Remove the coffee and the egg from Box 1. Remove the phone from Box 0. Put the game into Box 1. Move the pot from Box 6 to Box 5. Put the apple and the pipe into Box 4. Put the cash into Box 1.", "sample_id": 2049, "numops": 2, "final_states": {"Box 0": ["the leaf"], "Box 1": ["the cash", "the brain", "the game"], "Box 2": ["the car", "the book"], "Box 3": ["nothing"], "Box 4": ["the apple", "the pipe"], "Box 5": ["the clock", "the pot"], "Box 6": ["nothing"]}}
{"sentence": "Box 0 contains the coat and the coffee, Box 1 contains the cup and the fig, Box 2 contains nothing, Box 3 contains the shoe, Box 4 contains the crown and the drug and the train, Box 5 contains nothing, Box 6 contains the mirror and the tea. Put the letter into Box 0. Remove the letter from Box 0. Remove the crown from Box 4. Remove the drug and the train from Box 4. Put the bottle into Box 6. Remove the coat from Box 0. Remove the bottle and the tea from Box 6. Remove the mirror from Box 6. Put the phone into Box 6. Put the seed into Box 6. Put the jacket into Box 3. Move the phone from Box 6 to Box 4.", "sample_id": 2052, "numops": 3, "final_states": {"Box 0": ["the coffee"], "Box 1": ["the fig", "the cup"], "Box 2": ["nothing"], "Box 3": ["the shoe", "the jacket"], "Box 4": ["the phone"], "Box 5": ["nothing"], "Box 6": ["the seed"]}}
{"sentence": "Box 0 contains the branch and the fig, Box 1 contains the cake and the cash and the ice, Box 2 contains the clock, Box 3 contains nothing, Box 4 contains the fish and the string, Box 5 contains the bus, Box 6 contains the note. Move the note from Box 6 to Box 4. Move the clock from Box 2 to Box 5. Move the ice from Box 1 to Box 5. Put the wheel into Box 6. Remove the cake and the cash from Box 1. Move the clock and the ice from Box 5 to Box 2. Move the note and the string from Box 4 to Box 5. Put the sheet into Box 3. Remove the fish from Box 4. Move the note from Box 5 to Box 0. Remove the branch and the fig from Box 0.", "sample_id": 2055, "numops": 2, "final_states": {"Box 0": ["the note"], "Box 1": ["nothing"], "Box 2": ["the clock", "the ice"], "Box 3": ["the sheet"], "Box 4": ["nothing"], "Box 5": ["the bus", "the string"], "Box 6": ["the wheel"]}}
{"sentence": "Box 0 contains the fish and the paper, Box 1 contains the chemical and the painting, Box 2 contains nothing, Box 3 contains the beer and the map and the sheet, Box 4 contains the bomb and the cream and the plane, Box 5 contains the gift, Box 6 contains the clock and the meat. Put the bill and the coat into Box 2. Move the gift from Box 5 to Box 6. Remove the chemical from Box 1. Remove the bomb from Box 4. Move the fish and the paper from Box 0 to Box 5. Move the fish from Box 5 to Box 4. Remove the paper from Box 5.", "sample_id": 2072, "numops": 1, "final_states": {"Box 0": ["nothing"], "Box 1": ["the painting"], "Box 2": ["the drug", "the coat", "the bill"], "Box 3": ["the map", "the sheet", "the beer"], "Box 4": ["the cream", "the plane", "the fish", "the guitar"], "Box 5": ["nothing", "the meat"], "Box 6": ["the gift", "the meat", "the clock"]}}
{"sentence": "Box 0 contains the plane, Box 1 contains the apple and the branch and the letter, Box 2 contains nothing, Box 3 contains the bell and the watch, Box 4 contains the fan, Box 5 contains the crown, Box 6 contains the cake and the gift and the painting. Remove the crown from Box 5. Move the plane from Box 0 to Box 2. Remove the bell from Box 3. Put the meat into Box 0. Move the watch from Box 3 to Box 0. Move the plane from Box 2 to Box 0. Move the plane and the watch from Box 0 to Box 2. Put the beer and the crown into Box 4. Put the plant into Box 0. Remove the fan from Box 4. Move the crown from Box 4 to Box 5.", "sample_id": 2073, "numops": 6, "final_states": {"Box 0": ["the plant", "the meat"], "Box 1": ["the letter", "the apple", "the branch"], "Box 2": ["the plane", "the watch"], "Box 3": ["nothing"], "Box 4": ["the beer"], "Box 5": ["the crown"], "Box 6": ["the painting", "the gift", "the cake"]}}
{"sentence": "Box 0 contains the bus and the coat, Box 1 contains nothing, Box 2 contains the coffee, Box 3 contains the file, Box 4 contains the watch, Box 5 contains the meat and the tie and the train, Box 6 contains the medicine and the picture and the television. Remove the watch from Box 4. Put the game into Box 4. Put the cup into Box 2. Remove the game from Box 4. Remove the bus and the coat from Box 0. Move the coffee and the cup from Box 2 to Box 4. Move the cup from Box 4 to Box 2.", "sample_id": 2077, "numops": 1, "final_states": {"Box 0": ["nothing"], "Box 1": ["nothing"], "Box 2": ["the cup"], "Box 3": ["the file"], "Box 4": ["the coffee"], "Box 5": ["the tie", "the train", "the meat"], "Box 6": ["the television", "the medicine", "the picture"]}}
{"sentence": "Box 0 contains the mirror and the sheet and the tape, Box 1 contains the boat and the wheel, Box 2 contains the card and the television, Box 3 contains the cheese and the map and the picture, Box 4 contains the file and the machine, Box 5 contains the glass and the watch, Box 6 contains the block. Move the watch from Box 5 to Box 4. Remove the glass from Box 5. Move the picture from Box 3 to Box 5. Remove the mirror and the sheet and the tape from Box 0. Put the key into Box 2. Remove the boat from Box 1. Remove the television from Box 2. Remove the card and the key from Box 2. Move the block from Box 6 to Box 2. Move the block from Box 2 to Box 3. Move the machine and the watch from Box 4 to Box 6. Remove the block from Box 3.", "sample_id": 2079, "numops": 1, "final_states": {"Box 0": ["nothing"], "Box 1": ["the wheel"], "Box 2": ["nothing"], "Box 3": ["the map", "the cheese"], "Box 4": ["the file"], "Box 5": ["the picture"], "Box 6": ["the machine", "the watch"]}}
{"sentence": "Box 0 contains the computer and the file and the rock, Box 1 contains the ball and the egg and the engine, Box 2 contains the bill and the bomb and the brick, Box 3 contains the magazine, Box 4 contains the radio and the tape, Box 5 contains the coat, Box 6 contains the hat. Remove the file and the rock from Box 0. Move the egg from Box 1 to Box 6. Remove the tape from Box 4. Remove the magazine from Box 3. Remove the brick from Box 2. Remove the computer from Box 0. Remove the coat from Box 5.", "sample_id": 2082, "numops": 2, "final_states": {"Box 0": ["nothing"], "Box 1": ["the engine", "the ball"], "Box 2": ["the bomb", "the bill"], "Box 3": ["nothing"], "Box 4": ["the radio"], "Box 5": ["nothing"], "Box 6": ["the egg", "the hat"]}}
{"sentence": "Box 0 contains the magazine and the newspaper and the painting, Box 1 contains the bowl and the rock, Box 2 contains the flower, Box 3 contains the guitar and the pipe, Box 4 contains the brick and the drink and the phone, Box 5 contains the apple and the hat and the letter, Box 6 contains nothing. Move the bowl and the rock from Box 1 to Box 6. Remove the flower from Box 2. Remove the magazine and the newspaper and the painting from Box 0. Remove the guitar and the pipe from Box 3. Remove the brick and the drink from Box 4. Put the dress into Box 1. Move the dress from Box 1 to Box 3. Move the phone from Box 4 to Box 3. Put the radio into Box 3. Move the apple and the hat from Box 5 to Box 0.", "sample_id": 2083, "numops": 2, "final_states": {"Box 0": ["the apple", "the hat"], "Box 1": ["nothing"], "Box 2": ["nothing"], "Box 3": ["the phone", "the radio", "the dress"], "Box 4": ["nothing"], "Box 5": ["the letter"], "Box 6": ["the bowl", "the rock"]}}
{"sentence": "Box 0 contains the crown and the magazine and the sheet, Box 1 contains the document, Box 2 contains the cigarette, Box 3 contains the chemical and the drug, Box 4 contains the ring, Box 5 contains the brick and the wire, Box 6 contains the game and the television and the wheel. Move the document from Box 1 to Box 5. Put the bag and the medicine into Box 2. Remove the television from Box 6. Remove the chemical and the drug from Box 3. Put the stone into Box 4. Remove the wheel from Box 6. Remove the game from Box 6. Put the branch into Box 6. Remove the bag and the medicine from Box 2. Move the branch from Box 6 to Box 3. Remove the branch from Box 3. Move the cigarette from Box 2 to Box 1.", "sample_id": 2086, "numops": 0, "final_states": {"Box 0": ["the sheet", "the magazine", "the crown"], "Box 1": ["the cigarette"], "Box 2": ["nothing"], "Box 3": ["nothing"], "Box 4": ["the stone", "the ring"], "Box 5": ["the document", "the wire", "the brick"], "Box 6": ["nothing"]}}
{"sentence": "Box 0 contains the ball and the bread, Box 1 contains nothing, Box 2 contains the bottle and the cash and the creature, Box 3 contains the engine and the medicine and the tissue, Box 4 contains the fig and the rose, Box 5 contains the bell, Box 6 contains the guitar. Remove the rose from Box 4.", "sample_id": 2087, "numops": 0, "final_states": {"Box 0": ["the bread", "the ball"], "Box 1": ["nothing"], "Box 2": ["the creature", "the bottle", "the cash"], "Box 3": ["the medicine", "the engine", "the tissue"], "Box 4": ["the fig"], "Box 5": ["the bell"], "Box 6": ["the guitar"]}}
{"sentence": "Box 0 contains nothing, Box 1 contains the boat and the cream, Box 2 contains the car and the gift, Box 3 contains the bomb and the branch and the stone, Box 4 contains the dish, Box 5 contains the egg, Box 6 contains the plant. Remove the plant from Box 6. Move the cream from Box 1 to Box 6. Move the egg from Box 5 to Box 1. Move the cream from Box 6 to Box 1. Remove the car from Box 2. Move the boat and the egg from Box 1 to Box 6. Move the bomb from Box 3 to Box 4. Move the gift from Box 2 to Box 4. Remove the dish and the gift from Box 4. Put the radio into Box 3. Move the cream from Box 1 to Box 5.", "sample_id": 2091, "numops": 0, "final_states": {"Box 0": ["nothing"], "Box 1": ["nothing"], "Box 2": ["nothing"], "Box 3": ["the stone", "the branch", "the radio"], "Box 4": ["the bomb"], "Box 5": ["the cream"], "Box 6": ["the egg", "the boat"]}}
{"sentence": "Box 0 contains the machine and the painting, Box 1 contains the ball and the shell, Box 2 contains nothing, Box 3 contains the train, Box 4 contains the gift and the paper and the wheel, Box 5 contains the computer and the phone and the rock, Box 6 contains the bill and the cream and the meat. Move the meat from Box 6 to Box 0. Remove the train from Box 3. Remove the gift and the wheel from Box 4. Remove the cream from Box 6. Remove the machine from Box 0. Put the fig into Box 3.", "sample_id": 2092, "numops": 2, "final_states": {"Box 0": ["the painting", "the meat"], "Box 1": ["the shell", "the ball"], "Box 2": ["nothing"], "Box 3": ["the fig"], "Box 4": ["the paper"], "Box 5": ["the computer", "the rock", "the phone"], "Box 6": ["the bill"]}}
{"sentence": "Box 0 contains the bottle and the game, Box 1 contains the crown and the document and the fig, Box 2 contains nothing, Box 3 contains the drug and the plane, Box 4 contains the coffee and the shirt, Box 5 contains nothing, Box 6 contains the bus and the fish. Remove the bus from Box 6. Move the crown from Box 1 to Box 4.", "sample_id": 2095, "numops": 0, "final_states": {"Box 0": ["the game", "the bottle", "the bread"], "Box 1": ["the fig", "the document"], "Box 2": ["the game", "nothing"], "Box 3": ["the plane", "the drug", "the coffee"], "Box 4": ["the crown", "the shirt", "the coffee", "nothing"], "Box 5": ["nothing"], "Box 6": ["the fish"]}}
{"sentence": "Box 0 contains the cigarette, Box 1 contains the gift and the pipe, Box 2 contains the camera and the picture and the tape, Box 3 contains the stone and the television, Box 4 contains the fig and the key and the sheet, Box 5 contains nothing, Box 6 contains nothing. Move the gift from Box 1 to Box 3. Remove the pipe from Box 1. Remove the sheet from Box 4. Remove the cigarette from Box 0. Put the ring into Box 0. Remove the fig and the key from Box 4. Put the cup and the fig and the fish into Box 1. Move the ring from Box 0 to Box 4. Remove the picture from Box 2. Remove the cup and the fig and the fish from Box 1.", "sample_id": 2096, "numops": 3, "final_states": {"Box 0": ["nothing"], "Box 1": ["nothing"], "Box 2": ["the camera", "the tape"], "Box 3": ["the television", "the gift", "the stone"], "Box 4": ["the ring"], "Box 5": ["nothing"], "Box 6": ["nothing"]}}
{"sentence": "Box 0 contains the cream and the phone, Box 1 contains nothing, Box 2 contains the cross and the gift and the plate, Box 3 contains the ball and the document, Box 4 contains the bag and the jacket and the rose, Box 5 contains the ice and the knife, Box 6 contains the egg. Move the egg from Box 6 to Box 0.", "sample_id": 2102, "numops": 1, "final_states": {"Box 0": ["the cream", "the phone", "the jacket", "the bag", "the egg"], "Box 1": ["nothing", "the ice", "the brick"], "Box 2": ["the plate", "the cream", "the gift", "the phone", "the cross"], "Box 3": ["the document", "the ball"], "Box 4": ["the rose", "the bag", "the jacket", "the document", "nothing", "the wheel"], "Box 5": ["the knife", "nothing", "the ice"], "Box 6": ["the knife", "nothing"]}}
{"sentence": "Box 0 contains the chemical and the leaf and the shirt, Box 1 contains the coffee, Box 2 contains the ball and the beer and the hat, Box 3 contains the bill and the branch and the wire, Box 4 contains the cream and the document and the tissue, Box 5 contains the bone and the rock and the rose, Box 6 contains the bottle and the brain and the coat. Remove the coffee from Box 1. Move the wire from Box 3 to Box 1. Remove the cream from Box 4. Put the train into Box 1. Remove the chemical and the leaf and the shirt from Box 0. Move the document from Box 4 to Box 1. Put the brick into Box 4. Remove the bill from Box 3. Remove the branch from Box 3.", "sample_id": 2113, "numops": 1, "final_states": {"Box 0": ["the beer", "nothing"], "Box 1": ["the train", "the document", "the wire"], "Box 2": ["the hat", "the beer", "the ball"], "Box 3": ["nothing"], "Box 4": ["the brick", "the tissue"], "Box 5": ["the rose", "the bone", "the rock"], "Box 6": ["the coat", "the bottle", "the brain"]}}
{"sentence": "Box 0 contains nothing, Box 1 contains the book and the clock and the rose, Box 2 contains the tie, Box 3 contains the fig and the painting, Box 4 contains the ball and the glass and the stone, Box 5 contains the radio and the train, Box 6 contains the coffee. Move the radio from Box 5 to Box 2. Remove the book from Box 1. Remove the train from Box 5. Remove the glass from Box 4. Remove the radio from Box 2. Remove the rose from Box 1. Remove the clock from Box 1. Remove the ball and the stone from Box 4. Put the disk into Box 6. Remove the tie from Box 2.", "sample_id": 2114, "numops": 0, "final_states": {"Box 0": ["nothing"], "Box 1": ["nothing"], "Box 2": ["nothing"], "Box 3": ["the fig", "the painting"], "Box 4": ["nothing"], "Box 5": ["nothing"], "Box 6": ["the coffee", "the disk"]}}
{"sentence": "Box 0 contains the cheese and the disk, Box 1 contains the brain and the cake and the rose, Box 2 contains the crown and the shell, Box 3 contains the coffee and the painting, Box 4 contains the bill and the flower and the plane, Box 5 contains the coat and the glass, Box 6 contains nothing. Remove the painting from Box 3. Put the tie into Box 0. Remove the crown from Box 2. Move the brain and the rose from Box 1 to Box 3. Remove the coat from Box 5. Remove the bill from Box 4. Put the newspaper into Box 1. Remove the brain and the rose from Box 3. Remove the glass from Box 5. Move the flower from Box 4 to Box 3. Remove the shell from Box 2. Remove the flower from Box 3.", "sample_id": 2120, "numops": 1, "final_states": {"Box 0": ["the tie", "the disk", "the cheese"], "Box 1": ["the newspaper", "the cake"], "Box 2": ["nothing"], "Box 3": ["the coffee"], "Box 4": ["the plane"], "Box 5": ["nothing"], "Box 6": ["nothing"]}}
{"sentence": "Box 0 contains nothing, Box 1 contains the bottle and the knife, Box 2 contains the document, Box 3 contains nothing, Box 4 contains the clock and the medicine and the stone, Box 5 contains the boot and the bread and the shell, Box 6 contains the bowl and the mirror. Move the clock and the medicine from Box 4 to Box 2. Put the guitar into Box 6. Remove the stone from Box 4. Put the ice into Box 0. Put the creature and the machine into Box 0.", "sample_id": 2123, "numops": 2, "final_states": {"Box 0": ["the creature", "the ice", "the machine"], "Box 1": ["the knife", "the bottle"], "Box 2": ["the clock", "the document", "the medicine"], "Box 3": ["nothing"], "Box 4": ["nothing"], "Box 5": ["the shell", "the bread", "the boot"], "Box 6": ["the mirror", "the bowl", "the guitar"]}}
{"sentence": "Box 0 contains the computer, Box 1 contains nothing, Box 2 contains nothing, Box 3 contains the camera and the letter and the picture, Box 4 contains the ice and the machine and the ticket, Box 5 contains the ball and the cream and the pot, Box 6 contains the file. Remove the letter from Box 3. Remove the picture from Box 3. Put the wire into Box 3. Put the sheet into Box 3. Move the camera and the sheet and the wire from Box 3 to Box 1. Remove the cream and the pot from Box 5. Put the painting and the radio into Box 6. Remove the sheet from Box 1. Move the computer from Box 0 to Box 5. Move the ball from Box 5 to Box 0. Put the rock into Box 1.", "sample_id": 2124, "numops": 2, "final_states": {"Box 0": ["the ball"], "Box 1": ["the camera", "the wire", "the rock"], "Box 2": ["nothing"], "Box 3": ["nothing"], "Box 4": ["the ice", "the machine", "the ticket"], "Box 5": ["the computer"], "Box 6": ["the file", "the painting", "the radio"]}}
{"sentence": "Box 0 contains the brain, Box 1 contains the radio, Box 2 contains the boat and the tie, Box 3 contains the bomb and the tea, Box 4 contains the bone and the note and the stone, Box 5 contains the apple and the dress and the paper, Box 6 contains the branch and the guitar and the shell. Remove the branch from Box 6. Remove the radio from Box 1. Move the bone and the stone from Box 4 to Box 1. Remove the tea from Box 3. Remove the bone from Box 1. Remove the stone from Box 1. Remove the brain from Box 0. Remove the boat from Box 2. Move the tie from Box 2 to Box 1. Move the apple and the dress from Box 5 to Box 2. Remove the apple from Box 2. Move the paper from Box 5 to Box 0.", "sample_id": 2135, "numops": 2, "final_states": {"Box 0": ["the paper"], "Box 1": ["the tie"], "Box 2": ["the dress"], "Box 3": ["the bomb"], "Box 4": ["the note"], "Box 5": ["nothing"], "Box 6": ["the shell", "the guitar"]}}
{"sentence": "Box 0 contains nothing, Box 1 contains the jacket and the note and the ticket, Box 2 contains the branch and the cream, Box 3 contains the letter, Box 4 contains the apple and the medicine and the watch, Box 5 contains the brick, Box 6 contains the fish and the rose. Remove the fish from Box 6. Remove the rose from Box 6. Remove the brick from Box 5. Move the apple and the medicine from Box 4 to Box 6. Move the branch and the cream from Box 2 to Box 5. Put the paper into Box 0. Move the watch from Box 4 to Box 2. Move the ticket from Box 1 to Box 4. Remove the ticket from Box 4.", "sample_id": 2138, "numops": 1, "final_states": {"Box 0": ["the paper"], "Box 1": ["the note", "the jacket"], "Box 2": ["the watch"], "Box 3": ["the letter"], "Box 4": ["nothing"], "Box 5": ["the cream", "the branch"], "Box 6": ["the apple", "the medicine"]}}
{"sentence": "Box 0 contains the bell and the tape, Box 1 contains the picture and the television, Box 2 contains the ball and the boot and the fish, Box 3 contains the branch and the guitar and the leaf, Box 4 contains the creature and the map and the sheet, Box 5 contains the cream and the ice and the plant, Box 6 contains the string. Move the sheet from Box 4 to Box 0. Remove the picture from Box 1. Remove the tape from Box 0. Remove the string from Box 6. Move the ice from Box 5 to Box 1. Put the shell into Box 1. Remove the cream and the plant from Box 5. Remove the creature from Box 4. Move the ice and the shell and the television from Box 1 to Box 5. Put the apple and the coat into Box 1. Put the plane into Box 6. Move the fish from Box 2 to Box 1.", "sample_id": 2139, "numops": 2, "final_states": {"Box 0": ["the sheet", "the bell"], "Box 1": ["the apple", "the coat", "the fish"], "Box 2": ["the boot", "the ball"], "Box 3": ["the guitar", "the branch", "the leaf"], "Box 4": ["the map"], "Box 5": ["the shell", "the television", "the ice"], "Box 6": ["the plane"]}}
{"sentence": "Box 0 contains the disk, Box 1 contains the hat, Box 2 contains the bottle and the plane and the wire, Box 3 contains the bus and the crown, Box 4 contains the tie and the train, Box 5 contains the creature and the glass and the stone, Box 6 contains the bowl and the shirt and the watch. Remove the bowl and the watch from Box 6. Move the plane and the wire from Box 2 to Box 0. Remove the disk from Box 0.", "sample_id": 2140, "numops": 2, "final_states": {"Box 0": ["the plane", "the wire"], "Box 1": ["nothing", "the hat"], "Box 2": ["the bottle"], "Box 3": ["the bus", "the crown"], "Box 4": ["the tie", "the train"], "Box 5": ["the glass", "the creature", "the stone"], "Box 6": ["the shirt"]}}
{"sentence": "Box 0 contains nothing, Box 1 contains the apple and the ice, Box 2 contains the coat, Box 3 contains the cash and the drug and the pipe, Box 4 contains the bowl and the cross and the flower, Box 5 contains the painting and the plane, Box 6 contains the tape.", "sample_id": 2145, "numops": 0, "final_states": {"Box 0": ["nothing"], "Box 1": ["the apple", "the ice"], "Box 2": ["the coat"], "Box 3": ["the cash", "nothing", "the drug", "the pipe"], "Box 4": ["the bowl", "the cross", "the flower"], "Box 5": ["the painting", "the plane", "nothing"], "Box 6": ["nothing", "the tape"]}}
{"sentence": "Box 0 contains nothing, Box 1 contains the ice and the key, Box 2 contains the disk and the tape and the tie, Box 3 contains the knife and the television and the tissue, Box 4 contains the cigarette, Box 5 contains the boat and the dish and the shell, Box 6 contains the meat and the phone and the wheel. Remove the ice from Box 1. Put the cheese into Box 0. Remove the boat from Box 5. Remove the key from Box 1. Remove the dish and the shell from Box 5. Remove the cheese from Box 0. Remove the knife from Box 3. Move the cigarette from Box 4 to Box 0. Put the clock and the train into Box 5. Move the train from Box 5 to Box 1. Remove the cigarette from Box 0. Remove the meat from Box 6.", "sample_id": 2147, "numops": 4, "final_states": {"Box 0": ["nothing"], "Box 1": ["the train"], "Box 2": ["the disk", "the tie", "the tape"], "Box 3": ["the television", "the tissue"], "Box 4": ["nothing"], "Box 5": ["the clock"], "Box 6": ["the phone", "the wheel"]}}
{"sentence": "Box 0 contains the clock and the watch, Box 1 contains the map, Box 2 contains the gift and the guitar, Box 3 contains the block and the milk and the wire, Box 4 contains the boat and the bottle and the car, Box 5 contains the dish and the ticket, Box 6 contains the bag and the brick and the chemical. Remove the dish from Box 5. Put the ball and the bread into Box 1. Move the brick from Box 6 to Box 5. Remove the clock from Box 0. Remove the ball and the bread from Box 1. Remove the boat and the car from Box 4. Move the brick from Box 5 to Box 2.", "sample_id": 2148, "numops": 1, "final_states": {"Box 0": ["the milk", "the block", "the watch"], "Box 1": ["the map"], "Box 2": ["the gift", "the brick", "the guitar"], "Box 3": ["the milk", "the wire", "the block"], "Box 4": ["the bottle"], "Box 5": ["the ticket"], "Box 6": ["the chemical", "the bag"]}}
{"sentence": "Box 0 contains the shoe and the wheel, Box 1 contains the beer and the file and the pot, Box 2 contains the creature and the engine and the ring, Box 3 contains nothing, Box 4 contains the magazine, Box 5 contains nothing, Box 6 contains nothing. Remove the wheel from Box 0. Move the engine and the ring from Box 2 to Box 3. Move the shoe from Box 0 to Box 3. Remove the creature from Box 2. Put the meat into Box 5. Remove the magazine from Box 4. Remove the meat from Box 5.", "sample_id": 2150, "numops": 2, "final_states": {"Box 0": ["nothing"], "Box 1": ["the file", "the pot", "the beer"], "Box 2": ["nothing"], "Box 3": ["the engine", "the ring", "the shoe"], "Box 4": ["nothing"], "Box 5": ["nothing"], "Box 6": ["nothing"]}}
{"sentence": "Box 0 contains the ticket, Box 1 contains the mirror and the plane and the radio, Box 2 contains the bone and the cheese and the painting, Box 3 contains the bag and the medicine and the pipe, Box 4 contains the tape, Box 5 contains the plant and the shirt, Box 6 contains the fan and the sheet. Remove the mirror and the plane and the radio from Box 1. Put the block and the phone into Box 1. Move the pipe from Box 3 to Box 0. Move the plant and the shirt from Box 5 to Box 4. Move the ticket from Box 0 to Box 5. Remove the medicine from Box 3. Put the tie into Box 0. Move the ticket from Box 5 to Box 0. Remove the block and the phone from Box 1. Remove the bag from Box 3. Move the ticket and the tie from Box 0 to Box 1. Remove the pipe from Box 0.", "sample_id": 2151, "numops": 6, "final_states": {"Box 0": ["nothing"], "Box 1": ["the ticket", "the tie"], "Box 2": ["the bone", "the painting", "the cheese"], "Box 3": ["nothing"], "Box 4": ["the plant", "the tape", "the shirt"], "Box 5": ["nothing"], "Box 6": ["the fan", "the sheet"]}}
{"sentence": "Box 0 contains the boat and the book and the coffee, Box 1 contains nothing, Box 2 contains the ice and the machine and the painting, Box 3 contains the jacket, Box 4 contains the fan and the mirror and the stone, Box 5 contains the card and the coat and the cross, Box 6 contains the bill and the wire. Remove the book from Box 0. Move the machine and the painting from Box 2 to Box 3. Move the ice from Box 2 to Box 6. Remove the boat and the coffee from Box 0. Remove the wire from Box 6. Put the meat and the milk into Box 0. Move the bill from Box 6 to Box 1. Put the ball and the drink into Box 2. Move the milk from Box 0 to Box 6.", "sample_id": 2158, "numops": 4, "final_states": {"Box 0": ["nothing", "the meat"], "Box 1": ["the bill", "the meat"], "Box 2": ["the drink", "the ball"], "Box 3": ["the machine", "the jacket", "the painting"], "Box 4": ["the fan", "the stone", "the mirror"], "Box 5": ["the card", "the coat", "the cross"], "Box 6": ["the fan", "the milk", "the ice", "nothing", "the stone"]}}
{"sentence": "Box 0 contains the beer and the file, Box 1 contains the computer, Box 2 contains the hat and the tape, Box 3 contains the block and the meat, Box 4 contains the guitar and the map and the tissue, Box 5 contains the fan and the suit and the ticket, Box 6 contains the jacket. Put the bomb into Box 0. Remove the suit and the ticket from Box 5.", "sample_id": 2165, "numops": 1, "final_states": {"Box 0": ["the file", "the beer", "the bomb"], "Box 1": ["the computer"], "Box 2": ["the hat", "the tape"], "Box 3": ["the meat", "the block"], "Box 4": ["the map", "the guitar", "the tissue"], "Box 5": ["the fan"], "Box 6": ["the jacket"]}}
{"sentence": "Box 0 contains the gift, Box 1 contains the apple and the phone and the plane, Box 2 contains the machine and the ticket, Box 3 contains the fan and the string and the wire, Box 4 contains the television and the tie, Box 5 contains the note, Box 6 contains the boat and the glass and the milk. Move the note from Box 5 to Box 2. Remove the fan and the string and the wire from Box 3. Move the gift from Box 0 to Box 4. Move the gift and the tie from Box 4 to Box 0. Remove the television from Box 4. Move the glass and the milk from Box 6 to Box 3. Remove the note from Box 2. Put the knife and the map and the pipe into Box 4. Move the map from Box 4 to Box 5. Move the knife from Box 4 to Box 5. Move the boat from Box 6 to Box 5. Put the bill into Box 6.", "sample_id": 2169, "numops": 2, "final_states": {"Box 0": ["the gift", "the tie"], "Box 1": ["the apple", "the phone", "the plane"], "Box 2": ["the ticket", "the machine"], "Box 3": ["the glass", "the milk"], "Box 4": ["the pipe"], "Box 5": ["the map", "the knife", "the boat"], "Box 6": ["the bill"]}}
{"sentence": "Box 0 contains the brick and the cup and the plane, Box 1 contains the dish and the paper and the tie, Box 2 contains the gift, Box 3 contains the brain, Box 4 contains the drug and the glass, Box 5 contains the string, Box 6 contains the radio and the tea. Move the dish and the paper from Box 1 to Box 5.", "sample_id": 2183, "numops": 0, "final_states": {"Box 0": ["the plane", "the cup", "the brick"], "Box 1": ["nothing", "the tie"], "Box 2": ["the gift"], "Box 3": ["the brain"], "Box 4": ["the glass", "nothing", "the drug"], "Box 5": ["the paper", "the dish", "the string"], "Box 6": ["the tea", "the radio"]}}
{"sentence": "Box 0 contains nothing, Box 1 contains the coat and the shell and the television, Box 2 contains the boat and the crown and the key, Box 3 contains the cross and the dish, Box 4 contains the fish and the train and the wheel, Box 5 contains the painting and the plant and the ring, Box 6 contains the magazine. Put the leaf into Box 3. Remove the boat from Box 2. Remove the crown from Box 2. Move the magazine from Box 6 to Box 2. Remove the dish from Box 3. Put the drink into Box 3.", "sample_id": 2193, "numops": 0, "final_states": {"Box 0": ["nothing"], "Box 1": ["the shell", "the television", "the coat"], "Box 2": ["the fish", "the key", "the magazine", "the wheel"], "Box 3": ["the cross", "the leaf", "the drink"], "Box 4": ["the fish", "nothing", "the train", "the wheel"], "Box 5": ["the painting", "the plant", "the ring"], "Box 6": ["nothing"]}}
{"sentence": "Box 0 contains nothing, Box 1 contains the book and the brick and the pipe, Box 2 contains nothing, Box 3 contains the rock, Box 4 contains the shirt and the tea and the watch, Box 5 contains the boat and the bottle and the ice, Box 6 contains the ball and the fan and the file. Remove the boat from Box 5. Put the boat into Box 5. Put the coffee and the ticket into Box 3. Remove the tea from Box 4. Move the pipe from Box 1 to Box 2. Put the television into Box 4. Put the document into Box 2. Remove the coffee and the ticket from Box 3. Remove the book and the brick from Box 1.", "sample_id": 2199, "numops": 0, "final_states": {"Box 0": ["nothing"], "Box 1": ["nothing"], "Box 2": ["the document", "the pipe"], "Box 3": ["the rock"], "Box 4": ["the television", "the watch", "the shirt"], "Box 5": ["the bottle", "the boat", "the ice"], "Box 6": ["the fan", "the file", "the ball"]}}
{"sentence": "Box 0 contains the apple and the sheet, Box 1 contains the cream and the pot, Box 2 contains the bag and the cross and the pipe, Box 3 contains the bus and the meat and the paper, Box 4 contains the bill, Box 5 contains the beer and the bomb, Box 6 contains the bottle and the crown and the shell. Move the bomb from Box 5 to Box 0. Move the meat and the paper from Box 3 to Box 4. Remove the cream and the pot from Box 1. Move the bus from Box 3 to Box 1. Remove the beer from Box 5. Remove the sheet from Box 0. Move the cross from Box 2 to Box 1. Remove the bag and the pipe from Box 2. Move the crown from Box 6 to Box 2. Move the bottle from Box 6 to Box 2. Put the game into Box 2. Remove the bus from Box 1.", "sample_id": 2204, "numops": 2, "final_states": {"Box 0": ["the apple", "the bomb"], "Box 1": ["the cross"], "Box 2": ["the game", "the bottle", "the crown"], "Box 3": ["nothing"], "Box 4": ["the paper", "the bill", "the meat"], "Box 5": ["nothing"], "Box 6": ["the shell"]}}
{"sentence": "Box 0 contains the ball, Box 1 contains the apple and the plane and the ticket, Box 2 contains the tea, Box 3 contains the coffee and the plate and the string, Box 4 contains the leaf, Box 5 contains the fish and the tie and the train, Box 6 contains nothing. Remove the fish and the tie and the train from Box 5. Put the phone into Box 2. Move the ball from Box 0 to Box 6. Move the ball from Box 6 to Box 0. Remove the ball from Box 0. Move the tea from Box 2 to Box 5. Move the plane from Box 1 to Box 5. Put the game into Box 0. Put the magazine into Box 4. Move the string from Box 3 to Box 5. Remove the phone from Box 2. Move the game from Box 0 to Box 1.", "sample_id": 2205, "numops": 5, "final_states": {"Box 0": ["nothing"], "Box 1": ["the apple", "the game", "the ticket"], "Box 2": ["nothing"], "Box 3": ["the coffee", "the plate"], "Box 4": ["the magazine", "the leaf"], "Box 5": ["the plane", "the tea", "the string"], "Box 6": ["nothing"]}}
{"sentence": "Box 0 contains the leaf, Box 1 contains nothing, Box 2 contains the block and the camera and the knife, Box 3 contains the crown and the mirror and the tissue, Box 4 contains the gift and the pipe, Box 5 contains the ice, Box 6 contains the brick and the picture and the watch. Remove the leaf from Box 0. Move the mirror from Box 3 to Box 1. Remove the brick and the watch from Box 6. Remove the picture from Box 6. Put the card and the document and the letter into Box 6. Remove the mirror from Box 1. Put the cross into Box 1. Move the gift and the pipe from Box 4 to Box 1.", "sample_id": 2214, "numops": 1, "final_states": {"Box 0": ["nothing"], "Box 1": ["the gift", "the pipe", "the cross"], "Box 2": ["the camera", "the knife", "the block"], "Box 3": ["the crown", "the tissue"], "Box 4": ["nothing"], "Box 5": ["the ice"], "Box 6": ["the card", "the document", "the letter"]}}
{"sentence": "Box 0 contains the book, Box 1 contains the branch and the key, Box 2 contains nothing, Box 3 contains nothing, Box 4 contains the bottle and the brick and the computer, Box 5 contains the stone, Box 6 contains the block and the letter and the meat. Remove the book from Box 0. Move the branch from Box 1 to Box 5. Remove the key from Box 1. Put the egg and the seed into Box 3. Move the egg from Box 3 to Box 1. Put the clock into Box 5. Move the bottle and the brick from Box 4 to Box 1. Remove the stone from Box 5. Remove the bottle from Box 1.", "sample_id": 2217, "numops": 1, "final_states": {"Box 0": ["nothing"], "Box 1": ["the egg", "the brick"], "Box 2": ["nothing"], "Box 3": ["the seed"], "Box 4": ["the computer"], "Box 5": ["the clock", "the branch"], "Box 6": ["the meat", "the letter", "the block"]}}
